Workbook

Sheet LEIAME
A1: Despesas pagas 2026 – VINCO (planilha completa)
A2: Fonte: aba Notas de entradas_conferidas_2026_ajustado_v3.xlsx (Omie). R$; competência = mês de emissão; "Antes de 2026" = documentos emitidos antes de 2026 e conferidos em 2026 (memo, fora do total 2026).
A4: 1) Abas
A5: Aba | B5: Conteúdo
A6: Resumo geral | B6: Categoria e subcategoria × mês (Jan–Set/2026), total, % do total, memo antes de 2026, total por categoria de nível 1 e conferências (zero).
A7: Insumos e papel | B7: Subcategoria × mês e fornecedores com total e %.
A8: Uso e consumo | B8: Idem (material de consumo, peças, fardamento, EPI, limpeza, escritório).
A9: Frete de compra | B9: Idem (Aliança, Stancanelli, Gol, Planeta Azul).
A10: Frete de venda | B10: Idem (demais transportadoras).
A11: Outras despesas pagas | B11: Imobilizado, manutenção, sede, brindes, combustível e aluguel de contêiner (cada um uma subcategoria).
A12: Lançamentos | B12: Base: uma linha por documento pago (categoria, subcategoria, mês, data, tipo, número, fornecedor, CNPJ, bruto, crédito, líquido, CFOP, observação, impostos, chave). Todas as abas de resumo são SUMIFS sobre ela.
A13: Excluídos | B13: Documentos que não são pagamento ou são duplicidade (remessa, devolução, transferência, x.949, x.922, NF-e sem título), com o motivo.
A14: Premissas | B14: Tabela editável de créditos (IPI/ICMS/PIS/COFINS) por categoria e subcategoria, com a justificativa fiscal.
A16: 2) Regras aplicadas
A17: • Só o efetivamente pago: NF-e entra se "Gerou título a pagar" = Sim; CT-e (frete) entram todos.
A18: • Fora (aba Excluídos): remessa (categoria 2.01.84, exceto frete 2.01.84 "por conta do remetente", que entra como frete); devoluções (2.09); remessa sem venda x.949; transferências 0.01; simples faturamento x.922 (duplica x.116/x.117); NF-e sem título.
A19: • Aluguel de contêiner (UNIAO MULTIMODAL OTM LTDA) não é frete: fica em Outras despesas pagas.
A20: • Insumos e papel: 2.01.03, 79, 83, 89, 91, 92, 93, 94, 95, 96, 97, 99. Uso e consumo: 2.01.85, 2.01.87 (peças de máquinas), 2.03.88 fardamento, 2.03.90 EPI, 2.04.91, 2.04.06, 2.04.95, 2.04.96.
A21: • Frete de compra = somente ALIANCA NAVEGACAO E LOGISTICA (com/sem ponto final, unificadas), STANCANELLI, GOL LINHAS AEREAS e TRANSPORTES DE MAQUINAS PLANETA AZUL. Frete de venda = todas as demais transportadoras (inclui Cazan e RF BRA).
A22: • Créditos (Lucro Real): insumos = IPI+ICMS+PIS+COFINS; uso e consumo = só PIS/COFINS; frete de compra = só ICMS; frete de venda = nenhum; sem crédito de ICMS/IPI em CFOP x.556; ICMS-ST nunca é abatido. Detalhe por categoria na aba Premissas (editável).
A23: • Todas as demais categorias pagas (imobilizado 2.07 e 2.01.78, manutenção, sede 2.16, brindes/premiações/marketing, combustível) ficam em Outras despesas pagas, sem crédito modelado.
A25: 3) Correções fiscais desta revisão (comparação com a versão anterior despesas_2026.xlsx)
A26: Ajuste | B26: Motivo fiscal / o que mudou | G26: Efeito no líquido 2026 (R$)
A27: Impostos de documentos rateados (14 NF-e, 28 linhas) | B27: IPI/ICMS/PIS/COFINS constavam só na 1ª linha do rateio e eram creditados integralmente na categoria dessa linha (em 5 documentos o ICMS destacado chegava a superar o valor da categoria). Agora são redistribuídos proporcionalmente ao valor de cada categoria, pois o imposto do trecho de imobilizado/outra categoria não pertence ao insumo. Insumos: R$ 1.121,90; Uso e consumo: R$ 17,75. | G27: 1139.65
A28: PIS/COFINS de fardamento, material de escritório, copa e cozinha e bens de pequeno valor zerados | B28: Não são insumo da produção: o crédito de fardamento (Lei 10.833, art. 3º, X) é restrito a prestadoras de limpeza/conservação e material administrativo não gera crédito (PN Cosit 5/2018). EPI (2.03.90), peças (2.01.87), limpeza (2.04.91) e uso e consumo (2.01.85) mantêm PIS/COFINS. Editável na aba Premissas. | G28: 290.46
A29: Frete de compra classificado pelo nome da transportadora e Aliança unificada | B29: As grafias "ALIANCA ... LTDA" e "ALIANCA ... LTDA." viram um só fornecedor; o enquadramento em frete de compra/venda passa a seguir a lista de transportadoras da regra, não o grupo do Omie. Sem efeito nos totais. | G29: 0
A30: Aluguel de contêiner (UNIAO MULTIMODAL) em Outras despesas pagas | B30: CT-e da UNIAO MULTIMODAL OTM (R$ 293.060,00 bruto, sem ICMS) é locação/estadia de contêiner, não transporte; já estava fora do frete e agora aparece como subcategoria própria. | G30: 0
A31: Créditos calculados por fórmula em Lançamentos, por categoria | B31: A versão anterior definia créditos por destino; agora cada categoria tem seus flags (aba Premissas) e a coluna Crédito é fórmula, então qualquer ajuste recalcula tudo. | G31: 0
A32: Revisados e mantidos sem alteração | B32: ICMS-ST: nenhum valor relevante no escopo (R$ 250 em CT-e), nunca abatido, permanece no custo. PIS/COFINS de CT-e: não destacados nos CT-e (zero). CFOP x.556 sem ICMS/IPI: regra mantida. Frete de venda sem crédito: regra do usuário mantida (ver pendências). EPI: crédito de PIS/COFINS mantido (PN Cosit 5/2018). Estadia/cabotagem da Aliança (2.01.82): mantida com o ICMS destacado. | G32: 0
A34: 4) Totais por categoria (2026, fórmulas sobre Lançamentos)
A35: Categoria | B35: Nº docs 2026 | C35: Valor bruto 2026 | D35: Créditos 2026 | E35: Líquido 2026 | F35: % do líquido | G35: Bruto antes de 2026 | H35: Líquido antes de 2026
A36: Insumos e papel | B36: =COUNTIFS('Lançamentos'!$A$2:$A$5010,$A36,'Lançamentos'!$D$2:$D$5010,"Em 2026") | C36: =SUMIFS('Lançamentos'!$J$2:$J$5010,'Lançamentos'!$A$2:$A$5010,$A36,'Lançamentos'!$D$2:$D$5010,"Em 2026") | D36: =SUMIFS('Lançamentos'!$K$2:$K$5010,'Lançamentos'!$A$2:$A$5010,$A36,'Lançamentos'!$D$2:$D$5010,"Em 2026") | E36: =C36-D36 | F36: =E36/E$41 | G36: =SUMIFS('Lançamentos'!$J$2:$J$5010,'Lançamentos'!$A$2:$A$5010,$A36,'Lançamentos'!$D$2:$D$5010,"Antes de 2026") | H36: =G36-SUMIFS('Lançamentos'!$K$2:$K$5010,'Lançamentos'!$A$2:$A$5010,$A36,'Lançamentos'!$D$2:$D$5010,"Antes de 2026")
A37: Uso e consumo | B37: =COUNTIFS('Lançamentos'!$A$2:$A$5010,$A37,'Lançamentos'!$D$2:$D$5010,"Em 2026") | C37: =SUMIFS('Lançamentos'!$J$2:$J$5010,'Lançamentos'!$A$2:$A$5010,$A37,'Lançamentos'!$D$2:$D$5010,"Em 2026") | D37: =SUMIFS('Lançamentos'!$K$2:$K$5010,'Lançamentos'!$A$2:$A$5010,$A37,'Lançamentos'!$D$2:$D$5010,"Em 2026") | E37: =C37-D37 | F37: =E37/E$41 | G37: =SUMIFS('Lançamentos'!$J$2:$J$5010,'Lançamentos'!$A$2:$A$5010,$A37,'Lançamentos'!$D$2:$D$5010,"Antes de 2026") | H37: =G37-SUMIFS('Lançamentos'!$K$2:$K$5010,'Lançamentos'!$A$2:$A$5010,$A37,'Lançamentos'!$D$2:$D$5010,"Antes de 2026")
A38: Frete de compra | B38: =COUNTIFS('Lançamentos'!$A$2:$A$5010,$A38,'Lançamentos'!$D$2:$D$5010,"Em 2026") | C38: =SUMIFS('Lançamentos'!$J$2:$J$5010,'Lançamentos'!$A$2:$A$5010,$A38,'Lançamentos'!$D$2:$D$5010,"Em 2026") | D38: =SUMIFS('Lançamentos'!$K$2:$K$5010,'Lançamentos'!$A$2:$A$5010,$A38,'Lançamentos'!$D$2:$D$5010,"Em 2026") | E38: =C38-D38 | F38: =E38/E$41 | G38: =SUMIFS('Lançamentos'!$J$2:$J$5010,'Lançamentos'!$A$2:$A$5010,$A38,'Lançamentos'!$D$2:$D$5010,"Antes de 2026") | H38: =G38-SUMIFS('Lançamentos'!$K$2:$K$5010,'Lançamentos'!$A$2:$A$5010,$A38,'Lançamentos'!$D$2:$D$5010,"Antes de 2026")
A39: Frete de venda | B39: =COUNTIFS('Lançamentos'!$A$2:$A$5010,$A39,'Lançamentos'!$D$2:$D$5010,"Em 2026") | C39: =SUMIFS('Lançamentos'!$J$2:$J$5010,'Lançamentos'!$A$2:$A$5010,$A39,'Lançamentos'!$D$2:$D$5010,"Em 2026") | D39: =SUMIFS('Lançamentos'!$K$2:$K$5010,'Lançamentos'!$A$2:$A$5010,$A39,'Lançamentos'!$D$2:$D$5010,"Em 2026") | E39: =C39-D39 | F39: =E39/E$41 | G39: =SUMIFS('Lançamentos'!$J$2:$J$5010,'Lançamentos'!$A$2:$A$5010,$A39,'Lançamentos'!$D$2:$D$5010,"Antes de 2026") | H39: =G39-SUMIFS('Lançamentos'!$K$2:$K$5010,'Lançamentos'!$A$2:$A$5010,$A39,'Lançamentos'!$D$2:$D$5010,"Antes de 2026")
A40: Outras despesas pagas | B40: =COUNTIFS('Lançamentos'!$A$2:$A$5010,$A40,'Lançamentos'!$D$2:$D$5010,"Em 2026") | C40: =SUMIFS('Lançamentos'!$J$2:$J$5010,'Lançamentos'!$A$2:$A$5010,$A40,'Lançamentos'!$D$2:$D$5010,"Em 2026") | D40: =SUMIFS('Lançamentos'!$K$2:$K$5010,'Lançamentos'!$A$2:$A$5010,$A40,'Lançamentos'!$D$2:$D$5010,"Em 2026") | E40: =C40-D40 | F40: =E40/E$41 | G40: =SUMIFS('Lançamentos'!$J$2:$J$5010,'Lançamentos'!$A$2:$A$5010,$A40,'Lançamentos'!$D$2:$D$5010,"Antes de 2026") | H40: =G40-SUMIFS('Lançamentos'!$K$2:$K$5010,'Lançamentos'!$A$2:$A$5010,$A40,'Lançamentos'!$D$2:$D$5010,"Antes de 2026")
A41: TOTAL | B41: =SUM(B36:B40) | C41: =SUM(C36:C40) | D41: =SUM(D36:D40) | E41: =SUM(E36:E40) | F41: =E41/E41 | G41: =SUM(G36:G40) | H41: =SUM(H36:H40)
A43: 5) Reconciliação com a aba Notas (valor bruto, todas as linhas)
A44: Item | B44: Em 2026 | C44: Antes de 2026 | D44: Total | E44: Nº linhas
A45: Pago – Insumos e papel | B45: =SUMIFS('Lançamentos'!$J$2:$J$5010,'Lançamentos'!$A$2:$A$5010,"Insumos e papel",'Lançamentos'!$D$2:$D$5010,"Em 2026") | C45: =SUMIFS('Lançamentos'!$J$2:$J$5010,'Lançamentos'!$A$2:$A$5010,"Insumos e papel",'Lançamentos'!$D$2:$D$5010,"Antes de 2026") | D45: =B45+C45 | E45: =COUNTIFS('Lançamentos'!$A$2:$A$5010,"Insumos e papel")
A46: Pago – Uso e consumo | B46: =SUMIFS('Lançamentos'!$J$2:$J$5010,'Lançamentos'!$A$2:$A$5010,"Uso e consumo",'Lançamentos'!$D$2:$D$5010,"Em 2026") | C46: =SUMIFS('Lançamentos'!$J$2:$J$5010,'Lançamentos'!$A$2:$A$5010,"Uso e consumo",'Lançamentos'!$D$2:$D$5010,"Antes de 2026") | D46: =B46+C46 | E46: =COUNTIFS('Lançamentos'!$A$2:$A$5010,"Uso e consumo")
A47: Pago – Frete de compra | B47: =SUMIFS('Lançamentos'!$J$2:$J$5010,'Lançamentos'!$A$2:$A$5010,"Frete de compra",'Lançamentos'!$D$2:$D$5010,"Em 2026") | C47: =SUMIFS('Lançamentos'!$J$2:$J$5010,'Lançamentos'!$A$2:$A$5010,"Frete de compra",'Lançamentos'!$D$2:$D$5010,"Antes de 2026") | D47: =B47+C47 | E47: =COUNTIFS('Lançamentos'!$A$2:$A$5010,"Frete de compra")
A48: Pago – Frete de venda | B48: =SUMIFS('Lançamentos'!$J$2:$J$5010,'Lançamentos'!$A$2:$A$5010,"Frete de venda",'Lançamentos'!$D$2:$D$5010,"Em 2026") | C48: =SUMIFS('Lançamentos'!$J$2:$J$5010,'Lançamentos'!$A$2:$A$5010,"Frete de venda",'Lançamentos'!$D$2:$D$5010,"Antes de 2026") | D48: =B48+C48 | E48: =COUNTIFS('Lançamentos'!$A$2:$A$5010,"Frete de venda")
A49: Pago – Outras despesas pagas | B49: =SUMIFS('Lançamentos'!$J$2:$J$5010,'Lançamentos'!$A$2:$A$5010,"Outras despesas pagas",'Lançamentos'!$D$2:$D$5010,"Em 2026") | C49: =SUMIFS('Lançamentos'!$J$2:$J$5010,'Lançamentos'!$A$2:$A$5010,"Outras despesas pagas",'Lançamentos'!$D$2:$D$5010,"Antes de 2026") | D49: =B49+C49 | E49: =COUNTIFS('Lançamentos'!$A$2:$A$5010,"Outras despesas pagas")
A50: Excluído – NF-e sem título a pagar gerado no recebimento | B50: =SUMIFS(Excluídos!$J$2:$J$794,Excluídos!$A$2:$A$794,"NF-e sem título a pagar gerado no recebimento",Excluídos!$D$2:$D$794,"Em 2026") | C50: =SUMIFS(Excluídos!$J$2:$J$794,Excluídos!$A$2:$A$794,"NF-e sem título a pagar gerado no recebimento",Excluídos!$D$2:$D$794,"Antes de 2026") | D50: =B50+C50 | E50: =COUNTIFS(Excluídos!$A$2:$A$794,"NF-e sem título a pagar gerado no recebimento")
A51: Excluído – Remessa de mercadoria (categoria 2.01.84) | B51: =SUMIFS(Excluídos!$J$2:$J$794,Excluídos!$A$2:$A$794,"Remessa de mercadoria (categoria 2.01.84)",Excluídos!$D$2:$D$794,"Em 2026") | C51: =SUMIFS(Excluídos!$J$2:$J$794,Excluídos!$A$2:$A$794,"Remessa de mercadoria (categoria 2.01.84)",Excluídos!$D$2:$D$794,"Antes de 2026") | D51: =B51+C51 | E51: =COUNTIFS(Excluídos!$A$2:$A$794,"Remessa de mercadoria (categoria 2.01.84)")
A52: Excluído – Simples faturamento (x.922) – duplica x.116/x.117 | B52: =SUMIFS(Excluídos!$J$2:$J$794,Excluídos!$A$2:$A$794,"Simples faturamento (x.922) – duplica x.116/x.117",Excluídos!$D$2:$D$794,"Em 2026") | C52: =SUMIFS(Excluídos!$J$2:$J$794,Excluídos!$A$2:$A$794,"Simples faturamento (x.922) – duplica x.116/x.117",Excluídos!$D$2:$D$794,"Antes de 2026") | D52: =B52+C52 | E52: =COUNTIFS(Excluídos!$A$2:$A$794,"Simples faturamento (x.922) – duplica x.116/x.117")
A53: Excluído – Transferência (0.01) | B53: =SUMIFS(Excluídos!$J$2:$J$794,Excluídos!$A$2:$A$794,"Transferência (0.01)",Excluídos!$D$2:$D$794,"Em 2026") | C53: =SUMIFS(Excluídos!$J$2:$J$794,Excluídos!$A$2:$A$794,"Transferência (0.01)",Excluídos!$D$2:$D$794,"Antes de 2026") | D53: =B53+C53 | E53: =COUNTIFS(Excluídos!$A$2:$A$794,"Transferência (0.01)")
A54: SOMA (pagos + excluídos) | B54: =SUM(B45:B53) | C54: =SUM(C45:C53) | D54: =SUM(D45:D53) | E54: =SUM(E45:E53)
A55: Total da aba Notas (soma da coluna "Valor na categoria") | B55: 36108608 | C55: 11802908 | D55: =B55+C55 | E55: 5802
A56: Diferença (deve ser zero) | B56: =ROUND(B54-B55,2) | C56: =ROUND(C54-C55,2) | D56: =ROUND(D54-D55,2) | E56: =ROUND(E54-E55,2)
A58: 6) Pendências para o usuário / contador
A59: 1. Papel/insumos com CFOP de entrada x.556 (uso e consumo): 142 documentos, R$ 6.592.265,94 bruto em 2026, com R$ 408.407,94 de IPI e R$ 607.372,93 de ICMS destacados sem crédito (regra x.556). Se o CFOP estiver errado no Omie (papel é insumo, x.101/x.102), o custo líquido de Insumos cai em até ~R$ 1.015.780,87. Validar com o contador; maior ponto de atenção.
A60: 2. 10 documentos de insumos com CFOP misto (x.556 junto com x.102): R$ 382.154,86 bruto, ICMS+IPI de R$ 43.447,66 tratados integralmente sem crédito (a base não traz o item).
A61: 3. PIS/COFINS de frete de compra: o CT-e não destaca, mas em Lucro Real o frete na aquisição de insumos gera crédito (Lei 10.833, art. 3º, II). Potencial ~R$ 230.019,21 em 2026 (9,25% sobre bruto menos ICMS). Não modelado (regra do usuário: só ICMS).
A62: 4. Frete de venda: sem crédito por regra do usuário. Em Lucro Real, o frete na operação de venda por conta do vendedor gera PIS/COFINS (art. 3º, IX): potencial ~R$ 104.328,58, além de R$ 88.725,22 de ICMS destacado nos CT-e. Confirmar tratamento com o contador.
A63: 5. Pagamentos de frete de venda sem CT-e no Omie (4 lançamentos em ago/2026, R$ 67.250,00): destaque para a FATURA de ADIL CARLOS DA SILVA de R$ 34.500,00, que pode duplicar os 51 CT-e da mesma transportadora (R$ 36.930,00 no total). Confirmar se a fatura já está coberta pelos CT-e.
A64: 6. Gol Linhas Aéreas: 31 CT-e em 2026 (R$ 8.940,73) entram como frete de compra pela regra, mas no Omie estão categorizados como venda/amostras/descarregamento. Confirmar se são mesmo frete de compra de papel.
A65: 7. Fretes 2.01.84 (remessa) de Aliança e Planeta Azul excluídos pela regra (14 CT-e, R$ 258.995,12); se forem frete de compra de bobina/papel, deveriam entrar.
A66: 8. CFOPs de entrada incompatíveis no Omie: CT-e da Aliança com 3.250 (8 documentos) e 2.305 (1), e NF-e da CMPC Iguaçu (papel, R$ 121.242,55) com 1.553 (devolução de ativo). Os créditos foram mantidos, mas o cadastro deve ser corrigido.
A67: 9. NF-e da B. B. A. Indústria (R$ 6.521,26, CFOP 2.556) está categorizada como 2.04.87 Frete sobre Compra; ficou em Outras (a classificar). Provavelmente uso e consumo/peças; recategorizar no Omie.
A68: 10. PIS/COFINS usam os valores destacados na NF do fornecedor; o crédito legal é a alíquota do adquirente sobre o custo sem ICMS recuperável. A diferença tende a ser pequena, mas não foi recalculada.
A69: 11. CNPJ das transportadoras não existe na base do Omie: em CT-e a coluna CNPJ/CPF fica em branco e a observação traz a outra parte do frete (cliente/fornecedor) e seu CNPJ.
A70: 12. Fardamento, material de escritório, copa e bens de pequeno valor estão sem crédito de PIS/COFINS (ajuste conservador); se o contador entender que geram crédito, marque 1 na aba Premissas.

Sheet Resumo geral
A1: Despesas pagas 2026 – resumo geral (VINCO)
A2: R$ por mês de emissão, custo líquido de créditos (aba Premissas). Só o efetivamente pago (NF-e com título a pagar + CT-e); sem remessa, devolução, transferência, x.949, x.922 e NF-e sem título (aba Excluídos). Todos os valores são SUMIFS sobre a aba Lançamentos.
A4: Categoria / Subcategoria | B4: 46023 | C4: 46054 | D4: 46082 | E4: 46113 | F4: 46143 | G4: 46174 | H4: 46204 | I4: 46235 | J4: 46266 | K4: Total 2026 | L4: % do total | M4: Memo: antes de 2026
A5: Insumos e papel | B5: =SUM(B6:B17) | C5: =SUM(C6:C17) | D5: =SUM(D6:D17) | E5: =SUM(E6:E17) | F5: =SUM(F6:F17) | G5: =SUM(G6:G17) | H5: =SUM(H6:H17) | I5: =SUM(I6:I17) | ... K5: =SUM(K6:K17) | L5: =K5/K$51 | M5: =SUM(M6:M17)
A6: 2.01.03 Compra de Matéria Prima (Papel) | B6: =SUMIFS('Lançamentos'!$L$2:$L$5010,'Lançamentos'!$A$2:$A$5010,"Insumos e papel",'Lançamentos'!$B$2:$B$5010,$A6,'Lançamentos'!$C$2:$C$5010,B$4) | C6: =SUMIFS('Lançamentos'!$L$2:$L$5010,'Lançamentos'!$A$2:$A$5010,"Insumos e papel",'Lançamentos'!$B$2:$B$5010,$A6,'Lançamentos'!$C$2:$C$5010,C$4) | D6: =SUMIFS('Lançamentos'!$L$2:$L$5010,'Lançamentos'!$A$2:$A$5010,"Insumos e papel",'Lançamentos'!$B$2:$B$5010,$A6,'Lançamentos'!$C$2:$C$5010,D$4) | E6: =SUMIFS('Lançamentos'!$L$2:$L$5010,'Lançamentos'!$A$2:$A$5010,"Insumos e papel",'Lançamentos'!$B$2:$B$5010,$A6,'Lançamentos'!$C$2:$C$5010,E$4) | F6: =SUMIFS('Lançamentos'!$L$2:$L$5010,'Lançamentos'!$A$2:$A$5010,"Insumos e papel",'Lançamentos'!$B$2:$B$5010,$A6,'Lançamentos'!$C$2:$C$5010,F$4) | G6: =SUMIFS('Lançamentos'!$L$2:$L$5010,'Lançamentos'!$A$2:$A$5010,"Insumos e papel",'Lançamentos'!$B$2:$B$5010,$A6,'Lançamentos'!$C$2:$C$5010,G$4) | H6: =SUMIFS('Lançamentos'!$L$2:$L$5010,'Lançamentos'!$A$2:$A$5010,"Insumos e papel",'Lançamentos'!$B$2:$B$5010,$A6,'Lançamentos'!$C$2:$C$5010,H$4) | I6: =SUMIFS('Lançamentos'!$L$2:$L$5010,'Lançamentos'!$A$2:$A$5010,"Insumos e papel",'Lançamentos'!$B$2:$B$5010,$A6,'Lançamentos'!$C$2:$C$5010,I$4) | J6: =SUMIFS('Lançamentos'!$L$2:$L$5010,'Lançamentos'!$A$2:$A$5010,"Insumos e papel",'Lançamentos'!$B$2:$B$5010,$A6,'Lançamentos'!$C$2:$C$5010,J$4) | K6: =SUM(B6:J6) | L6: =K6/K$51 | M6: =SUMIFS('Lançamentos'!$L$2:$L$5010,'Lançamentos'!$A$2:$A$5010,"Insumos e papel",'Lançamentos'!$B$2:$B$5010,$A6,'Lançamentos'!$C$2:$C$5010,"Antes de 2026")
A7: 2.01.79 Compra de Gás | B7: =SUMIFS('Lançamentos'!$L$2:$L$5010,'Lançamentos'!$A$2:$A$5010,"Insumos e papel",'Lançamentos'!$B$2:$B$5010,$A7,'Lançamentos'!$C$2:$C$5010,B$4) | C7: =SUMIFS('Lançamentos'!$L$2:$L$5010,'Lançamentos'!$A$2:$A$5010,"Insumos e papel",'Lançamentos'!$B$2:$B$5010,$A7,'Lançamentos'!$C$2:$C$5010,C$4) | D7: =SUMIFS('Lançamentos'!$L$2:$L$5010,'Lançamentos'!$A$2:$A$5010,"Insumos e papel",'Lançamentos'!$B$2:$B$5010,$A7,'Lançamentos'!$C$2:$C$5010,D$4) | E7: =SUMIFS('Lançamentos'!$L$2:$L$5010,'Lançamentos'!$A$2:$A$5010,"Insumos e papel",'Lançamentos'!$B$2:$B$5010,$A7,'Lançamentos'!$C$2:$C$5010,E$4) | F7: =SUMIFS('Lançamentos'!$L$2:$L$5010,'Lançamentos'!$A$2:$A$5010,"Insumos e papel",'Lançamentos'!$B$2:$B$5010,$A7,'Lançamentos'!$C$2:$C$5010,F$4) | G7: =SUMIFS('Lançamentos'!$L$2:$L$5010,'Lançamentos'!$A$2:$A$5010,"Insumos e papel",'Lançamentos'!$B$2:$B$5010,$A7,'Lançamentos'!$C$2:$C$5010,G$4) | H7: =SUMIFS('Lançamentos'!$L$2:$L$5010,'Lançamentos'!$A$2:$A$5010,"Insumos e papel",'Lançamentos'!$B$2:$B$5010,$A7,'Lançamentos'!$C$2:$C$5010,H$4) | I7: =SUMIFS('Lançamentos'!$L$2:$L$5010,'Lançamentos'!$A$2:$A$5010,"Insumos e papel",'Lançamentos'!$B$2:$B$5010,$A7,'Lançamentos'!$C$2:$C$5010,I$4) | J7: =SUMIFS('Lançamentos'!$L$2:$L$5010,'Lançamentos'!$A$2:$A$5010,"Insumos e papel",'Lançamentos'!$B$2:$B$5010,$A7,'Lançamentos'!$C$2:$C$5010,J$4) | K7: =SUM(B7:J7) | L7: =K7/K$51 | M7: =SUMIFS('Lançamentos'!$L$2:$L$5010,'Lançamentos'!$A$2:$A$5010,"Insumos e papel",'Lançamentos'!$B$2:$B$5010,$A7,'Lançamentos'!$C$2:$C$5010,"Antes de 2026")
A8: 2.01.83 Compra de Etiqueta Personalizada | B8: =SUMIFS('Lançamentos'!$L$2:$L$5010,'Lançamentos'!$A$2:$A$5010,"Insumos e papel",'Lançamentos'!$B$2:$B$5010,$A8,'Lançamentos'!$C$2:$C$5010,B$4) | C8: =SUMIFS('Lançamentos'!$L$2:$L$5010,'Lançamentos'!$A$2:$A$5010,"Insumos e papel",'Lançamentos'!$B$2:$B$5010,$A8,'Lançamentos'!$C$2:$C$5010,C$4) | D8: =SUMIFS('Lançamentos'!$L$2:$L$5010,'Lançamentos'!$A$2:$A$5010,"Insumos e papel",'Lançamentos'!$B$2:$B$5010,$A8,'Lançamentos'!$C$2:$C$5010,D$4) | E8: =SUMIFS('Lançamentos'!$L$2:$L$5010,'Lançamentos'!$A$2:$A$5010,"Insumos e papel",'Lançamentos'!$B$2:$B$5010,$A8,'Lançamentos'!$C$2:$C$5010,E$4) | F8: =SUMIFS('Lançamentos'!$L$2:$L$5010,'Lançamentos'!$A$2:$A$5010,"Insumos e papel",'Lançamentos'!$B$2:$B$5010,$A8,'Lançamentos'!$C$2:$C$5010,F$4) | G8: =SUMIFS('Lançamentos'!$L$2:$L$5010,'Lançamentos'!$A$2:$A$5010,"Insumos e papel",'Lançamentos'!$B$2:$B$5010,$A8,'Lançamentos'!$C$2:$C$5010,G$4) | H8: =SUMIFS('Lançamentos'!$L$2:$L$5010,'Lançamentos'!$A$2:$A$5010,"Insumos e papel",'Lançamentos'!$B$2:$B$5010,$A8,'Lançamentos'!$C$2:$C$5010,H$4) | I8: =SUMIFS('Lançamentos'!$L$2:$L$5010,'Lançamentos'!$A$2:$A$5010,"Insumos e papel",'Lançamentos'!$B$2:$B$5010,$A8,'Lançamentos'!$C$2:$C$5010,I$4) | J8: =SUMIFS('Lançamentos'!$L$2:$L$5010,'Lançamentos'!$A$2:$A$5010,"Insumos e papel",'Lançamentos'!$B$2:$B$5010,$A8,'Lançamentos'!$C$2:$C$5010,J$4) | K8: =SUM(B8:J8) | L8: =K8/K$51 | M8: =SUMIFS('Lançamentos'!$L$2:$L$5010,'Lançamentos'!$A$2:$A$5010,"Insumos e papel",'Lançamentos'!$B$2:$B$5010,$A8,'Lançamentos'!$C$2:$C$5010,"Antes de 2026")
A9: 2.01.89 Compra de Pallet | B9: =SUMIFS('Lançamentos'!$L$2:$L$5010,'Lançamentos'!$A$2:$A$5010,"Insumos e papel",'Lançamentos'!$B$2:$B$5010,$A9,'Lançamentos'!$C$2:$C$5010,B$4) | C9: =SUMIFS('Lançamentos'!$L$2:$L$5010,'Lançamentos'!$A$2:$A$5010,"Insumos e papel",'Lançamentos'!$B$2:$B$5010,$A9,'Lançamentos'!$C$2:$C$5010,C$4) | D9: =SUMIFS('Lançamentos'!$L$2:$L$5010,'Lançamentos'!$A$2:$A$5010,"Insumos e papel",'Lançamentos'!$B$2:$B$5010,$A9,'Lançamentos'!$C$2:$C$5010,D$4) | E9: =SUMIFS('Lançamentos'!$L$2:$L$5010,'Lançamentos'!$A$2:$A$5010,"Insumos e papel",'Lançamentos'!$B$2:$B$5010,$A9,'Lançamentos'!$C$2:$C$5010,E$4) | F9: =SUMIFS('Lançamentos'!$L$2:$L$5010,'Lançamentos'!$A$2:$A$5010,"Insumos e papel",'Lançamentos'!$B$2:$B$5010,$A9,'Lançamentos'!$C$2:$C$5010,F$4) | G9: =SUMIFS('Lançamentos'!$L$2:$L$5010,'Lançamentos'!$A$2:$A$5010,"Insumos e papel",'Lançamentos'!$B$2:$B$5010,$A9,'Lançamentos'!$C$2:$C$5010,G$4) | H9: =SUMIFS('Lançamentos'!$L$2:$L$5010,'Lançamentos'!$A$2:$A$5010,"Insumos e papel",'Lançamentos'!$B$2:$B$5010,$A9,'Lançamentos'!$C$2:$C$5010,H$4) | I9: =SUMIFS('Lançamentos'!$L$2:$L$5010,'Lançamentos'!$A$2:$A$5010,"Insumos e papel",'Lançamentos'!$B$2:$B$5010,$A9,'Lançamentos'!$C$2:$C$5010,I$4) | J9: =SUMIFS('Lançamentos'!$L$2:$L$5010,'Lançamentos'!$A$2:$A$5010,"Insumos e papel",'Lançamentos'!$B$2:$B$5010,$A9,'Lançamentos'!$C$2:$C$5010,J$4) | K9: =SUM(B9:J9) | L9: =K9/K$51 | M9: =SUMIFS('Lançamentos'!$L$2:$L$5010,'Lançamentos'!$A$2:$A$5010,"Insumos e papel",'Lançamentos'!$B$2:$B$5010,$A9,'Lançamentos'!$C$2:$C$5010,"Antes de 2026")
A10: 2.01.91 Compra de Filme Strech | B10: =SUMIFS('Lançamentos'!$L$2:$L$5010,'Lançamentos'!$A$2:$A$5010,"Insumos e papel",'Lançamentos'!$B$2:$B$5010,$A10,'Lançamentos'!$C$2:$C$5010,B$4) | C10: =SUMIFS('Lançamentos'!$L$2:$L$5010,'Lançamentos'!$A$2:$A$5010,"Insumos e papel",'Lançamentos'!$B$2:$B$5010,$A10,'Lançamentos'!$C$2:$C$5010,C$4) | D10: =SUMIFS('Lançamentos'!$L$2:$L$5010,'Lançamentos'!$A$2:$A$5010,"Insumos e papel",'Lançamentos'!$B$2:$B$5010,$A10,'Lançamentos'!$C$2:$C$5010,D$4) | E10: =SUMIFS('Lançamentos'!$L$2:$L$5010,'Lançamentos'!$A$2:$A$5010,"Insumos e papel",'Lançamentos'!$B$2:$B$5010,$A10,'Lançamentos'!$C$2:$C$5010,E$4) | F10: =SUMIFS('Lançamentos'!$L$2:$L$5010,'Lançamentos'!$A$2:$A$5010,"Insumos e papel",'Lançamentos'!$B$2:$B$5010,$A10,'Lançamentos'!$C$2:$C$5010,F$4) | G10: =SUMIFS('Lançamentos'!$L$2:$L$5010,'Lançamentos'!$A$2:$A$5010,"Insumos e papel",'Lançamentos'!$B$2:$B$5010,$A10,'Lançamentos'!$C$2:$C$5010,G$4) | H10: =SUMIFS('Lançamentos'!$L$2:$L$5010,'Lançamentos'!$A$2:$A$5010,"Insumos e papel",'Lançamentos'!$B$2:$B$5010,$A10,'Lançamentos'!$C$2:$C$5010,H$4) | I10: =SUMIFS('Lançamentos'!$L$2:$L$5010,'Lançamentos'!$A$2:$A$5010,"Insumos e papel",'Lançamentos'!$B$2:$B$5010,$A10,'Lançamentos'!$C$2:$C$5010,I$4) | J10: =SUMIFS('Lançamentos'!$L$2:$L$5010,'Lançamentos'!$A$2:$A$5010,"Insumos e papel",'Lançamentos'!$B$2:$B$5010,$A10,'Lançamentos'!$C$2:$C$5010,J$4) | K10: =SUM(B10:J10) | L10: =K10/K$51 | M10: =SUMIFS('Lançamentos'!$L$2:$L$5010,'Lançamentos'!$A$2:$A$5010,"Insumos e papel",'Lançamentos'!$B$2:$B$5010,$A10,'Lançamentos'!$C$2:$C$5010,"Antes de 2026")
A11: 2.01.92 Compra de Tinta | B11: =SUMIFS('Lançamentos'!$L$2:$L$5010,'Lançamentos'!$A$2:$A$5010,"Insumos e papel",'Lançamentos'!$B$2:$B$5010,$A11,'Lançamentos'!$C$2:$C$5010,B$4) | C11: =SUMIFS('Lançamentos'!$L$2:$L$5010,'Lançamentos'!$A$2:$A$5010,"Insumos e papel",'Lançamentos'!$B$2:$B$5010,$A11,'Lançamentos'!$C$2:$C$5010,C$4) | D11: =SUMIFS('Lançamentos'!$L$2:$L$5010,'Lançamentos'!$A$2:$A$5010,"Insumos e papel",'Lançamentos'!$B$2:$B$5010,$A11,'Lançamentos'!$C$2:$C$5010,D$4) | E11: =SUMIFS('Lançamentos'!$L$2:$L$5010,'Lançamentos'!$A$2:$A$5010,"Insumos e papel",'Lançamentos'!$B$2:$B$5010,$A11,'Lançamentos'!$C$2:$C$5010,E$4) | F11: =SUMIFS('Lançamentos'!$L$2:$L$5010,'Lançamentos'!$A$2:$A$5010,"Insumos e papel",'Lançamentos'!$B$2:$B$5010,$A11,'Lançamentos'!$C$2:$C$5010,F$4) | G11: =SUMIFS('Lançamentos'!$L$2:$L$5010,'Lançamentos'!$A$2:$A$5010,"Insumos e papel",'Lançamentos'!$B$2:$B$5010,$A11,'Lançamentos'!$C$2:$C$5010,G$4) | H11: =SUMIFS('Lançamentos'!$L$2:$L$5010,'Lançamentos'!$A$2:$A$5010,"Insumos e papel",'Lançamentos'!$B$2:$B$5010,$A11,'Lançamentos'!$C$2:$C$5010,H$4) | I11: =SUMIFS('Lançamentos'!$L$2:$L$5010,'Lançamentos'!$A$2:$A$5010,"Insumos e papel",'Lançamentos'!$B$2:$B$5010,$A11,'Lançamentos'!$C$2:$C$5010,I$4) | J11: =SUMIFS('Lançamentos'!$L$2:$L$5010,'Lançamentos'!$A$2:$A$5010,"Insumos e papel",'Lançamentos'!$B$2:$B$5010,$A11,'Lançamentos'!$C$2:$C$5010,J$4) | K11: =SUM(B11:J11) | L11: =K11/K$51 | M11: =SUMIFS('Lançamentos'!$L$2:$L$5010,'Lançamentos'!$A$2:$A$5010,"Insumos e papel",'Lançamentos'!$B$2:$B$5010,$A11,'Lançamentos'!$C$2:$C$5010,"Antes de 2026")
A12: 2.01.93 Compra de Plástico Poliolefínico | B12: =SUMIFS('Lançamentos'!$L$2:$L$5010,'Lançamentos'!$A$2:$A$5010,"Insumos e papel",'Lançamentos'!$B$2:$B$5010,$A12,'Lançamentos'!$C$2:$C$5010,B$4) | C12: =SUMIFS('Lançamentos'!$L$2:$L$5010,'Lançamentos'!$A$2:$A$5010,"Insumos e papel",'Lançamentos'!$B$2:$B$5010,$A12,'Lançamentos'!$C$2:$C$5010,C$4) | D12: =SUMIFS('Lançamentos'!$L$2:$L$5010,'Lançamentos'!$A$2:$A$5010,"Insumos e papel",'Lançamentos'!$B$2:$B$5010,$A12,'Lançamentos'!$C$2:$C$5010,D$4) | E12: =SUMIFS('Lançamentos'!$L$2:$L$5010,'Lançamentos'!$A$2:$A$5010,"Insumos e papel",'Lançamentos'!$B$2:$B$5010,$A12,'Lançamentos'!$C$2:$C$5010,E$4) | F12: =SUMIFS('Lançamentos'!$L$2:$L$5010,'Lançamentos'!$A$2:$A$5010,"Insumos e papel",'Lançamentos'!$B$2:$B$5010,$A12,'Lançamentos'!$C$2:$C$5010,F$4) | G12: =SUMIFS('Lançamentos'!$L$2:$L$5010,'Lançamentos'!$A$2:$A$5010,"Insumos e papel",'Lançamentos'!$B$2:$B$5010,$A12,'Lançamentos'!$C$2:$C$5010,G$4) | H12: =SUMIFS('Lançamentos'!$L$2:$L$5010,'Lançamentos'!$A$2:$A$5010,"Insumos e papel",'Lançamentos'!$B$2:$B$5010,$A12,'Lançamentos'!$C$2:$C$5010,H$4) | I12: =SUMIFS('Lançamentos'!$L$2:$L$5010,'Lançamentos'!$A$2:$A$5010,"Insumos e papel",'Lançamentos'!$B$2:$B$5010,$A12,'Lançamentos'!$C$2:$C$5010,I$4) | J12: =SUMIFS('Lançamentos'!$L$2:$L$5010,'Lançamentos'!$A$2:$A$5010,"Insumos e papel",'Lançamentos'!$B$2:$B$5010,$A12,'Lançamentos'!$C$2:$C$5010,J$4) | K12: =SUM(B12:J12) | L12: =K12/K$51 | M12: =SUMIFS('Lançamentos'!$L$2:$L$5010,'Lançamentos'!$A$2:$A$5010,"Insumos e papel",'Lançamentos'!$B$2:$B$5010,$A12,'Lançamentos'!$C$2:$C$5010,"Antes de 2026")
A13: 2.01.94 Compra de Fita Adesiva | B13: =SUMIFS('Lançamentos'!$L$2:$L$5010,'Lançamentos'!$A$2:$A$5010,"Insumos e papel",'Lançamentos'!$B$2:$B$5010,$A13,'Lançamentos'!$C$2:$C$5010,B$4) | C13: =SUMIFS('Lançamentos'!$L$2:$L$5010,'Lançamentos'!$A$2:$A$5010,"Insumos e papel",'Lançamentos'!$B$2:$B$5010,$A13,'Lançamentos'!$C$2:$C$5010,C$4) | D13: =SUMIFS('Lançamentos'!$L$2:$L$5010,'Lançamentos'!$A$2:$A$5010,"Insumos e papel",'Lançamentos'!$B$2:$B$5010,$A13,'Lançamentos'!$C$2:$C$5010,D$4) | E13: =SUMIFS('Lançamentos'!$L$2:$L$5010,'Lançamentos'!$A$2:$A$5010,"Insumos e papel",'Lançamentos'!$B$2:$B$5010,$A13,'Lançamentos'!$C$2:$C$5010,E$4) | F13: =SUMIFS('Lançamentos'!$L$2:$L$5010,'Lançamentos'!$A$2:$A$5010,"Insumos e papel",'Lançamentos'!$B$2:$B$5010,$A13,'Lançamentos'!$C$2:$C$5010,F$4) | G13: =SUMIFS('Lançamentos'!$L$2:$L$5010,'Lançamentos'!$A$2:$A$5010,"Insumos e papel",'Lançamentos'!$B$2:$B$5010,$A13,'Lançamentos'!$C$2:$C$5010,G$4) | H13: =SUMIFS('Lançamentos'!$L$2:$L$5010,'Lançamentos'!$A$2:$A$5010,"Insumos e papel",'Lançamentos'!$B$2:$B$5010,$A13,'Lançamentos'!$C$2:$C$5010,H$4) | I13: =SUMIFS('Lançamentos'!$L$2:$L$5010,'Lançamentos'!$A$2:$A$5010,"Insumos e papel",'Lançamentos'!$B$2:$B$5010,$A13,'Lançamentos'!$C$2:$C$5010,I$4) | J13: =SUMIFS('Lançamentos'!$L$2:$L$5010,'Lançamentos'!$A$2:$A$5010,"Insumos e papel",'Lançamentos'!$B$2:$B$5010,$A13,'Lançamentos'!$C$2:$C$5010,J$4) | K13: =SUM(B13:J13) | L13: =K13/K$51 | M13: =SUMIFS('Lançamentos'!$L$2:$L$5010,'Lançamentos'!$A$2:$A$5010,"Insumos e papel",'Lançamentos'!$B$2:$B$5010,$A13,'Lançamentos'!$C$2:$C$5010,"Antes de 2026")
A14: 2.01.95 Compra de Etiqueta | B14: =SUMIFS('Lançamentos'!$L$2:$L$5010,'Lançamentos'!$A$2:$A$5010,"Insumos e papel",'Lançamentos'!$B$2:$B$5010,$A14,'Lançamentos'!$C$2:$C$5010,B$4) | C14: =SUMIFS('Lançamentos'!$L$2:$L$5010,'Lançamentos'!$A$2:$A$5010,"Insumos e papel",'Lançamentos'!$B$2:$B$5010,$A14,'Lançamentos'!$C$2:$C$5010,C$4) | D14: =SUMIFS('Lançamentos'!$L$2:$L$5010,'Lançamentos'!$A$2:$A$5010,"Insumos e papel",'Lançamentos'!$B$2:$B$5010,$A14,'Lançamentos'!$C$2:$C$5010,D$4) | E14: =SUMIFS('Lançamentos'!$L$2:$L$5010,'Lançamentos'!$A$2:$A$5010,"Insumos e papel",'Lançamentos'!$B$2:$B$5010,$A14,'Lançamentos'!$C$2:$C$5010,E$4) | F14: =SUMIFS('Lançamentos'!$L$2:$L$5010,'Lançamentos'!$A$2:$A$5010,"Insumos e papel",'Lançamentos'!$B$2:$B$5010,$A14,'Lançamentos'!$C$2:$C$5010,F$4) | G14: =SUMIFS('Lançamentos'!$L$2:$L$5010,'Lançamentos'!$A$2:$A$5010,"Insumos e papel",'Lançamentos'!$B$2:$B$5010,$A14,'Lançamentos'!$C$2:$C$5010,G$4) | H14: =SUMIFS('Lançamentos'!$L$2:$L$5010,'Lançamentos'!$A$2:$A$5010,"Insumos e papel",'Lançamentos'!$B$2:$B$5010,$A14,'Lançamentos'!$C$2:$C$5010,H$4) | I14: =SUMIFS('Lançamentos'!$L$2:$L$5010,'Lançamentos'!$A$2:$A$5010,"Insumos e papel",'Lançamentos'!$B$2:$B$5010,$A14,'Lançamentos'!$C$2:$C$5010,I$4) | J14: =SUMIFS('Lançamentos'!$L$2:$L$5010,'Lançamentos'!$A$2:$A$5010,"Insumos e papel",'Lançamentos'!$B$2:$B$5010,$A14,'Lançamentos'!$C$2:$C$5010,J$4) | K14: =SUM(B14:J14) | L14: =K14/K$51 | M14: =SUMIFS('Lançamentos'!$L$2:$L$5010,'Lançamentos'!$A$2:$A$5010,"Insumos e papel",'Lançamentos'!$B$2:$B$5010,$A14,'Lançamentos'!$C$2:$C$5010,"Antes de 2026")
A15: 2.01.96 Compra de Cola | B15: =SUMIFS('Lançamentos'!$L$2:$L$5010,'Lançamentos'!$A$2:$A$5010,"Insumos e papel",'Lançamentos'!$B$2:$B$5010,$A15,'Lançamentos'!$C$2:$C$5010,B$4) | C15: =SUMIFS('Lançamentos'!$L$2:$L$5010,'Lançamentos'!$A$2:$A$5010,"Insumos e papel",'Lançamentos'!$B$2:$B$5010,$A15,'Lançamentos'!$C$2:$C$5010,C$4) | D15: =SUMIFS('Lançamentos'!$L$2:$L$5010,'Lançamentos'!$A$2:$A$5010,"Insumos e papel",'Lançamentos'!$B$2:$B$5010,$A15,'Lançamentos'!$C$2:$C$5010,D$4) | E15: =SUMIFS('Lançamentos'!$L$2:$L$5010,'Lançamentos'!$A$2:$A$5010,"Insumos e papel",'Lançamentos'!$B$2:$B$5010,$A15,'Lançamentos'!$C$2:$C$5010,E$4) | F15: =SUMIFS('Lançamentos'!$L$2:$L$5010,'Lançamentos'!$A$2:$A$5010,"Insumos e papel",'Lançamentos'!$B$2:$B$5010,$A15,'Lançamentos'!$C$2:$C$5010,F$4) | G15: =SUMIFS('Lançamentos'!$L$2:$L$5010,'Lançamentos'!$A$2:$A$5010,"Insumos e papel",'Lançamentos'!$B$2:$B$5010,$A15,'Lançamentos'!$C$2:$C$5010,G$4) | H15: =SUMIFS('Lançamentos'!$L$2:$L$5010,'Lançamentos'!$A$2:$A$5010,"Insumos e papel",'Lançamentos'!$B$2:$B$5010,$A15,'Lançamentos'!$C$2:$C$5010,H$4) | I15: =SUMIFS('Lançamentos'!$L$2:$L$5010,'Lançamentos'!$A$2:$A$5010,"Insumos e papel",'Lançamentos'!$B$2:$B$5010,$A15,'Lançamentos'!$C$2:$C$5010,I$4) | J15: =SUMIFS('Lançamentos'!$L$2:$L$5010,'Lançamentos'!$A$2:$A$5010,"Insumos e papel",'Lançamentos'!$B$2:$B$5010,$A15,'Lançamentos'!$C$2:$C$5010,J$4) | K15: =SUM(B15:J15) | L15: =K15/K$51 | M15: =SUMIFS('Lançamentos'!$L$2:$L$5010,'Lançamentos'!$A$2:$A$5010,"Insumos e papel",'Lançamentos'!$B$2:$B$5010,$A15,'Lançamentos'!$C$2:$C$5010,"Antes de 2026")
A16: 2.01.97 Compra de Clichê | B16: =SUMIFS('Lançamentos'!$L$2:$L$5010,'Lançamentos'!$A$2:$A$5010,"Insumos e papel",'Lançamentos'!$B$2:$B$5010,$A16,'Lançamentos'!$C$2:$C$5010,B$4) | C16: =SUMIFS('Lançamentos'!$L$2:$L$5010,'Lançamentos'!$A$2:$A$5010,"Insumos e papel",'Lançamentos'!$B$2:$B$5010,$A16,'Lançamentos'!$C$2:$C$5010,C$4) | D16: =SUMIFS('Lançamentos'!$L$2:$L$5010,'Lançamentos'!$A$2:$A$5010,"Insumos e papel",'Lançamentos'!$B$2:$B$5010,$A16,'Lançamentos'!$C$2:$C$5010,D$4) | E16: =SUMIFS('Lançamentos'!$L$2:$L$5010,'Lançamentos'!$A$2:$A$5010,"Insumos e papel",'Lançamentos'!$B$2:$B$5010,$A16,'Lançamentos'!$C$2:$C$5010,E$4) | F16: =SUMIFS('Lançamentos'!$L$2:$L$5010,'Lançamentos'!$A$2:$A$5010,"Insumos e papel",'Lançamentos'!$B$2:$B$5010,$A16,'Lançamentos'!$C$2:$C$5010,F$4) | G16: =SUMIFS('Lançamentos'!$L$2:$L$5010,'Lançamentos'!$A$2:$A$5010,"Insumos e papel",'Lançamentos'!$B$2:$B$5010,$A16,'Lançamentos'!$C$2:$C$5010,G$4) | H16: =SUMIFS('Lançamentos'!$L$2:$L$5010,'Lançamentos'!$A$2:$A$5010,"Insumos e papel",'Lançamentos'!$B$2:$B$5010,$A16,'Lançamentos'!$C$2:$C$5010,H$4) | I16: =SUMIFS('Lançamentos'!$L$2:$L$5010,'Lançamentos'!$A$2:$A$5010,"Insumos e papel",'Lançamentos'!$B$2:$B$5010,$A16,'Lançamentos'!$C$2:$C$5010,I$4) | J16: =SUMIFS('Lançamentos'!$L$2:$L$5010,'Lançamentos'!$A$2:$A$5010,"Insumos e papel",'Lançamentos'!$B$2:$B$5010,$A16,'Lançamentos'!$C$2:$C$5010,J$4) | K16: =SUM(B16:J16) | L16: =K16/K$51 | M16: =SUMIFS('Lançamentos'!$L$2:$L$5010,'Lançamentos'!$A$2:$A$5010,"Insumos e papel",'Lançamentos'!$B$2:$B$5010,$A16,'Lançamentos'!$C$2:$C$5010,"Antes de 2026")
A17: 2.01.99 Compra de Caixas | B17: =SUMIFS('Lançamentos'!$L$2:$L$5010,'Lançamentos'!$A$2:$A$5010,"Insumos e papel",'Lançamentos'!$B$2:$B$5010,$A17,'Lançamentos'!$C$2:$C$5010,B$4) | C17: =SUMIFS('Lançamentos'!$L$2:$L$5010,'Lançamentos'!$A$2:$A$5010,"Insumos e papel",'Lançamentos'!$B$2:$B$5010,$A17,'Lançamentos'!$C$2:$C$5010,C$4) | D17: =SUMIFS('Lançamentos'!$L$2:$L$5010,'Lançamentos'!$A$2:$A$5010,"Insumos e papel",'Lançamentos'!$B$2:$B$5010,$A17,'Lançamentos'!$C$2:$C$5010,D$4) | E17: =SUMIFS('Lançamentos'!$L$2:$L$5010,'Lançamentos'!$A$2:$A$5010,"Insumos e papel",'Lançamentos'!$B$2:$B$5010,$A17,'Lançamentos'!$C$2:$C$5010,E$4) | F17: =SUMIFS('Lançamentos'!$L$2:$L$5010,'Lançamentos'!$A$2:$A$5010,"Insumos e papel",'Lançamentos'!$B$2:$B$5010,$A17,'Lançamentos'!$C$2:$C$5010,F$4) | G17: =SUMIFS('Lançamentos'!$L$2:$L$5010,'Lançamentos'!$A$2:$A$5010,"Insumos e papel",'Lançamentos'!$B$2:$B$5010,$A17,'Lançamentos'!$C$2:$C$5010,G$4) | H17: =SUMIFS('Lançamentos'!$L$2:$L$5010,'Lançamentos'!$A$2:$A$5010,"Insumos e papel",'Lançamentos'!$B$2:$B$5010,$A17,'Lançamentos'!$C$2:$C$5010,H$4) | I17: =SUMIFS('Lançamentos'!$L$2:$L$5010,'Lançamentos'!$A$2:$A$5010,"Insumos e papel",'Lançamentos'!$B$2:$B$5010,$A17,'Lançamentos'!$C$2:$C$5010,I$4) | J17: =SUMIFS('Lançamentos'!$L$2:$L$5010,'Lançamentos'!$A$2:$A$5010,"Insumos e papel",'Lançamentos'!$B$2:$B$5010,$A17,'Lançamentos'!$C$2:$C$5010,J$4) | K17: =SUM(B17:J17) | L17: =K17/K$51 | M17: =SUMIFS('Lançamentos'!$L$2:$L$5010,'Lançamentos'!$A$2:$A$5010,"Insumos e papel",'Lançamentos'!$B$2:$B$5010,$A17,'Lançamentos'!$C$2:$C$5010,"Antes de 2026")
A18: Uso e consumo | B18: =SUM(B19:B26) | C18: =SUM(C19:C26) | D18: =SUM(D19:D26) | E18: =SUM(E19:E26) | F18: =SUM(F19:F26) | G18: =SUM(G19:G26) | H18: =SUM(H19:H26) | I18: =SUM(I19:I26) | ... K18: =SUM(K19:K26) | L18: =K18/K$51 | M18: =SUM(M19:M26)
A19: 2.01.85 Compra de Uso e Consumo | B19: =SUMIFS('Lançamentos'!$L$2:$L$5010,'Lançamentos'!$A$2:$A$5010,"Uso e consumo",'Lançamentos'!$B$2:$B$5010,$A19,'Lançamentos'!$C$2:$C$5010,B$4) | C19: =SUMIFS('Lançamentos'!$L$2:$L$5010,'Lançamentos'!$A$2:$A$5010,"Uso e consumo",'Lançamentos'!$B$2:$B$5010,$A19,'Lançamentos'!$C$2:$C$5010,C$4) | D19: =SUMIFS('Lançamentos'!$L$2:$L$5010,'Lançamentos'!$A$2:$A$5010,"Uso e consumo",'Lançamentos'!$B$2:$B$5010,$A19,'Lançamentos'!$C$2:$C$5010,D$4) | E19: =SUMIFS('Lançamentos'!$L$2:$L$5010,'Lançamentos'!$A$2:$A$5010,"Uso e consumo",'Lançamentos'!$B$2:$B$5010,$A19,'Lançamentos'!$C$2:$C$5010,E$4) | F19: =SUMIFS('Lançamentos'!$L$2:$L$5010,'Lançamentos'!$A$2:$A$5010,"Uso e consumo",'Lançamentos'!$B$2:$B$5010,$A19,'Lançamentos'!$C$2:$C$5010,F$4) | G19: =SUMIFS('Lançamentos'!$L$2:$L$5010,'Lançamentos'!$A$2:$A$5010,"Uso e consumo",'Lançamentos'!$B$2:$B$5010,$A19,'Lançamentos'!$C$2:$C$5010,G$4) | H19: =SUMIFS('Lançamentos'!$L$2:$L$5010,'Lançamentos'!$A$2:$A$5010,"Uso e consumo",'Lançamentos'!$B$2:$B$5010,$A19,'Lançamentos'!$C$2:$C$5010,H$4) | I19: =SUMIFS('Lançamentos'!$L$2:$L$5010,'Lançamentos'!$A$2:$A$5010,"Uso e consumo",'Lançamentos'!$B$2:$B$5010,$A19,'Lançamentos'!$C$2:$C$5010,I$4) | J19: =SUMIFS('Lançamentos'!$L$2:$L$5010,'Lançamentos'!$A$2:$A$5010,"Uso e consumo",'Lançamentos'!$B$2:$B$5010,$A19,'Lançamentos'!$C$2:$C$5010,J$4) | K19: =SUM(B19:J19) | L19: =K19/K$51 | M19: =SUMIFS('Lançamentos'!$L$2:$L$5010,'Lançamentos'!$A$2:$A$5010,"Uso e consumo",'Lançamentos'!$B$2:$B$5010,$A19,'Lançamentos'!$C$2:$C$5010,"Antes de 2026")
A20: 2.01.87 Compra de Peças de Máquinas | B20: =SUMIFS('Lançamentos'!$L$2:$L$5010,'Lançamentos'!$A$2:$A$5010,"Uso e consumo",'Lançamentos'!$B$2:$B$5010,$A20,'Lançamentos'!$C$2:$C$5010,B$4) | C20: =SUMIFS('Lançamentos'!$L$2:$L$5010,'Lançamentos'!$A$2:$A$5010,"Uso e consumo",'Lançamentos'!$B$2:$B$5010,$A20,'Lançamentos'!$C$2:$C$5010,C$4) | D20: =SUMIFS('Lançamentos'!$L$2:$L$5010,'Lançamentos'!$A$2:$A$5010,"Uso e consumo",'Lançamentos'!$B$2:$B$5010,$A20,'Lançamentos'!$C$2:$C$5010,D$4) | E20: =SUMIFS('Lançamentos'!$L$2:$L$5010,'Lançamentos'!$A$2:$A$5010,"Uso e consumo",'Lançamentos'!$B$2:$B$5010,$A20,'Lançamentos'!$C$2:$C$5010,E$4) | F20: =SUMIFS('Lançamentos'!$L$2:$L$5010,'Lançamentos'!$A$2:$A$5010,"Uso e consumo",'Lançamentos'!$B$2:$B$5010,$A20,'Lançamentos'!$C$2:$C$5010,F$4) | G20: =SUMIFS('Lançamentos'!$L$2:$L$5010,'Lançamentos'!$A$2:$A$5010,"Uso e consumo",'Lançamentos'!$B$2:$B$5010,$A20,'Lançamentos'!$C$2:$C$5010,G$4) | H20: =SUMIFS('Lançamentos'!$L$2:$L$5010,'Lançamentos'!$A$2:$A$5010,"Uso e consumo",'Lançamentos'!$B$2:$B$5010,$A20,'Lançamentos'!$C$2:$C$5010,H$4) | I20: =SUMIFS('Lançamentos'!$L$2:$L$5010,'Lançamentos'!$A$2:$A$5010,"Uso e consumo",'Lançamentos'!$B$2:$B$5010,$A20,'Lançamentos'!$C$2:$C$5010,I$4) | J20: =SUMIFS('Lançamentos'!$L$2:$L$5010,'Lançamentos'!$A$2:$A$5010,"Uso e consumo",'Lançamentos'!$B$2:$B$5010,$A20,'Lançamentos'!$C$2:$C$5010,J$4) | K20: =SUM(B20:J20) | L20: =K20/K$51 | M20: =SUMIFS('Lançamentos'!$L$2:$L$5010,'Lançamentos'!$A$2:$A$5010,"Uso e consumo",'Lançamentos'!$B$2:$B$5010,$A20,'Lançamentos'!$C$2:$C$5010,"Antes de 2026")
A21: 2.03.88 Compra de Fardamento | B21: =SUMIFS('Lançamentos'!$L$2:$L$5010,'Lançamentos'!$A$2:$A$5010,"Uso e consumo",'Lançamentos'!$B$2:$B$5010,$A21,'Lançamentos'!$C$2:$C$5010,B$4) | C21: =SUMIFS('Lançamentos'!$L$2:$L$5010,'Lançamentos'!$A$2:$A$5010,"Uso e consumo",'Lançamentos'!$B$2:$B$5010,$A21,'Lançamentos'!$C$2:$C$5010,C$4) | D21: =SUMIFS('Lançamentos'!$L$2:$L$5010,'Lançamentos'!$A$2:$A$5010,"Uso e consumo",'Lançamentos'!$B$2:$B$5010,$A21,'Lançamentos'!$C$2:$C$5010,D$4) | E21: =SUMIFS('Lançamentos'!$L$2:$L$5010,'Lançamentos'!$A$2:$A$5010,"Uso e consumo",'Lançamentos'!$B$2:$B$5010,$A21,'Lançamentos'!$C$2:$C$5010,E$4) | F21: =SUMIFS('Lançamentos'!$L$2:$L$5010,'Lançamentos'!$A$2:$A$5010,"Uso e consumo",'Lançamentos'!$B$2:$B$5010,$A21,'Lançamentos'!$C$2:$C$5010,F$4) | G21: =SUMIFS('Lançamentos'!$L$2:$L$5010,'Lançamentos'!$A$2:$A$5010,"Uso e consumo",'Lançamentos'!$B$2:$B$5010,$A21,'Lançamentos'!$C$2:$C$5010,G$4) | H21: =SUMIFS('Lançamentos'!$L$2:$L$5010,'Lançamentos'!$A$2:$A$5010,"Uso e consumo",'Lançamentos'!$B$2:$B$5010,$A21,'Lançamentos'!$C$2:$C$5010,H$4) | I21: =SUMIFS('Lançamentos'!$L$2:$L$5010,'Lançamentos'!$A$2:$A$5010,"Uso e consumo",'Lançamentos'!$B$2:$B$5010,$A21,'Lançamentos'!$C$2:$C$5010,I$4) | J21: =SUMIFS('Lançamentos'!$L$2:$L$5010,'Lançamentos'!$A$2:$A$5010,"Uso e consumo",'Lançamentos'!$B$2:$B$5010,$A21,'Lançamentos'!$C$2:$C$5010,J$4) | K21: =SUM(B21:J21) | L21: =K21/K$51 | M21: =SUMIFS('Lançamentos'!$L$2:$L$5010,'Lançamentos'!$A$2:$A$5010,"Uso e consumo",'Lançamentos'!$B$2:$B$5010,$A21,'Lançamentos'!$C$2:$C$5010,"Antes de 2026")
A22: 2.03.90 Compra de EPI | B22: =SUMIFS('Lançamentos'!$L$2:$L$5010,'Lançamentos'!$A$2:$A$5010,"Uso e consumo",'Lançamentos'!$B$2:$B$5010,$A22,'Lançamentos'!$C$2:$C$5010,B$4) | C22: =SUMIFS('Lançamentos'!$L$2:$L$5010,'Lançamentos'!$A$2:$A$5010,"Uso e consumo",'Lançamentos'!$B$2:$B$5010,$A22,'Lançamentos'!$C$2:$C$5010,C$4) | D22: =SUMIFS('Lançamentos'!$L$2:$L$5010,'Lançamentos'!$A$2:$A$5010,"Uso e consumo",'Lançamentos'!$B$2:$B$5010,$A22,'Lançamentos'!$C$2:$C$5010,D$4) | E22: =SUMIFS('Lançamentos'!$L$2:$L$5010,'Lançamentos'!$A$2:$A$5010,"Uso e consumo",'Lançamentos'!$B$2:$B$5010,$A22,'Lançamentos'!$C$2:$C$5010,E$4) | F22: =SUMIFS('Lançamentos'!$L$2:$L$5010,'Lançamentos'!$A$2:$A$5010,"Uso e consumo",'Lançamentos'!$B$2:$B$5010,$A22,'Lançamentos'!$C$2:$C$5010,F$4) | G22: =SUMIFS('Lançamentos'!$L$2:$L$5010,'Lançamentos'!$A$2:$A$5010,"Uso e consumo",'Lançamentos'!$B$2:$B$5010,$A22,'Lançamentos'!$C$2:$C$5010,G$4) | H22: =SUMIFS('Lançamentos'!$L$2:$L$5010,'Lançamentos'!$A$2:$A$5010,"Uso e consumo",'Lançamentos'!$B$2:$B$5010,$A22,'Lançamentos'!$C$2:$C$5010,H$4) | I22: =SUMIFS('Lançamentos'!$L$2:$L$5010,'Lançamentos'!$A$2:$A$5010,"Uso e consumo",'Lançamentos'!$B$2:$B$5010,$A22,'Lançamentos'!$C$2:$C$5010,I$4) | J22: =SUMIFS('Lançamentos'!$L$2:$L$5010,'Lançamentos'!$A$2:$A$5010,"Uso e consumo",'Lançamentos'!$B$2:$B$5010,$A22,'Lançamentos'!$C$2:$C$5010,J$4) | K22: =SUM(B22:J22) | L22: =K22/K$51 | M22: =SUMIFS('Lançamentos'!$L$2:$L$5010,'Lançamentos'!$A$2:$A$5010,"Uso e consumo",'Lançamentos'!$B$2:$B$5010,$A22,'Lançamentos'!$C$2:$C$5010,"Antes de 2026")
A23: 2.04.06 Material de Escritório | B23: =SUMIFS('Lançamentos'!$L$2:$L$5010,'Lançamentos'!$A$2:$A$5010,"Uso e consumo",'Lançamentos'!$B$2:$B$5010,$A23,'Lançamentos'!$C$2:$C$5010,B$4) | C23: =SUMIFS('Lançamentos'!$L$2:$L$5010,'Lançamentos'!$A$2:$A$5010,"Uso e consumo",'Lançamentos'!$B$2:$B$5010,$A23,'Lançamentos'!$C$2:$C$5010,C$4) | D23: =SUMIFS('Lançamentos'!$L$2:$L$5010,'Lançamentos'!$A$2:$A$5010,"Uso e consumo",'Lançamentos'!$B$2:$B$5010,$A23,'Lançamentos'!$C$2:$C$5010,D$4) | E23: =SUMIFS('Lançamentos'!$L$2:$L$5010,'Lançamentos'!$A$2:$A$5010,"Uso e consumo",'Lançamentos'!$B$2:$B$5010,$A23,'Lançamentos'!$C$2:$C$5010,E$4) | F23: =SUMIFS('Lançamentos'!$L$2:$L$5010,'Lançamentos'!$A$2:$A$5010,"Uso e consumo",'Lançamentos'!$B$2:$B$5010,$A23,'Lançamentos'!$C$2:$C$5010,F$4) | G23: =SUMIFS('Lançamentos'!$L$2:$L$5010,'Lançamentos'!$A$2:$A$5010,"Uso e consumo",'Lançamentos'!$B$2:$B$5010,$A23,'Lançamentos'!$C$2:$C$5010,G$4) | H23: =SUMIFS('Lançamentos'!$L$2:$L$5010,'Lançamentos'!$A$2:$A$5010,"Uso e consumo",'Lançamentos'!$B$2:$B$5010,$A23,'Lançamentos'!$C$2:$C$5010,H$4) | I23: =SUMIFS('Lançamentos'!$L$2:$L$5010,'Lançamentos'!$A$2:$A$5010,"Uso e consumo",'Lançamentos'!$B$2:$B$5010,$A23,'Lançamentos'!$C$2:$C$5010,I$4) | J23: =SUMIFS('Lançamentos'!$L$2:$L$5010,'Lançamentos'!$A$2:$A$5010,"Uso e consumo",'Lançamentos'!$B$2:$B$5010,$A23,'Lançamentos'!$C$2:$C$5010,J$4) | K23: =SUM(B23:J23) | L23: =K23/K$51 | M23: =SUMIFS('Lançamentos'!$L$2:$L$5010,'Lançamentos'!$A$2:$A$5010,"Uso e consumo",'Lançamentos'!$B$2:$B$5010,$A23,'Lançamentos'!$C$2:$C$5010,"Antes de 2026")
A24: 2.04.91 Compra de Material de Limpeza | B24: =SUMIFS('Lançamentos'!$L$2:$L$5010,'Lançamentos'!$A$2:$A$5010,"Uso e consumo",'Lançamentos'!$B$2:$B$5010,$A24,'Lançamentos'!$C$2:$C$5010,B$4) | C24: =SUMIFS('Lançamentos'!$L$2:$L$5010,'Lançamentos'!$A$2:$A$5010,"Uso e consumo",'Lançamentos'!$B$2:$B$5010,$A24,'Lançamentos'!$C$2:$C$5010,C$4) | D24: =SUMIFS('Lançamentos'!$L$2:$L$5010,'Lançamentos'!$A$2:$A$5010,"Uso e consumo",'Lançamentos'!$B$2:$B$5010,$A24,'Lançamentos'!$C$2:$C$5010,D$4) | E24: =SUMIFS('Lançamentos'!$L$2:$L$5010,'Lançamentos'!$A$2:$A$5010,"Uso e consumo",'Lançamentos'!$B$2:$B$5010,$A24,'Lançamentos'!$C$2:$C$5010,E$4) | F24: =SUMIFS('Lançamentos'!$L$2:$L$5010,'Lançamentos'!$A$2:$A$5010,"Uso e consumo",'Lançamentos'!$B$2:$B$5010,$A24,'Lançamentos'!$C$2:$C$5010,F$4) | G24: =SUMIFS('Lançamentos'!$L$2:$L$5010,'Lançamentos'!$A$2:$A$5010,"Uso e consumo",'Lançamentos'!$B$2:$B$5010,$A24,'Lançamentos'!$C$2:$C$5010,G$4) | H24: =SUMIFS('Lançamentos'!$L$2:$L$5010,'Lançamentos'!$A$2:$A$5010,"Uso e consumo",'Lançamentos'!$B$2:$B$5010,$A24,'Lançamentos'!$C$2:$C$5010,H$4) | I24: =SUMIFS('Lançamentos'!$L$2:$L$5010,'Lançamentos'!$A$2:$A$5010,"Uso e consumo",'Lançamentos'!$B$2:$B$5010,$A24,'Lançamentos'!$C$2:$C$5010,I$4) | J24: =SUMIFS('Lançamentos'!$L$2:$L$5010,'Lançamentos'!$A$2:$A$5010,"Uso e consumo",'Lançamentos'!$B$2:$B$5010,$A24,'Lançamentos'!$C$2:$C$5010,J$4) | K24: =SUM(B24:J24) | L24: =K24/K$51 | M24: =SUMIFS('Lançamentos'!$L$2:$L$5010,'Lançamentos'!$A$2:$A$5010,"Uso e consumo",'Lançamentos'!$B$2:$B$5010,$A24,'Lançamentos'!$C$2:$C$5010,"Antes de 2026")
A25: 2.04.95 Copa e Cozinha | B25: =SUMIFS('Lançamentos'!$L$2:$L$5010,'Lançamentos'!$A$2:$A$5010,"Uso e consumo",'Lançamentos'!$B$2:$B$5010,$A25,'Lançamentos'!$C$2:$C$5010,B$4) | C25: =SUMIFS('Lançamentos'!$L$2:$L$5010,'Lançamentos'!$A$2:$A$5010,"Uso e consumo",'Lançamentos'!$B$2:$B$5010,$A25,'Lançamentos'!$C$2:$C$5010,C$4) | D25: =SUMIFS('Lançamentos'!$L$2:$L$5010,'Lançamentos'!$A$2:$A$5010,"Uso e consumo",'Lançamentos'!$B$2:$B$5010,$A25,'Lançamentos'!$C$2:$C$5010,D$4) | E25: =SUMIFS('Lançamentos'!$L$2:$L$5010,'Lançamentos'!$A$2:$A$5010,"Uso e consumo",'Lançamentos'!$B$2:$B$5010,$A25,'Lançamentos'!$C$2:$C$5010,E$4) | F25: =SUMIFS('Lançamentos'!$L$2:$L$5010,'Lançamentos'!$A$2:$A$5010,"Uso e consumo",'Lançamentos'!$B$2:$B$5010,$A25,'Lançamentos'!$C$2:$C$5010,F$4) | G25: =SUMIFS('Lançamentos'!$L$2:$L$5010,'Lançamentos'!$A$2:$A$5010,"Uso e consumo",'Lançamentos'!$B$2:$B$5010,$A25,'Lançamentos'!$C$2:$C$5010,G$4) | H25: =SUMIFS('Lançamentos'!$L$2:$L$5010,'Lançamentos'!$A$2:$A$5010,"Uso e consumo",'Lançamentos'!$B$2:$B$5010,$A25,'Lançamentos'!$C$2:$C$5010,H$4) | I25: =SUMIFS('Lançamentos'!$L$2:$L$5010,'Lançamentos'!$A$2:$A$5010,"Uso e consumo",'Lançamentos'!$B$2:$B$5010,$A25,'Lançamentos'!$C$2:$C$5010,I$4) | J25: =SUMIFS('Lançamentos'!$L$2:$L$5010,'Lançamentos'!$A$2:$A$5010,"Uso e consumo",'Lançamentos'!$B$2:$B$5010,$A25,'Lançamentos'!$C$2:$C$5010,J$4) | K25: =SUM(B25:J25) | L25: =K25/K$51 | M25: =SUMIFS('Lançamentos'!$L$2:$L$5010,'Lançamentos'!$A$2:$A$5010,"Uso e consumo",'Lançamentos'!$B$2:$B$5010,$A25,'Lançamentos'!$C$2:$C$5010,"Antes de 2026")
A26: 2.04.96 Bens de Pequeno Valor | B26: =SUMIFS('Lançamentos'!$L$2:$L$5010,'Lançamentos'!$A$2:$A$5010,"Uso e consumo",'Lançamentos'!$B$2:$B$5010,$A26,'Lançamentos'!$C$2:$C$5010,B$4) | C26: =SUMIFS('Lançamentos'!$L$2:$L$5010,'Lançamentos'!$A$2:$A$5010,"Uso e consumo",'Lançamentos'!$B$2:$B$5010,$A26,'Lançamentos'!$C$2:$C$5010,C$4) | D26: =SUMIFS('Lançamentos'!$L$2:$L$5010,'Lançamentos'!$A$2:$A$5010,"Uso e consumo",'Lançamentos'!$B$2:$B$5010,$A26,'Lançamentos'!$C$2:$C$5010,D$4) | E26: =SUMIFS('Lançamentos'!$L$2:$L$5010,'Lançamentos'!$A$2:$A$5010,"Uso e consumo",'Lançamentos'!$B$2:$B$5010,$A26,'Lançamentos'!$C$2:$C$5010,E$4) | F26: =SUMIFS('Lançamentos'!$L$2:$L$5010,'Lançamentos'!$A$2:$A$5010,"Uso e consumo",'Lançamentos'!$B$2:$B$5010,$A26,'Lançamentos'!$C$2:$C$5010,F$4) | G26: =SUMIFS('Lançamentos'!$L$2:$L$5010,'Lançamentos'!$A$2:$A$5010,"Uso e consumo",'Lançamentos'!$B$2:$B$5010,$A26,'Lançamentos'!$C$2:$C$5010,G$4) | H26: =SUMIFS('Lançamentos'!$L$2:$L$5010,'Lançamentos'!$A$2:$A$5010,"Uso e consumo",'Lançamentos'!$B$2:$B$5010,$A26,'Lançamentos'!$C$2:$C$5010,H$4) | I26: =SUMIFS('Lançamentos'!$L$2:$L$5010,'Lançamentos'!$A$2:$A$5010,"Uso e consumo",'Lançamentos'!$B$2:$B$5010,$A26,'Lançamentos'!$C$2:$C$5010,I$4) | J26: =SUMIFS('Lançamentos'!$L$2:$L$5010,'Lançamentos'!$A$2:$A$5010,"Uso e consumo",'Lançamentos'!$B$2:$B$5010,$A26,'Lançamentos'!$C$2:$C$5010,J$4) | K26: =SUM(B26:J26) | L26: =K26/K$51 | M26: =SUMIFS('Lançamentos'!$L$2:$L$5010,'Lançamentos'!$A$2:$A$5010,"Uso e consumo",'Lançamentos'!$B$2:$B$5010,$A26,'Lançamentos'!$C$2:$C$5010,"Antes de 2026")
A27: Frete de compra | B27: =SUM(B28:B34) | C27: =SUM(C28:C34) | D27: =SUM(D28:D34) | E27: =SUM(E28:E34) | F27: =SUM(F28:F34) | G27: =SUM(G28:G34) | H27: =SUM(H28:H34) | I27: =SUM(I28:I34) | ... K27: =SUM(K28:K34) | L27: =K27/K$51 | M27: =SUM(M28:M34)
A28: 1.01.01 Venda de Mercadoria Fabricadas | B28: =SUMIFS('Lançamentos'!$L$2:$L$5010,'Lançamentos'!$A$2:$A$5010,"Frete de compra",'Lançamentos'!$B$2:$B$5010,$A28,'Lançamentos'!$C$2:$C$5010,B$4) | C28: =SUMIFS('Lançamentos'!$L$2:$L$5010,'Lançamentos'!$A$2:$A$5010,"Frete de compra",'Lançamentos'!$B$2:$B$5010,$A28,'Lançamentos'!$C$2:$C$5010,C$4) | D28: =SUMIFS('Lançamentos'!$L$2:$L$5010,'Lançamentos'!$A$2:$A$5010,"Frete de compra",'Lançamentos'!$B$2:$B$5010,$A28,'Lançamentos'!$C$2:$C$5010,D$4) | E28: =SUMIFS('Lançamentos'!$L$2:$L$5010,'Lançamentos'!$A$2:$A$5010,"Frete de compra",'Lançamentos'!$B$2:$B$5010,$A28,'Lançamentos'!$C$2:$C$5010,E$4) | F28: =SUMIFS('Lançamentos'!$L$2:$L$5010,'Lançamentos'!$A$2:$A$5010,"Frete de compra",'Lançamentos'!$B$2:$B$5010,$A28,'Lançamentos'!$C$2:$C$5010,F$4) | G28: =SUMIFS('Lançamentos'!$L$2:$L$5010,'Lançamentos'!$A$2:$A$5010,"Frete de compra",'Lançamentos'!$B$2:$B$5010,$A28,'Lançamentos'!$C$2:$C$5010,G$4) | H28: =SUMIFS('Lançamentos'!$L$2:$L$5010,'Lançamentos'!$A$2:$A$5010,"Frete de compra",'Lançamentos'!$B$2:$B$5010,$A28,'Lançamentos'!$C$2:$C$5010,H$4) | I28: =SUMIFS('Lançamentos'!$L$2:$L$5010,'Lançamentos'!$A$2:$A$5010,"Frete de compra",'Lançamentos'!$B$2:$B$5010,$A28,'Lançamentos'!$C$2:$C$5010,I$4) | J28: =SUMIFS('Lançamentos'!$L$2:$L$5010,'Lançamentos'!$A$2:$A$5010,"Frete de compra",'Lançamentos'!$B$2:$B$5010,$A28,'Lançamentos'!$C$2:$C$5010,J$4) | K28: =SUM(B28:J28) | L28: =K28/K$51 | M28: =SUMIFS('Lançamentos'!$L$2:$L$5010,'Lançamentos'!$A$2:$A$5010,"Frete de compra",'Lançamentos'!$B$2:$B$5010,$A28,'Lançamentos'!$C$2:$C$5010,"Antes de 2026")
A29: 2.01.01 Frete Galpão Produto Acabado | B29: =SUMIFS('Lançamentos'!$L$2:$L$5010,'Lançamentos'!$A$2:$A$5010,"Frete de compra",'Lançamentos'!$B$2:$B$5010,$A29,'Lançamentos'!$C$2:$C$5010,B$4) | C29: =SUMIFS('Lançamentos'!$L$2:$L$5010,'Lançamentos'!$A$2:$A$5010,"Frete de compra",'Lançamentos'!$B$2:$B$5010,$A29,'Lançamentos'!$C$2:$C$5010,C$4) | D29: =SUMIFS('Lançamentos'!$L$2:$L$5010,'Lançamentos'!$A$2:$A$5010,"Frete de compra",'Lançamentos'!$B$2:$B$5010,$A29,'Lançamentos'!$C$2:$C$5010,D$4) | E29: =SUMIFS('Lançamentos'!$L$2:$L$5010,'Lançamentos'!$A$2:$A$5010,"Frete de compra",'Lançamentos'!$B$2:$B$5010,$A29,'Lançamentos'!$C$2:$C$5010,E$4) | F29: =SUMIFS('Lançamentos'!$L$2:$L$5010,'Lançamentos'!$A$2:$A$5010,"Frete de compra",'Lançamentos'!$B$2:$B$5010,$A29,'Lançamentos'!$C$2:$C$5010,F$4) | G29: =SUMIFS('Lançamentos'!$L$2:$L$5010,'Lançamentos'!$A$2:$A$5010,"Frete de compra",'Lançamentos'!$B$2:$B$5010,$A29,'Lançamentos'!$C$2:$C$5010,G$4) | H29: =SUMIFS('Lançamentos'!$L$2:$L$5010,'Lançamentos'!$A$2:$A$5010,"Frete de compra",'Lançamentos'!$B$2:$B$5010,$A29,'Lançamentos'!$C$2:$C$5010,H$4) | I29: =SUMIFS('Lançamentos'!$L$2:$L$5010,'Lançamentos'!$A$2:$A$5010,"Frete de compra",'Lançamentos'!$B$2:$B$5010,$A29,'Lançamentos'!$C$2:$C$5010,I$4) | J29: =SUMIFS('Lançamentos'!$L$2:$L$5010,'Lançamentos'!$A$2:$A$5010,"Frete de compra",'Lançamentos'!$B$2:$B$5010,$A29,'Lançamentos'!$C$2:$C$5010,J$4) | K29: =SUM(B29:J29) | L29: =K29/K$51 | M29: =SUMIFS('Lançamentos'!$L$2:$L$5010,'Lançamentos'!$A$2:$A$5010,"Frete de compra",'Lançamentos'!$B$2:$B$5010,$A29,'Lançamentos'!$C$2:$C$5010,"Antes de 2026")
A30: 2.01.02 Frete sobre Vendas | B30: =SUMIFS('Lançamentos'!$L$2:$L$5010,'Lançamentos'!$A$2:$A$5010,"Frete de compra",'Lançamentos'!$B$2:$B$5010,$A30,'Lançamentos'!$C$2:$C$5010,B$4) | C30: =SUMIFS('Lançamentos'!$L$2:$L$5010,'Lançamentos'!$A$2:$A$5010,"Frete de compra",'Lançamentos'!$B$2:$B$5010,$A30,'Lançamentos'!$C$2:$C$5010,C$4) | D30: =SUMIFS('Lançamentos'!$L$2:$L$5010,'Lançamentos'!$A$2:$A$5010,"Frete de compra",'Lançamentos'!$B$2:$B$5010,$A30,'Lançamentos'!$C$2:$C$5010,D$4) | E30: =SUMIFS('Lançamentos'!$L$2:$L$5010,'Lançamentos'!$A$2:$A$5010,"Frete de compra",'Lançamentos'!$B$2:$B$5010,$A30,'Lançamentos'!$C$2:$C$5010,E$4) | F30: =SUMIFS('Lançamentos'!$L$2:$L$5010,'Lançamentos'!$A$2:$A$5010,"Frete de compra",'Lançamentos'!$B$2:$B$5010,$A30,'Lançamentos'!$C$2:$C$5010,F$4) | G30: =SUMIFS('Lançamentos'!$L$2:$L$5010,'Lançamentos'!$A$2:$A$5010,"Frete de compra",'Lançamentos'!$B$2:$B$5010,$A30,'Lançamentos'!$C$2:$C$5010,G$4) | H30: =SUMIFS('Lançamentos'!$L$2:$L$5010,'Lançamentos'!$A$2:$A$5010,"Frete de compra",'Lançamentos'!$B$2:$B$5010,$A30,'Lançamentos'!$C$2:$C$5010,H$4) | I30: =SUMIFS('Lançamentos'!$L$2:$L$5010,'Lançamentos'!$A$2:$A$5010,"Frete de compra",'Lançamentos'!$B$2:$B$5010,$A30,'Lançamentos'!$C$2:$C$5010,I$4) | J30: =SUMIFS('Lançamentos'!$L$2:$L$5010,'Lançamentos'!$A$2:$A$5010,"Frete de compra",'Lançamentos'!$B$2:$B$5010,$A30,'Lançamentos'!$C$2:$C$5010,J$4) | K30: =SUM(B30:J30) | L30: =K30/K$51 | M30: =SUMIFS('Lançamentos'!$L$2:$L$5010,'Lançamentos'!$A$2:$A$5010,"Frete de compra",'Lançamentos'!$B$2:$B$5010,$A30,'Lançamentos'!$C$2:$C$5010,"Antes de 2026")
A31: 2.01.82 Estadia - Cabotagem | B31: =SUMIFS('Lançamentos'!$L$2:$L$5010,'Lançamentos'!$A$2:$A$5010,"Frete de compra",'Lançamentos'!$B$2:$B$5010,$A31,'Lançamentos'!$C$2:$C$5010,B$4) | C31: =SUMIFS('Lançamentos'!$L$2:$L$5010,'Lançamentos'!$A$2:$A$5010,"Frete de compra",'Lançamentos'!$B$2:$B$5010,$A31,'Lançamentos'!$C$2:$C$5010,C$4) | D31: =SUMIFS('Lançamentos'!$L$2:$L$5010,'Lançamentos'!$A$2:$A$5010,"Frete de compra",'Lançamentos'!$B$2:$B$5010,$A31,'Lançamentos'!$C$2:$C$5010,D$4) | E31: =SUMIFS('Lançamentos'!$L$2:$L$5010,'Lançamentos'!$A$2:$A$5010,"Frete de compra",'Lançamentos'!$B$2:$B$5010,$A31,'Lançamentos'!$C$2:$C$5010,E$4) | F31: =SUMIFS('Lançamentos'!$L$2:$L$5010,'Lançamentos'!$A$2:$A$5010,"Frete de compra",'Lançamentos'!$B$2:$B$5010,$A31,'Lançamentos'!$C$2:$C$5010,F$4) | G31: =SUMIFS('Lançamentos'!$L$2:$L$5010,'Lançamentos'!$A$2:$A$5010,"Frete de compra",'Lançamentos'!$B$2:$B$5010,$A31,'Lançamentos'!$C$2:$C$5010,G$4) | H31: =SUMIFS('Lançamentos'!$L$2:$L$5010,'Lançamentos'!$A$2:$A$5010,"Frete de compra",'Lançamentos'!$B$2:$B$5010,$A31,'Lançamentos'!$C$2:$C$5010,H$4) | I31: =SUMIFS('Lançamentos'!$L$2:$L$5010,'Lançamentos'!$A$2:$A$5010,"Frete de compra",'Lançamentos'!$B$2:$B$5010,$A31,'Lançamentos'!$C$2:$C$5010,I$4) | J31: =SUMIFS('Lançamentos'!$L$2:$L$5010,'Lançamentos'!$A$2:$A$5010,"Frete de compra",'Lançamentos'!$B$2:$B$5010,$A31,'Lançamentos'!$C$2:$C$5010,J$4) | K31: =SUM(B31:J31) | L31: =K31/K$51 | M31: =SUMIFS('Lançamentos'!$L$2:$L$5010,'Lançamentos'!$A$2:$A$5010,"Frete de compra",'Lançamentos'!$B$2:$B$5010,$A31,'Lançamentos'!$C$2:$C$5010,"Antes de 2026")
A32: 2.01.98 Frete Descarregamento | B32: =SUMIFS('Lançamentos'!$L$2:$L$5010,'Lançamentos'!$A$2:$A$5010,"Frete de compra",'Lançamentos'!$B$2:$B$5010,$A32,'Lançamentos'!$C$2:$C$5010,B$4) | C32: =SUMIFS('Lançamentos'!$L$2:$L$5010,'Lançamentos'!$A$2:$A$5010,"Frete de compra",'Lançamentos'!$B$2:$B$5010,$A32,'Lançamentos'!$C$2:$C$5010,C$4) | D32: =SUMIFS('Lançamentos'!$L$2:$L$5010,'Lançamentos'!$A$2:$A$5010,"Frete de compra",'Lançamentos'!$B$2:$B$5010,$A32,'Lançamentos'!$C$2:$C$5010,D$4) | E32: =SUMIFS('Lançamentos'!$L$2:$L$5010,'Lançamentos'!$A$2:$A$5010,"Frete de compra",'Lançamentos'!$B$2:$B$5010,$A32,'Lançamentos'!$C$2:$C$5010,E$4) | F32: =SUMIFS('Lançamentos'!$L$2:$L$5010,'Lançamentos'!$A$2:$A$5010,"Frete de compra",'Lançamentos'!$B$2:$B$5010,$A32,'Lançamentos'!$C$2:$C$5010,F$4) | G32: =SUMIFS('Lançamentos'!$L$2:$L$5010,'Lançamentos'!$A$2:$A$5010,"Frete de compra",'Lançamentos'!$B$2:$B$5010,$A32,'Lançamentos'!$C$2:$C$5010,G$4) | H32: =SUMIFS('Lançamentos'!$L$2:$L$5010,'Lançamentos'!$A$2:$A$5010,"Frete de compra",'Lançamentos'!$B$2:$B$5010,$A32,'Lançamentos'!$C$2:$C$5010,H$4) | I32: =SUMIFS('Lançamentos'!$L$2:$L$5010,'Lançamentos'!$A$2:$A$5010,"Frete de compra",'Lançamentos'!$B$2:$B$5010,$A32,'Lançamentos'!$C$2:$C$5010,I$4) | J32: =SUMIFS('Lançamentos'!$L$2:$L$5010,'Lançamentos'!$A$2:$A$5010,"Frete de compra",'Lançamentos'!$B$2:$B$5010,$A32,'Lançamentos'!$C$2:$C$5010,J$4) | K32: =SUM(B32:J32) | L32: =K32/K$51 | M32: =SUMIFS('Lançamentos'!$L$2:$L$5010,'Lançamentos'!$A$2:$A$5010,"Frete de compra",'Lançamentos'!$B$2:$B$5010,$A32,'Lançamentos'!$C$2:$C$5010,"Antes de 2026")
A33: 2.02.93 Frete Amostras/Brindes | B33: =SUMIFS('Lançamentos'!$L$2:$L$5010,'Lançamentos'!$A$2:$A$5010,"Frete de compra",'Lançamentos'!$B$2:$B$5010,$A33,'Lançamentos'!$C$2:$C$5010,B$4) | C33: =SUMIFS('Lançamentos'!$L$2:$L$5010,'Lançamentos'!$A$2:$A$5010,"Frete de compra",'Lançamentos'!$B$2:$B$5010,$A33,'Lançamentos'!$C$2:$C$5010,C$4) | D33: =SUMIFS('Lançamentos'!$L$2:$L$5010,'Lançamentos'!$A$2:$A$5010,"Frete de compra",'Lançamentos'!$B$2:$B$5010,$A33,'Lançamentos'!$C$2:$C$5010,D$4) | E33: =SUMIFS('Lançamentos'!$L$2:$L$5010,'Lançamentos'!$A$2:$A$5010,"Frete de compra",'Lançamentos'!$B$2:$B$5010,$A33,'Lançamentos'!$C$2:$C$5010,E$4) | F33: =SUMIFS('Lançamentos'!$L$2:$L$5010,'Lançamentos'!$A$2:$A$5010,"Frete de compra",'Lançamentos'!$B$2:$B$5010,$A33,'Lançamentos'!$C$2:$C$5010,F$4) | G33: =SUMIFS('Lançamentos'!$L$2:$L$5010,'Lançamentos'!$A$2:$A$5010,"Frete de compra",'Lançamentos'!$B$2:$B$5010,$A33,'Lançamentos'!$C$2:$C$5010,G$4) | H33: =SUMIFS('Lançamentos'!$L$2:$L$5010,'Lançamentos'!$A$2:$A$5010,"Frete de compra",'Lançamentos'!$B$2:$B$5010,$A33,'Lançamentos'!$C$2:$C$5010,H$4) | I33: =SUMIFS('Lançamentos'!$L$2:$L$5010,'Lançamentos'!$A$2:$A$5010,"Frete de compra",'Lançamentos'!$B$2:$B$5010,$A33,'Lançamentos'!$C$2:$C$5010,I$4) | J33: =SUMIFS('Lançamentos'!$L$2:$L$5010,'Lançamentos'!$A$2:$A$5010,"Frete de compra",'Lançamentos'!$B$2:$B$5010,$A33,'Lançamentos'!$C$2:$C$5010,J$4) | K33: =SUM(B33:J33) | L33: =K33/K$51 | M33: =SUMIFS('Lançamentos'!$L$2:$L$5010,'Lançamentos'!$A$2:$A$5010,"Frete de compra",'Lançamentos'!$B$2:$B$5010,$A33,'Lançamentos'!$C$2:$C$5010,"Antes de 2026")
A34: 2.04.87 Frete sobre Compra | B34: =SUMIFS('Lançamentos'!$L$2:$L$5010,'Lançamentos'!$A$2:$A$5010,"Frete de compra",'Lançamentos'!$B$2:$B$5010,$A34,'Lançamentos'!$C$2:$C$5010,B$4) | C34: =SUMIFS('Lançamentos'!$L$2:$L$5010,'Lançamentos'!$A$2:$A$5010,"Frete de compra",'Lançamentos'!$B$2:$B$5010,$A34,'Lançamentos'!$C$2:$C$5010,C$4) | D34: =SUMIFS('Lançamentos'!$L$2:$L$5010,'Lançamentos'!$A$2:$A$5010,"Frete de compra",'Lançamentos'!$B$2:$B$5010,$A34,'Lançamentos'!$C$2:$C$5010,D$4) | E34: =SUMIFS('Lançamentos'!$L$2:$L$5010,'Lançamentos'!$A$2:$A$5010,"Frete de compra",'Lançamentos'!$B$2:$B$5010,$A34,'Lançamentos'!$C$2:$C$5010,E$4) | F34: =SUMIFS('Lançamentos'!$L$2:$L$5010,'Lançamentos'!$A$2:$A$5010,"Frete de compra",'Lançamentos'!$B$2:$B$5010,$A34,'Lançamentos'!$C$2:$C$5010,F$4) | G34: =SUMIFS('Lançamentos'!$L$2:$L$5010,'Lançamentos'!$A$2:$A$5010,"Frete de compra",'Lançamentos'!$B$2:$B$5010,$A34,'Lançamentos'!$C$2:$C$5010,G$4) | H34: =SUMIFS('Lançamentos'!$L$2:$L$5010,'Lançamentos'!$A$2:$A$5010,"Frete de compra",'Lançamentos'!$B$2:$B$5010,$A34,'Lançamentos'!$C$2:$C$5010,H$4) | I34: =SUMIFS('Lançamentos'!$L$2:$L$5010,'Lançamentos'!$A$2:$A$5010,"Frete de compra",'Lançamentos'!$B$2:$B$5010,$A34,'Lançamentos'!$C$2:$C$5010,I$4) | J34: =SUMIFS('Lançamentos'!$L$2:$L$5010,'Lançamentos'!$A$2:$A$5010,"Frete de compra",'Lançamentos'!$B$2:$B$5010,$A34,'Lançamentos'!$C$2:$C$5010,J$4) | K34: =SUM(B34:J34) | L34: =K34/K$51 | M34: =SUMIFS('Lançamentos'!$L$2:$L$5010,'Lançamentos'!$A$2:$A$5010,"Frete de compra",'Lançamentos'!$B$2:$B$5010,$A34,'Lançamentos'!$C$2:$C$5010,"Antes de 2026")
A35: Frete de venda | B35: =SUM(B36:B41) | C35: =SUM(C36:C41) | D35: =SUM(D36:D41) | E35: =SUM(E36:E41) | F35: =SUM(F36:F41) | G35: =SUM(G36:G41) | H35: =SUM(H36:H41) | I35: =SUM(I36:I41) | ... K35: =SUM(K36:K41) | L35: =K35/K$51 | M35: =SUM(M36:M41)
A36: 1.01.01 Venda de Mercadoria Fabricadas | B36: =SUMIFS('Lançamentos'!$L$2:$L$5010,'Lançamentos'!$A$2:$A$5010,"Frete de venda",'Lançamentos'!$B$2:$B$5010,$A36,'Lançamentos'!$C$2:$C$5010,B$4) | C36: =SUMIFS('Lançamentos'!$L$2:$L$5010,'Lançamentos'!$A$2:$A$5010,"Frete de venda",'Lançamentos'!$B$2:$B$5010,$A36,'Lançamentos'!$C$2:$C$5010,C$4) | D36: =SUMIFS('Lançamentos'!$L$2:$L$5010,'Lançamentos'!$A$2:$A$5010,"Frete de venda",'Lançamentos'!$B$2:$B$5010,$A36,'Lançamentos'!$C$2:$C$5010,D$4) | E36: =SUMIFS('Lançamentos'!$L$2:$L$5010,'Lançamentos'!$A$2:$A$5010,"Frete de venda",'Lançamentos'!$B$2:$B$5010,$A36,'Lançamentos'!$C$2:$C$5010,E$4) | F36: =SUMIFS('Lançamentos'!$L$2:$L$5010,'Lançamentos'!$A$2:$A$5010,"Frete de venda",'Lançamentos'!$B$2:$B$5010,$A36,'Lançamentos'!$C$2:$C$5010,F$4) | G36: =SUMIFS('Lançamentos'!$L$2:$L$5010,'Lançamentos'!$A$2:$A$5010,"Frete de venda",'Lançamentos'!$B$2:$B$5010,$A36,'Lançamentos'!$C$2:$C$5010,G$4) | H36: =SUMIFS('Lançamentos'!$L$2:$L$5010,'Lançamentos'!$A$2:$A$5010,"Frete de venda",'Lançamentos'!$B$2:$B$5010,$A36,'Lançamentos'!$C$2:$C$5010,H$4) | I36: =SUMIFS('Lançamentos'!$L$2:$L$5010,'Lançamentos'!$A$2:$A$5010,"Frete de venda",'Lançamentos'!$B$2:$B$5010,$A36,'Lançamentos'!$C$2:$C$5010,I$4) | J36: =SUMIFS('Lançamentos'!$L$2:$L$5010,'Lançamentos'!$A$2:$A$5010,"Frete de venda",'Lançamentos'!$B$2:$B$5010,$A36,'Lançamentos'!$C$2:$C$5010,J$4) | K36: =SUM(B36:J36) | L36: =K36/K$51 | M36: =SUMIFS('Lançamentos'!$L$2:$L$5010,'Lançamentos'!$A$2:$A$5010,"Frete de venda",'Lançamentos'!$B$2:$B$5010,$A36,'Lançamentos'!$C$2:$C$5010,"Antes de 2026")
A37: 2.01.01 Frete Galpão Produto Acabado | B37: =SUMIFS('Lançamentos'!$L$2:$L$5010,'Lançamentos'!$A$2:$A$5010,"Frete de venda",'Lançamentos'!$B$2:$B$5010,$A37,'Lançamentos'!$C$2:$C$5010,B$4) | C37: =SUMIFS('Lançamentos'!$L$2:$L$5010,'Lançamentos'!$A$2:$A$5010,"Frete de venda",'Lançamentos'!$B$2:$B$5010,$A37,'Lançamentos'!$C$2:$C$5010,C$4) | D37: =SUMIFS('Lançamentos'!$L$2:$L$5010,'Lançamentos'!$A$2:$A$5010,"Frete de venda",'Lançamentos'!$B$2:$B$5010,$A37,'Lançamentos'!$C$2:$C$5010,D$4) | E37: =SUMIFS('Lançamentos'!$L$2:$L$5010,'Lançamentos'!$A$2:$A$5010,"Frete de venda",'Lançamentos'!$B$2:$B$5010,$A37,'Lançamentos'!$C$2:$C$5010,E$4) | F37: =SUMIFS('Lançamentos'!$L$2:$L$5010,'Lançamentos'!$A$2:$A$5010,"Frete de venda",'Lançamentos'!$B$2:$B$5010,$A37,'Lançamentos'!$C$2:$C$5010,F$4) | G37: =SUMIFS('Lançamentos'!$L$2:$L$5010,'Lançamentos'!$A$2:$A$5010,"Frete de venda",'Lançamentos'!$B$2:$B$5010,$A37,'Lançamentos'!$C$2:$C$5010,G$4) | H37: =SUMIFS('Lançamentos'!$L$2:$L$5010,'Lançamentos'!$A$2:$A$5010,"Frete de venda",'Lançamentos'!$B$2:$B$5010,$A37,'Lançamentos'!$C$2:$C$5010,H$4) | I37: =SUMIFS('Lançamentos'!$L$2:$L$5010,'Lançamentos'!$A$2:$A$5010,"Frete de venda",'Lançamentos'!$B$2:$B$5010,$A37,'Lançamentos'!$C$2:$C$5010,I$4) | J37: =SUMIFS('Lançamentos'!$L$2:$L$5010,'Lançamentos'!$A$2:$A$5010,"Frete de venda",'Lançamentos'!$B$2:$B$5010,$A37,'Lançamentos'!$C$2:$C$5010,J$4) | K37: =SUM(B37:J37) | L37: =K37/K$51 | M37: =SUMIFS('Lançamentos'!$L$2:$L$5010,'Lançamentos'!$A$2:$A$5010,"Frete de venda",'Lançamentos'!$B$2:$B$5010,$A37,'Lançamentos'!$C$2:$C$5010,"Antes de 2026")
A38: 2.01.02 Frete sobre Vendas | B38: =SUMIFS('Lançamentos'!$L$2:$L$5010,'Lançamentos'!$A$2:$A$5010,"Frete de venda",'Lançamentos'!$B$2:$B$5010,$A38,'Lançamentos'!$C$2:$C$5010,B$4) | C38: =SUMIFS('Lançamentos'!$L$2:$L$5010,'Lançamentos'!$A$2:$A$5010,"Frete de venda",'Lançamentos'!$B$2:$B$5010,$A38,'Lançamentos'!$C$2:$C$5010,C$4) | D38: =SUMIFS('Lançamentos'!$L$2:$L$5010,'Lançamentos'!$A$2:$A$5010,"Frete de venda",'Lançamentos'!$B$2:$B$5010,$A38,'Lançamentos'!$C$2:$C$5010,D$4) | E38: =SUMIFS('Lançamentos'!$L$2:$L$5010,'Lançamentos'!$A$2:$A$5010,"Frete de venda",'Lançamentos'!$B$2:$B$5010,$A38,'Lançamentos'!$C$2:$C$5010,E$4) | F38: =SUMIFS('Lançamentos'!$L$2:$L$5010,'Lançamentos'!$A$2:$A$5010,"Frete de venda",'Lançamentos'!$B$2:$B$5010,$A38,'Lançamentos'!$C$2:$C$5010,F$4) | G38: =SUMIFS('Lançamentos'!$L$2:$L$5010,'Lançamentos'!$A$2:$A$5010,"Frete de venda",'Lançamentos'!$B$2:$B$5010,$A38,'Lançamentos'!$C$2:$C$5010,G$4) | H38: =SUMIFS('Lançamentos'!$L$2:$L$5010,'Lançamentos'!$A$2:$A$5010,"Frete de venda",'Lançamentos'!$B$2:$B$5010,$A38,'Lançamentos'!$C$2:$C$5010,H$4) | I38: =SUMIFS('Lançamentos'!$L$2:$L$5010,'Lançamentos'!$A$2:$A$5010,"Frete de venda",'Lançamentos'!$B$2:$B$5010,$A38,'Lançamentos'!$C$2:$C$5010,I$4) | J38: =SUMIFS('Lançamentos'!$L$2:$L$5010,'Lançamentos'!$A$2:$A$5010,"Frete de venda",'Lançamentos'!$B$2:$B$5010,$A38,'Lançamentos'!$C$2:$C$5010,J$4) | K38: =SUM(B38:J38) | L38: =K38/K$51 | M38: =SUMIFS('Lançamentos'!$L$2:$L$5010,'Lançamentos'!$A$2:$A$5010,"Frete de venda",'Lançamentos'!$B$2:$B$5010,$A38,'Lançamentos'!$C$2:$C$5010,"Antes de 2026")
A39: 2.01.84 Remessa de Mercadoria | B39: =SUMIFS('Lançamentos'!$L$2:$L$5010,'Lançamentos'!$A$2:$A$5010,"Frete de venda",'Lançamentos'!$B$2:$B$5010,$A39,'Lançamentos'!$C$2:$C$5010,B$4) | C39: =SUMIFS('Lançamentos'!$L$2:$L$5010,'Lançamentos'!$A$2:$A$5010,"Frete de venda",'Lançamentos'!$B$2:$B$5010,$A39,'Lançamentos'!$C$2:$C$5010,C$4) | D39: =SUMIFS('Lançamentos'!$L$2:$L$5010,'Lançamentos'!$A$2:$A$5010,"Frete de venda",'Lançamentos'!$B$2:$B$5010,$A39,'Lançamentos'!$C$2:$C$5010,D$4) | E39: =SUMIFS('Lançamentos'!$L$2:$L$5010,'Lançamentos'!$A$2:$A$5010,"Frete de venda",'Lançamentos'!$B$2:$B$5010,$A39,'Lançamentos'!$C$2:$C$5010,E$4) | F39: =SUMIFS('Lançamentos'!$L$2:$L$5010,'Lançamentos'!$A$2:$A$5010,"Frete de venda",'Lançamentos'!$B$2:$B$5010,$A39,'Lançamentos'!$C$2:$C$5010,F$4) | G39: =SUMIFS('Lançamentos'!$L$2:$L$5010,'Lançamentos'!$A$2:$A$5010,"Frete de venda",'Lançamentos'!$B$2:$B$5010,$A39,'Lançamentos'!$C$2:$C$5010,G$4) | H39: =SUMIFS('Lançamentos'!$L$2:$L$5010,'Lançamentos'!$A$2:$A$5010,"Frete de venda",'Lançamentos'!$B$2:$B$5010,$A39,'Lançamentos'!$C$2:$C$5010,H$4) | I39: =SUMIFS('Lançamentos'!$L$2:$L$5010,'Lançamentos'!$A$2:$A$5010,"Frete de venda",'Lançamentos'!$B$2:$B$5010,$A39,'Lançamentos'!$C$2:$C$5010,I$4) | J39: =SUMIFS('Lançamentos'!$L$2:$L$5010,'Lançamentos'!$A$2:$A$5010,"Frete de venda",'Lançamentos'!$B$2:$B$5010,$A39,'Lançamentos'!$C$2:$C$5010,J$4) | K39: =SUM(B39:J39) | L39: =K39/K$51 | M39: =SUMIFS('Lançamentos'!$L$2:$L$5010,'Lançamentos'!$A$2:$A$5010,"Frete de venda",'Lançamentos'!$B$2:$B$5010,$A39,'Lançamentos'!$C$2:$C$5010,"Antes de 2026")
A40: 2.01.98 Frete Descarregamento | B40: =SUMIFS('Lançamentos'!$L$2:$L$5010,'Lançamentos'!$A$2:$A$5010,"Frete de venda",'Lançamentos'!$B$2:$B$5010,$A40,'Lançamentos'!$C$2:$C$5010,B$4) | C40: =SUMIFS('Lançamentos'!$L$2:$L$5010,'Lançamentos'!$A$2:$A$5010,"Frete de venda",'Lançamentos'!$B$2:$B$5010,$A40,'Lançamentos'!$C$2:$C$5010,C$4) | D40: =SUMIFS('Lançamentos'!$L$2:$L$5010,'Lançamentos'!$A$2:$A$5010,"Frete de venda",'Lançamentos'!$B$2:$B$5010,$A40,'Lançamentos'!$C$2:$C$5010,D$4) | E40: =SUMIFS('Lançamentos'!$L$2:$L$5010,'Lançamentos'!$A$2:$A$5010,"Frete de venda",'Lançamentos'!$B$2:$B$5010,$A40,'Lançamentos'!$C$2:$C$5010,E$4) | F40: =SUMIFS('Lançamentos'!$L$2:$L$5010,'Lançamentos'!$A$2:$A$5010,"Frete de venda",'Lançamentos'!$B$2:$B$5010,$A40,'Lançamentos'!$C$2:$C$5010,F$4) | G40: =SUMIFS('Lançamentos'!$L$2:$L$5010,'Lançamentos'!$A$2:$A$5010,"Frete de venda",'Lançamentos'!$B$2:$B$5010,$A40,'Lançamentos'!$C$2:$C$5010,G$4) | H40: =SUMIFS('Lançamentos'!$L$2:$L$5010,'Lançamentos'!$A$2:$A$5010,"Frete de venda",'Lançamentos'!$B$2:$B$5010,$A40,'Lançamentos'!$C$2:$C$5010,H$4) | I40: =SUMIFS('Lançamentos'!$L$2:$L$5010,'Lançamentos'!$A$2:$A$5010,"Frete de venda",'Lançamentos'!$B$2:$B$5010,$A40,'Lançamentos'!$C$2:$C$5010,I$4) | J40: =SUMIFS('Lançamentos'!$L$2:$L$5010,'Lançamentos'!$A$2:$A$5010,"Frete de venda",'Lançamentos'!$B$2:$B$5010,$A40,'Lançamentos'!$C$2:$C$5010,J$4) | K40: =SUM(B40:J40) | L40: =K40/K$51 | M40: =SUMIFS('Lançamentos'!$L$2:$L$5010,'Lançamentos'!$A$2:$A$5010,"Frete de venda",'Lançamentos'!$B$2:$B$5010,$A40,'Lançamentos'!$C$2:$C$5010,"Antes de 2026")
A41: 2.04.87 Frete sobre Compra | B41: =SUMIFS('Lançamentos'!$L$2:$L$5010,'Lançamentos'!$A$2:$A$5010,"Frete de venda",'Lançamentos'!$B$2:$B$5010,$A41,'Lançamentos'!$C$2:$C$5010,B$4) | C41: =SUMIFS('Lançamentos'!$L$2:$L$5010,'Lançamentos'!$A$2:$A$5010,"Frete de venda",'Lançamentos'!$B$2:$B$5010,$A41,'Lançamentos'!$C$2:$C$5010,C$4) | D41: =SUMIFS('Lançamentos'!$L$2:$L$5010,'Lançamentos'!$A$2:$A$5010,"Frete de venda",'Lançamentos'!$B$2:$B$5010,$A41,'Lançamentos'!$C$2:$C$5010,D$4) | E41: =SUMIFS('Lançamentos'!$L$2:$L$5010,'Lançamentos'!$A$2:$A$5010,"Frete de venda",'Lançamentos'!$B$2:$B$5010,$A41,'Lançamentos'!$C$2:$C$5010,E$4) | F41: =SUMIFS('Lançamentos'!$L$2:$L$5010,'Lançamentos'!$A$2:$A$5010,"Frete de venda",'Lançamentos'!$B$2:$B$5010,$A41,'Lançamentos'!$C$2:$C$5010,F$4) | G41: =SUMIFS('Lançamentos'!$L$2:$L$5010,'Lançamentos'!$A$2:$A$5010,"Frete de venda",'Lançamentos'!$B$2:$B$5010,$A41,'Lançamentos'!$C$2:$C$5010,G$4) | H41: =SUMIFS('Lançamentos'!$L$2:$L$5010,'Lançamentos'!$A$2:$A$5010,"Frete de venda",'Lançamentos'!$B$2:$B$5010,$A41,'Lançamentos'!$C$2:$C$5010,H$4) | I41: =SUMIFS('Lançamentos'!$L$2:$L$5010,'Lançamentos'!$A$2:$A$5010,"Frete de venda",'Lançamentos'!$B$2:$B$5010,$A41,'Lançamentos'!$C$2:$C$5010,I$4) | J41: =SUMIFS('Lançamentos'!$L$2:$L$5010,'Lançamentos'!$A$2:$A$5010,"Frete de venda",'Lançamentos'!$B$2:$B$5010,$A41,'Lançamentos'!$C$2:$C$5010,J$4) | K41: =SUM(B41:J41) | L41: =K41/K$51 | M41: =SUMIFS('Lançamentos'!$L$2:$L$5010,'Lançamentos'!$A$2:$A$5010,"Frete de venda",'Lançamentos'!$B$2:$B$5010,$A41,'Lançamentos'!$C$2:$C$5010,"Antes de 2026")
A42: Outras despesas pagas | B42: =SUM(B43:B49) | C42: =SUM(C43:C49) | D42: =SUM(D43:D49) | E42: =SUM(E43:E49) | F42: =SUM(F43:F49) | G42: =SUM(G43:G49) | H42: =SUM(H43:H49) | I42: =SUM(I43:I49) | ... K42: =SUM(K43:K49) | L42: =K42/K$51 | M42: =SUM(M43:M49)
A43: Aluguel de contêiner | B43: =SUMIFS('Lançamentos'!$L$2:$L$5010,'Lançamentos'!$A$2:$A$5010,"Outras despesas pagas",'Lançamentos'!$B$2:$B$5010,$A43,'Lançamentos'!$C$2:$C$5010,B$4) | C43: =SUMIFS('Lançamentos'!$L$2:$L$5010,'Lançamentos'!$A$2:$A$5010,"Outras despesas pagas",'Lançamentos'!$B$2:$B$5010,$A43,'Lançamentos'!$C$2:$C$5010,C$4) | D43: =SUMIFS('Lançamentos'!$L$2:$L$5010,'Lançamentos'!$A$2:$A$5010,"Outras despesas pagas",'Lançamentos'!$B$2:$B$5010,$A43,'Lançamentos'!$C$2:$C$5010,D$4) | E43: =SUMIFS('Lançamentos'!$L$2:$L$5010,'Lançamentos'!$A$2:$A$5010,"Outras despesas pagas",'Lançamentos'!$B$2:$B$5010,$A43,'Lançamentos'!$C$2:$C$5010,E$4) | F43: =SUMIFS('Lançamentos'!$L$2:$L$5010,'Lançamentos'!$A$2:$A$5010,"Outras despesas pagas",'Lançamentos'!$B$2:$B$5010,$A43,'Lançamentos'!$C$2:$C$5010,F$4) | G43: =SUMIFS('Lançamentos'!$L$2:$L$5010,'Lançamentos'!$A$2:$A$5010,"Outras despesas pagas",'Lançamentos'!$B$2:$B$5010,$A43,'Lançamentos'!$C$2:$C$5010,G$4) | H43: =SUMIFS('Lançamentos'!$L$2:$L$5010,'Lançamentos'!$A$2:$A$5010,"Outras despesas pagas",'Lançamentos'!$B$2:$B$5010,$A43,'Lançamentos'!$C$2:$C$5010,H$4) | I43: =SUMIFS('Lançamentos'!$L$2:$L$5010,'Lançamentos'!$A$2:$A$5010,"Outras despesas pagas",'Lançamentos'!$B$2:$B$5010,$A43,'Lançamentos'!$C$2:$C$5010,I$4) | J43: =SUMIFS('Lançamentos'!$L$2:$L$5010,'Lançamentos'!$A$2:$A$5010,"Outras despesas pagas",'Lançamentos'!$B$2:$B$5010,$A43,'Lançamentos'!$C$2:$C$5010,J$4) | K43: =SUM(B43:J43) | L43: =K43/K$51 | M43: =SUMIFS('Lançamentos'!$L$2:$L$5010,'Lançamentos'!$A$2:$A$5010,"Outras despesas pagas",'Lançamentos'!$B$2:$B$5010,$A43,'Lançamentos'!$C$2:$C$5010,"Antes de 2026")
A44: Brindes, premiações e marketing | B44: =SUMIFS('Lançamentos'!$L$2:$L$5010,'Lançamentos'!$A$2:$A$5010,"Outras despesas pagas",'Lançamentos'!$B$2:$B$5010,$A44,'Lançamentos'!$C$2:$C$5010,B$4) | C44: =SUMIFS('Lançamentos'!$L$2:$L$5010,'Lançamentos'!$A$2:$A$5010,"Outras despesas pagas",'Lançamentos'!$B$2:$B$5010,$A44,'Lançamentos'!$C$2:$C$5010,C$4) | D44: =SUMIFS('Lançamentos'!$L$2:$L$5010,'Lançamentos'!$A$2:$A$5010,"Outras despesas pagas",'Lançamentos'!$B$2:$B$5010,$A44,'Lançamentos'!$C$2:$C$5010,D$4) | E44: =SUMIFS('Lançamentos'!$L$2:$L$5010,'Lançamentos'!$A$2:$A$5010,"Outras despesas pagas",'Lançamentos'!$B$2:$B$5010,$A44,'Lançamentos'!$C$2:$C$5010,E$4) | F44: =SUMIFS('Lançamentos'!$L$2:$L$5010,'Lançamentos'!$A$2:$A$5010,"Outras despesas pagas",'Lançamentos'!$B$2:$B$5010,$A44,'Lançamentos'!$C$2:$C$5010,F$4) | G44: =SUMIFS('Lançamentos'!$L$2:$L$5010,'Lançamentos'!$A$2:$A$5010,"Outras despesas pagas",'Lançamentos'!$B$2:$B$5010,$A44,'Lançamentos'!$C$2:$C$5010,G$4) | H44: =SUMIFS('Lançamentos'!$L$2:$L$5010,'Lançamentos'!$A$2:$A$5010,"Outras despesas pagas",'Lançamentos'!$B$2:$B$5010,$A44,'Lançamentos'!$C$2:$C$5010,H$4) | I44: =SUMIFS('Lançamentos'!$L$2:$L$5010,'Lançamentos'!$A$2:$A$5010,"Outras despesas pagas",'Lançamentos'!$B$2:$B$5010,$A44,'Lançamentos'!$C$2:$C$5010,I$4) | J44: =SUMIFS('Lançamentos'!$L$2:$L$5010,'Lançamentos'!$A$2:$A$5010,"Outras despesas pagas",'Lançamentos'!$B$2:$B$5010,$A44,'Lançamentos'!$C$2:$C$5010,J$4) | K44: =SUM(B44:J44) | L44: =K44/K$51 | M44: =SUMIFS('Lançamentos'!$L$2:$L$5010,'Lançamentos'!$A$2:$A$5010,"Outras despesas pagas",'Lançamentos'!$B$2:$B$5010,$A44,'Lançamentos'!$C$2:$C$5010,"Antes de 2026")
A45: Combustível | B45: =SUMIFS('Lançamentos'!$L$2:$L$5010,'Lançamentos'!$A$2:$A$5010,"Outras despesas pagas",'Lançamentos'!$B$2:$B$5010,$A45,'Lançamentos'!$C$2:$C$5010,B$4) | C45: =SUMIFS('Lançamentos'!$L$2:$L$5010,'Lançamentos'!$A$2:$A$5010,"Outras despesas pagas",'Lançamentos'!$B$2:$B$5010,$A45,'Lançamentos'!$C$2:$C$5010,C$4) | D45: =SUMIFS('Lançamentos'!$L$2:$L$5010,'Lançamentos'!$A$2:$A$5010,"Outras despesas pagas",'Lançamentos'!$B$2:$B$5010,$A45,'Lançamentos'!$C$2:$C$5010,D$4) | E45: =SUMIFS('Lançamentos'!$L$2:$L$5010,'Lançamentos'!$A$2:$A$5010,"Outras despesas pagas",'Lançamentos'!$B$2:$B$5010,$A45,'Lançamentos'!$C$2:$C$5010,E$4) | F45: =SUMIFS('Lançamentos'!$L$2:$L$5010,'Lançamentos'!$A$2:$A$5010,"Outras despesas pagas",'Lançamentos'!$B$2:$B$5010,$A45,'Lançamentos'!$C$2:$C$5010,F$4) | G45: =SUMIFS('Lançamentos'!$L$2:$L$5010,'Lançamentos'!$A$2:$A$5010,"Outras despesas pagas",'Lançamentos'!$B$2:$B$5010,$A45,'Lançamentos'!$C$2:$C$5010,G$4) | H45: =SUMIFS('Lançamentos'!$L$2:$L$5010,'Lançamentos'!$A$2:$A$5010,"Outras despesas pagas",'Lançamentos'!$B$2:$B$5010,$A45,'Lançamentos'!$C$2:$C$5010,H$4) | I45: =SUMIFS('Lançamentos'!$L$2:$L$5010,'Lançamentos'!$A$2:$A$5010,"Outras despesas pagas",'Lançamentos'!$B$2:$B$5010,$A45,'Lançamentos'!$C$2:$C$5010,I$4) | J45: =SUMIFS('Lançamentos'!$L$2:$L$5010,'Lançamentos'!$A$2:$A$5010,"Outras despesas pagas",'Lançamentos'!$B$2:$B$5010,$A45,'Lançamentos'!$C$2:$C$5010,J$4) | K45: =SUM(B45:J45) | L45: =K45/K$51 | M45: =SUMIFS('Lançamentos'!$L$2:$L$5010,'Lançamentos'!$A$2:$A$5010,"Outras despesas pagas",'Lançamentos'!$B$2:$B$5010,$A45,'Lançamentos'!$C$2:$C$5010,"Antes de 2026")
A46: Imobilizado | B46: =SUMIFS('Lançamentos'!$L$2:$L$5010,'Lançamentos'!$A$2:$A$5010,"Outras despesas pagas",'Lançamentos'!$B$2:$B$5010,$A46,'Lançamentos'!$C$2:$C$5010,B$4) | C46: =SUMIFS('Lançamentos'!$L$2:$L$5010,'Lançamentos'!$A$2:$A$5010,"Outras despesas pagas",'Lançamentos'!$B$2:$B$5010,$A46,'Lançamentos'!$C$2:$C$5010,C$4) | D46: =SUMIFS('Lançamentos'!$L$2:$L$5010,'Lançamentos'!$A$2:$A$5010,"Outras despesas pagas",'Lançamentos'!$B$2:$B$5010,$A46,'Lançamentos'!$C$2:$C$5010,D$4) | E46: =SUMIFS('Lançamentos'!$L$2:$L$5010,'Lançamentos'!$A$2:$A$5010,"Outras despesas pagas",'Lançamentos'!$B$2:$B$5010,$A46,'Lançamentos'!$C$2:$C$5010,E$4) | F46: =SUMIFS('Lançamentos'!$L$2:$L$5010,'Lançamentos'!$A$2:$A$5010,"Outras despesas pagas",'Lançamentos'!$B$2:$B$5010,$A46,'Lançamentos'!$C$2:$C$5010,F$4) | G46: =SUMIFS('Lançamentos'!$L$2:$L$5010,'Lançamentos'!$A$2:$A$5010,"Outras despesas pagas",'Lançamentos'!$B$2:$B$5010,$A46,'Lançamentos'!$C$2:$C$5010,G$4) | H46: =SUMIFS('Lançamentos'!$L$2:$L$5010,'Lançamentos'!$A$2:$A$5010,"Outras despesas pagas",'Lançamentos'!$B$2:$B$5010,$A46,'Lançamentos'!$C$2:$C$5010,H$4) | I46: =SUMIFS('Lançamentos'!$L$2:$L$5010,'Lançamentos'!$A$2:$A$5010,"Outras despesas pagas",'Lançamentos'!$B$2:$B$5010,$A46,'Lançamentos'!$C$2:$C$5010,I$4) | J46: =SUMIFS('Lançamentos'!$L$2:$L$5010,'Lançamentos'!$A$2:$A$5010,"Outras despesas pagas",'Lançamentos'!$B$2:$B$5010,$A46,'Lançamentos'!$C$2:$C$5010,J$4) | K46: =SUM(B46:J46) | L46: =K46/K$51 | M46: =SUMIFS('Lançamentos'!$L$2:$L$5010,'Lançamentos'!$A$2:$A$5010,"Outras despesas pagas",'Lançamentos'!$B$2:$B$5010,$A46,'Lançamentos'!$C$2:$C$5010,"Antes de 2026")
A47: Manutenção e serviços | B47: =SUMIFS('Lançamentos'!$L$2:$L$5010,'Lançamentos'!$A$2:$A$5010,"Outras despesas pagas",'Lançamentos'!$B$2:$B$5010,$A47,'Lançamentos'!$C$2:$C$5010,B$4) | C47: =SUMIFS('Lançamentos'!$L$2:$L$5010,'Lançamentos'!$A$2:$A$5010,"Outras despesas pagas",'Lançamentos'!$B$2:$B$5010,$A47,'Lançamentos'!$C$2:$C$5010,C$4) | D47: =SUMIFS('Lançamentos'!$L$2:$L$5010,'Lançamentos'!$A$2:$A$5010,"Outras despesas pagas",'Lançamentos'!$B$2:$B$5010,$A47,'Lançamentos'!$C$2:$C$5010,D$4) | E47: =SUMIFS('Lançamentos'!$L$2:$L$5010,'Lançamentos'!$A$2:$A$5010,"Outras despesas pagas",'Lançamentos'!$B$2:$B$5010,$A47,'Lançamentos'!$C$2:$C$5010,E$4) | F47: =SUMIFS('Lançamentos'!$L$2:$L$5010,'Lançamentos'!$A$2:$A$5010,"Outras despesas pagas",'Lançamentos'!$B$2:$B$5010,$A47,'Lançamentos'!$C$2:$C$5010,F$4) | G47: =SUMIFS('Lançamentos'!$L$2:$L$5010,'Lançamentos'!$A$2:$A$5010,"Outras despesas pagas",'Lançamentos'!$B$2:$B$5010,$A47,'Lançamentos'!$C$2:$C$5010,G$4) | H47: =SUMIFS('Lançamentos'!$L$2:$L$5010,'Lançamentos'!$A$2:$A$5010,"Outras despesas pagas",'Lançamentos'!$B$2:$B$5010,$A47,'Lançamentos'!$C$2:$C$5010,H$4) | I47: =SUMIFS('Lançamentos'!$L$2:$L$5010,'Lançamentos'!$A$2:$A$5010,"Outras despesas pagas",'Lançamentos'!$B$2:$B$5010,$A47,'Lançamentos'!$C$2:$C$5010,I$4) | J47: =SUMIFS('Lançamentos'!$L$2:$L$5010,'Lançamentos'!$A$2:$A$5010,"Outras despesas pagas",'Lançamentos'!$B$2:$B$5010,$A47,'Lançamentos'!$C$2:$C$5010,J$4) | K47: =SUM(B47:J47) | L47: =K47/K$51 | M47: =SUMIFS('Lançamentos'!$L$2:$L$5010,'Lançamentos'!$A$2:$A$5010,"Outras despesas pagas",'Lançamentos'!$B$2:$B$5010,$A47,'Lançamentos'!$C$2:$C$5010,"Antes de 2026")
A48: Outras (a classificar) | B48: =SUMIFS('Lançamentos'!$L$2:$L$5010,'Lançamentos'!$A$2:$A$5010,"Outras despesas pagas",'Lançamentos'!$B$2:$B$5010,$A48,'Lançamentos'!$C$2:$C$5010,B$4) | C48: =SUMIFS('Lançamentos'!$L$2:$L$5010,'Lançamentos'!$A$2:$A$5010,"Outras despesas pagas",'Lançamentos'!$B$2:$B$5010,$A48,'Lançamentos'!$C$2:$C$5010,C$4) | D48: =SUMIFS('Lançamentos'!$L$2:$L$5010,'Lançamentos'!$A$2:$A$5010,"Outras despesas pagas",'Lançamentos'!$B$2:$B$5010,$A48,'Lançamentos'!$C$2:$C$5010,D$4) | E48: =SUMIFS('Lançamentos'!$L$2:$L$5010,'Lançamentos'!$A$2:$A$5010,"Outras despesas pagas",'Lançamentos'!$B$2:$B$5010,$A48,'Lançamentos'!$C$2:$C$5010,E$4) | F48: =SUMIFS('Lançamentos'!$L$2:$L$5010,'Lançamentos'!$A$2:$A$5010,"Outras despesas pagas",'Lançamentos'!$B$2:$B$5010,$A48,'Lançamentos'!$C$2:$C$5010,F$4) | G48: =SUMIFS('Lançamentos'!$L$2:$L$5010,'Lançamentos'!$A$2:$A$5010,"Outras despesas pagas",'Lançamentos'!$B$2:$B$5010,$A48,'Lançamentos'!$C$2:$C$5010,G$4) | H48: =SUMIFS('Lançamentos'!$L$2:$L$5010,'Lançamentos'!$A$2:$A$5010,"Outras despesas pagas",'Lançamentos'!$B$2:$B$5010,$A48,'Lançamentos'!$C$2:$C$5010,H$4) | I48: =SUMIFS('Lançamentos'!$L$2:$L$5010,'Lançamentos'!$A$2:$A$5010,"Outras despesas pagas",'Lançamentos'!$B$2:$B$5010,$A48,'Lançamentos'!$C$2:$C$5010,I$4) | J48: =SUMIFS('Lançamentos'!$L$2:$L$5010,'Lançamentos'!$A$2:$A$5010,"Outras despesas pagas",'Lançamentos'!$B$2:$B$5010,$A48,'Lançamentos'!$C$2:$C$5010,J$4) | K48: =SUM(B48:J48) | L48: =K48/K$51 | M48: =SUMIFS('Lançamentos'!$L$2:$L$5010,'Lançamentos'!$A$2:$A$5010,"Outras despesas pagas",'Lançamentos'!$B$2:$B$5010,$A48,'Lançamentos'!$C$2:$C$5010,"Antes de 2026")
A49: Sede | B49: =SUMIFS('Lançamentos'!$L$2:$L$5010,'Lançamentos'!$A$2:$A$5010,"Outras despesas pagas",'Lançamentos'!$B$2:$B$5010,$A49,'Lançamentos'!$C$2:$C$5010,B$4) | C49: =SUMIFS('Lançamentos'!$L$2:$L$5010,'Lançamentos'!$A$2:$A$5010,"Outras despesas pagas",'Lançamentos'!$B$2:$B$5010,$A49,'Lançamentos'!$C$2:$C$5010,C$4) | D49: =SUMIFS('Lançamentos'!$L$2:$L$5010,'Lançamentos'!$A$2:$A$5010,"Outras despesas pagas",'Lançamentos'!$B$2:$B$5010,$A49,'Lançamentos'!$C$2:$C$5010,D$4) | E49: =SUMIFS('Lançamentos'!$L$2:$L$5010,'Lançamentos'!$A$2:$A$5010,"Outras despesas pagas",'Lançamentos'!$B$2:$B$5010,$A49,'Lançamentos'!$C$2:$C$5010,E$4) | F49: =SUMIFS('Lançamentos'!$L$2:$L$5010,'Lançamentos'!$A$2:$A$5010,"Outras despesas pagas",'Lançamentos'!$B$2:$B$5010,$A49,'Lançamentos'!$C$2:$C$5010,F$4) | G49: =SUMIFS('Lançamentos'!$L$2:$L$5010,'Lançamentos'!$A$2:$A$5010,"Outras despesas pagas",'Lançamentos'!$B$2:$B$5010,$A49,'Lançamentos'!$C$2:$C$5010,G$4) | H49: =SUMIFS('Lançamentos'!$L$2:$L$5010,'Lançamentos'!$A$2:$A$5010,"Outras despesas pagas",'Lançamentos'!$B$2:$B$5010,$A49,'Lançamentos'!$C$2:$C$5010,H$4) | I49: =SUMIFS('Lançamentos'!$L$2:$L$5010,'Lançamentos'!$A$2:$A$5010,"Outras despesas pagas",'Lançamentos'!$B$2:$B$5010,$A49,'Lançamentos'!$C$2:$C$5010,I$4) | J49: =SUMIFS('Lançamentos'!$L$2:$L$5010,'Lançamentos'!$A$2:$A$5010,"Outras despesas pagas",'Lançamentos'!$B$2:$B$5010,$A49,'Lançamentos'!$C$2:$C$5010,J$4) | K49: =SUM(B49:J49) | L49: =K49/K$51 | M49: =SUMIFS('Lançamentos'!$L$2:$L$5010,'Lançamentos'!$A$2:$A$5010,"Outras despesas pagas",'Lançamentos'!$B$2:$B$5010,$A49,'Lançamentos'!$C$2:$C$5010,"Antes de 2026")
A51: TOTAL GERAL DAS DESPESAS PAGAS (líquido de créditos) | B51: =B5+B18+B27+B35+B42 | C51: =C5+C18+C27+C35+C42 | D51: =D5+D18+D27+D35+D42 | E51: =E5+E18+E27+E35+E42 | F51: =F5+F18+F27+F35+F42 | G51: =G5+G18+G27+G35+G42 | H51: =H5+H18+H27+H35+H42 | I51: =I5+I18+I27+I35+I42 | ... K51: =K5+K18+K27+K35+K42 | L51: =K51/K51 | M51: =M5+M18+M27+M35+M42
A52: Subtotal – 4 categorias principais (sem Outras despesas pagas) | B52: =B5+B18+B27+B35 | C52: =C5+C18+C27+C35 | D52: =D5+D18+D27+D35 | E52: =E5+E18+E27+E35 | F52: =F5+F18+F27+F35 | G52: =G5+G18+G27+G35 | H52: =H5+H18+H27+H35 | I52: =I5+I18+I27+I35 | ... K52: =K5+K18+K27+K35 | L52: =K52/K51 | M52: =M5+M18+M27+M35
A54: Memo: valor bruto (com impostos) | B54: =SUMIFS('Lançamentos'!$J$2:$J$5010,'Lançamentos'!$C$2:$C$5010,B$4) | C54: =SUMIFS('Lançamentos'!$J$2:$J$5010,'Lançamentos'!$C$2:$C$5010,C$4) | D54: =SUMIFS('Lançamentos'!$J$2:$J$5010,'Lançamentos'!$C$2:$C$5010,D$4) | E54: =SUMIFS('Lançamentos'!$J$2:$J$5010,'Lançamentos'!$C$2:$C$5010,E$4) | F54: =SUMIFS('Lançamentos'!$J$2:$J$5010,'Lançamentos'!$C$2:$C$5010,F$4) | G54: =SUMIFS('Lançamentos'!$J$2:$J$5010,'Lançamentos'!$C$2:$C$5010,G$4) | H54: =SUMIFS('Lançamentos'!$J$2:$J$5010,'Lançamentos'!$C$2:$C$5010,H$4) | I54: =SUMIFS('Lançamentos'!$J$2:$J$5010,'Lançamentos'!$C$2:$C$5010,I$4) | J54: =SUMIFS('Lançamentos'!$J$2:$J$5010,'Lançamentos'!$C$2:$C$5010,J$4) | K54: =SUM(B54:J54) | M54: =SUMIFS('Lançamentos'!$J$2:$J$5010,'Lançamentos'!$C$2:$C$5010,"Antes de 2026")
A55: Memo: créditos abatidos | B55: =SUMIFS('Lançamentos'!$K$2:$K$5010,'Lançamentos'!$C$2:$C$5010,B$4) | C55: =SUMIFS('Lançamentos'!$K$2:$K$5010,'Lançamentos'!$C$2:$C$5010,C$4) | D55: =SUMIFS('Lançamentos'!$K$2:$K$5010,'Lançamentos'!$C$2:$C$5010,D$4) | E55: =SUMIFS('Lançamentos'!$K$2:$K$5010,'Lançamentos'!$C$2:$C$5010,E$4) | F55: =SUMIFS('Lançamentos'!$K$2:$K$5010,'Lançamentos'!$C$2:$C$5010,F$4) | G55: =SUMIFS('Lançamentos'!$K$2:$K$5010,'Lançamentos'!$C$2:$C$5010,G$4) | H55: =SUMIFS('Lançamentos'!$K$2:$K$5010,'Lançamentos'!$C$2:$C$5010,H$4) | I55: =SUMIFS('Lançamentos'!$K$2:$K$5010,'Lançamentos'!$C$2:$C$5010,I$4) | J55: =SUMIFS('Lançamentos'!$K$2:$K$5010,'Lançamentos'!$C$2:$C$5010,J$4) | K55: =SUM(B55:J55) | M55: =SUMIFS('Lançamentos'!$K$2:$K$5010,'Lançamentos'!$C$2:$C$5010,"Antes de 2026")
A56: Conferência: bruto − créditos − total geral (deve ser zero) | B56: =ROUND(B54-B55-B51,2) | C56: =ROUND(C54-C55-C51,2) | D56: =ROUND(D54-D55-D51,2) | E56: =ROUND(E54-E55-E51,2) | F56: =ROUND(F54-F55-F51,2) | G56: =ROUND(G54-G55-G51,2) | H56: =ROUND(H54-H55-H51,2) | I56: =ROUND(I54-I55-I51,2) | ... K56: =ROUND(K54-K55-K51,2) | M56: =ROUND(M54-M55-M51,2)
A57: Conferência: total geral − soma direta de Lançamentos (deve ser zero) | B57: =ROUND(B51-SUMIFS('Lançamentos'!$L$2:$L$5010,'Lançamentos'!$C$2:$C$5010,B$4),2) | C57: =ROUND(C51-SUMIFS('Lançamentos'!$L$2:$L$5010,'Lançamentos'!$C$2:$C$5010,C$4),2) | D57: =ROUND(D51-SUMIFS('Lançamentos'!$L$2:$L$5010,'Lançamentos'!$C$2:$C$5010,D$4),2) | E57: =ROUND(E51-SUMIFS('Lançamentos'!$L$2:$L$5010,'Lançamentos'!$C$2:$C$5010,E$4),2) | F57: =ROUND(F51-SUMIFS('Lançamentos'!$L$2:$L$5010,'Lançamentos'!$C$2:$C$5010,F$4),2) | G57: =ROUND(G51-SUMIFS('Lançamentos'!$L$2:$L$5010,'Lançamentos'!$C$2:$C$5010,G$4),2) | H57: =ROUND(H51-SUMIFS('Lançamentos'!$L$2:$L$5010,'Lançamentos'!$C$2:$C$5010,H$4),2) | I57: =ROUND(I51-SUMIFS('Lançamentos'!$L$2:$L$5010,'Lançamentos'!$C$2:$C$5010,I$4),2) | J57: =ROUND(J51-SUMIFS('Lançamentos'!$L$2:$L$5010,'Lançamentos'!$C$2:$C$5010,J$4),2) | K57: =ROUND(K51-SUMIFS('Lançamentos'!$L$2:$L$5010,'Lançamentos'!$D$2:$D$5010,"Em 2026"),2) | M57: =ROUND(M51-SUMIFS('Lançamentos'!$L$2:$L$5010,'Lançamentos'!$C$2:$C$5010,"Antes de 2026"),2)
A59: Total por categoria (nível 1)
A60: Categoria | B60: Valor bruto 2026 | C60: Créditos 2026 | D60: Líquido 2026 | E60: % do líquido | F60: Memo: líquido antes de 2026
A61: Insumos e papel | B61: =SUMIFS('Lançamentos'!$J$2:$J$5010,'Lançamentos'!$A$2:$A$5010,$A61,'Lançamentos'!$D$2:$D$5010,"Em 2026") | C61: =SUMIFS('Lançamentos'!$K$2:$K$5010,'Lançamentos'!$A$2:$A$5010,$A61,'Lançamentos'!$D$2:$D$5010,"Em 2026") | D61: =B61-C61 | E61: =D61/D$66 | F61: =M5
A62: Uso e consumo | B62: =SUMIFS('Lançamentos'!$J$2:$J$5010,'Lançamentos'!$A$2:$A$5010,$A62,'Lançamentos'!$D$2:$D$5010,"Em 2026") | C62: =SUMIFS('Lançamentos'!$K$2:$K$5010,'Lançamentos'!$A$2:$A$5010,$A62,'Lançamentos'!$D$2:$D$5010,"Em 2026") | D62: =B62-C62 | E62: =D62/D$66 | F62: =M18
A63: Frete de compra | B63: =SUMIFS('Lançamentos'!$J$2:$J$5010,'Lançamentos'!$A$2:$A$5010,$A63,'Lançamentos'!$D$2:$D$5010,"Em 2026") | C63: =SUMIFS('Lançamentos'!$K$2:$K$5010,'Lançamentos'!$A$2:$A$5010,$A63,'Lançamentos'!$D$2:$D$5010,"Em 2026") | D63: =B63-C63 | E63: =D63/D$66 | F63: =M27
A64: Frete de venda | B64: =SUMIFS('Lançamentos'!$J$2:$J$5010,'Lançamentos'!$A$2:$A$5010,$A64,'Lançamentos'!$D$2:$D$5010,"Em 2026") | C64: =SUMIFS('Lançamentos'!$K$2:$K$5010,'Lançamentos'!$A$2:$A$5010,$A64,'Lançamentos'!$D$2:$D$5010,"Em 2026") | D64: =B64-C64 | E64: =D64/D$66 | F64: =M35
A65: Outras despesas pagas | B65: =SUMIFS('Lançamentos'!$J$2:$J$5010,'Lançamentos'!$A$2:$A$5010,$A65,'Lançamentos'!$D$2:$D$5010,"Em 2026") | C65: =SUMIFS('Lançamentos'!$K$2:$K$5010,'Lançamentos'!$A$2:$A$5010,$A65,'Lançamentos'!$D$2:$D$5010,"Em 2026") | D65: =B65-C65 | E65: =D65/D$66 | F65: =M42
A66: TOTAL | B66: =SUM(B61:B65) | C66: =SUM(C61:C65) | D66: =SUM(D61:D65) | E66: =D66/D66 | F66: =SUM(F61:F65)
A67: Conferência: total nível 1 − total geral (deve ser zero) | D67: =ROUND(D66-K51,2)

Sheet Insumos e papel
A1: Insumos e papel – 2026 (VINCO)
A2: Compras de matéria-prima e insumos de produção (papel, tinta, cola, caixas, filme, etiquetas etc.). R$, mês de emissão. Custo líquido = bruto − créditos de impostos (aba Premissas).
A4: Subcategoria (categoria do Omie) | B4: 46023 | C4: 46054 | D4: 46082 | E4: 46113 | F4: 46143 | G4: 46174 | H4: 46204 | I4: 46235 | J4: 46266 | K4: Total 2026 | L4: % do total | M4: Memo: antes de 2026
A5: 2.01.03 Compra de Matéria Prima (Papel) | B5: =SUMIFS('Lançamentos'!$L$2:$L$5010,'Lançamentos'!$A$2:$A$5010,"Insumos e papel",'Lançamentos'!$B$2:$B$5010,$A5,'Lançamentos'!$C$2:$C$5010,B$4) | C5: =SUMIFS('Lançamentos'!$L$2:$L$5010,'Lançamentos'!$A$2:$A$5010,"Insumos e papel",'Lançamentos'!$B$2:$B$5010,$A5,'Lançamentos'!$C$2:$C$5010,C$4) | D5: =SUMIFS('Lançamentos'!$L$2:$L$5010,'Lançamentos'!$A$2:$A$5010,"Insumos e papel",'Lançamentos'!$B$2:$B$5010,$A5,'Lançamentos'!$C$2:$C$5010,D$4) | E5: =SUMIFS('Lançamentos'!$L$2:$L$5010,'Lançamentos'!$A$2:$A$5010,"Insumos e papel",'Lançamentos'!$B$2:$B$5010,$A5,'Lançamentos'!$C$2:$C$5010,E$4) | F5: =SUMIFS('Lançamentos'!$L$2:$L$5010,'Lançamentos'!$A$2:$A$5010,"Insumos e papel",'Lançamentos'!$B$2:$B$5010,$A5,'Lançamentos'!$C$2:$C$5010,F$4) | G5: =SUMIFS('Lançamentos'!$L$2:$L$5010,'Lançamentos'!$A$2:$A$5010,"Insumos e papel",'Lançamentos'!$B$2:$B$5010,$A5,'Lançamentos'!$C$2:$C$5010,G$4) | H5: =SUMIFS('Lançamentos'!$L$2:$L$5010,'Lançamentos'!$A$2:$A$5010,"Insumos e papel",'Lançamentos'!$B$2:$B$5010,$A5,'Lançamentos'!$C$2:$C$5010,H$4) | I5: =SUMIFS('Lançamentos'!$L$2:$L$5010,'Lançamentos'!$A$2:$A$5010,"Insumos e papel",'Lançamentos'!$B$2:$B$5010,$A5,'Lançamentos'!$C$2:$C$5010,I$4) | J5: =SUMIFS('Lançamentos'!$L$2:$L$5010,'Lançamentos'!$A$2:$A$5010,"Insumos e papel",'Lançamentos'!$B$2:$B$5010,$A5,'Lançamentos'!$C$2:$C$5010,J$4) | K5: =SUM(B5:J5) | L5: =K5/K$17 | M5: =SUMIFS('Lançamentos'!$L$2:$L$5010,'Lançamentos'!$A$2:$A$5010,"Insumos e papel",'Lançamentos'!$B$2:$B$5010,$A5,'Lançamentos'!$C$2:$C$5010,"Antes de 2026")
A6: 2.01.79 Compra de Gás | B6: =SUMIFS('Lançamentos'!$L$2:$L$5010,'Lançamentos'!$A$2:$A$5010,"Insumos e papel",'Lançamentos'!$B$2:$B$5010,$A6,'Lançamentos'!$C$2:$C$5010,B$4) | C6: =SUMIFS('Lançamentos'!$L$2:$L$5010,'Lançamentos'!$A$2:$A$5010,"Insumos e papel",'Lançamentos'!$B$2:$B$5010,$A6,'Lançamentos'!$C$2:$C$5010,C$4) | D6: =SUMIFS('Lançamentos'!$L$2:$L$5010,'Lançamentos'!$A$2:$A$5010,"Insumos e papel",'Lançamentos'!$B$2:$B$5010,$A6,'Lançamentos'!$C$2:$C$5010,D$4) | E6: =SUMIFS('Lançamentos'!$L$2:$L$5010,'Lançamentos'!$A$2:$A$5010,"Insumos e papel",'Lançamentos'!$B$2:$B$5010,$A6,'Lançamentos'!$C$2:$C$5010,E$4) | F6: =SUMIFS('Lançamentos'!$L$2:$L$5010,'Lançamentos'!$A$2:$A$5010,"Insumos e papel",'Lançamentos'!$B$2:$B$5010,$A6,'Lançamentos'!$C$2:$C$5010,F$4) | G6: =SUMIFS('Lançamentos'!$L$2:$L$5010,'Lançamentos'!$A$2:$A$5010,"Insumos e papel",'Lançamentos'!$B$2:$B$5010,$A6,'Lançamentos'!$C$2:$C$5010,G$4) | H6: =SUMIFS('Lançamentos'!$L$2:$L$5010,'Lançamentos'!$A$2:$A$5010,"Insumos e papel",'Lançamentos'!$B$2:$B$5010,$A6,'Lançamentos'!$C$2:$C$5010,H$4) | I6: =SUMIFS('Lançamentos'!$L$2:$L$5010,'Lançamentos'!$A$2:$A$5010,"Insumos e papel",'Lançamentos'!$B$2:$B$5010,$A6,'Lançamentos'!$C$2:$C$5010,I$4) | J6: =SUMIFS('Lançamentos'!$L$2:$L$5010,'Lançamentos'!$A$2:$A$5010,"Insumos e papel",'Lançamentos'!$B$2:$B$5010,$A6,'Lançamentos'!$C$2:$C$5010,J$4) | K6: =SUM(B6:J6) | L6: =K6/K$17 | M6: =SUMIFS('Lançamentos'!$L$2:$L$5010,'Lançamentos'!$A$2:$A$5010,"Insumos e papel",'Lançamentos'!$B$2:$B$5010,$A6,'Lançamentos'!$C$2:$C$5010,"Antes de 2026")
A7: 2.01.83 Compra de Etiqueta Personalizada | B7: =SUMIFS('Lançamentos'!$L$2:$L$5010,'Lançamentos'!$A$2:$A$5010,"Insumos e papel",'Lançamentos'!$B$2:$B$5010,$A7,'Lançamentos'!$C$2:$C$5010,B$4) | C7: =SUMIFS('Lançamentos'!$L$2:$L$5010,'Lançamentos'!$A$2:$A$5010,"Insumos e papel",'Lançamentos'!$B$2:$B$5010,$A7,'Lançamentos'!$C$2:$C$5010,C$4) | D7: =SUMIFS('Lançamentos'!$L$2:$L$5010,'Lançamentos'!$A$2:$A$5010,"Insumos e papel",'Lançamentos'!$B$2:$B$5010,$A7,'Lançamentos'!$C$2:$C$5010,D$4) | E7: =SUMIFS('Lançamentos'!$L$2:$L$5010,'Lançamentos'!$A$2:$A$5010,"Insumos e papel",'Lançamentos'!$B$2:$B$5010,$A7,'Lançamentos'!$C$2:$C$5010,E$4) | F7: =SUMIFS('Lançamentos'!$L$2:$L$5010,'Lançamentos'!$A$2:$A$5010,"Insumos e papel",'Lançamentos'!$B$2:$B$5010,$A7,'Lançamentos'!$C$2:$C$5010,F$4) | G7: =SUMIFS('Lançamentos'!$L$2:$L$5010,'Lançamentos'!$A$2:$A$5010,"Insumos e papel",'Lançamentos'!$B$2:$B$5010,$A7,'Lançamentos'!$C$2:$C$5010,G$4) | H7: =SUMIFS('Lançamentos'!$L$2:$L$5010,'Lançamentos'!$A$2:$A$5010,"Insumos e papel",'Lançamentos'!$B$2:$B$5010,$A7,'Lançamentos'!$C$2:$C$5010,H$4) | I7: =SUMIFS('Lançamentos'!$L$2:$L$5010,'Lançamentos'!$A$2:$A$5010,"Insumos e papel",'Lançamentos'!$B$2:$B$5010,$A7,'Lançamentos'!$C$2:$C$5010,I$4) | J7: =SUMIFS('Lançamentos'!$L$2:$L$5010,'Lançamentos'!$A$2:$A$5010,"Insumos e papel",'Lançamentos'!$B$2:$B$5010,$A7,'Lançamentos'!$C$2:$C$5010,J$4) | K7: =SUM(B7:J7) | L7: =K7/K$17 | M7: =SUMIFS('Lançamentos'!$L$2:$L$5010,'Lançamentos'!$A$2:$A$5010,"Insumos e papel",'Lançamentos'!$B$2:$B$5010,$A7,'Lançamentos'!$C$2:$C$5010,"Antes de 2026")
A8: 2.01.89 Compra de Pallet | B8: =SUMIFS('Lançamentos'!$L$2:$L$5010,'Lançamentos'!$A$2:$A$5010,"Insumos e papel",'Lançamentos'!$B$2:$B$5010,$A8,'Lançamentos'!$C$2:$C$5010,B$4) | C8: =SUMIFS('Lançamentos'!$L$2:$L$5010,'Lançamentos'!$A$2:$A$5010,"Insumos e papel",'Lançamentos'!$B$2:$B$5010,$A8,'Lançamentos'!$C$2:$C$5010,C$4) | D8: =SUMIFS('Lançamentos'!$L$2:$L$5010,'Lançamentos'!$A$2:$A$5010,"Insumos e papel",'Lançamentos'!$B$2:$B$5010,$A8,'Lançamentos'!$C$2:$C$5010,D$4) | E8: =SUMIFS('Lançamentos'!$L$2:$L$5010,'Lançamentos'!$A$2:$A$5010,"Insumos e papel",'Lançamentos'!$B$2:$B$5010,$A8,'Lançamentos'!$C$2:$C$5010,E$4) | F8: =SUMIFS('Lançamentos'!$L$2:$L$5010,'Lançamentos'!$A$2:$A$5010,"Insumos e papel",'Lançamentos'!$B$2:$B$5010,$A8,'Lançamentos'!$C$2:$C$5010,F$4) | G8: =SUMIFS('Lançamentos'!$L$2:$L$5010,'Lançamentos'!$A$2:$A$5010,"Insumos e papel",'Lançamentos'!$B$2:$B$5010,$A8,'Lançamentos'!$C$2:$C$5010,G$4) | H8: =SUMIFS('Lançamentos'!$L$2:$L$5010,'Lançamentos'!$A$2:$A$5010,"Insumos e papel",'Lançamentos'!$B$2:$B$5010,$A8,'Lançamentos'!$C$2:$C$5010,H$4) | I8: =SUMIFS('Lançamentos'!$L$2:$L$5010,'Lançamentos'!$A$2:$A$5010,"Insumos e papel",'Lançamentos'!$B$2:$B$5010,$A8,'Lançamentos'!$C$2:$C$5010,I$4) | J8: =SUMIFS('Lançamentos'!$L$2:$L$5010,'Lançamentos'!$A$2:$A$5010,"Insumos e papel",'Lançamentos'!$B$2:$B$5010,$A8,'Lançamentos'!$C$2:$C$5010,J$4) | K8: =SUM(B8:J8) | L8: =K8/K$17 | M8: =SUMIFS('Lançamentos'!$L$2:$L$5010,'Lançamentos'!$A$2:$A$5010,"Insumos e papel",'Lançamentos'!$B$2:$B$5010,$A8,'Lançamentos'!$C$2:$C$5010,"Antes de 2026")
A9: 2.01.91 Compra de Filme Strech | B9: =SUMIFS('Lançamentos'!$L$2:$L$5010,'Lançamentos'!$A$2:$A$5010,"Insumos e papel",'Lançamentos'!$B$2:$B$5010,$A9,'Lançamentos'!$C$2:$C$5010,B$4) | C9: =SUMIFS('Lançamentos'!$L$2:$L$5010,'Lançamentos'!$A$2:$A$5010,"Insumos e papel",'Lançamentos'!$B$2:$B$5010,$A9,'Lançamentos'!$C$2:$C$5010,C$4) | D9: =SUMIFS('Lançamentos'!$L$2:$L$5010,'Lançamentos'!$A$2:$A$5010,"Insumos e papel",'Lançamentos'!$B$2:$B$5010,$A9,'Lançamentos'!$C$2:$C$5010,D$4) | E9: =SUMIFS('Lançamentos'!$L$2:$L$5010,'Lançamentos'!$A$2:$A$5010,"Insumos e papel",'Lançamentos'!$B$2:$B$5010,$A9,'Lançamentos'!$C$2:$C$5010,E$4) | F9: =SUMIFS('Lançamentos'!$L$2:$L$5010,'Lançamentos'!$A$2:$A$5010,"Insumos e papel",'Lançamentos'!$B$2:$B$5010,$A9,'Lançamentos'!$C$2:$C$5010,F$4) | G9: =SUMIFS('Lançamentos'!$L$2:$L$5010,'Lançamentos'!$A$2:$A$5010,"Insumos e papel",'Lançamentos'!$B$2:$B$5010,$A9,'Lançamentos'!$C$2:$C$5010,G$4) | H9: =SUMIFS('Lançamentos'!$L$2:$L$5010,'Lançamentos'!$A$2:$A$5010,"Insumos e papel",'Lançamentos'!$B$2:$B$5010,$A9,'Lançamentos'!$C$2:$C$5010,H$4) | I9: =SUMIFS('Lançamentos'!$L$2:$L$5010,'Lançamentos'!$A$2:$A$5010,"Insumos e papel",'Lançamentos'!$B$2:$B$5010,$A9,'Lançamentos'!$C$2:$C$5010,I$4) | J9: =SUMIFS('Lançamentos'!$L$2:$L$5010,'Lançamentos'!$A$2:$A$5010,"Insumos e papel",'Lançamentos'!$B$2:$B$5010,$A9,'Lançamentos'!$C$2:$C$5010,J$4) | K9: =SUM(B9:J9) | L9: =K9/K$17 | M9: =SUMIFS('Lançamentos'!$L$2:$L$5010,'Lançamentos'!$A$2:$A$5010,"Insumos e papel",'Lançamentos'!$B$2:$B$5010,$A9,'Lançamentos'!$C$2:$C$5010,"Antes de 2026")
A10: 2.01.92 Compra de Tinta | B10: =SUMIFS('Lançamentos'!$L$2:$L$5010,'Lançamentos'!$A$2:$A$5010,"Insumos e papel",'Lançamentos'!$B$2:$B$5010,$A10,'Lançamentos'!$C$2:$C$5010,B$4) | C10: =SUMIFS('Lançamentos'!$L$2:$L$5010,'Lançamentos'!$A$2:$A$5010,"Insumos e papel",'Lançamentos'!$B$2:$B$5010,$A10,'Lançamentos'!$C$2:$C$5010,C$4) | D10: =SUMIFS('Lançamentos'!$L$2:$L$5010,'Lançamentos'!$A$2:$A$5010,"Insumos e papel",'Lançamentos'!$B$2:$B$5010,$A10,'Lançamentos'!$C$2:$C$5010,D$4) | E10: =SUMIFS('Lançamentos'!$L$2:$L$5010,'Lançamentos'!$A$2:$A$5010,"Insumos e papel",'Lançamentos'!$B$2:$B$5010,$A10,'Lançamentos'!$C$2:$C$5010,E$4) | F10: =SUMIFS('Lançamentos'!$L$2:$L$5010,'Lançamentos'!$A$2:$A$5010,"Insumos e papel",'Lançamentos'!$B$2:$B$5010,$A10,'Lançamentos'!$C$2:$C$5010,F$4) | G10: =SUMIFS('Lançamentos'!$L$2:$L$5010,'Lançamentos'!$A$2:$A$5010,"Insumos e papel",'Lançamentos'!$B$2:$B$5010,$A10,'Lançamentos'!$C$2:$C$5010,G$4) | H10: =SUMIFS('Lançamentos'!$L$2:$L$5010,'Lançamentos'!$A$2:$A$5010,"Insumos e papel",'Lançamentos'!$B$2:$B$5010,$A10,'Lançamentos'!$C$2:$C$5010,H$4) | I10: =SUMIFS('Lançamentos'!$L$2:$L$5010,'Lançamentos'!$A$2:$A$5010,"Insumos e papel",'Lançamentos'!$B$2:$B$5010,$A10,'Lançamentos'!$C$2:$C$5010,I$4) | J10: =SUMIFS('Lançamentos'!$L$2:$L$5010,'Lançamentos'!$A$2:$A$5010,"Insumos e papel",'Lançamentos'!$B$2:$B$5010,$A10,'Lançamentos'!$C$2:$C$5010,J$4) | K10: =SUM(B10:J10) | L10: =K10/K$17 | M10: =SUMIFS('Lançamentos'!$L$2:$L$5010,'Lançamentos'!$A$2:$A$5010,"Insumos e papel",'Lançamentos'!$B$2:$B$5010,$A10,'Lançamentos'!$C$2:$C$5010,"Antes de 2026")
A11: 2.01.93 Compra de Plástico Poliolefínico | B11: =SUMIFS('Lançamentos'!$L$2:$L$5010,'Lançamentos'!$A$2:$A$5010,"Insumos e papel",'Lançamentos'!$B$2:$B$5010,$A11,'Lançamentos'!$C$2:$C$5010,B$4) | C11: =SUMIFS('Lançamentos'!$L$2:$L$5010,'Lançamentos'!$A$2:$A$5010,"Insumos e papel",'Lançamentos'!$B$2:$B$5010,$A11,'Lançamentos'!$C$2:$C$5010,C$4) | D11: =SUMIFS('Lançamentos'!$L$2:$L$5010,'Lançamentos'!$A$2:$A$5010,"Insumos e papel",'Lançamentos'!$B$2:$B$5010,$A11,'Lançamentos'!$C$2:$C$5010,D$4) | E11: =SUMIFS('Lançamentos'!$L$2:$L$5010,'Lançamentos'!$A$2:$A$5010,"Insumos e papel",'Lançamentos'!$B$2:$B$5010,$A11,'Lançamentos'!$C$2:$C$5010,E$4) | F11: =SUMIFS('Lançamentos'!$L$2:$L$5010,'Lançamentos'!$A$2:$A$5010,"Insumos e papel",'Lançamentos'!$B$2:$B$5010,$A11,'Lançamentos'!$C$2:$C$5010,F$4) | G11: =SUMIFS('Lançamentos'!$L$2:$L$5010,'Lançamentos'!$A$2:$A$5010,"Insumos e papel",'Lançamentos'!$B$2:$B$5010,$A11,'Lançamentos'!$C$2:$C$5010,G$4) | H11: =SUMIFS('Lançamentos'!$L$2:$L$5010,'Lançamentos'!$A$2:$A$5010,"Insumos e papel",'Lançamentos'!$B$2:$B$5010,$A11,'Lançamentos'!$C$2:$C$5010,H$4) | I11: =SUMIFS('Lançamentos'!$L$2:$L$5010,'Lançamentos'!$A$2:$A$5010,"Insumos e papel",'Lançamentos'!$B$2:$B$5010,$A11,'Lançamentos'!$C$2:$C$5010,I$4) | J11: =SUMIFS('Lançamentos'!$L$2:$L$5010,'Lançamentos'!$A$2:$A$5010,"Insumos e papel",'Lançamentos'!$B$2:$B$5010,$A11,'Lançamentos'!$C$2:$C$5010,J$4) | K11: =SUM(B11:J11) | L11: =K11/K$17 | M11: =SUMIFS('Lançamentos'!$L$2:$L$5010,'Lançamentos'!$A$2:$A$5010,"Insumos e papel",'Lançamentos'!$B$2:$B$5010,$A11,'Lançamentos'!$C$2:$C$5010,"Antes de 2026")
A12: 2.01.94 Compra de Fita Adesiva | B12: =SUMIFS('Lançamentos'!$L$2:$L$5010,'Lançamentos'!$A$2:$A$5010,"Insumos e papel",'Lançamentos'!$B$2:$B$5010,$A12,'Lançamentos'!$C$2:$C$5010,B$4) | C12: =SUMIFS('Lançamentos'!$L$2:$L$5010,'Lançamentos'!$A$2:$A$5010,"Insumos e papel",'Lançamentos'!$B$2:$B$5010,$A12,'Lançamentos'!$C$2:$C$5010,C$4) | D12: =SUMIFS('Lançamentos'!$L$2:$L$5010,'Lançamentos'!$A$2:$A$5010,"Insumos e papel",'Lançamentos'!$B$2:$B$5010,$A12,'Lançamentos'!$C$2:$C$5010,D$4) | E12: =SUMIFS('Lançamentos'!$L$2:$L$5010,'Lançamentos'!$A$2:$A$5010,"Insumos e papel",'Lançamentos'!$B$2:$B$5010,$A12,'Lançamentos'!$C$2:$C$5010,E$4) | F12: =SUMIFS('Lançamentos'!$L$2:$L$5010,'Lançamentos'!$A$2:$A$5010,"Insumos e papel",'Lançamentos'!$B$2:$B$5010,$A12,'Lançamentos'!$C$2:$C$5010,F$4) | G12: =SUMIFS('Lançamentos'!$L$2:$L$5010,'Lançamentos'!$A$2:$A$5010,"Insumos e papel",'Lançamentos'!$B$2:$B$5010,$A12,'Lançamentos'!$C$2:$C$5010,G$4) | H12: =SUMIFS('Lançamentos'!$L$2:$L$5010,'Lançamentos'!$A$2:$A$5010,"Insumos e papel",'Lançamentos'!$B$2:$B$5010,$A12,'Lançamentos'!$C$2:$C$5010,H$4) | I12: =SUMIFS('Lançamentos'!$L$2:$L$5010,'Lançamentos'!$A$2:$A$5010,"Insumos e papel",'Lançamentos'!$B$2:$B$5010,$A12,'Lançamentos'!$C$2:$C$5010,I$4) | J12: =SUMIFS('Lançamentos'!$L$2:$L$5010,'Lançamentos'!$A$2:$A$5010,"Insumos e papel",'Lançamentos'!$B$2:$B$5010,$A12,'Lançamentos'!$C$2:$C$5010,J$4) | K12: =SUM(B12:J12) | L12: =K12/K$17 | M12: =SUMIFS('Lançamentos'!$L$2:$L$5010,'Lançamentos'!$A$2:$A$5010,"Insumos e papel",'Lançamentos'!$B$2:$B$5010,$A12,'Lançamentos'!$C$2:$C$5010,"Antes de 2026")
A13: 2.01.95 Compra de Etiqueta | B13: =SUMIFS('Lançamentos'!$L$2:$L$5010,'Lançamentos'!$A$2:$A$5010,"Insumos e papel",'Lançamentos'!$B$2:$B$5010,$A13,'Lançamentos'!$C$2:$C$5010,B$4) | C13: =SUMIFS('Lançamentos'!$L$2:$L$5010,'Lançamentos'!$A$2:$A$5010,"Insumos e papel",'Lançamentos'!$B$2:$B$5010,$A13,'Lançamentos'!$C$2:$C$5010,C$4) | D13: =SUMIFS('Lançamentos'!$L$2:$L$5010,'Lançamentos'!$A$2:$A$5010,"Insumos e papel",'Lançamentos'!$B$2:$B$5010,$A13,'Lançamentos'!$C$2:$C$5010,D$4) | E13: =SUMIFS('Lançamentos'!$L$2:$L$5010,'Lançamentos'!$A$2:$A$5010,"Insumos e papel",'Lançamentos'!$B$2:$B$5010,$A13,'Lançamentos'!$C$2:$C$5010,E$4) | F13: =SUMIFS('Lançamentos'!$L$2:$L$5010,'Lançamentos'!$A$2:$A$5010,"Insumos e papel",'Lançamentos'!$B$2:$B$5010,$A13,'Lançamentos'!$C$2:$C$5010,F$4) | G13: =SUMIFS('Lançamentos'!$L$2:$L$5010,'Lançamentos'!$A$2:$A$5010,"Insumos e papel",'Lançamentos'!$B$2:$B$5010,$A13,'Lançamentos'!$C$2:$C$5010,G$4) | H13: =SUMIFS('Lançamentos'!$L$2:$L$5010,'Lançamentos'!$A$2:$A$5010,"Insumos e papel",'Lançamentos'!$B$2:$B$5010,$A13,'Lançamentos'!$C$2:$C$5010,H$4) | I13: =SUMIFS('Lançamentos'!$L$2:$L$5010,'Lançamentos'!$A$2:$A$5010,"Insumos e papel",'Lançamentos'!$B$2:$B$5010,$A13,'Lançamentos'!$C$2:$C$5010,I$4) | J13: =SUMIFS('Lançamentos'!$L$2:$L$5010,'Lançamentos'!$A$2:$A$5010,"Insumos e papel",'Lançamentos'!$B$2:$B$5010,$A13,'Lançamentos'!$C$2:$C$5010,J$4) | K13: =SUM(B13:J13) | L13: =K13/K$17 | M13: =SUMIFS('Lançamentos'!$L$2:$L$5010,'Lançamentos'!$A$2:$A$5010,"Insumos e papel",'Lançamentos'!$B$2:$B$5010,$A13,'Lançamentos'!$C$2:$C$5010,"Antes de 2026")
A14: 2.01.96 Compra de Cola | B14: =SUMIFS('Lançamentos'!$L$2:$L$5010,'Lançamentos'!$A$2:$A$5010,"Insumos e papel",'Lançamentos'!$B$2:$B$5010,$A14,'Lançamentos'!$C$2:$C$5010,B$4) | C14: =SUMIFS('Lançamentos'!$L$2:$L$5010,'Lançamentos'!$A$2:$A$5010,"Insumos e papel",'Lançamentos'!$B$2:$B$5010,$A14,'Lançamentos'!$C$2:$C$5010,C$4) | D14: =SUMIFS('Lançamentos'!$L$2:$L$5010,'Lançamentos'!$A$2:$A$5010,"Insumos e papel",'Lançamentos'!$B$2:$B$5010,$A14,'Lançamentos'!$C$2:$C$5010,D$4) | E14: =SUMIFS('Lançamentos'!$L$2:$L$5010,'Lançamentos'!$A$2:$A$5010,"Insumos e papel",'Lançamentos'!$B$2:$B$5010,$A14,'Lançamentos'!$C$2:$C$5010,E$4) | F14: =SUMIFS('Lançamentos'!$L$2:$L$5010,'Lançamentos'!$A$2:$A$5010,"Insumos e papel",'Lançamentos'!$B$2:$B$5010,$A14,'Lançamentos'!$C$2:$C$5010,F$4) | G14: =SUMIFS('Lançamentos'!$L$2:$L$5010,'Lançamentos'!$A$2:$A$5010,"Insumos e papel",'Lançamentos'!$B$2:$B$5010,$A14,'Lançamentos'!$C$2:$C$5010,G$4) | H14: =SUMIFS('Lançamentos'!$L$2:$L$5010,'Lançamentos'!$A$2:$A$5010,"Insumos e papel",'Lançamentos'!$B$2:$B$5010,$A14,'Lançamentos'!$C$2:$C$5010,H$4) | I14: =SUMIFS('Lançamentos'!$L$2:$L$5010,'Lançamentos'!$A$2:$A$5010,"Insumos e papel",'Lançamentos'!$B$2:$B$5010,$A14,'Lançamentos'!$C$2:$C$5010,I$4) | J14: =SUMIFS('Lançamentos'!$L$2:$L$5010,'Lançamentos'!$A$2:$A$5010,"Insumos e papel",'Lançamentos'!$B$2:$B$5010,$A14,'Lançamentos'!$C$2:$C$5010,J$4) | K14: =SUM(B14:J14) | L14: =K14/K$17 | M14: =SUMIFS('Lançamentos'!$L$2:$L$5010,'Lançamentos'!$A$2:$A$5010,"Insumos e papel",'Lançamentos'!$B$2:$B$5010,$A14,'Lançamentos'!$C$2:$C$5010,"Antes de 2026")
A15: 2.01.97 Compra de Clichê | B15: =SUMIFS('Lançamentos'!$L$2:$L$5010,'Lançamentos'!$A$2:$A$5010,"Insumos e papel",'Lançamentos'!$B$2:$B$5010,$A15,'Lançamentos'!$C$2:$C$5010,B$4) | C15: =SUMIFS('Lançamentos'!$L$2:$L$5010,'Lançamentos'!$A$2:$A$5010,"Insumos e papel",'Lançamentos'!$B$2:$B$5010,$A15,'Lançamentos'!$C$2:$C$5010,C$4) | D15: =SUMIFS('Lançamentos'!$L$2:$L$5010,'Lançamentos'!$A$2:$A$5010,"Insumos e papel",'Lançamentos'!$B$2:$B$5010,$A15,'Lançamentos'!$C$2:$C$5010,D$4) | E15: =SUMIFS('Lançamentos'!$L$2:$L$5010,'Lançamentos'!$A$2:$A$5010,"Insumos e papel",'Lançamentos'!$B$2:$B$5010,$A15,'Lançamentos'!$C$2:$C$5010,E$4) | F15: =SUMIFS('Lançamentos'!$L$2:$L$5010,'Lançamentos'!$A$2:$A$5010,"Insumos e papel",'Lançamentos'!$B$2:$B$5010,$A15,'Lançamentos'!$C$2:$C$5010,F$4) | G15: =SUMIFS('Lançamentos'!$L$2:$L$5010,'Lançamentos'!$A$2:$A$5010,"Insumos e papel",'Lançamentos'!$B$2:$B$5010,$A15,'Lançamentos'!$C$2:$C$5010,G$4) | H15: =SUMIFS('Lançamentos'!$L$2:$L$5010,'Lançamentos'!$A$2:$A$5010,"Insumos e papel",'Lançamentos'!$B$2:$B$5010,$A15,'Lançamentos'!$C$2:$C$5010,H$4) | I15: =SUMIFS('Lançamentos'!$L$2:$L$5010,'Lançamentos'!$A$2:$A$5010,"Insumos e papel",'Lançamentos'!$B$2:$B$5010,$A15,'Lançamentos'!$C$2:$C$5010,I$4) | J15: =SUMIFS('Lançamentos'!$L$2:$L$5010,'Lançamentos'!$A$2:$A$5010,"Insumos e papel",'Lançamentos'!$B$2:$B$5010,$A15,'Lançamentos'!$C$2:$C$5010,J$4) | K15: =SUM(B15:J15) | L15: =K15/K$17 | M15: =SUMIFS('Lançamentos'!$L$2:$L$5010,'Lançamentos'!$A$2:$A$5010,"Insumos e papel",'Lançamentos'!$B$2:$B$5010,$A15,'Lançamentos'!$C$2:$C$5010,"Antes de 2026")
A16: 2.01.99 Compra de Caixas | B16: =SUMIFS('Lançamentos'!$L$2:$L$5010,'Lançamentos'!$A$2:$A$5010,"Insumos e papel",'Lançamentos'!$B$2:$B$5010,$A16,'Lançamentos'!$C$2:$C$5010,B$4) | C16: =SUMIFS('Lançamentos'!$L$2:$L$5010,'Lançamentos'!$A$2:$A$5010,"Insumos e papel",'Lançamentos'!$B$2:$B$5010,$A16,'Lançamentos'!$C$2:$C$5010,C$4) | D16: =SUMIFS('Lançamentos'!$L$2:$L$5010,'Lançamentos'!$A$2:$A$5010,"Insumos e papel",'Lançamentos'!$B$2:$B$5010,$A16,'Lançamentos'!$C$2:$C$5010,D$4) | E16: =SUMIFS('Lançamentos'!$L$2:$L$5010,'Lançamentos'!$A$2:$A$5010,"Insumos e papel",'Lançamentos'!$B$2:$B$5010,$A16,'Lançamentos'!$C$2:$C$5010,E$4) | F16: =SUMIFS('Lançamentos'!$L$2:$L$5010,'Lançamentos'!$A$2:$A$5010,"Insumos e papel",'Lançamentos'!$B$2:$B$5010,$A16,'Lançamentos'!$C$2:$C$5010,F$4) | G16: =SUMIFS('Lançamentos'!$L$2:$L$5010,'Lançamentos'!$A$2:$A$5010,"Insumos e papel",'Lançamentos'!$B$2:$B$5010,$A16,'Lançamentos'!$C$2:$C$5010,G$4) | H16: =SUMIFS('Lançamentos'!$L$2:$L$5010,'Lançamentos'!$A$2:$A$5010,"Insumos e papel",'Lançamentos'!$B$2:$B$5010,$A16,'Lançamentos'!$C$2:$C$5010,H$4) | I16: =SUMIFS('Lançamentos'!$L$2:$L$5010,'Lançamentos'!$A$2:$A$5010,"Insumos e papel",'Lançamentos'!$B$2:$B$5010,$A16,'Lançamentos'!$C$2:$C$5010,I$4) | J16: =SUMIFS('Lançamentos'!$L$2:$L$5010,'Lançamentos'!$A$2:$A$5010,"Insumos e papel",'Lançamentos'!$B$2:$B$5010,$A16,'Lançamentos'!$C$2:$C$5010,J$4) | K16: =SUM(B16:J16) | L16: =K16/K$17 | M16: =SUMIFS('Lançamentos'!$L$2:$L$5010,'Lançamentos'!$A$2:$A$5010,"Insumos e papel",'Lançamentos'!$B$2:$B$5010,$A16,'Lançamentos'!$C$2:$C$5010,"Antes de 2026")
A17: TOTAL INSUMOS E PAPEL | B17: =SUM(B5:B16) | C17: =SUM(C5:C16) | D17: =SUM(D5:D16) | E17: =SUM(E5:E16) | F17: =SUM(F5:F16) | G17: =SUM(G5:G16) | H17: =SUM(H5:H16) | I17: =SUM(I5:I16) | ... K17: =SUM(K5:K16) | L17: =K17/K$17 | M17: =SUM(M5:M16)
A19: Memo: valor bruto (com impostos) | B19: =SUMIFS('Lançamentos'!$J$2:$J$5010,'Lançamentos'!$A$2:$A$5010,"Insumos e papel",'Lançamentos'!$C$2:$C$5010,B$4) | C19: =SUMIFS('Lançamentos'!$J$2:$J$5010,'Lançamentos'!$A$2:$A$5010,"Insumos e papel",'Lançamentos'!$C$2:$C$5010,C$4) | D19: =SUMIFS('Lançamentos'!$J$2:$J$5010,'Lançamentos'!$A$2:$A$5010,"Insumos e papel",'Lançamentos'!$C$2:$C$5010,D$4) | E19: =SUMIFS('Lançamentos'!$J$2:$J$5010,'Lançamentos'!$A$2:$A$5010,"Insumos e papel",'Lançamentos'!$C$2:$C$5010,E$4) | F19: =SUMIFS('Lançamentos'!$J$2:$J$5010,'Lançamentos'!$A$2:$A$5010,"Insumos e papel",'Lançamentos'!$C$2:$C$5010,F$4) | G19: =SUMIFS('Lançamentos'!$J$2:$J$5010,'Lançamentos'!$A$2:$A$5010,"Insumos e papel",'Lançamentos'!$C$2:$C$5010,G$4) | H19: =SUMIFS('Lançamentos'!$J$2:$J$5010,'Lançamentos'!$A$2:$A$5010,"Insumos e papel",'Lançamentos'!$C$2:$C$5010,H$4) | I19: =SUMIFS('Lançamentos'!$J$2:$J$5010,'Lançamentos'!$A$2:$A$5010,"Insumos e papel",'Lançamentos'!$C$2:$C$5010,I$4) | J19: =SUMIFS('Lançamentos'!$J$2:$J$5010,'Lançamentos'!$A$2:$A$5010,"Insumos e papel",'Lançamentos'!$C$2:$C$5010,J$4) | K19: =SUM(B19:J19) | M19: =SUMIFS('Lançamentos'!$J$2:$J$5010,'Lançamentos'!$A$2:$A$5010,"Insumos e papel",'Lançamentos'!$C$2:$C$5010,"Antes de 2026")
A20: Memo: créditos abatidos | B20: =SUMIFS('Lançamentos'!$K$2:$K$5010,'Lançamentos'!$A$2:$A$5010,"Insumos e papel",'Lançamentos'!$C$2:$C$5010,B$4) | C20: =SUMIFS('Lançamentos'!$K$2:$K$5010,'Lançamentos'!$A$2:$A$5010,"Insumos e papel",'Lançamentos'!$C$2:$C$5010,C$4) | D20: =SUMIFS('Lançamentos'!$K$2:$K$5010,'Lançamentos'!$A$2:$A$5010,"Insumos e papel",'Lançamentos'!$C$2:$C$5010,D$4) | E20: =SUMIFS('Lançamentos'!$K$2:$K$5010,'Lançamentos'!$A$2:$A$5010,"Insumos e papel",'Lançamentos'!$C$2:$C$5010,E$4) | F20: =SUMIFS('Lançamentos'!$K$2:$K$5010,'Lançamentos'!$A$2:$A$5010,"Insumos e papel",'Lançamentos'!$C$2:$C$5010,F$4) | G20: =SUMIFS('Lançamentos'!$K$2:$K$5010,'Lançamentos'!$A$2:$A$5010,"Insumos e papel",'Lançamentos'!$C$2:$C$5010,G$4) | H20: =SUMIFS('Lançamentos'!$K$2:$K$5010,'Lançamentos'!$A$2:$A$5010,"Insumos e papel",'Lançamentos'!$C$2:$C$5010,H$4) | I20: =SUMIFS('Lançamentos'!$K$2:$K$5010,'Lançamentos'!$A$2:$A$5010,"Insumos e papel",'Lançamentos'!$C$2:$C$5010,I$4) | J20: =SUMIFS('Lançamentos'!$K$2:$K$5010,'Lançamentos'!$A$2:$A$5010,"Insumos e papel",'Lançamentos'!$C$2:$C$5010,J$4) | K20: =SUM(B20:J20) | M20: =SUMIFS('Lançamentos'!$K$2:$K$5010,'Lançamentos'!$A$2:$A$5010,"Insumos e papel",'Lançamentos'!$C$2:$C$5010,"Antes de 2026")
A21: Conferência: bruto − créditos − total (deve ser zero) | B21: =ROUND(B19-B20-B17,2) | C21: =ROUND(C19-C20-C17,2) | D21: =ROUND(D19-D20-D17,2) | E21: =ROUND(E19-E20-E17,2) | F21: =ROUND(F19-F20-F17,2) | G21: =ROUND(G19-G20-G17,2) | H21: =ROUND(H19-H20-H17,2) | I21: =ROUND(I19-I20-I17,2) | ... K21: =ROUND(K19-K20-K17,2) | M21: =ROUND(M19-M20-M17,2)
A23: Por fornecedor / transportadora
A24: Fornecedor / Transportadora | B24: 46023 | C24: 46054 | D24: 46082 | E24: 46113 | F24: 46143 | G24: 46174 | H24: 46204 | I24: 46235 | J24: 46266 | K24: Total 2026 | L24: % do total | M24: Memo: antes de 2026 | N24: Valor bruto 2026 | O24: Créditos 2026 | P24: Nº docs 2026
A25: CMPC Iguacu Embalagens Ltda | B25: =SUMIFS('Lançamentos'!$L$2:$L$5010,'Lançamentos'!$A$2:$A$5010,"Insumos e papel",'Lançamentos'!$H$2:$H$5010,$A25,'Lançamentos'!$C$2:$C$5010,B$24) | C25: =SUMIFS('Lançamentos'!$L$2:$L$5010,'Lançamentos'!$A$2:$A$5010,"Insumos e papel",'Lançamentos'!$H$2:$H$5010,$A25,'Lançamentos'!$C$2:$C$5010,C$24) | D25: =SUMIFS('Lançamentos'!$L$2:$L$5010,'Lançamentos'!$A$2:$A$5010,"Insumos e papel",'Lançamentos'!$H$2:$H$5010,$A25,'Lançamentos'!$C$2:$C$5010,D$24) | E25: =SUMIFS('Lançamentos'!$L$2:$L$5010,'Lançamentos'!$A$2:$A$5010,"Insumos e papel",'Lançamentos'!$H$2:$H$5010,$A25,'Lançamentos'!$C$2:$C$5010,E$24) | F25: =SUMIFS('Lançamentos'!$L$2:$L$5010,'Lançamentos'!$A$2:$A$5010,"Insumos e papel",'Lançamentos'!$H$2:$H$5010,$A25,'Lançamentos'!$C$2:$C$5010,F$24) | G25: =SUMIFS('Lançamentos'!$L$2:$L$5010,'Lançamentos'!$A$2:$A$5010,"Insumos e papel",'Lançamentos'!$H$2:$H$5010,$A25,'Lançamentos'!$C$2:$C$5010,G$24) | H25: =SUMIFS('Lançamentos'!$L$2:$L$5010,'Lançamentos'!$A$2:$A$5010,"Insumos e papel",'Lançamentos'!$H$2:$H$5010,$A25,'Lançamentos'!$C$2:$C$5010,H$24) | I25: =SUMIFS('Lançamentos'!$L$2:$L$5010,'Lançamentos'!$A$2:$A$5010,"Insumos e papel",'Lançamentos'!$H$2:$H$5010,$A25,'Lançamentos'!$C$2:$C$5010,I$24) | J25: =SUMIFS('Lançamentos'!$L$2:$L$5010,'Lançamentos'!$A$2:$A$5010,"Insumos e papel",'Lançamentos'!$H$2:$H$5010,$A25,'Lançamentos'!$C$2:$C$5010,J$24) | K25: =SUM(B25:J25) | L25: =K25/K$61 | M25: =SUMIFS('Lançamentos'!$L$2:$L$5010,'Lançamentos'!$A$2:$A$5010,"Insumos e papel",'Lançamentos'!$H$2:$H$5010,$A25,'Lançamentos'!$C$2:$C$5010,"Antes de 2026") | N25: =SUMIFS('Lançamentos'!$J$2:$J$5010,'Lançamentos'!$A$2:$A$5010,"Insumos e papel",'Lançamentos'!$H$2:$H$5010,$A25,'Lançamentos'!$D$2:$D$5010,"Em 2026") | O25: =SUMIFS('Lançamentos'!$K$2:$K$5010,'Lançamentos'!$A$2:$A$5010,"Insumos e papel",'Lançamentos'!$H$2:$H$5010,$A25,'Lançamentos'!$D$2:$D$5010,"Em 2026") | P25: =COUNTIFS('Lançamentos'!$A$2:$A$5010,"Insumos e papel",'Lançamentos'!$H$2:$H$5010,$A25,'Lançamentos'!$D$2:$D$5010,"Em 2026")
A26: NOVA CONPEL COMPANHIA NORDESTINA DE PAPEL LTDA | B26: =SUMIFS('Lançamentos'!$L$2:$L$5010,'Lançamentos'!$A$2:$A$5010,"Insumos e papel",'Lançamentos'!$H$2:$H$5010,$A26,'Lançamentos'!$C$2:$C$5010,B$24) | C26: =SUMIFS('Lançamentos'!$L$2:$L$5010,'Lançamentos'!$A$2:$A$5010,"Insumos e papel",'Lançamentos'!$H$2:$H$5010,$A26,'Lançamentos'!$C$2:$C$5010,C$24) | D26: =SUMIFS('Lançamentos'!$L$2:$L$5010,'Lançamentos'!$A$2:$A$5010,"Insumos e papel",'Lançamentos'!$H$2:$H$5010,$A26,'Lançamentos'!$C$2:$C$5010,D$24) | E26: =SUMIFS('Lançamentos'!$L$2:$L$5010,'Lançamentos'!$A$2:$A$5010,"Insumos e papel",'Lançamentos'!$H$2:$H$5010,$A26,'Lançamentos'!$C$2:$C$5010,E$24) | F26: =SUMIFS('Lançamentos'!$L$2:$L$5010,'Lançamentos'!$A$2:$A$5010,"Insumos e papel",'Lançamentos'!$H$2:$H$5010,$A26,'Lançamentos'!$C$2:$C$5010,F$24) | G26: =SUMIFS('Lançamentos'!$L$2:$L$5010,'Lançamentos'!$A$2:$A$5010,"Insumos e papel",'Lançamentos'!$H$2:$H$5010,$A26,'Lançamentos'!$C$2:$C$5010,G$24) | H26: =SUMIFS('Lançamentos'!$L$2:$L$5010,'Lançamentos'!$A$2:$A$5010,"Insumos e papel",'Lançamentos'!$H$2:$H$5010,$A26,'Lançamentos'!$C$2:$C$5010,H$24) | I26: =SUMIFS('Lançamentos'!$L$2:$L$5010,'Lançamentos'!$A$2:$A$5010,"Insumos e papel",'Lançamentos'!$H$2:$H$5010,$A26,'Lançamentos'!$C$2:$C$5010,I$24) | J26: =SUMIFS('Lançamentos'!$L$2:$L$5010,'Lançamentos'!$A$2:$A$5010,"Insumos e papel",'Lançamentos'!$H$2:$H$5010,$A26,'Lançamentos'!$C$2:$C$5010,J$24) | K26: =SUM(B26:J26) | L26: =K26/K$61 | M26: =SUMIFS('Lançamentos'!$L$2:$L$5010,'Lançamentos'!$A$2:$A$5010,"Insumos e papel",'Lançamentos'!$H$2:$H$5010,$A26,'Lançamentos'!$C$2:$C$5010,"Antes de 2026") | N26: =SUMIFS('Lançamentos'!$J$2:$J$5010,'Lançamentos'!$A$2:$A$5010,"Insumos e papel",'Lançamentos'!$H$2:$H$5010,$A26,'Lançamentos'!$D$2:$D$5010,"Em 2026") | O26: =SUMIFS('Lançamentos'!$K$2:$K$5010,'Lançamentos'!$A$2:$A$5010,"Insumos e papel",'Lançamentos'!$H$2:$H$5010,$A26,'Lançamentos'!$D$2:$D$5010,"Em 2026") | P26: =COUNTIFS('Lançamentos'!$A$2:$A$5010,"Insumos e papel",'Lançamentos'!$H$2:$H$5010,$A26,'Lançamentos'!$D$2:$D$5010,"Em 2026")
A27: COCELPA CIA DE CEL. E PAPEL DO PARANA SA | B27: =SUMIFS('Lançamentos'!$L$2:$L$5010,'Lançamentos'!$A$2:$A$5010,"Insumos e papel",'Lançamentos'!$H$2:$H$5010,$A27,'Lançamentos'!$C$2:$C$5010,B$24) | C27: =SUMIFS('Lançamentos'!$L$2:$L$5010,'Lançamentos'!$A$2:$A$5010,"Insumos e papel",'Lançamentos'!$H$2:$H$5010,$A27,'Lançamentos'!$C$2:$C$5010,C$24) | D27: =SUMIFS('Lançamentos'!$L$2:$L$5010,'Lançamentos'!$A$2:$A$5010,"Insumos e papel",'Lançamentos'!$H$2:$H$5010,$A27,'Lançamentos'!$C$2:$C$5010,D$24) | E27: =SUMIFS('Lançamentos'!$L$2:$L$5010,'Lançamentos'!$A$2:$A$5010,"Insumos e papel",'Lançamentos'!$H$2:$H$5010,$A27,'Lançamentos'!$C$2:$C$5010,E$24) | F27: =SUMIFS('Lançamentos'!$L$2:$L$5010,'Lançamentos'!$A$2:$A$5010,"Insumos e papel",'Lançamentos'!$H$2:$H$5010,$A27,'Lançamentos'!$C$2:$C$5010,F$24) | G27: =SUMIFS('Lançamentos'!$L$2:$L$5010,'Lançamentos'!$A$2:$A$5010,"Insumos e papel",'Lançamentos'!$H$2:$H$5010,$A27,'Lançamentos'!$C$2:$C$5010,G$24) | H27: =SUMIFS('Lançamentos'!$L$2:$L$5010,'Lançamentos'!$A$2:$A$5010,"Insumos e papel",'Lançamentos'!$H$2:$H$5010,$A27,'Lançamentos'!$C$2:$C$5010,H$24) | I27: =SUMIFS('Lançamentos'!$L$2:$L$5010,'Lançamentos'!$A$2:$A$5010,"Insumos e papel",'Lançamentos'!$H$2:$H$5010,$A27,'Lançamentos'!$C$2:$C$5010,I$24) | J27: =SUMIFS('Lançamentos'!$L$2:$L$5010,'Lançamentos'!$A$2:$A$5010,"Insumos e papel",'Lançamentos'!$H$2:$H$5010,$A27,'Lançamentos'!$C$2:$C$5010,J$24) | K27: =SUM(B27:J27) | L27: =K27/K$61 | M27: =SUMIFS('Lançamentos'!$L$2:$L$5010,'Lançamentos'!$A$2:$A$5010,"Insumos e papel",'Lançamentos'!$H$2:$H$5010,$A27,'Lançamentos'!$C$2:$C$5010,"Antes de 2026") | N27: =SUMIFS('Lançamentos'!$J$2:$J$5010,'Lançamentos'!$A$2:$A$5010,"Insumos e papel",'Lançamentos'!$H$2:$H$5010,$A27,'Lançamentos'!$D$2:$D$5010,"Em 2026") | O27: =SUMIFS('Lançamentos'!$K$2:$K$5010,'Lançamentos'!$A$2:$A$5010,"Insumos e papel",'Lançamentos'!$H$2:$H$5010,$A27,'Lançamentos'!$D$2:$D$5010,"Em 2026") | P27: =COUNTIFS('Lançamentos'!$A$2:$A$5010,"Insumos e papel",'Lançamentos'!$H$2:$H$5010,$A27,'Lançamentos'!$D$2:$D$5010,"Em 2026")
A28: COLAMID | B28: =SUMIFS('Lançamentos'!$L$2:$L$5010,'Lançamentos'!$A$2:$A$5010,"Insumos e papel",'Lançamentos'!$H$2:$H$5010,$A28,'Lançamentos'!$C$2:$C$5010,B$24) | C28: =SUMIFS('Lançamentos'!$L$2:$L$5010,'Lançamentos'!$A$2:$A$5010,"Insumos e papel",'Lançamentos'!$H$2:$H$5010,$A28,'Lançamentos'!$C$2:$C$5010,C$24) | D28: =SUMIFS('Lançamentos'!$L$2:$L$5010,'Lançamentos'!$A$2:$A$5010,"Insumos e papel",'Lançamentos'!$H$2:$H$5010,$A28,'Lançamentos'!$C$2:$C$5010,D$24) | E28: =SUMIFS('Lançamentos'!$L$2:$L$5010,'Lançamentos'!$A$2:$A$5010,"Insumos e papel",'Lançamentos'!$H$2:$H$5010,$A28,'Lançamentos'!$C$2:$C$5010,E$24) | F28: =SUMIFS('Lançamentos'!$L$2:$L$5010,'Lançamentos'!$A$2:$A$5010,"Insumos e papel",'Lançamentos'!$H$2:$H$5010,$A28,'Lançamentos'!$C$2:$C$5010,F$24) | G28: =SUMIFS('Lançamentos'!$L$2:$L$5010,'Lançamentos'!$A$2:$A$5010,"Insumos e papel",'Lançamentos'!$H$2:$H$5010,$A28,'Lançamentos'!$C$2:$C$5010,G$24) | H28: =SUMIFS('Lançamentos'!$L$2:$L$5010,'Lançamentos'!$A$2:$A$5010,"Insumos e papel",'Lançamentos'!$H$2:$H$5010,$A28,'Lançamentos'!$C$2:$C$5010,H$24) | I28: =SUMIFS('Lançamentos'!$L$2:$L$5010,'Lançamentos'!$A$2:$A$5010,"Insumos e papel",'Lançamentos'!$H$2:$H$5010,$A28,'Lançamentos'!$C$2:$C$5010,I$24) | J28: =SUMIFS('Lançamentos'!$L$2:$L$5010,'Lançamentos'!$A$2:$A$5010,"Insumos e papel",'Lançamentos'!$H$2:$H$5010,$A28,'Lançamentos'!$C$2:$C$5010,J$24) | K28: =SUM(B28:J28) | L28: =K28/K$61 | M28: =SUMIFS('Lançamentos'!$L$2:$L$5010,'Lançamentos'!$A$2:$A$5010,"Insumos e papel",'Lançamentos'!$H$2:$H$5010,$A28,'Lançamentos'!$C$2:$C$5010,"Antes de 2026") | N28: =SUMIFS('Lançamentos'!$J$2:$J$5010,'Lançamentos'!$A$2:$A$5010,"Insumos e papel",'Lançamentos'!$H$2:$H$5010,$A28,'Lançamentos'!$D$2:$D$5010,"Em 2026") | O28: =SUMIFS('Lançamentos'!$K$2:$K$5010,'Lançamentos'!$A$2:$A$5010,"Insumos e papel",'Lançamentos'!$H$2:$H$5010,$A28,'Lançamentos'!$D$2:$D$5010,"Em 2026") | P28: =COUNTIFS('Lançamentos'!$A$2:$A$5010,"Insumos e papel",'Lançamentos'!$H$2:$H$5010,$A28,'Lançamentos'!$D$2:$D$5010,"Em 2026")
A29: SANTA MARIA CIA DE PAPEL E CELULOSE | B29: =SUMIFS('Lançamentos'!$L$2:$L$5010,'Lançamentos'!$A$2:$A$5010,"Insumos e papel",'Lançamentos'!$H$2:$H$5010,$A29,'Lançamentos'!$C$2:$C$5010,B$24) | C29: =SUMIFS('Lançamentos'!$L$2:$L$5010,'Lançamentos'!$A$2:$A$5010,"Insumos e papel",'Lançamentos'!$H$2:$H$5010,$A29,'Lançamentos'!$C$2:$C$5010,C$24) | D29: =SUMIFS('Lançamentos'!$L$2:$L$5010,'Lançamentos'!$A$2:$A$5010,"Insumos e papel",'Lançamentos'!$H$2:$H$5010,$A29,'Lançamentos'!$C$2:$C$5010,D$24) | E29: =SUMIFS('Lançamentos'!$L$2:$L$5010,'Lançamentos'!$A$2:$A$5010,"Insumos e papel",'Lançamentos'!$H$2:$H$5010,$A29,'Lançamentos'!$C$2:$C$5010,E$24) | F29: =SUMIFS('Lançamentos'!$L$2:$L$5010,'Lançamentos'!$A$2:$A$5010,"Insumos e papel",'Lançamentos'!$H$2:$H$5010,$A29,'Lançamentos'!$C$2:$C$5010,F$24) | G29: =SUMIFS('Lançamentos'!$L$2:$L$5010,'Lançamentos'!$A$2:$A$5010,"Insumos e papel",'Lançamentos'!$H$2:$H$5010,$A29,'Lançamentos'!$C$2:$C$5010,G$24) | H29: =SUMIFS('Lançamentos'!$L$2:$L$5010,'Lançamentos'!$A$2:$A$5010,"Insumos e papel",'Lançamentos'!$H$2:$H$5010,$A29,'Lançamentos'!$C$2:$C$5010,H$24) | I29: =SUMIFS('Lançamentos'!$L$2:$L$5010,'Lançamentos'!$A$2:$A$5010,"Insumos e papel",'Lançamentos'!$H$2:$H$5010,$A29,'Lançamentos'!$C$2:$C$5010,I$24) | J29: =SUMIFS('Lançamentos'!$L$2:$L$5010,'Lançamentos'!$A$2:$A$5010,"Insumos e papel",'Lançamentos'!$H$2:$H$5010,$A29,'Lançamentos'!$C$2:$C$5010,J$24) | K29: =SUM(B29:J29) | L29: =K29/K$61 | M29: =SUMIFS('Lançamentos'!$L$2:$L$5010,'Lançamentos'!$A$2:$A$5010,"Insumos e papel",'Lançamentos'!$H$2:$H$5010,$A29,'Lançamentos'!$C$2:$C$5010,"Antes de 2026") | N29: =SUMIFS('Lançamentos'!$J$2:$J$5010,'Lançamentos'!$A$2:$A$5010,"Insumos e papel",'Lançamentos'!$H$2:$H$5010,$A29,'Lançamentos'!$D$2:$D$5010,"Em 2026") | O29: =SUMIFS('Lançamentos'!$K$2:$K$5010,'Lançamentos'!$A$2:$A$5010,"Insumos e papel",'Lançamentos'!$H$2:$H$5010,$A29,'Lançamentos'!$D$2:$D$5010,"Em 2026") | P29: =COUNTIFS('Lançamentos'!$A$2:$A$5010,"Insumos e papel",'Lançamentos'!$H$2:$H$5010,$A29,'Lançamentos'!$D$2:$D$5010,"Em 2026")
A30: ALSTEK SOLUCOES EM EMBALAGENS LTDA | B30: =SUMIFS('Lançamentos'!$L$2:$L$5010,'Lançamentos'!$A$2:$A$5010,"Insumos e papel",'Lançamentos'!$H$2:$H$5010,$A30,'Lançamentos'!$C$2:$C$5010,B$24) | C30: =SUMIFS('Lançamentos'!$L$2:$L$5010,'Lançamentos'!$A$2:$A$5010,"Insumos e papel",'Lançamentos'!$H$2:$H$5010,$A30,'Lançamentos'!$C$2:$C$5010,C$24) | D30: =SUMIFS('Lançamentos'!$L$2:$L$5010,'Lançamentos'!$A$2:$A$5010,"Insumos e papel",'Lançamentos'!$H$2:$H$5010,$A30,'Lançamentos'!$C$2:$C$5010,D$24) | E30: =SUMIFS('Lançamentos'!$L$2:$L$5010,'Lançamentos'!$A$2:$A$5010,"Insumos e papel",'Lançamentos'!$H$2:$H$5010,$A30,'Lançamentos'!$C$2:$C$5010,E$24) | F30: =SUMIFS('Lançamentos'!$L$2:$L$5010,'Lançamentos'!$A$2:$A$5010,"Insumos e papel",'Lançamentos'!$H$2:$H$5010,$A30,'Lançamentos'!$C$2:$C$5010,F$24) | G30: =SUMIFS('Lançamentos'!$L$2:$L$5010,'Lançamentos'!$A$2:$A$5010,"Insumos e papel",'Lançamentos'!$H$2:$H$5010,$A30,'Lançamentos'!$C$2:$C$5010,G$24) | H30: =SUMIFS('Lançamentos'!$L$2:$L$5010,'Lançamentos'!$A$2:$A$5010,"Insumos e papel",'Lançamentos'!$H$2:$H$5010,$A30,'Lançamentos'!$C$2:$C$5010,H$24) | I30: =SUMIFS('Lançamentos'!$L$2:$L$5010,'Lançamentos'!$A$2:$A$5010,"Insumos e papel",'Lançamentos'!$H$2:$H$5010,$A30,'Lançamentos'!$C$2:$C$5010,I$24) | J30: =SUMIFS('Lançamentos'!$L$2:$L$5010,'Lançamentos'!$A$2:$A$5010,"Insumos e papel",'Lançamentos'!$H$2:$H$5010,$A30,'Lançamentos'!$C$2:$C$5010,J$24) | K30: =SUM(B30:J30) | L30: =K30/K$61 | M30: =SUMIFS('Lançamentos'!$L$2:$L$5010,'Lançamentos'!$A$2:$A$5010,"Insumos e papel",'Lançamentos'!$H$2:$H$5010,$A30,'Lançamentos'!$C$2:$C$5010,"Antes de 2026") | N30: =SUMIFS('Lançamentos'!$J$2:$J$5010,'Lançamentos'!$A$2:$A$5010,"Insumos e papel",'Lançamentos'!$H$2:$H$5010,$A30,'Lançamentos'!$D$2:$D$5010,"Em 2026") | O30: =SUMIFS('Lançamentos'!$K$2:$K$5010,'Lançamentos'!$A$2:$A$5010,"Insumos e papel",'Lançamentos'!$H$2:$H$5010,$A30,'Lançamentos'!$D$2:$D$5010,"Em 2026") | P30: =COUNTIFS('Lançamentos'!$A$2:$A$5010,"Insumos e papel",'Lançamentos'!$H$2:$H$5010,$A30,'Lançamentos'!$D$2:$D$5010,"Em 2026")
A31: REQUIM PRODUTOS QUIMICOS LTDA | B31: =SUMIFS('Lançamentos'!$L$2:$L$5010,'Lançamentos'!$A$2:$A$5010,"Insumos e papel",'Lançamentos'!$H$2:$H$5010,$A31,'Lançamentos'!$C$2:$C$5010,B$24) | C31: =SUMIFS('Lançamentos'!$L$2:$L$5010,'Lançamentos'!$A$2:$A$5010,"Insumos e papel",'Lançamentos'!$H$2:$H$5010,$A31,'Lançamentos'!$C$2:$C$5010,C$24) | D31: =SUMIFS('Lançamentos'!$L$2:$L$5010,'Lançamentos'!$A$2:$A$5010,"Insumos e papel",'Lançamentos'!$H$2:$H$5010,$A31,'Lançamentos'!$C$2:$C$5010,D$24) | E31: =SUMIFS('Lançamentos'!$L$2:$L$5010,'Lançamentos'!$A$2:$A$5010,"Insumos e papel",'Lançamentos'!$H$2:$H$5010,$A31,'Lançamentos'!$C$2:$C$5010,E$24) | F31: =SUMIFS('Lançamentos'!$L$2:$L$5010,'Lançamentos'!$A$2:$A$5010,"Insumos e papel",'Lançamentos'!$H$2:$H$5010,$A31,'Lançamentos'!$C$2:$C$5010,F$24) | G31: =SUMIFS('Lançamentos'!$L$2:$L$5010,'Lançamentos'!$A$2:$A$5010,"Insumos e papel",'Lançamentos'!$H$2:$H$5010,$A31,'Lançamentos'!$C$2:$C$5010,G$24) | H31: =SUMIFS('Lançamentos'!$L$2:$L$5010,'Lançamentos'!$A$2:$A$5010,"Insumos e papel",'Lançamentos'!$H$2:$H$5010,$A31,'Lançamentos'!$C$2:$C$5010,H$24) | I31: =SUMIFS('Lançamentos'!$L$2:$L$5010,'Lançamentos'!$A$2:$A$5010,"Insumos e papel",'Lançamentos'!$H$2:$H$5010,$A31,'Lançamentos'!$C$2:$C$5010,I$24) | J31: =SUMIFS('Lançamentos'!$L$2:$L$5010,'Lançamentos'!$A$2:$A$5010,"Insumos e papel",'Lançamentos'!$H$2:$H$5010,$A31,'Lançamentos'!$C$2:$C$5010,J$24) | K31: =SUM(B31:J31) | L31: =K31/K$61 | M31: =SUMIFS('Lançamentos'!$L$2:$L$5010,'Lançamentos'!$A$2:$A$5010,"Insumos e papel",'Lançamentos'!$H$2:$H$5010,$A31,'Lançamentos'!$C$2:$C$5010,"Antes de 2026") | N31: =SUMIFS('Lançamentos'!$J$2:$J$5010,'Lançamentos'!$A$2:$A$5010,"Insumos e papel",'Lançamentos'!$H$2:$H$5010,$A31,'Lançamentos'!$D$2:$D$5010,"Em 2026") | O31: =SUMIFS('Lançamentos'!$K$2:$K$5010,'Lançamentos'!$A$2:$A$5010,"Insumos e papel",'Lançamentos'!$H$2:$H$5010,$A31,'Lançamentos'!$D$2:$D$5010,"Em 2026") | P31: =COUNTIFS('Lançamentos'!$A$2:$A$5010,"Insumos e papel",'Lançamentos'!$H$2:$H$5010,$A31,'Lançamentos'!$D$2:$D$5010,"Em 2026")
A32: IRANI PAPEL E EMBALAGEM S.A. | B32: =SUMIFS('Lançamentos'!$L$2:$L$5010,'Lançamentos'!$A$2:$A$5010,"Insumos e papel",'Lançamentos'!$H$2:$H$5010,$A32,'Lançamentos'!$C$2:$C$5010,B$24) | C32: =SUMIFS('Lançamentos'!$L$2:$L$5010,'Lançamentos'!$A$2:$A$5010,"Insumos e papel",'Lançamentos'!$H$2:$H$5010,$A32,'Lançamentos'!$C$2:$C$5010,C$24) | D32: =SUMIFS('Lançamentos'!$L$2:$L$5010,'Lançamentos'!$A$2:$A$5010,"Insumos e papel",'Lançamentos'!$H$2:$H$5010,$A32,'Lançamentos'!$C$2:$C$5010,D$24) | E32: =SUMIFS('Lançamentos'!$L$2:$L$5010,'Lançamentos'!$A$2:$A$5010,"Insumos e papel",'Lançamentos'!$H$2:$H$5010,$A32,'Lançamentos'!$C$2:$C$5010,E$24) | F32: =SUMIFS('Lançamentos'!$L$2:$L$5010,'Lançamentos'!$A$2:$A$5010,"Insumos e papel",'Lançamentos'!$H$2:$H$5010,$A32,'Lançamentos'!$C$2:$C$5010,F$24) | G32: =SUMIFS('Lançamentos'!$L$2:$L$5010,'Lançamentos'!$A$2:$A$5010,"Insumos e papel",'Lançamentos'!$H$2:$H$5010,$A32,'Lançamentos'!$C$2:$C$5010,G$24) | H32: =SUMIFS('Lançamentos'!$L$2:$L$5010,'Lançamentos'!$A$2:$A$5010,"Insumos e papel",'Lançamentos'!$H$2:$H$5010,$A32,'Lançamentos'!$C$2:$C$5010,H$24) | I32: =SUMIFS('Lançamentos'!$L$2:$L$5010,'Lançamentos'!$A$2:$A$5010,"Insumos e papel",'Lançamentos'!$H$2:$H$5010,$A32,'Lançamentos'!$C$2:$C$5010,I$24) | J32: =SUMIFS('Lançamentos'!$L$2:$L$5010,'Lançamentos'!$A$2:$A$5010,"Insumos e papel",'Lançamentos'!$H$2:$H$5010,$A32,'Lançamentos'!$C$2:$C$5010,J$24) | K32: =SUM(B32:J32) | L32: =K32/K$61 | M32: =SUMIFS('Lançamentos'!$L$2:$L$5010,'Lançamentos'!$A$2:$A$5010,"Insumos e papel",'Lançamentos'!$H$2:$H$5010,$A32,'Lançamentos'!$C$2:$C$5010,"Antes de 2026") | N32: =SUMIFS('Lançamentos'!$J$2:$J$5010,'Lançamentos'!$A$2:$A$5010,"Insumos e papel",'Lançamentos'!$H$2:$H$5010,$A32,'Lançamentos'!$D$2:$D$5010,"Em 2026") | O32: =SUMIFS('Lançamentos'!$K$2:$K$5010,'Lançamentos'!$A$2:$A$5010,"Insumos e papel",'Lançamentos'!$H$2:$H$5010,$A32,'Lançamentos'!$D$2:$D$5010,"Em 2026") | P32: =COUNTIFS('Lançamentos'!$A$2:$A$5010,"Insumos e papel",'Lançamentos'!$H$2:$H$5010,$A32,'Lançamentos'!$D$2:$D$5010,"Em 2026")
A33: FITTYCOR - INDUSTRIA E COMERCIO DE TINTAS ESPECIAIS LTDA | B33: =SUMIFS('Lançamentos'!$L$2:$L$5010,'Lançamentos'!$A$2:$A$5010,"Insumos e papel",'Lançamentos'!$H$2:$H$5010,$A33,'Lançamentos'!$C$2:$C$5010,B$24) | C33: =SUMIFS('Lançamentos'!$L$2:$L$5010,'Lançamentos'!$A$2:$A$5010,"Insumos e papel",'Lançamentos'!$H$2:$H$5010,$A33,'Lançamentos'!$C$2:$C$5010,C$24) | D33: =SUMIFS('Lançamentos'!$L$2:$L$5010,'Lançamentos'!$A$2:$A$5010,"Insumos e papel",'Lançamentos'!$H$2:$H$5010,$A33,'Lançamentos'!$C$2:$C$5010,D$24) | E33: =SUMIFS('Lançamentos'!$L$2:$L$5010,'Lançamentos'!$A$2:$A$5010,"Insumos e papel",'Lançamentos'!$H$2:$H$5010,$A33,'Lançamentos'!$C$2:$C$5010,E$24) | F33: =SUMIFS('Lançamentos'!$L$2:$L$5010,'Lançamentos'!$A$2:$A$5010,"Insumos e papel",'Lançamentos'!$H$2:$H$5010,$A33,'Lançamentos'!$C$2:$C$5010,F$24) | G33: =SUMIFS('Lançamentos'!$L$2:$L$5010,'Lançamentos'!$A$2:$A$5010,"Insumos e papel",'Lançamentos'!$H$2:$H$5010,$A33,'Lançamentos'!$C$2:$C$5010,G$24) | H33: =SUMIFS('Lançamentos'!$L$2:$L$5010,'Lançamentos'!$A$2:$A$5010,"Insumos e papel",'Lançamentos'!$H$2:$H$5010,$A33,'Lançamentos'!$C$2:$C$5010,H$24) | I33: =SUMIFS('Lançamentos'!$L$2:$L$5010,'Lançamentos'!$A$2:$A$5010,"Insumos e papel",'Lançamentos'!$H$2:$H$5010,$A33,'Lançamentos'!$C$2:$C$5010,I$24) | J33: =SUMIFS('Lançamentos'!$L$2:$L$5010,'Lançamentos'!$A$2:$A$5010,"Insumos e papel",'Lançamentos'!$H$2:$H$5010,$A33,'Lançamentos'!$C$2:$C$5010,J$24) | K33: =SUM(B33:J33) | L33: =K33/K$61 | M33: =SUMIFS('Lançamentos'!$L$2:$L$5010,'Lançamentos'!$A$2:$A$5010,"Insumos e papel",'Lançamentos'!$H$2:$H$5010,$A33,'Lançamentos'!$C$2:$C$5010,"Antes de 2026") | N33: =SUMIFS('Lançamentos'!$J$2:$J$5010,'Lançamentos'!$A$2:$A$5010,"Insumos e papel",'Lançamentos'!$H$2:$H$5010,$A33,'Lançamentos'!$D$2:$D$5010,"Em 2026") | O33: =SUMIFS('Lançamentos'!$K$2:$K$5010,'Lançamentos'!$A$2:$A$5010,"Insumos e papel",'Lançamentos'!$H$2:$H$5010,$A33,'Lançamentos'!$D$2:$D$5010,"Em 2026") | P33: =COUNTIFS('Lançamentos'!$A$2:$A$5010,"Insumos e papel",'Lançamentos'!$H$2:$H$5010,$A33,'Lançamentos'!$D$2:$D$5010,"Em 2026")
A34: BR EMBALAGENS INDUSTRIA E COMERCIO LTDA | B34: =SUMIFS('Lançamentos'!$L$2:$L$5010,'Lançamentos'!$A$2:$A$5010,"Insumos e papel",'Lançamentos'!$H$2:$H$5010,$A34,'Lançamentos'!$C$2:$C$5010,B$24) | C34: =SUMIFS('Lançamentos'!$L$2:$L$5010,'Lançamentos'!$A$2:$A$5010,"Insumos e papel",'Lançamentos'!$H$2:$H$5010,$A34,'Lançamentos'!$C$2:$C$5010,C$24) | D34: =SUMIFS('Lançamentos'!$L$2:$L$5010,'Lançamentos'!$A$2:$A$5010,"Insumos e papel",'Lançamentos'!$H$2:$H$5010,$A34,'Lançamentos'!$C$2:$C$5010,D$24) | E34: =SUMIFS('Lançamentos'!$L$2:$L$5010,'Lançamentos'!$A$2:$A$5010,"Insumos e papel",'Lançamentos'!$H$2:$H$5010,$A34,'Lançamentos'!$C$2:$C$5010,E$24) | F34: =SUMIFS('Lançamentos'!$L$2:$L$5010,'Lançamentos'!$A$2:$A$5010,"Insumos e papel",'Lançamentos'!$H$2:$H$5010,$A34,'Lançamentos'!$C$2:$C$5010,F$24) | G34: =SUMIFS('Lançamentos'!$L$2:$L$5010,'Lançamentos'!$A$2:$A$5010,"Insumos e papel",'Lançamentos'!$H$2:$H$5010,$A34,'Lançamentos'!$C$2:$C$5010,G$24) | H34: =SUMIFS('Lançamentos'!$L$2:$L$5010,'Lançamentos'!$A$2:$A$5010,"Insumos e papel",'Lançamentos'!$H$2:$H$5010,$A34,'Lançamentos'!$C$2:$C$5010,H$24) | I34: =SUMIFS('Lançamentos'!$L$2:$L$5010,'Lançamentos'!$A$2:$A$5010,"Insumos e papel",'Lançamentos'!$H$2:$H$5010,$A34,'Lançamentos'!$C$2:$C$5010,I$24) | J34: =SUMIFS('Lançamentos'!$L$2:$L$5010,'Lançamentos'!$A$2:$A$5010,"Insumos e papel",'Lançamentos'!$H$2:$H$5010,$A34,'Lançamentos'!$C$2:$C$5010,J$24) | K34: =SUM(B34:J34) | L34: =K34/K$61 | M34: =SUMIFS('Lançamentos'!$L$2:$L$5010,'Lançamentos'!$A$2:$A$5010,"Insumos e papel",'Lançamentos'!$H$2:$H$5010,$A34,'Lançamentos'!$C$2:$C$5010,"Antes de 2026") | N34: =SUMIFS('Lançamentos'!$J$2:$J$5010,'Lançamentos'!$A$2:$A$5010,"Insumos e papel",'Lançamentos'!$H$2:$H$5010,$A34,'Lançamentos'!$D$2:$D$5010,"Em 2026") | O34: =SUMIFS('Lançamentos'!$K$2:$K$5010,'Lançamentos'!$A$2:$A$5010,"Insumos e papel",'Lançamentos'!$H$2:$H$5010,$A34,'Lançamentos'!$D$2:$D$5010,"Em 2026") | P34: =COUNTIFS('Lançamentos'!$A$2:$A$5010,"Insumos e papel",'Lançamentos'!$H$2:$H$5010,$A34,'Lançamentos'!$D$2:$D$5010,"Em 2026")
A35: GDM INDUSTRIA E COMERCIO DE PLASTICOS LTDA. | B35: =SUMIFS('Lançamentos'!$L$2:$L$5010,'Lançamentos'!$A$2:$A$5010,"Insumos e papel",'Lançamentos'!$H$2:$H$5010,$A35,'Lançamentos'!$C$2:$C$5010,B$24) | C35: =SUMIFS('Lançamentos'!$L$2:$L$5010,'Lançamentos'!$A$2:$A$5010,"Insumos e papel",'Lançamentos'!$H$2:$H$5010,$A35,'Lançamentos'!$C$2:$C$5010,C$24) | D35: =SUMIFS('Lançamentos'!$L$2:$L$5010,'Lançamentos'!$A$2:$A$5010,"Insumos e papel",'Lançamentos'!$H$2:$H$5010,$A35,'Lançamentos'!$C$2:$C$5010,D$24) | E35: =SUMIFS('Lançamentos'!$L$2:$L$5010,'Lançamentos'!$A$2:$A$5010,"Insumos e papel",'Lançamentos'!$H$2:$H$5010,$A35,'Lançamentos'!$C$2:$C$5010,E$24) | F35: =SUMIFS('Lançamentos'!$L$2:$L$5010,'Lançamentos'!$A$2:$A$5010,"Insumos e papel",'Lançamentos'!$H$2:$H$5010,$A35,'Lançamentos'!$C$2:$C$5010,F$24) | G35: =SUMIFS('Lançamentos'!$L$2:$L$5010,'Lançamentos'!$A$2:$A$5010,"Insumos e papel",'Lançamentos'!$H$2:$H$5010,$A35,'Lançamentos'!$C$2:$C$5010,G$24) | H35: =SUMIFS('Lançamentos'!$L$2:$L$5010,'Lançamentos'!$A$2:$A$5010,"Insumos e papel",'Lançamentos'!$H$2:$H$5010,$A35,'Lançamentos'!$C$2:$C$5010,H$24) | I35: =SUMIFS('Lançamentos'!$L$2:$L$5010,'Lançamentos'!$A$2:$A$5010,"Insumos e papel",'Lançamentos'!$H$2:$H$5010,$A35,'Lançamentos'!$C$2:$C$5010,I$24) | J35: =SUMIFS('Lançamentos'!$L$2:$L$5010,'Lançamentos'!$A$2:$A$5010,"Insumos e papel",'Lançamentos'!$H$2:$H$5010,$A35,'Lançamentos'!$C$2:$C$5010,J$24) | K35: =SUM(B35:J35) | L35: =K35/K$61 | M35: =SUMIFS('Lançamentos'!$L$2:$L$5010,'Lançamentos'!$A$2:$A$5010,"Insumos e papel",'Lançamentos'!$H$2:$H$5010,$A35,'Lançamentos'!$C$2:$C$5010,"Antes de 2026") | N35: =SUMIFS('Lançamentos'!$J$2:$J$5010,'Lançamentos'!$A$2:$A$5010,"Insumos e papel",'Lançamentos'!$H$2:$H$5010,$A35,'Lançamentos'!$D$2:$D$5010,"Em 2026") | O35: =SUMIFS('Lançamentos'!$K$2:$K$5010,'Lançamentos'!$A$2:$A$5010,"Insumos e papel",'Lançamentos'!$H$2:$H$5010,$A35,'Lançamentos'!$D$2:$D$5010,"Em 2026") | P35: =COUNTIFS('Lançamentos'!$A$2:$A$5010,"Insumos e papel",'Lançamentos'!$H$2:$H$5010,$A35,'Lançamentos'!$D$2:$D$5010,"Em 2026")
A36: ANIN INDUSTRIA E COMERCIO DE PAPEL LTDA | B36: =SUMIFS('Lançamentos'!$L$2:$L$5010,'Lançamentos'!$A$2:$A$5010,"Insumos e papel",'Lançamentos'!$H$2:$H$5010,$A36,'Lançamentos'!$C$2:$C$5010,B$24) | C36: =SUMIFS('Lançamentos'!$L$2:$L$5010,'Lançamentos'!$A$2:$A$5010,"Insumos e papel",'Lançamentos'!$H$2:$H$5010,$A36,'Lançamentos'!$C$2:$C$5010,C$24) | D36: =SUMIFS('Lançamentos'!$L$2:$L$5010,'Lançamentos'!$A$2:$A$5010,"Insumos e papel",'Lançamentos'!$H$2:$H$5010,$A36,'Lançamentos'!$C$2:$C$5010,D$24) | E36: =SUMIFS('Lançamentos'!$L$2:$L$5010,'Lançamentos'!$A$2:$A$5010,"Insumos e papel",'Lançamentos'!$H$2:$H$5010,$A36,'Lançamentos'!$C$2:$C$5010,E$24) | F36: =SUMIFS('Lançamentos'!$L$2:$L$5010,'Lançamentos'!$A$2:$A$5010,"Insumos e papel",'Lançamentos'!$H$2:$H$5010,$A36,'Lançamentos'!$C$2:$C$5010,F$24) | G36: =SUMIFS('Lançamentos'!$L$2:$L$5010,'Lançamentos'!$A$2:$A$5010,"Insumos e papel",'Lançamentos'!$H$2:$H$5010,$A36,'Lançamentos'!$C$2:$C$5010,G$24) | H36: =SUMIFS('Lançamentos'!$L$2:$L$5010,'Lançamentos'!$A$2:$A$5010,"Insumos e papel",'Lançamentos'!$H$2:$H$5010,$A36,'Lançamentos'!$C$2:$C$5010,H$24) | I36: =SUMIFS('Lançamentos'!$L$2:$L$5010,'Lançamentos'!$A$2:$A$5010,"Insumos e papel",'Lançamentos'!$H$2:$H$5010,$A36,'Lançamentos'!$C$2:$C$5010,I$24) | J36: =SUMIFS('Lançamentos'!$L$2:$L$5010,'Lançamentos'!$A$2:$A$5010,"Insumos e papel",'Lançamentos'!$H$2:$H$5010,$A36,'Lançamentos'!$C$2:$C$5010,J$24) | K36: =SUM(B36:J36) | L36: =K36/K$61 | M36: =SUMIFS('Lançamentos'!$L$2:$L$5010,'Lançamentos'!$A$2:$A$5010,"Insumos e papel",'Lançamentos'!$H$2:$H$5010,$A36,'Lançamentos'!$C$2:$C$5010,"Antes de 2026") | N36: =SUMIFS('Lançamentos'!$J$2:$J$5010,'Lançamentos'!$A$2:$A$5010,"Insumos e papel",'Lançamentos'!$H$2:$H$5010,$A36,'Lançamentos'!$D$2:$D$5010,"Em 2026") | O36: =SUMIFS('Lançamentos'!$K$2:$K$5010,'Lançamentos'!$A$2:$A$5010,"Insumos e papel",'Lançamentos'!$H$2:$H$5010,$A36,'Lançamentos'!$D$2:$D$5010,"Em 2026") | P36: =COUNTIFS('Lançamentos'!$A$2:$A$5010,"Insumos e papel",'Lançamentos'!$H$2:$H$5010,$A36,'Lançamentos'!$D$2:$D$5010,"Em 2026")
... A60: INFORPOINT SERVICOS E COMERCIO EM TECNOLOGIA LTDA | B60: =SUMIFS('Lançamentos'!$L$2:$L$5010,'Lançamentos'!$A$2:$A$5010,"Insumos e papel",'Lançamentos'!$H$2:$H$5010,$A60,'Lançamentos'!$C$2:$C$5010,B$24) | C60: =SUMIFS('Lançamentos'!$L$2:$L$5010,'Lançamentos'!$A$2:$A$5010,"Insumos e papel",'Lançamentos'!$H$2:$H$5010,$A60,'Lançamentos'!$C$2:$C$5010,C$24) | D60: =SUMIFS('Lançamentos'!$L$2:$L$5010,'Lançamentos'!$A$2:$A$5010,"Insumos e papel",'Lançamentos'!$H$2:$H$5010,$A60,'Lançamentos'!$C$2:$C$5010,D$24) | E60: =SUMIFS('Lançamentos'!$L$2:$L$5010,'Lançamentos'!$A$2:$A$5010,"Insumos e papel",'Lançamentos'!$H$2:$H$5010,$A60,'Lançamentos'!$C$2:$C$5010,E$24) | F60: =SUMIFS('Lançamentos'!$L$2:$L$5010,'Lançamentos'!$A$2:$A$5010,"Insumos e papel",'Lançamentos'!$H$2:$H$5010,$A60,'Lançamentos'!$C$2:$C$5010,F$24) | G60: =SUMIFS('Lançamentos'!$L$2:$L$5010,'Lançamentos'!$A$2:$A$5010,"Insumos e papel",'Lançamentos'!$H$2:$H$5010,$A60,'Lançamentos'!$C$2:$C$5010,G$24) | H60: =SUMIFS('Lançamentos'!$L$2:$L$5010,'Lançamentos'!$A$2:$A$5010,"Insumos e papel",'Lançamentos'!$H$2:$H$5010,$A60,'Lançamentos'!$C$2:$C$5010,H$24) | I60: =SUMIFS('Lançamentos'!$L$2:$L$5010,'Lançamentos'!$A$2:$A$5010,"Insumos e papel",'Lançamentos'!$H$2:$H$5010,$A60,'Lançamentos'!$C$2:$C$5010,I$24) | J60: =SUMIFS('Lançamentos'!$L$2:$L$5010,'Lançamentos'!$A$2:$A$5010,"Insumos e papel",'Lançamentos'!$H$2:$H$5010,$A60,'Lançamentos'!$C$2:$C$5010,J$24) | K60: =SUM(B60:J60) | L60: =K60/K$61 | M60: =SUMIFS('Lançamentos'!$L$2:$L$5010,'Lançamentos'!$A$2:$A$5010,"Insumos e papel",'Lançamentos'!$H$2:$H$5010,$A60,'Lançamentos'!$C$2:$C$5010,"Antes de 2026") | N60: =SUMIFS('Lançamentos'!$J$2:$J$5010,'Lançamentos'!$A$2:$A$5010,"Insumos e papel",'Lançamentos'!$H$2:$H$5010,$A60,'Lançamentos'!$D$2:$D$5010,"Em 2026") | O60: =SUMIFS('Lançamentos'!$K$2:$K$5010,'Lançamentos'!$A$2:$A$5010,"Insumos e papel",'Lançamentos'!$H$2:$H$5010,$A60,'Lançamentos'!$D$2:$D$5010,"Em 2026") | P60: =COUNTIFS('Lançamentos'!$A$2:$A$5010,"Insumos e papel",'Lançamentos'!$H$2:$H$5010,$A60,'Lançamentos'!$D$2:$D$5010,"Em 2026")
A61: TOTAL INSUMOS E PAPEL | B61: =SUM(B25:B60) | C61: =SUM(C25:C60) | D61: =SUM(D25:D60) | E61: =SUM(E25:E60) | F61: =SUM(F25:F60) | G61: =SUM(G25:G60) | H61: =SUM(H25:H60) | I61: =SUM(I25:I60) | ... K61: =SUM(K25:K60) | L61: =K61/K$61 | M61: =SUM(M25:M60) | N61: =SUM(N25:N60) | O61: =SUM(O25:O60) | P61: =SUM(P25:P60)
A62: Conferência: total por fornecedor − total por subcategoria (deve ser zero) | B62: =ROUND(B61-B17,2) | C62: =ROUND(C61-C17,2) | D62: =ROUND(D61-D17,2) | E62: =ROUND(E61-E17,2) | F62: =ROUND(F61-F17,2) | G62: =ROUND(G61-G17,2) | H62: =ROUND(H61-H17,2) | I62: =ROUND(I61-I17,2) | ... K62: =ROUND(K61-K17,2) | M62: =ROUND(M61-M17,2)

Sheet Uso e consumo
A1: Uso e consumo – 2026 (VINCO)
A2: Material de uso e consumo, peças de máquinas, fardamento, EPI, limpeza e materiais administrativos. R$, mês de emissão, líquido de créditos (aba Premissas).
A4: Subcategoria (categoria do Omie) | B4: 46023 | C4: 46054 | D4: 46082 | E4: 46113 | F4: 46143 | G4: 46174 | H4: 46204 | I4: 46235 | J4: 46266 | K4: Total 2026 | L4: % do total | M4: Memo: antes de 2026
A5: 2.01.85 Compra de Uso e Consumo | B5: =SUMIFS('Lançamentos'!$L$2:$L$5010,'Lançamentos'!$A$2:$A$5010,"Uso e consumo",'Lançamentos'!$B$2:$B$5010,$A5,'Lançamentos'!$C$2:$C$5010,B$4) | C5: =SUMIFS('Lançamentos'!$L$2:$L$5010,'Lançamentos'!$A$2:$A$5010,"Uso e consumo",'Lançamentos'!$B$2:$B$5010,$A5,'Lançamentos'!$C$2:$C$5010,C$4) | D5: =SUMIFS('Lançamentos'!$L$2:$L$5010,'Lançamentos'!$A$2:$A$5010,"Uso e consumo",'Lançamentos'!$B$2:$B$5010,$A5,'Lançamentos'!$C$2:$C$5010,D$4) | E5: =SUMIFS('Lançamentos'!$L$2:$L$5010,'Lançamentos'!$A$2:$A$5010,"Uso e consumo",'Lançamentos'!$B$2:$B$5010,$A5,'Lançamentos'!$C$2:$C$5010,E$4) | F5: =SUMIFS('Lançamentos'!$L$2:$L$5010,'Lançamentos'!$A$2:$A$5010,"Uso e consumo",'Lançamentos'!$B$2:$B$5010,$A5,'Lançamentos'!$C$2:$C$5010,F$4) | G5: =SUMIFS('Lançamentos'!$L$2:$L$5010,'Lançamentos'!$A$2:$A$5010,"Uso e consumo",'Lançamentos'!$B$2:$B$5010,$A5,'Lançamentos'!$C$2:$C$5010,G$4) | H5: =SUMIFS('Lançamentos'!$L$2:$L$5010,'Lançamentos'!$A$2:$A$5010,"Uso e consumo",'Lançamentos'!$B$2:$B$5010,$A5,'Lançamentos'!$C$2:$C$5010,H$4) | I5: =SUMIFS('Lançamentos'!$L$2:$L$5010,'Lançamentos'!$A$2:$A$5010,"Uso e consumo",'Lançamentos'!$B$2:$B$5010,$A5,'Lançamentos'!$C$2:$C$5010,I$4) | J5: =SUMIFS('Lançamentos'!$L$2:$L$5010,'Lançamentos'!$A$2:$A$5010,"Uso e consumo",'Lançamentos'!$B$2:$B$5010,$A5,'Lançamentos'!$C$2:$C$5010,J$4) | K5: =SUM(B5:J5) | L5: =K5/K$13 | M5: =SUMIFS('Lançamentos'!$L$2:$L$5010,'Lançamentos'!$A$2:$A$5010,"Uso e consumo",'Lançamentos'!$B$2:$B$5010,$A5,'Lançamentos'!$C$2:$C$5010,"Antes de 2026")
A6: 2.01.87 Compra de Peças de Máquinas | B6: =SUMIFS('Lançamentos'!$L$2:$L$5010,'Lançamentos'!$A$2:$A$5010,"Uso e consumo",'Lançamentos'!$B$2:$B$5010,$A6,'Lançamentos'!$C$2:$C$5010,B$4) | C6: =SUMIFS('Lançamentos'!$L$2:$L$5010,'Lançamentos'!$A$2:$A$5010,"Uso e consumo",'Lançamentos'!$B$2:$B$5010,$A6,'Lançamentos'!$C$2:$C$5010,C$4) | D6: =SUMIFS('Lançamentos'!$L$2:$L$5010,'Lançamentos'!$A$2:$A$5010,"Uso e consumo",'Lançamentos'!$B$2:$B$5010,$A6,'Lançamentos'!$C$2:$C$5010,D$4) | E6: =SUMIFS('Lançamentos'!$L$2:$L$5010,'Lançamentos'!$A$2:$A$5010,"Uso e consumo",'Lançamentos'!$B$2:$B$5010,$A6,'Lançamentos'!$C$2:$C$5010,E$4) | F6: =SUMIFS('Lançamentos'!$L$2:$L$5010,'Lançamentos'!$A$2:$A$5010,"Uso e consumo",'Lançamentos'!$B$2:$B$5010,$A6,'Lançamentos'!$C$2:$C$5010,F$4) | G6: =SUMIFS('Lançamentos'!$L$2:$L$5010,'Lançamentos'!$A$2:$A$5010,"Uso e consumo",'Lançamentos'!$B$2:$B$5010,$A6,'Lançamentos'!$C$2:$C$5010,G$4) | H6: =SUMIFS('Lançamentos'!$L$2:$L$5010,'Lançamentos'!$A$2:$A$5010,"Uso e consumo",'Lançamentos'!$B$2:$B$5010,$A6,'Lançamentos'!$C$2:$C$5010,H$4) | I6: =SUMIFS('Lançamentos'!$L$2:$L$5010,'Lançamentos'!$A$2:$A$5010,"Uso e consumo",'Lançamentos'!$B$2:$B$5010,$A6,'Lançamentos'!$C$2:$C$5010,I$4) | J6: =SUMIFS('Lançamentos'!$L$2:$L$5010,'Lançamentos'!$A$2:$A$5010,"Uso e consumo",'Lançamentos'!$B$2:$B$5010,$A6,'Lançamentos'!$C$2:$C$5010,J$4) | K6: =SUM(B6:J6) | L6: =K6/K$13 | M6: =SUMIFS('Lançamentos'!$L$2:$L$5010,'Lançamentos'!$A$2:$A$5010,"Uso e consumo",'Lançamentos'!$B$2:$B$5010,$A6,'Lançamentos'!$C$2:$C$5010,"Antes de 2026")
A7: 2.03.88 Compra de Fardamento | B7: =SUMIFS('Lançamentos'!$L$2:$L$5010,'Lançamentos'!$A$2:$A$5010,"Uso e consumo",'Lançamentos'!$B$2:$B$5010,$A7,'Lançamentos'!$C$2:$C$5010,B$4) | C7: =SUMIFS('Lançamentos'!$L$2:$L$5010,'Lançamentos'!$A$2:$A$5010,"Uso e consumo",'Lançamentos'!$B$2:$B$5010,$A7,'Lançamentos'!$C$2:$C$5010,C$4) | D7: =SUMIFS('Lançamentos'!$L$2:$L$5010,'Lançamentos'!$A$2:$A$5010,"Uso e consumo",'Lançamentos'!$B$2:$B$5010,$A7,'Lançamentos'!$C$2:$C$5010,D$4) | E7: =SUMIFS('Lançamentos'!$L$2:$L$5010,'Lançamentos'!$A$2:$A$5010,"Uso e consumo",'Lançamentos'!$B$2:$B$5010,$A7,'Lançamentos'!$C$2:$C$5010,E$4) | F7: =SUMIFS('Lançamentos'!$L$2:$L$5010,'Lançamentos'!$A$2:$A$5010,"Uso e consumo",'Lançamentos'!$B$2:$B$5010,$A7,'Lançamentos'!$C$2:$C$5010,F$4) | G7: =SUMIFS('Lançamentos'!$L$2:$L$5010,'Lançamentos'!$A$2:$A$5010,"Uso e consumo",'Lançamentos'!$B$2:$B$5010,$A7,'Lançamentos'!$C$2:$C$5010,G$4) | H7: =SUMIFS('Lançamentos'!$L$2:$L$5010,'Lançamentos'!$A$2:$A$5010,"Uso e consumo",'Lançamentos'!$B$2:$B$5010,$A7,'Lançamentos'!$C$2:$C$5010,H$4) | I7: =SUMIFS('Lançamentos'!$L$2:$L$5010,'Lançamentos'!$A$2:$A$5010,"Uso e consumo",'Lançamentos'!$B$2:$B$5010,$A7,'Lançamentos'!$C$2:$C$5010,I$4) | J7: =SUMIFS('Lançamentos'!$L$2:$L$5010,'Lançamentos'!$A$2:$A$5010,"Uso e consumo",'Lançamentos'!$B$2:$B$5010,$A7,'Lançamentos'!$C$2:$C$5010,J$4) | K7: =SUM(B7:J7) | L7: =K7/K$13 | M7: =SUMIFS('Lançamentos'!$L$2:$L$5010,'Lançamentos'!$A$2:$A$5010,"Uso e consumo",'Lançamentos'!$B$2:$B$5010,$A7,'Lançamentos'!$C$2:$C$5010,"Antes de 2026")
A8: 2.03.90 Compra de EPI | B8: =SUMIFS('Lançamentos'!$L$2:$L$5010,'Lançamentos'!$A$2:$A$5010,"Uso e consumo",'Lançamentos'!$B$2:$B$5010,$A8,'Lançamentos'!$C$2:$C$5010,B$4) | C8: =SUMIFS('Lançamentos'!$L$2:$L$5010,'Lançamentos'!$A$2:$A$5010,"Uso e consumo",'Lançamentos'!$B$2:$B$5010,$A8,'Lançamentos'!$C$2:$C$5010,C$4) | D8: =SUMIFS('Lançamentos'!$L$2:$L$5010,'Lançamentos'!$A$2:$A$5010,"Uso e consumo",'Lançamentos'!$B$2:$B$5010,$A8,'Lançamentos'!$C$2:$C$5010,D$4) | E8: =SUMIFS('Lançamentos'!$L$2:$L$5010,'Lançamentos'!$A$2:$A$5010,"Uso e consumo",'Lançamentos'!$B$2:$B$5010,$A8,'Lançamentos'!$C$2:$C$5010,E$4) | F8: =SUMIFS('Lançamentos'!$L$2:$L$5010,'Lançamentos'!$A$2:$A$5010,"Uso e consumo",'Lançamentos'!$B$2:$B$5010,$A8,'Lançamentos'!$C$2:$C$5010,F$4) | G8: =SUMIFS('Lançamentos'!$L$2:$L$5010,'Lançamentos'!$A$2:$A$5010,"Uso e consumo",'Lançamentos'!$B$2:$B$5010,$A8,'Lançamentos'!$C$2:$C$5010,G$4) | H8: =SUMIFS('Lançamentos'!$L$2:$L$5010,'Lançamentos'!$A$2:$A$5010,"Uso e consumo",'Lançamentos'!$B$2:$B$5010,$A8,'Lançamentos'!$C$2:$C$5010,H$4) | I8: =SUMIFS('Lançamentos'!$L$2:$L$5010,'Lançamentos'!$A$2:$A$5010,"Uso e consumo",'Lançamentos'!$B$2:$B$5010,$A8,'Lançamentos'!$C$2:$C$5010,I$4) | J8: =SUMIFS('Lançamentos'!$L$2:$L$5010,'Lançamentos'!$A$2:$A$5010,"Uso e consumo",'Lançamentos'!$B$2:$B$5010,$A8,'Lançamentos'!$C$2:$C$5010,J$4) | K8: =SUM(B8:J8) | L8: =K8/K$13 | M8: =SUMIFS('Lançamentos'!$L$2:$L$5010,'Lançamentos'!$A$2:$A$5010,"Uso e consumo",'Lançamentos'!$B$2:$B$5010,$A8,'Lançamentos'!$C$2:$C$5010,"Antes de 2026")
A9: 2.04.06 Material de Escritório | B9: =SUMIFS('Lançamentos'!$L$2:$L$5010,'Lançamentos'!$A$2:$A$5010,"Uso e consumo",'Lançamentos'!$B$2:$B$5010,$A9,'Lançamentos'!$C$2:$C$5010,B$4) | C9: =SUMIFS('Lançamentos'!$L$2:$L$5010,'Lançamentos'!$A$2:$A$5010,"Uso e consumo",'Lançamentos'!$B$2:$B$5010,$A9,'Lançamentos'!$C$2:$C$5010,C$4) | D9: =SUMIFS('Lançamentos'!$L$2:$L$5010,'Lançamentos'!$A$2:$A$5010,"Uso e consumo",'Lançamentos'!$B$2:$B$5010,$A9,'Lançamentos'!$C$2:$C$5010,D$4) | E9: =SUMIFS('Lançamentos'!$L$2:$L$5010,'Lançamentos'!$A$2:$A$5010,"Uso e consumo",'Lançamentos'!$B$2:$B$5010,$A9,'Lançamentos'!$C$2:$C$5010,E$4) | F9: =SUMIFS('Lançamentos'!$L$2:$L$5010,'Lançamentos'!$A$2:$A$5010,"Uso e consumo",'Lançamentos'!$B$2:$B$5010,$A9,'Lançamentos'!$C$2:$C$5010,F$4) | G9: =SUMIFS('Lançamentos'!$L$2:$L$5010,'Lançamentos'!$A$2:$A$5010,"Uso e consumo",'Lançamentos'!$B$2:$B$5010,$A9,'Lançamentos'!$C$2:$C$5010,G$4) | H9: =SUMIFS('Lançamentos'!$L$2:$L$5010,'Lançamentos'!$A$2:$A$5010,"Uso e consumo",'Lançamentos'!$B$2:$B$5010,$A9,'Lançamentos'!$C$2:$C$5010,H$4) | I9: =SUMIFS('Lançamentos'!$L$2:$L$5010,'Lançamentos'!$A$2:$A$5010,"Uso e consumo",'Lançamentos'!$B$2:$B$5010,$A9,'Lançamentos'!$C$2:$C$5010,I$4) | J9: =SUMIFS('Lançamentos'!$L$2:$L$5010,'Lançamentos'!$A$2:$A$5010,"Uso e consumo",'Lançamentos'!$B$2:$B$5010,$A9,'Lançamentos'!$C$2:$C$5010,J$4) | K9: =SUM(B9:J9) | L9: =K9/K$13 | M9: =SUMIFS('Lançamentos'!$L$2:$L$5010,'Lançamentos'!$A$2:$A$5010,"Uso e consumo",'Lançamentos'!$B$2:$B$5010,$A9,'Lançamentos'!$C$2:$C$5010,"Antes de 2026")
A10: 2.04.91 Compra de Material de Limpeza | B10: =SUMIFS('Lançamentos'!$L$2:$L$5010,'Lançamentos'!$A$2:$A$5010,"Uso e consumo",'Lançamentos'!$B$2:$B$5010,$A10,'Lançamentos'!$C$2:$C$5010,B$4) | C10: =SUMIFS('Lançamentos'!$L$2:$L$5010,'Lançamentos'!$A$2:$A$5010,"Uso e consumo",'Lançamentos'!$B$2:$B$5010,$A10,'Lançamentos'!$C$2:$C$5010,C$4) | D10: =SUMIFS('Lançamentos'!$L$2:$L$5010,'Lançamentos'!$A$2:$A$5010,"Uso e consumo",'Lançamentos'!$B$2:$B$5010,$A10,'Lançamentos'!$C$2:$C$5010,D$4) | E10: =SUMIFS('Lançamentos'!$L$2:$L$5010,'Lançamentos'!$A$2:$A$5010,"Uso e consumo",'Lançamentos'!$B$2:$B$5010,$A10,'Lançamentos'!$C$2:$C$5010,E$4) | F10: =SUMIFS('Lançamentos'!$L$2:$L$5010,'Lançamentos'!$A$2:$A$5010,"Uso e consumo",'Lançamentos'!$B$2:$B$5010,$A10,'Lançamentos'!$C$2:$C$5010,F$4) | G10: =SUMIFS('Lançamentos'!$L$2:$L$5010,'Lançamentos'!$A$2:$A$5010,"Uso e consumo",'Lançamentos'!$B$2:$B$5010,$A10,'Lançamentos'!$C$2:$C$5010,G$4) | H10: =SUMIFS('Lançamentos'!$L$2:$L$5010,'Lançamentos'!$A$2:$A$5010,"Uso e consumo",'Lançamentos'!$B$2:$B$5010,$A10,'Lançamentos'!$C$2:$C$5010,H$4) | I10: =SUMIFS('Lançamentos'!$L$2:$L$5010,'Lançamentos'!$A$2:$A$5010,"Uso e consumo",'Lançamentos'!$B$2:$B$5010,$A10,'Lançamentos'!$C$2:$C$5010,I$4) | J10: =SUMIFS('Lançamentos'!$L$2:$L$5010,'Lançamentos'!$A$2:$A$5010,"Uso e consumo",'Lançamentos'!$B$2:$B$5010,$A10,'Lançamentos'!$C$2:$C$5010,J$4) | K10: =SUM(B10:J10) | L10: =K10/K$13 | M10: =SUMIFS('Lançamentos'!$L$2:$L$5010,'Lançamentos'!$A$2:$A$5010,"Uso e consumo",'Lançamentos'!$B$2:$B$5010,$A10,'Lançamentos'!$C$2:$C$5010,"Antes de 2026")
A11: 2.04.95 Copa e Cozinha | B11: =SUMIFS('Lançamentos'!$L$2:$L$5010,'Lançamentos'!$A$2:$A$5010,"Uso e consumo",'Lançamentos'!$B$2:$B$5010,$A11,'Lançamentos'!$C$2:$C$5010,B$4) | C11: =SUMIFS('Lançamentos'!$L$2:$L$5010,'Lançamentos'!$A$2:$A$5010,"Uso e consumo",'Lançamentos'!$B$2:$B$5010,$A11,'Lançamentos'!$C$2:$C$5010,C$4) | D11: =SUMIFS('Lançamentos'!$L$2:$L$5010,'Lançamentos'!$A$2:$A$5010,"Uso e consumo",'Lançamentos'!$B$2:$B$5010,$A11,'Lançamentos'!$C$2:$C$5010,D$4) | E11: =SUMIFS('Lançamentos'!$L$2:$L$5010,'Lançamentos'!$A$2:$A$5010,"Uso e consumo",'Lançamentos'!$B$2:$B$5010,$A11,'Lançamentos'!$C$2:$C$5010,E$4) | F11: =SUMIFS('Lançamentos'!$L$2:$L$5010,'Lançamentos'!$A$2:$A$5010,"Uso e consumo",'Lançamentos'!$B$2:$B$5010,$A11,'Lançamentos'!$C$2:$C$5010,F$4) | G11: =SUMIFS('Lançamentos'!$L$2:$L$5010,'Lançamentos'!$A$2:$A$5010,"Uso e consumo",'Lançamentos'!$B$2:$B$5010,$A11,'Lançamentos'!$C$2:$C$5010,G$4) | H11: =SUMIFS('Lançamentos'!$L$2:$L$5010,'Lançamentos'!$A$2:$A$5010,"Uso e consumo",'Lançamentos'!$B$2:$B$5010,$A11,'Lançamentos'!$C$2:$C$5010,H$4) | I11: =SUMIFS('Lançamentos'!$L$2:$L$5010,'Lançamentos'!$A$2:$A$5010,"Uso e consumo",'Lançamentos'!$B$2:$B$5010,$A11,'Lançamentos'!$C$2:$C$5010,I$4) | J11: =SUMIFS('Lançamentos'!$L$2:$L$5010,'Lançamentos'!$A$2:$A$5010,"Uso e consumo",'Lançamentos'!$B$2:$B$5010,$A11,'Lançamentos'!$C$2:$C$5010,J$4) | K11: =SUM(B11:J11) | L11: =K11/K$13 | M11: =SUMIFS('Lançamentos'!$L$2:$L$5010,'Lançamentos'!$A$2:$A$5010,"Uso e consumo",'Lançamentos'!$B$2:$B$5010,$A11,'Lançamentos'!$C$2:$C$5010,"Antes de 2026")
A12: 2.04.96 Bens de Pequeno Valor | B12: =SUMIFS('Lançamentos'!$L$2:$L$5010,'Lançamentos'!$A$2:$A$5010,"Uso e consumo",'Lançamentos'!$B$2:$B$5010,$A12,'Lançamentos'!$C$2:$C$5010,B$4) | C12: =SUMIFS('Lançamentos'!$L$2:$L$5010,'Lançamentos'!$A$2:$A$5010,"Uso e consumo",'Lançamentos'!$B$2:$B$5010,$A12,'Lançamentos'!$C$2:$C$5010,C$4) | D12: =SUMIFS('Lançamentos'!$L$2:$L$5010,'Lançamentos'!$A$2:$A$5010,"Uso e consumo",'Lançamentos'!$B$2:$B$5010,$A12,'Lançamentos'!$C$2:$C$5010,D$4) | E12: =SUMIFS('Lançamentos'!$L$2:$L$5010,'Lançamentos'!$A$2:$A$5010,"Uso e consumo",'Lançamentos'!$B$2:$B$5010,$A12,'Lançamentos'!$C$2:$C$5010,E$4) | F12: =SUMIFS('Lançamentos'!$L$2:$L$5010,'Lançamentos'!$A$2:$A$5010,"Uso e consumo",'Lançamentos'!$B$2:$B$5010,$A12,'Lançamentos'!$C$2:$C$5010,F$4) | G12: =SUMIFS('Lançamentos'!$L$2:$L$5010,'Lançamentos'!$A$2:$A$5010,"Uso e consumo",'Lançamentos'!$B$2:$B$5010,$A12,'Lançamentos'!$C$2:$C$5010,G$4) | H12: =SUMIFS('Lançamentos'!$L$2:$L$5010,'Lançamentos'!$A$2:$A$5010,"Uso e consumo",'Lançamentos'!$B$2:$B$5010,$A12,'Lançamentos'!$C$2:$C$5010,H$4) | I12: =SUMIFS('Lançamentos'!$L$2:$L$5010,'Lançamentos'!$A$2:$A$5010,"Uso e consumo",'Lançamentos'!$B$2:$B$5010,$A12,'Lançamentos'!$C$2:$C$5010,I$4) | J12: =SUMIFS('Lançamentos'!$L$2:$L$5010,'Lançamentos'!$A$2:$A$5010,"Uso e consumo",'Lançamentos'!$B$2:$B$5010,$A12,'Lançamentos'!$C$2:$C$5010,J$4) | K12: =SUM(B12:J12) | L12: =K12/K$13 | M12: =SUMIFS('Lançamentos'!$L$2:$L$5010,'Lançamentos'!$A$2:$A$5010,"Uso e consumo",'Lançamentos'!$B$2:$B$5010,$A12,'Lançamentos'!$C$2:$C$5010,"Antes de 2026")
A13: TOTAL USO E CONSUMO | B13: =SUM(B5:B12) | C13: =SUM(C5:C12) | D13: =SUM(D5:D12) | E13: =SUM(E5:E12) | F13: =SUM(F5:F12) | G13: =SUM(G5:G12) | H13: =SUM(H5:H12) | I13: =SUM(I5:I12) | ... K13: =SUM(K5:K12) | L13: =K13/K$13 | M13: =SUM(M5:M12)
A15: Memo: valor bruto (com impostos) | B15: =SUMIFS('Lançamentos'!$J$2:$J$5010,'Lançamentos'!$A$2:$A$5010,"Uso e consumo",'Lançamentos'!$C$2:$C$5010,B$4) | C15: =SUMIFS('Lançamentos'!$J$2:$J$5010,'Lançamentos'!$A$2:$A$5010,"Uso e consumo",'Lançamentos'!$C$2:$C$5010,C$4) | D15: =SUMIFS('Lançamentos'!$J$2:$J$5010,'Lançamentos'!$A$2:$A$5010,"Uso e consumo",'Lançamentos'!$C$2:$C$5010,D$4) | E15: =SUMIFS('Lançamentos'!$J$2:$J$5010,'Lançamentos'!$A$2:$A$5010,"Uso e consumo",'Lançamentos'!$C$2:$C$5010,E$4) | F15: =SUMIFS('Lançamentos'!$J$2:$J$5010,'Lançamentos'!$A$2:$A$5010,"Uso e consumo",'Lançamentos'!$C$2:$C$5010,F$4) | G15: =SUMIFS('Lançamentos'!$J$2:$J$5010,'Lançamentos'!$A$2:$A$5010,"Uso e consumo",'Lançamentos'!$C$2:$C$5010,G$4) | H15: =SUMIFS('Lançamentos'!$J$2:$J$5010,'Lançamentos'!$A$2:$A$5010,"Uso e consumo",'Lançamentos'!$C$2:$C$5010,H$4) | I15: =SUMIFS('Lançamentos'!$J$2:$J$5010,'Lançamentos'!$A$2:$A$5010,"Uso e consumo",'Lançamentos'!$C$2:$C$5010,I$4) | J15: =SUMIFS('Lançamentos'!$J$2:$J$5010,'Lançamentos'!$A$2:$A$5010,"Uso e consumo",'Lançamentos'!$C$2:$C$5010,J$4) | K15: =SUM(B15:J15) | M15: =SUMIFS('Lançamentos'!$J$2:$J$5010,'Lançamentos'!$A$2:$A$5010,"Uso e consumo",'Lançamentos'!$C$2:$C$5010,"Antes de 2026")
A16: Memo: créditos abatidos | B16: =SUMIFS('Lançamentos'!$K$2:$K$5010,'Lançamentos'!$A$2:$A$5010,"Uso e consumo",'Lançamentos'!$C$2:$C$5010,B$4) | C16: =SUMIFS('Lançamentos'!$K$2:$K$5010,'Lançamentos'!$A$2:$A$5010,"Uso e consumo",'Lançamentos'!$C$2:$C$5010,C$4) | D16: =SUMIFS('Lançamentos'!$K$2:$K$5010,'Lançamentos'!$A$2:$A$5010,"Uso e consumo",'Lançamentos'!$C$2:$C$5010,D$4) | E16: =SUMIFS('Lançamentos'!$K$2:$K$5010,'Lançamentos'!$A$2:$A$5010,"Uso e consumo",'Lançamentos'!$C$2:$C$5010,E$4) | F16: =SUMIFS('Lançamentos'!$K$2:$K$5010,'Lançamentos'!$A$2:$A$5010,"Uso e consumo",'Lançamentos'!$C$2:$C$5010,F$4) | G16: =SUMIFS('Lançamentos'!$K$2:$K$5010,'Lançamentos'!$A$2:$A$5010,"Uso e consumo",'Lançamentos'!$C$2:$C$5010,G$4) | H16: =SUMIFS('Lançamentos'!$K$2:$K$5010,'Lançamentos'!$A$2:$A$5010,"Uso e consumo",'Lançamentos'!$C$2:$C$5010,H$4) | I16: =SUMIFS('Lançamentos'!$K$2:$K$5010,'Lançamentos'!$A$2:$A$5010,"Uso e consumo",'Lançamentos'!$C$2:$C$5010,I$4) | J16: =SUMIFS('Lançamentos'!$K$2:$K$5010,'Lançamentos'!$A$2:$A$5010,"Uso e consumo",'Lançamentos'!$C$2:$C$5010,J$4) | K16: =SUM(B16:J16) | M16: =SUMIFS('Lançamentos'!$K$2:$K$5010,'Lançamentos'!$A$2:$A$5010,"Uso e consumo",'Lançamentos'!$C$2:$C$5010,"Antes de 2026")
A17: Conferência: bruto − créditos − total (deve ser zero) | B17: =ROUND(B15-B16-B13,2) | C17: =ROUND(C15-C16-C13,2) | D17: =ROUND(D15-D16-D13,2) | E17: =ROUND(E15-E16-E13,2) | F17: =ROUND(F15-F16-F13,2) | G17: =ROUND(G15-G16-G13,2) | H17: =ROUND(H15-H16-H13,2) | I17: =ROUND(I15-I16-I13,2) | ... K17: =ROUND(K15-K16-K13,2) | M17: =ROUND(M15-M16-M13,2)
A19: Por fornecedor / transportadora
A20: Fornecedor / Transportadora | B20: 46023 | C20: 46054 | D20: 46082 | E20: 46113 | F20: 46143 | G20: 46174 | H20: 46204 | I20: 46235 | J20: 46266 | K20: Total 2026 | L20: % do total | M20: Memo: antes de 2026 | N20: Valor bruto 2026 | O20: Créditos 2026 | P20: Nº docs 2026
A21: FURNAX COMERCIAL E IMPORTADORA EIRELI | B21: =SUMIFS('Lançamentos'!$L$2:$L$5010,'Lançamentos'!$A$2:$A$5010,"Uso e consumo",'Lançamentos'!$H$2:$H$5010,$A21,'Lançamentos'!$C$2:$C$5010,B$20) | C21: =SUMIFS('Lançamentos'!$L$2:$L$5010,'Lançamentos'!$A$2:$A$5010,"Uso e consumo",'Lançamentos'!$H$2:$H$5010,$A21,'Lançamentos'!$C$2:$C$5010,C$20) | D21: =SUMIFS('Lançamentos'!$L$2:$L$5010,'Lançamentos'!$A$2:$A$5010,"Uso e consumo",'Lançamentos'!$H$2:$H$5010,$A21,'Lançamentos'!$C$2:$C$5010,D$20) | E21: =SUMIFS('Lançamentos'!$L$2:$L$5010,'Lançamentos'!$A$2:$A$5010,"Uso e consumo",'Lançamentos'!$H$2:$H$5010,$A21,'Lançamentos'!$C$2:$C$5010,E$20) | F21: =SUMIFS('Lançamentos'!$L$2:$L$5010,'Lançamentos'!$A$2:$A$5010,"Uso e consumo",'Lançamentos'!$H$2:$H$5010,$A21,'Lançamentos'!$C$2:$C$5010,F$20) | G21: =SUMIFS('Lançamentos'!$L$2:$L$5010,'Lançamentos'!$A$2:$A$5010,"Uso e consumo",'Lançamentos'!$H$2:$H$5010,$A21,'Lançamentos'!$C$2:$C$5010,G$20) | H21: =SUMIFS('Lançamentos'!$L$2:$L$5010,'Lançamentos'!$A$2:$A$5010,"Uso e consumo",'Lançamentos'!$H$2:$H$5010,$A21,'Lançamentos'!$C$2:$C$5010,H$20) | I21: =SUMIFS('Lançamentos'!$L$2:$L$5010,'Lançamentos'!$A$2:$A$5010,"Uso e consumo",'Lançamentos'!$H$2:$H$5010,$A21,'Lançamentos'!$C$2:$C$5010,I$20) | J21: =SUMIFS('Lançamentos'!$L$2:$L$5010,'Lançamentos'!$A$2:$A$5010,"Uso e consumo",'Lançamentos'!$H$2:$H$5010,$A21,'Lançamentos'!$C$2:$C$5010,J$20) | K21: =SUM(B21:J21) | L21: =K21/K$101 | M21: =SUMIFS('Lançamentos'!$L$2:$L$5010,'Lançamentos'!$A$2:$A$5010,"Uso e consumo",'Lançamentos'!$H$2:$H$5010,$A21,'Lançamentos'!$C$2:$C$5010,"Antes de 2026") | N21: =SUMIFS('Lançamentos'!$J$2:$J$5010,'Lançamentos'!$A$2:$A$5010,"Uso e consumo",'Lançamentos'!$H$2:$H$5010,$A21,'Lançamentos'!$D$2:$D$5010,"Em 2026") | O21: =SUMIFS('Lançamentos'!$K$2:$K$5010,'Lançamentos'!$A$2:$A$5010,"Uso e consumo",'Lançamentos'!$H$2:$H$5010,$A21,'Lançamentos'!$D$2:$D$5010,"Em 2026") | P21: =COUNTIFS('Lançamentos'!$A$2:$A$5010,"Uso e consumo",'Lançamentos'!$H$2:$H$5010,$A21,'Lançamentos'!$D$2:$D$5010,"Em 2026")
A22: Limptech Paper Comercio Ltda | B22: =SUMIFS('Lançamentos'!$L$2:$L$5010,'Lançamentos'!$A$2:$A$5010,"Uso e consumo",'Lançamentos'!$H$2:$H$5010,$A22,'Lançamentos'!$C$2:$C$5010,B$20) | C22: =SUMIFS('Lançamentos'!$L$2:$L$5010,'Lançamentos'!$A$2:$A$5010,"Uso e consumo",'Lançamentos'!$H$2:$H$5010,$A22,'Lançamentos'!$C$2:$C$5010,C$20) | D22: =SUMIFS('Lançamentos'!$L$2:$L$5010,'Lançamentos'!$A$2:$A$5010,"Uso e consumo",'Lançamentos'!$H$2:$H$5010,$A22,'Lançamentos'!$C$2:$C$5010,D$20) | E22: =SUMIFS('Lançamentos'!$L$2:$L$5010,'Lançamentos'!$A$2:$A$5010,"Uso e consumo",'Lançamentos'!$H$2:$H$5010,$A22,'Lançamentos'!$C$2:$C$5010,E$20) | F22: =SUMIFS('Lançamentos'!$L$2:$L$5010,'Lançamentos'!$A$2:$A$5010,"Uso e consumo",'Lançamentos'!$H$2:$H$5010,$A22,'Lançamentos'!$C$2:$C$5010,F$20) | G22: =SUMIFS('Lançamentos'!$L$2:$L$5010,'Lançamentos'!$A$2:$A$5010,"Uso e consumo",'Lançamentos'!$H$2:$H$5010,$A22,'Lançamentos'!$C$2:$C$5010,G$20) | H22: =SUMIFS('Lançamentos'!$L$2:$L$5010,'Lançamentos'!$A$2:$A$5010,"Uso e consumo",'Lançamentos'!$H$2:$H$5010,$A22,'Lançamentos'!$C$2:$C$5010,H$20) | I22: =SUMIFS('Lançamentos'!$L$2:$L$5010,'Lançamentos'!$A$2:$A$5010,"Uso e consumo",'Lançamentos'!$H$2:$H$5010,$A22,'Lançamentos'!$C$2:$C$5010,I$20) | J22: =SUMIFS('Lançamentos'!$L$2:$L$5010,'Lançamentos'!$A$2:$A$5010,"Uso e consumo",'Lançamentos'!$H$2:$H$5010,$A22,'Lançamentos'!$C$2:$C$5010,J$20) | K22: =SUM(B22:J22) | L22: =K22/K$101 | M22: =SUMIFS('Lançamentos'!$L$2:$L$5010,'Lançamentos'!$A$2:$A$5010,"Uso e consumo",'Lançamentos'!$H$2:$H$5010,$A22,'Lançamentos'!$C$2:$C$5010,"Antes de 2026") | N22: =SUMIFS('Lançamentos'!$J$2:$J$5010,'Lançamentos'!$A$2:$A$5010,"Uso e consumo",'Lançamentos'!$H$2:$H$5010,$A22,'Lançamentos'!$D$2:$D$5010,"Em 2026") | O22: =SUMIFS('Lançamentos'!$K$2:$K$5010,'Lançamentos'!$A$2:$A$5010,"Uso e consumo",'Lançamentos'!$H$2:$H$5010,$A22,'Lançamentos'!$D$2:$D$5010,"Em 2026") | P22: =COUNTIFS('Lançamentos'!$A$2:$A$5010,"Uso e consumo",'Lançamentos'!$H$2:$H$5010,$A22,'Lançamentos'!$D$2:$D$5010,"Em 2026")
A23: R M FARDAMENTOS LTDA | B23: =SUMIFS('Lançamentos'!$L$2:$L$5010,'Lançamentos'!$A$2:$A$5010,"Uso e consumo",'Lançamentos'!$H$2:$H$5010,$A23,'Lançamentos'!$C$2:$C$5010,B$20) | C23: =SUMIFS('Lançamentos'!$L$2:$L$5010,'Lançamentos'!$A$2:$A$5010,"Uso e consumo",'Lançamentos'!$H$2:$H$5010,$A23,'Lançamentos'!$C$2:$C$5010,C$20) | D23: =SUMIFS('Lançamentos'!$L$2:$L$5010,'Lançamentos'!$A$2:$A$5010,"Uso e consumo",'Lançamentos'!$H$2:$H$5010,$A23,'Lançamentos'!$C$2:$C$5010,D$20) | E23: =SUMIFS('Lançamentos'!$L$2:$L$5010,'Lançamentos'!$A$2:$A$5010,"Uso e consumo",'Lançamentos'!$H$2:$H$5010,$A23,'Lançamentos'!$C$2:$C$5010,E$20) | F23: =SUMIFS('Lançamentos'!$L$2:$L$5010,'Lançamentos'!$A$2:$A$5010,"Uso e consumo",'Lançamentos'!$H$2:$H$5010,$A23,'Lançamentos'!$C$2:$C$5010,F$20) | G23: =SUMIFS('Lançamentos'!$L$2:$L$5010,'Lançamentos'!$A$2:$A$5010,"Uso e consumo",'Lançamentos'!$H$2:$H$5010,$A23,'Lançamentos'!$C$2:$C$5010,G$20) | H23: =SUMIFS('Lançamentos'!$L$2:$L$5010,'Lançamentos'!$A$2:$A$5010,"Uso e consumo",'Lançamentos'!$H$2:$H$5010,$A23,'Lançamentos'!$C$2:$C$5010,H$20) | I23: =SUMIFS('Lançamentos'!$L$2:$L$5010,'Lançamentos'!$A$2:$A$5010,"Uso e consumo",'Lançamentos'!$H$2:$H$5010,$A23,'Lançamentos'!$C$2:$C$5010,I$20) | J23: =SUMIFS('Lançamentos'!$L$2:$L$5010,'Lançamentos'!$A$2:$A$5010,"Uso e consumo",'Lançamentos'!$H$2:$H$5010,$A23,'Lançamentos'!$C$2:$C$5010,J$20) | K23: =SUM(B23:J23) | L23: =K23/K$101 | M23: =SUMIFS('Lançamentos'!$L$2:$L$5010,'Lançamentos'!$A$2:$A$5010,"Uso e consumo",'Lançamentos'!$H$2:$H$5010,$A23,'Lançamentos'!$C$2:$C$5010,"Antes de 2026") | N23: =SUMIFS('Lançamentos'!$J$2:$J$5010,'Lançamentos'!$A$2:$A$5010,"Uso e consumo",'Lançamentos'!$H$2:$H$5010,$A23,'Lançamentos'!$D$2:$D$5010,"Em 2026") | O23: =SUMIFS('Lançamentos'!$K$2:$K$5010,'Lançamentos'!$A$2:$A$5010,"Uso e consumo",'Lançamentos'!$H$2:$H$5010,$A23,'Lançamentos'!$D$2:$D$5010,"Em 2026") | P23: =COUNTIFS('Lançamentos'!$A$2:$A$5010,"Uso e consumo",'Lançamentos'!$H$2:$H$5010,$A23,'Lançamentos'!$D$2:$D$5010,"Em 2026")
A24: PERNAMBUCO DISTRIBUIDORA ATAC EPIS, INS IND e MRO LTDA | B24: =SUMIFS('Lançamentos'!$L$2:$L$5010,'Lançamentos'!$A$2:$A$5010,"Uso e consumo",'Lançamentos'!$H$2:$H$5010,$A24,'Lançamentos'!$C$2:$C$5010,B$20) | C24: =SUMIFS('Lançamentos'!$L$2:$L$5010,'Lançamentos'!$A$2:$A$5010,"Uso e consumo",'Lançamentos'!$H$2:$H$5010,$A24,'Lançamentos'!$C$2:$C$5010,C$20) | D24: =SUMIFS('Lançamentos'!$L$2:$L$5010,'Lançamentos'!$A$2:$A$5010,"Uso e consumo",'Lançamentos'!$H$2:$H$5010,$A24,'Lançamentos'!$C$2:$C$5010,D$20) | E24: =SUMIFS('Lançamentos'!$L$2:$L$5010,'Lançamentos'!$A$2:$A$5010,"Uso e consumo",'Lançamentos'!$H$2:$H$5010,$A24,'Lançamentos'!$C$2:$C$5010,E$20) | F24: =SUMIFS('Lançamentos'!$L$2:$L$5010,'Lançamentos'!$A$2:$A$5010,"Uso e consumo",'Lançamentos'!$H$2:$H$5010,$A24,'Lançamentos'!$C$2:$C$5010,F$20) | G24: =SUMIFS('Lançamentos'!$L$2:$L$5010,'Lançamentos'!$A$2:$A$5010,"Uso e consumo",'Lançamentos'!$H$2:$H$5010,$A24,'Lançamentos'!$C$2:$C$5010,G$20) | H24: =SUMIFS('Lançamentos'!$L$2:$L$5010,'Lançamentos'!$A$2:$A$5010,"Uso e consumo",'Lançamentos'!$H$2:$H$5010,$A24,'Lançamentos'!$C$2:$C$5010,H$20) | I24: =SUMIFS('Lançamentos'!$L$2:$L$5010,'Lançamentos'!$A$2:$A$5010,"Uso e consumo",'Lançamentos'!$H$2:$H$5010,$A24,'Lançamentos'!$C$2:$C$5010,I$20) | J24: =SUMIFS('Lançamentos'!$L$2:$L$5010,'Lançamentos'!$A$2:$A$5010,"Uso e consumo",'Lançamentos'!$H$2:$H$5010,$A24,'Lançamentos'!$C$2:$C$5010,J$20) | K24: =SUM(B24:J24) | L24: =K24/K$101 | M24: =SUMIFS('Lançamentos'!$L$2:$L$5010,'Lançamentos'!$A$2:$A$5010,"Uso e consumo",'Lançamentos'!$H$2:$H$5010,$A24,'Lançamentos'!$C$2:$C$5010,"Antes de 2026") | N24: =SUMIFS('Lançamentos'!$J$2:$J$5010,'Lançamentos'!$A$2:$A$5010,"Uso e consumo",'Lançamentos'!$H$2:$H$5010,$A24,'Lançamentos'!$D$2:$D$5010,"Em 2026") | O24: =SUMIFS('Lançamentos'!$K$2:$K$5010,'Lançamentos'!$A$2:$A$5010,"Uso e consumo",'Lançamentos'!$H$2:$H$5010,$A24,'Lançamentos'!$D$2:$D$5010,"Em 2026") | P24: =COUNTIFS('Lançamentos'!$A$2:$A$5010,"Uso e consumo",'Lançamentos'!$H$2:$H$5010,$A24,'Lançamentos'!$D$2:$D$5010,"Em 2026")
A25: ELETROPOLO ELETRICIDADE LTDA | B25: =SUMIFS('Lançamentos'!$L$2:$L$5010,'Lançamentos'!$A$2:$A$5010,"Uso e consumo",'Lançamentos'!$H$2:$H$5010,$A25,'Lançamentos'!$C$2:$C$5010,B$20) | C25: =SUMIFS('Lançamentos'!$L$2:$L$5010,'Lançamentos'!$A$2:$A$5010,"Uso e consumo",'Lançamentos'!$H$2:$H$5010,$A25,'Lançamentos'!$C$2:$C$5010,C$20) | D25: =SUMIFS('Lançamentos'!$L$2:$L$5010,'Lançamentos'!$A$2:$A$5010,"Uso e consumo",'Lançamentos'!$H$2:$H$5010,$A25,'Lançamentos'!$C$2:$C$5010,D$20) | E25: =SUMIFS('Lançamentos'!$L$2:$L$5010,'Lançamentos'!$A$2:$A$5010,"Uso e consumo",'Lançamentos'!$H$2:$H$5010,$A25,'Lançamentos'!$C$2:$C$5010,E$20) | F25: =SUMIFS('Lançamentos'!$L$2:$L$5010,'Lançamentos'!$A$2:$A$5010,"Uso e consumo",'Lançamentos'!$H$2:$H$5010,$A25,'Lançamentos'!$C$2:$C$5010,F$20) | G25: =SUMIFS('Lançamentos'!$L$2:$L$5010,'Lançamentos'!$A$2:$A$5010,"Uso e consumo",'Lançamentos'!$H$2:$H$5010,$A25,'Lançamentos'!$C$2:$C$5010,G$20) | H25: =SUMIFS('Lançamentos'!$L$2:$L$5010,'Lançamentos'!$A$2:$A$5010,"Uso e consumo",'Lançamentos'!$H$2:$H$5010,$A25,'Lançamentos'!$C$2:$C$5010,H$20) | I25: =SUMIFS('Lançamentos'!$L$2:$L$5010,'Lançamentos'!$A$2:$A$5010,"Uso e consumo",'Lançamentos'!$H$2:$H$5010,$A25,'Lançamentos'!$C$2:$C$5010,I$20) | J25: =SUMIFS('Lançamentos'!$L$2:$L$5010,'Lançamentos'!$A$2:$A$5010,"Uso e consumo",'Lançamentos'!$H$2:$H$5010,$A25,'Lançamentos'!$C$2:$C$5010,J$20) | K25: =SUM(B25:J25) | L25: =K25/K$101 | M25: =SUMIFS('Lançamentos'!$L$2:$L$5010,'Lançamentos'!$A$2:$A$5010,"Uso e consumo",'Lançamentos'!$H$2:$H$5010,$A25,'Lançamentos'!$C$2:$C$5010,"Antes de 2026") | N25: =SUMIFS('Lançamentos'!$J$2:$J$5010,'Lançamentos'!$A$2:$A$5010,"Uso e consumo",'Lançamentos'!$H$2:$H$5010,$A25,'Lançamentos'!$D$2:$D$5010,"Em 2026") | O25: =SUMIFS('Lançamentos'!$K$2:$K$5010,'Lançamentos'!$A$2:$A$5010,"Uso e consumo",'Lançamentos'!$H$2:$H$5010,$A25,'Lançamentos'!$D$2:$D$5010,"Em 2026") | P25: =COUNTIFS('Lançamentos'!$A$2:$A$5010,"Uso e consumo",'Lançamentos'!$H$2:$H$5010,$A25,'Lançamentos'!$D$2:$D$5010,"Em 2026")
A26: FERGE COMERCIO DE PRODUTOS INDUSTRIAIS LTDA | B26: =SUMIFS('Lançamentos'!$L$2:$L$5010,'Lançamentos'!$A$2:$A$5010,"Uso e consumo",'Lançamentos'!$H$2:$H$5010,$A26,'Lançamentos'!$C$2:$C$5010,B$20) | C26: =SUMIFS('Lançamentos'!$L$2:$L$5010,'Lançamentos'!$A$2:$A$5010,"Uso e consumo",'Lançamentos'!$H$2:$H$5010,$A26,'Lançamentos'!$C$2:$C$5010,C$20) | D26: =SUMIFS('Lançamentos'!$L$2:$L$5010,'Lançamentos'!$A$2:$A$5010,"Uso e consumo",'Lançamentos'!$H$2:$H$5010,$A26,'Lançamentos'!$C$2:$C$5010,D$20) | E26: =SUMIFS('Lançamentos'!$L$2:$L$5010,'Lançamentos'!$A$2:$A$5010,"Uso e consumo",'Lançamentos'!$H$2:$H$5010,$A26,'Lançamentos'!$C$2:$C$5010,E$20) | F26: =SUMIFS('Lançamentos'!$L$2:$L$5010,'Lançamentos'!$A$2:$A$5010,"Uso e consumo",'Lançamentos'!$H$2:$H$5010,$A26,'Lançamentos'!$C$2:$C$5010,F$20) | G26: =SUMIFS('Lançamentos'!$L$2:$L$5010,'Lançamentos'!$A$2:$A$5010,"Uso e consumo",'Lançamentos'!$H$2:$H$5010,$A26,'Lançamentos'!$C$2:$C$5010,G$20) | H26: =SUMIFS('Lançamentos'!$L$2:$L$5010,'Lançamentos'!$A$2:$A$5010,"Uso e consumo",'Lançamentos'!$H$2:$H$5010,$A26,'Lançamentos'!$C$2:$C$5010,H$20) | I26: =SUMIFS('Lançamentos'!$L$2:$L$5010,'Lançamentos'!$A$2:$A$5010,"Uso e consumo",'Lançamentos'!$H$2:$H$5010,$A26,'Lançamentos'!$C$2:$C$5010,I$20) | J26: =SUMIFS('Lançamentos'!$L$2:$L$5010,'Lançamentos'!$A$2:$A$5010,"Uso e consumo",'Lançamentos'!$H$2:$H$5010,$A26,'Lançamentos'!$C$2:$C$5010,J$20) | K26: =SUM(B26:J26) | L26: =K26/K$101 | M26: =SUMIFS('Lançamentos'!$L$2:$L$5010,'Lançamentos'!$A$2:$A$5010,"Uso e consumo",'Lançamentos'!$H$2:$H$5010,$A26,'Lançamentos'!$C$2:$C$5010,"Antes de 2026") | N26: =SUMIFS('Lançamentos'!$J$2:$J$5010,'Lançamentos'!$A$2:$A$5010,"Uso e consumo",'Lançamentos'!$H$2:$H$5010,$A26,'Lançamentos'!$D$2:$D$5010,"Em 2026") | O26: =SUMIFS('Lançamentos'!$K$2:$K$5010,'Lançamentos'!$A$2:$A$5010,"Uso e consumo",'Lançamentos'!$H$2:$H$5010,$A26,'Lançamentos'!$D$2:$D$5010,"Em 2026") | P26: =COUNTIFS('Lançamentos'!$A$2:$A$5010,"Uso e consumo",'Lançamentos'!$H$2:$H$5010,$A26,'Lançamentos'!$D$2:$D$5010,"Em 2026")
A27: GF COMERCIO DE PRODUTOS INDUSTRIAIS LTDA | B27: =SUMIFS('Lançamentos'!$L$2:$L$5010,'Lançamentos'!$A$2:$A$5010,"Uso e consumo",'Lançamentos'!$H$2:$H$5010,$A27,'Lançamentos'!$C$2:$C$5010,B$20) | C27: =SUMIFS('Lançamentos'!$L$2:$L$5010,'Lançamentos'!$A$2:$A$5010,"Uso e consumo",'Lançamentos'!$H$2:$H$5010,$A27,'Lançamentos'!$C$2:$C$5010,C$20) | D27: =SUMIFS('Lançamentos'!$L$2:$L$5010,'Lançamentos'!$A$2:$A$5010,"Uso e consumo",'Lançamentos'!$H$2:$H$5010,$A27,'Lançamentos'!$C$2:$C$5010,D$20) | E27: =SUMIFS('Lançamentos'!$L$2:$L$5010,'Lançamentos'!$A$2:$A$5010,"Uso e consumo",'Lançamentos'!$H$2:$H$5010,$A27,'Lançamentos'!$C$2:$C$5010,E$20) | F27: =SUMIFS('Lançamentos'!$L$2:$L$5010,'Lançamentos'!$A$2:$A$5010,"Uso e consumo",'Lançamentos'!$H$2:$H$5010,$A27,'Lançamentos'!$C$2:$C$5010,F$20) | G27: =SUMIFS('Lançamentos'!$L$2:$L$5010,'Lançamentos'!$A$2:$A$5010,"Uso e consumo",'Lançamentos'!$H$2:$H$5010,$A27,'Lançamentos'!$C$2:$C$5010,G$20) | H27: =SUMIFS('Lançamentos'!$L$2:$L$5010,'Lançamentos'!$A$2:$A$5010,"Uso e consumo",'Lançamentos'!$H$2:$H$5010,$A27,'Lançamentos'!$C$2:$C$5010,H$20) | I27: =SUMIFS('Lançamentos'!$L$2:$L$5010,'Lançamentos'!$A$2:$A$5010,"Uso e consumo",'Lançamentos'!$H$2:$H$5010,$A27,'Lançamentos'!$C$2:$C$5010,I$20) | J27: =SUMIFS('Lançamentos'!$L$2:$L$5010,'Lançamentos'!$A$2:$A$5010,"Uso e consumo",'Lançamentos'!$H$2:$H$5010,$A27,'Lançamentos'!$C$2:$C$5010,J$20) | K27: =SUM(B27:J27) | L27: =K27/K$101 | M27: =SUMIFS('Lançamentos'!$L$2:$L$5010,'Lançamentos'!$A$2:$A$5010,"Uso e consumo",'Lançamentos'!$H$2:$H$5010,$A27,'Lançamentos'!$C$2:$C$5010,"Antes de 2026") | N27: =SUMIFS('Lançamentos'!$J$2:$J$5010,'Lançamentos'!$A$2:$A$5010,"Uso e consumo",'Lançamentos'!$H$2:$H$5010,$A27,'Lançamentos'!$D$2:$D$5010,"Em 2026") | O27: =SUMIFS('Lançamentos'!$K$2:$K$5010,'Lançamentos'!$A$2:$A$5010,"Uso e consumo",'Lançamentos'!$H$2:$H$5010,$A27,'Lançamentos'!$D$2:$D$5010,"Em 2026") | P27: =COUNTIFS('Lançamentos'!$A$2:$A$5010,"Uso e consumo",'Lançamentos'!$H$2:$H$5010,$A27,'Lançamentos'!$D$2:$D$5010,"Em 2026")
A28: ATACADAO ECONOMICO - COMERCIO DE MATERIAL DE CONSTRUCAO LTDA | B28: =SUMIFS('Lançamentos'!$L$2:$L$5010,'Lançamentos'!$A$2:$A$5010,"Uso e consumo",'Lançamentos'!$H$2:$H$5010,$A28,'Lançamentos'!$C$2:$C$5010,B$20) | C28: =SUMIFS('Lançamentos'!$L$2:$L$5010,'Lançamentos'!$A$2:$A$5010,"Uso e consumo",'Lançamentos'!$H$2:$H$5010,$A28,'Lançamentos'!$C$2:$C$5010,C$20) | D28: =SUMIFS('Lançamentos'!$L$2:$L$5010,'Lançamentos'!$A$2:$A$5010,"Uso e consumo",'Lançamentos'!$H$2:$H$5010,$A28,'Lançamentos'!$C$2:$C$5010,D$20) | E28: =SUMIFS('Lançamentos'!$L$2:$L$5010,'Lançamentos'!$A$2:$A$5010,"Uso e consumo",'Lançamentos'!$H$2:$H$5010,$A28,'Lançamentos'!$C$2:$C$5010,E$20) | F28: =SUMIFS('Lançamentos'!$L$2:$L$5010,'Lançamentos'!$A$2:$A$5010,"Uso e consumo",'Lançamentos'!$H$2:$H$5010,$A28,'Lançamentos'!$C$2:$C$5010,F$20) | G28: =SUMIFS('Lançamentos'!$L$2:$L$5010,'Lançamentos'!$A$2:$A$5010,"Uso e consumo",'Lançamentos'!$H$2:$H$5010,$A28,'Lançamentos'!$C$2:$C$5010,G$20) | H28: =SUMIFS('Lançamentos'!$L$2:$L$5010,'Lançamentos'!$A$2:$A$5010,"Uso e consumo",'Lançamentos'!$H$2:$H$5010,$A28,'Lançamentos'!$C$2:$C$5010,H$20) | I28: =SUMIFS('Lançamentos'!$L$2:$L$5010,'Lançamentos'!$A$2:$A$5010,"Uso e consumo",'Lançamentos'!$H$2:$H$5010,$A28,'Lançamentos'!$C$2:$C$5010,I$20) | J28: =SUMIFS('Lançamentos'!$L$2:$L$5010,'Lançamentos'!$A$2:$A$5010,"Uso e consumo",'Lançamentos'!$H$2:$H$5010,$A28,'Lançamentos'!$C$2:$C$5010,J$20) | K28: =SUM(B28:J28) | L28: =K28/K$101 | M28: =SUMIFS('Lançamentos'!$L$2:$L$5010,'Lançamentos'!$A$2:$A$5010,"Uso e consumo",'Lançamentos'!$H$2:$H$5010,$A28,'Lançamentos'!$C$2:$C$5010,"Antes de 2026") | N28: =SUMIFS('Lançamentos'!$J$2:$J$5010,'Lançamentos'!$A$2:$A$5010,"Uso e consumo",'Lançamentos'!$H$2:$H$5010,$A28,'Lançamentos'!$D$2:$D$5010,"Em 2026") | O28: =SUMIFS('Lançamentos'!$K$2:$K$5010,'Lançamentos'!$A$2:$A$5010,"Uso e consumo",'Lançamentos'!$H$2:$H$5010,$A28,'Lançamentos'!$D$2:$D$5010,"Em 2026") | P28: =COUNTIFS('Lançamentos'!$A$2:$A$5010,"Uso e consumo",'Lançamentos'!$H$2:$H$5010,$A28,'Lançamentos'!$D$2:$D$5010,"Em 2026")
A29: TECHPRINT FACAS INDUSTRIAIS | B29: =SUMIFS('Lançamentos'!$L$2:$L$5010,'Lançamentos'!$A$2:$A$5010,"Uso e consumo",'Lançamentos'!$H$2:$H$5010,$A29,'Lançamentos'!$C$2:$C$5010,B$20) | C29: =SUMIFS('Lançamentos'!$L$2:$L$5010,'Lançamentos'!$A$2:$A$5010,"Uso e consumo",'Lançamentos'!$H$2:$H$5010,$A29,'Lançamentos'!$C$2:$C$5010,C$20) | D29: =SUMIFS('Lançamentos'!$L$2:$L$5010,'Lançamentos'!$A$2:$A$5010,"Uso e consumo",'Lançamentos'!$H$2:$H$5010,$A29,'Lançamentos'!$C$2:$C$5010,D$20) | E29: =SUMIFS('Lançamentos'!$L$2:$L$5010,'Lançamentos'!$A$2:$A$5010,"Uso e consumo",'Lançamentos'!$H$2:$H$5010,$A29,'Lançamentos'!$C$2:$C$5010,E$20) | F29: =SUMIFS('Lançamentos'!$L$2:$L$5010,'Lançamentos'!$A$2:$A$5010,"Uso e consumo",'Lançamentos'!$H$2:$H$5010,$A29,'Lançamentos'!$C$2:$C$5010,F$20) | G29: =SUMIFS('Lançamentos'!$L$2:$L$5010,'Lançamentos'!$A$2:$A$5010,"Uso e consumo",'Lançamentos'!$H$2:$H$5010,$A29,'Lançamentos'!$C$2:$C$5010,G$20) | H29: =SUMIFS('Lançamentos'!$L$2:$L$5010,'Lançamentos'!$A$2:$A$5010,"Uso e consumo",'Lançamentos'!$H$2:$H$5010,$A29,'Lançamentos'!$C$2:$C$5010,H$20) | I29: =SUMIFS('Lançamentos'!$L$2:$L$5010,'Lançamentos'!$A$2:$A$5010,"Uso e consumo",'Lançamentos'!$H$2:$H$5010,$A29,'Lançamentos'!$C$2:$C$5010,I$20) | J29: =SUMIFS('Lançamentos'!$L$2:$L$5010,'Lançamentos'!$A$2:$A$5010,"Uso e consumo",'Lançamentos'!$H$2:$H$5010,$A29,'Lançamentos'!$C$2:$C$5010,J$20) | K29: =SUM(B29:J29) | L29: =K29/K$101 | M29: =SUMIFS('Lançamentos'!$L$2:$L$5010,'Lançamentos'!$A$2:$A$5010,"Uso e consumo",'Lançamentos'!$H$2:$H$5010,$A29,'Lançamentos'!$C$2:$C$5010,"Antes de 2026") | N29: =SUMIFS('Lançamentos'!$J$2:$J$5010,'Lançamentos'!$A$2:$A$5010,"Uso e consumo",'Lançamentos'!$H$2:$H$5010,$A29,'Lançamentos'!$D$2:$D$5010,"Em 2026") | O29: =SUMIFS('Lançamentos'!$K$2:$K$5010,'Lançamentos'!$A$2:$A$5010,"Uso e consumo",'Lançamentos'!$H$2:$H$5010,$A29,'Lançamentos'!$D$2:$D$5010,"Em 2026") | P29: =COUNTIFS('Lançamentos'!$A$2:$A$5010,"Uso e consumo",'Lançamentos'!$H$2:$H$5010,$A29,'Lançamentos'!$D$2:$D$5010,"Em 2026")
A30: MARILENE CARVALHO LUCENA DE BRITO - ME | B30: =SUMIFS('Lançamentos'!$L$2:$L$5010,'Lançamentos'!$A$2:$A$5010,"Uso e consumo",'Lançamentos'!$H$2:$H$5010,$A30,'Lançamentos'!$C$2:$C$5010,B$20) | C30: =SUMIFS('Lançamentos'!$L$2:$L$5010,'Lançamentos'!$A$2:$A$5010,"Uso e consumo",'Lançamentos'!$H$2:$H$5010,$A30,'Lançamentos'!$C$2:$C$5010,C$20) | D30: =SUMIFS('Lançamentos'!$L$2:$L$5010,'Lançamentos'!$A$2:$A$5010,"Uso e consumo",'Lançamentos'!$H$2:$H$5010,$A30,'Lançamentos'!$C$2:$C$5010,D$20) | E30: =SUMIFS('Lançamentos'!$L$2:$L$5010,'Lançamentos'!$A$2:$A$5010,"Uso e consumo",'Lançamentos'!$H$2:$H$5010,$A30,'Lançamentos'!$C$2:$C$5010,E$20) | F30: =SUMIFS('Lançamentos'!$L$2:$L$5010,'Lançamentos'!$A$2:$A$5010,"Uso e consumo",'Lançamentos'!$H$2:$H$5010,$A30,'Lançamentos'!$C$2:$C$5010,F$20) | G30: =SUMIFS('Lançamentos'!$L$2:$L$5010,'Lançamentos'!$A$2:$A$5010,"Uso e consumo",'Lançamentos'!$H$2:$H$5010,$A30,'Lançamentos'!$C$2:$C$5010,G$20) | H30: =SUMIFS('Lançamentos'!$L$2:$L$5010,'Lançamentos'!$A$2:$A$5010,"Uso e consumo",'Lançamentos'!$H$2:$H$5010,$A30,'Lançamentos'!$C$2:$C$5010,H$20) | I30: =SUMIFS('Lançamentos'!$L$2:$L$5010,'Lançamentos'!$A$2:$A$5010,"Uso e consumo",'Lançamentos'!$H$2:$H$5010,$A30,'Lançamentos'!$C$2:$C$5010,I$20) | J30: =SUMIFS('Lançamentos'!$L$2:$L$5010,'Lançamentos'!$A$2:$A$5010,"Uso e consumo",'Lançamentos'!$H$2:$H$5010,$A30,'Lançamentos'!$C$2:$C$5010,J$20) | K30: =SUM(B30:J30) | L30: =K30/K$101 | M30: =SUMIFS('Lançamentos'!$L$2:$L$5010,'Lançamentos'!$A$2:$A$5010,"Uso e consumo",'Lançamentos'!$H$2:$H$5010,$A30,'Lançamentos'!$C$2:$C$5010,"Antes de 2026") | N30: =SUMIFS('Lançamentos'!$J$2:$J$5010,'Lançamentos'!$A$2:$A$5010,"Uso e consumo",'Lançamentos'!$H$2:$H$5010,$A30,'Lançamentos'!$D$2:$D$5010,"Em 2026") | O30: =SUMIFS('Lançamentos'!$K$2:$K$5010,'Lançamentos'!$A$2:$A$5010,"Uso e consumo",'Lançamentos'!$H$2:$H$5010,$A30,'Lançamentos'!$D$2:$D$5010,"Em 2026") | P30: =COUNTIFS('Lançamentos'!$A$2:$A$5010,"Uso e consumo",'Lançamentos'!$H$2:$H$5010,$A30,'Lançamentos'!$D$2:$D$5010,"Em 2026")
A31: EDNA DE ARAUJO PACHECO LTDA | B31: =SUMIFS('Lançamentos'!$L$2:$L$5010,'Lançamentos'!$A$2:$A$5010,"Uso e consumo",'Lançamentos'!$H$2:$H$5010,$A31,'Lançamentos'!$C$2:$C$5010,B$20) | C31: =SUMIFS('Lançamentos'!$L$2:$L$5010,'Lançamentos'!$A$2:$A$5010,"Uso e consumo",'Lançamentos'!$H$2:$H$5010,$A31,'Lançamentos'!$C$2:$C$5010,C$20) | D31: =SUMIFS('Lançamentos'!$L$2:$L$5010,'Lançamentos'!$A$2:$A$5010,"Uso e consumo",'Lançamentos'!$H$2:$H$5010,$A31,'Lançamentos'!$C$2:$C$5010,D$20) | E31: =SUMIFS('Lançamentos'!$L$2:$L$5010,'Lançamentos'!$A$2:$A$5010,"Uso e consumo",'Lançamentos'!$H$2:$H$5010,$A31,'Lançamentos'!$C$2:$C$5010,E$20) | F31: =SUMIFS('Lançamentos'!$L$2:$L$5010,'Lançamentos'!$A$2:$A$5010,"Uso e consumo",'Lançamentos'!$H$2:$H$5010,$A31,'Lançamentos'!$C$2:$C$5010,F$20) | G31: =SUMIFS('Lançamentos'!$L$2:$L$5010,'Lançamentos'!$A$2:$A$5010,"Uso e consumo",'Lançamentos'!$H$2:$H$5010,$A31,'Lançamentos'!$C$2:$C$5010,G$20) | H31: =SUMIFS('Lançamentos'!$L$2:$L$5010,'Lançamentos'!$A$2:$A$5010,"Uso e consumo",'Lançamentos'!$H$2:$H$5010,$A31,'Lançamentos'!$C$2:$C$5010,H$20) | I31: =SUMIFS('Lançamentos'!$L$2:$L$5010,'Lançamentos'!$A$2:$A$5010,"Uso e consumo",'Lançamentos'!$H$2:$H$5010,$A31,'Lançamentos'!$C$2:$C$5010,I$20) | J31: =SUMIFS('Lançamentos'!$L$2:$L$5010,'Lançamentos'!$A$2:$A$5010,"Uso e consumo",'Lançamentos'!$H$2:$H$5010,$A31,'Lançamentos'!$C$2:$C$5010,J$20) | K31: =SUM(B31:J31) | L31: =K31/K$101 | M31: =SUMIFS('Lançamentos'!$L$2:$L$5010,'Lançamentos'!$A$2:$A$5010,"Uso e consumo",'Lançamentos'!$H$2:$H$5010,$A31,'Lançamentos'!$C$2:$C$5010,"Antes de 2026") | N31: =SUMIFS('Lançamentos'!$J$2:$J$5010,'Lançamentos'!$A$2:$A$5010,"Uso e consumo",'Lançamentos'!$H$2:$H$5010,$A31,'Lançamentos'!$D$2:$D$5010,"Em 2026") | O31: =SUMIFS('Lançamentos'!$K$2:$K$5010,'Lançamentos'!$A$2:$A$5010,"Uso e consumo",'Lançamentos'!$H$2:$H$5010,$A31,'Lançamentos'!$D$2:$D$5010,"Em 2026") | P31: =COUNTIFS('Lançamentos'!$A$2:$A$5010,"Uso e consumo",'Lançamentos'!$H$2:$H$5010,$A31,'Lançamentos'!$D$2:$D$5010,"Em 2026")
A32: GDM INDUSTRIA E COMERCIO DE PLASTICOS LTDA. | B32: =SUMIFS('Lançamentos'!$L$2:$L$5010,'Lançamentos'!$A$2:$A$5010,"Uso e consumo",'Lançamentos'!$H$2:$H$5010,$A32,'Lançamentos'!$C$2:$C$5010,B$20) | C32: =SUMIFS('Lançamentos'!$L$2:$L$5010,'Lançamentos'!$A$2:$A$5010,"Uso e consumo",'Lançamentos'!$H$2:$H$5010,$A32,'Lançamentos'!$C$2:$C$5010,C$20) | D32: =SUMIFS('Lançamentos'!$L$2:$L$5010,'Lançamentos'!$A$2:$A$5010,"Uso e consumo",'Lançamentos'!$H$2:$H$5010,$A32,'Lançamentos'!$C$2:$C$5010,D$20) | E32: =SUMIFS('Lançamentos'!$L$2:$L$5010,'Lançamentos'!$A$2:$A$5010,"Uso e consumo",'Lançamentos'!$H$2:$H$5010,$A32,'Lançamentos'!$C$2:$C$5010,E$20) | F32: =SUMIFS('Lançamentos'!$L$2:$L$5010,'Lançamentos'!$A$2:$A$5010,"Uso e consumo",'Lançamentos'!$H$2:$H$5010,$A32,'Lançamentos'!$C$2:$C$5010,F$20) | G32: =SUMIFS('Lançamentos'!$L$2:$L$5010,'Lançamentos'!$A$2:$A$5010,"Uso e consumo",'Lançamentos'!$H$2:$H$5010,$A32,'Lançamentos'!$C$2:$C$5010,G$20) | H32: =SUMIFS('Lançamentos'!$L$2:$L$5010,'Lançamentos'!$A$2:$A$5010,"Uso e consumo",'Lançamentos'!$H$2:$H$5010,$A32,'Lançamentos'!$C$2:$C$5010,H$20) | I32: =SUMIFS('Lançamentos'!$L$2:$L$5010,'Lançamentos'!$A$2:$A$5010,"Uso e consumo",'Lançamentos'!$H$2:$H$5010,$A32,'Lançamentos'!$C$2:$C$5010,I$20) | J32: =SUMIFS('Lançamentos'!$L$2:$L$5010,'Lançamentos'!$A$2:$A$5010,"Uso e consumo",'Lançamentos'!$H$2:$H$5010,$A32,'Lançamentos'!$C$2:$C$5010,J$20) | K32: =SUM(B32:J32) | L32: =K32/K$101 | M32: =SUMIFS('Lançamentos'!$L$2:$L$5010,'Lançamentos'!$A$2:$A$5010,"Uso e consumo",'Lançamentos'!$H$2:$H$5010,$A32,'Lançamentos'!$C$2:$C$5010,"Antes de 2026") | N32: =SUMIFS('Lançamentos'!$J$2:$J$5010,'Lançamentos'!$A$2:$A$5010,"Uso e consumo",'Lançamentos'!$H$2:$H$5010,$A32,'Lançamentos'!$D$2:$D$5010,"Em 2026") | O32: =SUMIFS('Lançamentos'!$K$2:$K$5010,'Lançamentos'!$A$2:$A$5010,"Uso e consumo",'Lançamentos'!$H$2:$H$5010,$A32,'Lançamentos'!$D$2:$D$5010,"Em 2026") | P32: =COUNTIFS('Lançamentos'!$A$2:$A$5010,"Uso e consumo",'Lançamentos'!$H$2:$H$5010,$A32,'Lançamentos'!$D$2:$D$5010,"Em 2026")
... A100: TECFAG COMERCIO E IMPORTACAO DE MAQUINAS LTDA | B100: =SUMIFS('Lançamentos'!$L$2:$L$5010,'Lançamentos'!$A$2:$A$5010,"Uso e consumo",'Lançamentos'!$H$2:$H$5010,$A100,'Lançamentos'!$C$2:$C$5010,B$20) | C100: =SUMIFS('Lançamentos'!$L$2:$L$5010,'Lançamentos'!$A$2:$A$5010,"Uso e consumo",'Lançamentos'!$H$2:$H$5010,$A100,'Lançamentos'!$C$2:$C$5010,C$20) | D100: =SUMIFS('Lançamentos'!$L$2:$L$5010,'Lançamentos'!$A$2:$A$5010,"Uso e consumo",'Lançamentos'!$H$2:$H$5010,$A100,'Lançamentos'!$C$2:$C$5010,D$20) | E100: =SUMIFS('Lançamentos'!$L$2:$L$5010,'Lançamentos'!$A$2:$A$5010,"Uso e consumo",'Lançamentos'!$H$2:$H$5010,$A100,'Lançamentos'!$C$2:$C$5010,E$20) | F100: =SUMIFS('Lançamentos'!$L$2:$L$5010,'Lançamentos'!$A$2:$A$5010,"Uso e consumo",'Lançamentos'!$H$2:$H$5010,$A100,'Lançamentos'!$C$2:$C$5010,F$20) | G100: =SUMIFS('Lançamentos'!$L$2:$L$5010,'Lançamentos'!$A$2:$A$5010,"Uso e consumo",'Lançamentos'!$H$2:$H$5010,$A100,'Lançamentos'!$C$2:$C$5010,G$20) | H100: =SUMIFS('Lançamentos'!$L$2:$L$5010,'Lançamentos'!$A$2:$A$5010,"Uso e consumo",'Lançamentos'!$H$2:$H$5010,$A100,'Lançamentos'!$C$2:$C$5010,H$20) | I100: =SUMIFS('Lançamentos'!$L$2:$L$5010,'Lançamentos'!$A$2:$A$5010,"Uso e consumo",'Lançamentos'!$H$2:$H$5010,$A100,'Lançamentos'!$C$2:$C$5010,I$20) | J100: =SUMIFS('Lançamentos'!$L$2:$L$5010,'Lançamentos'!$A$2:$A$5010,"Uso e consumo",'Lançamentos'!$H$2:$H$5010,$A100,'Lançamentos'!$C$2:$C$5010,J$20) | K100: =SUM(B100:J100) | L100: =K100/K$101 | M100: =SUMIFS('Lançamentos'!$L$2:$L$5010,'Lançamentos'!$A$2:$A$5010,"Uso e consumo",'Lançamentos'!$H$2:$H$5010,$A100,'Lançamentos'!$C$2:$C$5010,"Antes de 2026") | N100: =SUMIFS('Lançamentos'!$J$2:$J$5010,'Lançamentos'!$A$2:$A$5010,"Uso e consumo",'Lançamentos'!$H$2:$H$5010,$A100,'Lançamentos'!$D$2:$D$5010,"Em 2026") | O100: =SUMIFS('Lançamentos'!$K$2:$K$5010,'Lançamentos'!$A$2:$A$5010,"Uso e consumo",'Lançamentos'!$H$2:$H$5010,$A100,'Lançamentos'!$D$2:$D$5010,"Em 2026") | P100: =COUNTIFS('Lançamentos'!$A$2:$A$5010,"Uso e consumo",'Lançamentos'!$H$2:$H$5010,$A100,'Lançamentos'!$D$2:$D$5010,"Em 2026")
A101: TOTAL USO E CONSUMO | B101: =SUM(B21:B100) | C101: =SUM(C21:C100) | D101: =SUM(D21:D100) | E101: =SUM(E21:E100) | F101: =SUM(F21:F100) | G101: =SUM(G21:G100) | H101: =SUM(H21:H100) | I101: =SUM(I21:I100) | ... K101: =SUM(K21:K100) | L101: =K101/K$101 | M101: =SUM(M21:M100) | N101: =SUM(N21:N100) | O101: =SUM(O21:O100) | P101: =SUM(P21:P100)
A102: Conferência: total por fornecedor − total por subcategoria (deve ser zero) | B102: =ROUND(B101-B13,2) | C102: =ROUND(C101-C13,2) | D102: =ROUND(D101-D13,2) | E102: =ROUND(E101-E13,2) | F102: =ROUND(F101-F13,2) | G102: =ROUND(G101-G13,2) | H102: =ROUND(H101-H13,2) | I102: =ROUND(I101-I13,2) | ... K102: =ROUND(K101-K13,2) | M102: =ROUND(M101-M13,2)

Sheet Frete de compra
A1: Frete de compra – 2026 (VINCO)
A2: Fretes de compra de papel/bobina: Aliança Navegação, Stancanelli, Gol Linhas Aéreas e Planeta Azul. Todos os CT-e emitidos; líquido do ICMS creditável.
A4: Subcategoria (categoria do Omie) | B4: 46023 | C4: 46054 | D4: 46082 | E4: 46113 | F4: 46143 | G4: 46174 | H4: 46204 | I4: 46235 | J4: 46266 | K4: Total 2026 | L4: % do total | M4: Memo: antes de 2026
A5: 1.01.01 Venda de Mercadoria Fabricadas | B5: =SUMIFS('Lançamentos'!$L$2:$L$5010,'Lançamentos'!$A$2:$A$5010,"Frete de compra",'Lançamentos'!$B$2:$B$5010,$A5,'Lançamentos'!$C$2:$C$5010,B$4) | C5: =SUMIFS('Lançamentos'!$L$2:$L$5010,'Lançamentos'!$A$2:$A$5010,"Frete de compra",'Lançamentos'!$B$2:$B$5010,$A5,'Lançamentos'!$C$2:$C$5010,C$4) | D5: =SUMIFS('Lançamentos'!$L$2:$L$5010,'Lançamentos'!$A$2:$A$5010,"Frete de compra",'Lançamentos'!$B$2:$B$5010,$A5,'Lançamentos'!$C$2:$C$5010,D$4) | E5: =SUMIFS('Lançamentos'!$L$2:$L$5010,'Lançamentos'!$A$2:$A$5010,"Frete de compra",'Lançamentos'!$B$2:$B$5010,$A5,'Lançamentos'!$C$2:$C$5010,E$4) | F5: =SUMIFS('Lançamentos'!$L$2:$L$5010,'Lançamentos'!$A$2:$A$5010,"Frete de compra",'Lançamentos'!$B$2:$B$5010,$A5,'Lançamentos'!$C$2:$C$5010,F$4) | G5: =SUMIFS('Lançamentos'!$L$2:$L$5010,'Lançamentos'!$A$2:$A$5010,"Frete de compra",'Lançamentos'!$B$2:$B$5010,$A5,'Lançamentos'!$C$2:$C$5010,G$4) | H5: =SUMIFS('Lançamentos'!$L$2:$L$5010,'Lançamentos'!$A$2:$A$5010,"Frete de compra",'Lançamentos'!$B$2:$B$5010,$A5,'Lançamentos'!$C$2:$C$5010,H$4) | I5: =SUMIFS('Lançamentos'!$L$2:$L$5010,'Lançamentos'!$A$2:$A$5010,"Frete de compra",'Lançamentos'!$B$2:$B$5010,$A5,'Lançamentos'!$C$2:$C$5010,I$4) | J5: =SUMIFS('Lançamentos'!$L$2:$L$5010,'Lançamentos'!$A$2:$A$5010,"Frete de compra",'Lançamentos'!$B$2:$B$5010,$A5,'Lançamentos'!$C$2:$C$5010,J$4) | K5: =SUM(B5:J5) | L5: =K5/K$12 | M5: =SUMIFS('Lançamentos'!$L$2:$L$5010,'Lançamentos'!$A$2:$A$5010,"Frete de compra",'Lançamentos'!$B$2:$B$5010,$A5,'Lançamentos'!$C$2:$C$5010,"Antes de 2026")
A6: 2.01.01 Frete Galpão Produto Acabado | B6: =SUMIFS('Lançamentos'!$L$2:$L$5010,'Lançamentos'!$A$2:$A$5010,"Frete de compra",'Lançamentos'!$B$2:$B$5010,$A6,'Lançamentos'!$C$2:$C$5010,B$4) | C6: =SUMIFS('Lançamentos'!$L$2:$L$5010,'Lançamentos'!$A$2:$A$5010,"Frete de compra",'Lançamentos'!$B$2:$B$5010,$A6,'Lançamentos'!$C$2:$C$5010,C$4) | D6: =SUMIFS('Lançamentos'!$L$2:$L$5010,'Lançamentos'!$A$2:$A$5010,"Frete de compra",'Lançamentos'!$B$2:$B$5010,$A6,'Lançamentos'!$C$2:$C$5010,D$4) | E6: =SUMIFS('Lançamentos'!$L$2:$L$5010,'Lançamentos'!$A$2:$A$5010,"Frete de compra",'Lançamentos'!$B$2:$B$5010,$A6,'Lançamentos'!$C$2:$C$5010,E$4) | F6: =SUMIFS('Lançamentos'!$L$2:$L$5010,'Lançamentos'!$A$2:$A$5010,"Frete de compra",'Lançamentos'!$B$2:$B$5010,$A6,'Lançamentos'!$C$2:$C$5010,F$4) | G6: =SUMIFS('Lançamentos'!$L$2:$L$5010,'Lançamentos'!$A$2:$A$5010,"Frete de compra",'Lançamentos'!$B$2:$B$5010,$A6,'Lançamentos'!$C$2:$C$5010,G$4) | H6: =SUMIFS('Lançamentos'!$L$2:$L$5010,'Lançamentos'!$A$2:$A$5010,"Frete de compra",'Lançamentos'!$B$2:$B$5010,$A6,'Lançamentos'!$C$2:$C$5010,H$4) | I6: =SUMIFS('Lançamentos'!$L$2:$L$5010,'Lançamentos'!$A$2:$A$5010,"Frete de compra",'Lançamentos'!$B$2:$B$5010,$A6,'Lançamentos'!$C$2:$C$5010,I$4) | J6: =SUMIFS('Lançamentos'!$L$2:$L$5010,'Lançamentos'!$A$2:$A$5010,"Frete de compra",'Lançamentos'!$B$2:$B$5010,$A6,'Lançamentos'!$C$2:$C$5010,J$4) | K6: =SUM(B6:J6) | L6: =K6/K$12 | M6: =SUMIFS('Lançamentos'!$L$2:$L$5010,'Lançamentos'!$A$2:$A$5010,"Frete de compra",'Lançamentos'!$B$2:$B$5010,$A6,'Lançamentos'!$C$2:$C$5010,"Antes de 2026")
A7: 2.01.02 Frete sobre Vendas | B7: =SUMIFS('Lançamentos'!$L$2:$L$5010,'Lançamentos'!$A$2:$A$5010,"Frete de compra",'Lançamentos'!$B$2:$B$5010,$A7,'Lançamentos'!$C$2:$C$5010,B$4) | C7: =SUMIFS('Lançamentos'!$L$2:$L$5010,'Lançamentos'!$A$2:$A$5010,"Frete de compra",'Lançamentos'!$B$2:$B$5010,$A7,'Lançamentos'!$C$2:$C$5010,C$4) | D7: =SUMIFS('Lançamentos'!$L$2:$L$5010,'Lançamentos'!$A$2:$A$5010,"Frete de compra",'Lançamentos'!$B$2:$B$5010,$A7,'Lançamentos'!$C$2:$C$5010,D$4) | E7: =SUMIFS('Lançamentos'!$L$2:$L$5010,'Lançamentos'!$A$2:$A$5010,"Frete de compra",'Lançamentos'!$B$2:$B$5010,$A7,'Lançamentos'!$C$2:$C$5010,E$4) | F7: =SUMIFS('Lançamentos'!$L$2:$L$5010,'Lançamentos'!$A$2:$A$5010,"Frete de compra",'Lançamentos'!$B$2:$B$5010,$A7,'Lançamentos'!$C$2:$C$5010,F$4) | G7: =SUMIFS('Lançamentos'!$L$2:$L$5010,'Lançamentos'!$A$2:$A$5010,"Frete de compra",'Lançamentos'!$B$2:$B$5010,$A7,'Lançamentos'!$C$2:$C$5010,G$4) | H7: =SUMIFS('Lançamentos'!$L$2:$L$5010,'Lançamentos'!$A$2:$A$5010,"Frete de compra",'Lançamentos'!$B$2:$B$5010,$A7,'Lançamentos'!$C$2:$C$5010,H$4) | I7: =SUMIFS('Lançamentos'!$L$2:$L$5010,'Lançamentos'!$A$2:$A$5010,"Frete de compra",'Lançamentos'!$B$2:$B$5010,$A7,'Lançamentos'!$C$2:$C$5010,I$4) | J7: =SUMIFS('Lançamentos'!$L$2:$L$5010,'Lançamentos'!$A$2:$A$5010,"Frete de compra",'Lançamentos'!$B$2:$B$5010,$A7,'Lançamentos'!$C$2:$C$5010,J$4) | K7: =SUM(B7:J7) | L7: =K7/K$12 | M7: =SUMIFS('Lançamentos'!$L$2:$L$5010,'Lançamentos'!$A$2:$A$5010,"Frete de compra",'Lançamentos'!$B$2:$B$5010,$A7,'Lançamentos'!$C$2:$C$5010,"Antes de 2026")
A8: 2.01.82 Estadia - Cabotagem | B8: =SUMIFS('Lançamentos'!$L$2:$L$5010,'Lançamentos'!$A$2:$A$5010,"Frete de compra",'Lançamentos'!$B$2:$B$5010,$A8,'Lançamentos'!$C$2:$C$5010,B$4) | C8: =SUMIFS('Lançamentos'!$L$2:$L$5010,'Lançamentos'!$A$2:$A$5010,"Frete de compra",'Lançamentos'!$B$2:$B$5010,$A8,'Lançamentos'!$C$2:$C$5010,C$4) | D8: =SUMIFS('Lançamentos'!$L$2:$L$5010,'Lançamentos'!$A$2:$A$5010,"Frete de compra",'Lançamentos'!$B$2:$B$5010,$A8,'Lançamentos'!$C$2:$C$5010,D$4) | E8: =SUMIFS('Lançamentos'!$L$2:$L$5010,'Lançamentos'!$A$2:$A$5010,"Frete de compra",'Lançamentos'!$B$2:$B$5010,$A8,'Lançamentos'!$C$2:$C$5010,E$4) | F8: =SUMIFS('Lançamentos'!$L$2:$L$5010,'Lançamentos'!$A$2:$A$5010,"Frete de compra",'Lançamentos'!$B$2:$B$5010,$A8,'Lançamentos'!$C$2:$C$5010,F$4) | G8: =SUMIFS('Lançamentos'!$L$2:$L$5010,'Lançamentos'!$A$2:$A$5010,"Frete de compra",'Lançamentos'!$B$2:$B$5010,$A8,'Lançamentos'!$C$2:$C$5010,G$4) | H8: =SUMIFS('Lançamentos'!$L$2:$L$5010,'Lançamentos'!$A$2:$A$5010,"Frete de compra",'Lançamentos'!$B$2:$B$5010,$A8,'Lançamentos'!$C$2:$C$5010,H$4) | I8: =SUMIFS('Lançamentos'!$L$2:$L$5010,'Lançamentos'!$A$2:$A$5010,"Frete de compra",'Lançamentos'!$B$2:$B$5010,$A8,'Lançamentos'!$C$2:$C$5010,I$4) | J8: =SUMIFS('Lançamentos'!$L$2:$L$5010,'Lançamentos'!$A$2:$A$5010,"Frete de compra",'Lançamentos'!$B$2:$B$5010,$A8,'Lançamentos'!$C$2:$C$5010,J$4) | K8: =SUM(B8:J8) | L8: =K8/K$12 | M8: =SUMIFS('Lançamentos'!$L$2:$L$5010,'Lançamentos'!$A$2:$A$5010,"Frete de compra",'Lançamentos'!$B$2:$B$5010,$A8,'Lançamentos'!$C$2:$C$5010,"Antes de 2026")
A9: 2.01.98 Frete Descarregamento | B9: =SUMIFS('Lançamentos'!$L$2:$L$5010,'Lançamentos'!$A$2:$A$5010,"Frete de compra",'Lançamentos'!$B$2:$B$5010,$A9,'Lançamentos'!$C$2:$C$5010,B$4) | C9: =SUMIFS('Lançamentos'!$L$2:$L$5010,'Lançamentos'!$A$2:$A$5010,"Frete de compra",'Lançamentos'!$B$2:$B$5010,$A9,'Lançamentos'!$C$2:$C$5010,C$4) | D9: =SUMIFS('Lançamentos'!$L$2:$L$5010,'Lançamentos'!$A$2:$A$5010,"Frete de compra",'Lançamentos'!$B$2:$B$5010,$A9,'Lançamentos'!$C$2:$C$5010,D$4) | E9: =SUMIFS('Lançamentos'!$L$2:$L$5010,'Lançamentos'!$A$2:$A$5010,"Frete de compra",'Lançamentos'!$B$2:$B$5010,$A9,'Lançamentos'!$C$2:$C$5010,E$4) | F9: =SUMIFS('Lançamentos'!$L$2:$L$5010,'Lançamentos'!$A$2:$A$5010,"Frete de compra",'Lançamentos'!$B$2:$B$5010,$A9,'Lançamentos'!$C$2:$C$5010,F$4) | G9: =SUMIFS('Lançamentos'!$L$2:$L$5010,'Lançamentos'!$A$2:$A$5010,"Frete de compra",'Lançamentos'!$B$2:$B$5010,$A9,'Lançamentos'!$C$2:$C$5010,G$4) | H9: =SUMIFS('Lançamentos'!$L$2:$L$5010,'Lançamentos'!$A$2:$A$5010,"Frete de compra",'Lançamentos'!$B$2:$B$5010,$A9,'Lançamentos'!$C$2:$C$5010,H$4) | I9: =SUMIFS('Lançamentos'!$L$2:$L$5010,'Lançamentos'!$A$2:$A$5010,"Frete de compra",'Lançamentos'!$B$2:$B$5010,$A9,'Lançamentos'!$C$2:$C$5010,I$4) | J9: =SUMIFS('Lançamentos'!$L$2:$L$5010,'Lançamentos'!$A$2:$A$5010,"Frete de compra",'Lançamentos'!$B$2:$B$5010,$A9,'Lançamentos'!$C$2:$C$5010,J$4) | K9: =SUM(B9:J9) | L9: =K9/K$12 | M9: =SUMIFS('Lançamentos'!$L$2:$L$5010,'Lançamentos'!$A$2:$A$5010,"Frete de compra",'Lançamentos'!$B$2:$B$5010,$A9,'Lançamentos'!$C$2:$C$5010,"Antes de 2026")
A10: 2.02.93 Frete Amostras/Brindes | B10: =SUMIFS('Lançamentos'!$L$2:$L$5010,'Lançamentos'!$A$2:$A$5010,"Frete de compra",'Lançamentos'!$B$2:$B$5010,$A10,'Lançamentos'!$C$2:$C$5010,B$4) | C10: =SUMIFS('Lançamentos'!$L$2:$L$5010,'Lançamentos'!$A$2:$A$5010,"Frete de compra",'Lançamentos'!$B$2:$B$5010,$A10,'Lançamentos'!$C$2:$C$5010,C$4) | D10: =SUMIFS('Lançamentos'!$L$2:$L$5010,'Lançamentos'!$A$2:$A$5010,"Frete de compra",'Lançamentos'!$B$2:$B$5010,$A10,'Lançamentos'!$C$2:$C$5010,D$4) | E10: =SUMIFS('Lançamentos'!$L$2:$L$5010,'Lançamentos'!$A$2:$A$5010,"Frete de compra",'Lançamentos'!$B$2:$B$5010,$A10,'Lançamentos'!$C$2:$C$5010,E$4) | F10: =SUMIFS('Lançamentos'!$L$2:$L$5010,'Lançamentos'!$A$2:$A$5010,"Frete de compra",'Lançamentos'!$B$2:$B$5010,$A10,'Lançamentos'!$C$2:$C$5010,F$4) | G10: =SUMIFS('Lançamentos'!$L$2:$L$5010,'Lançamentos'!$A$2:$A$5010,"Frete de compra",'Lançamentos'!$B$2:$B$5010,$A10,'Lançamentos'!$C$2:$C$5010,G$4) | H10: =SUMIFS('Lançamentos'!$L$2:$L$5010,'Lançamentos'!$A$2:$A$5010,"Frete de compra",'Lançamentos'!$B$2:$B$5010,$A10,'Lançamentos'!$C$2:$C$5010,H$4) | I10: =SUMIFS('Lançamentos'!$L$2:$L$5010,'Lançamentos'!$A$2:$A$5010,"Frete de compra",'Lançamentos'!$B$2:$B$5010,$A10,'Lançamentos'!$C$2:$C$5010,I$4) | J10: =SUMIFS('Lançamentos'!$L$2:$L$5010,'Lançamentos'!$A$2:$A$5010,"Frete de compra",'Lançamentos'!$B$2:$B$5010,$A10,'Lançamentos'!$C$2:$C$5010,J$4) | K10: =SUM(B10:J10) | L10: =K10/K$12 | M10: =SUMIFS('Lançamentos'!$L$2:$L$5010,'Lançamentos'!$A$2:$A$5010,"Frete de compra",'Lançamentos'!$B$2:$B$5010,$A10,'Lançamentos'!$C$2:$C$5010,"Antes de 2026")
A11: 2.04.87 Frete sobre Compra | B11: =SUMIFS('Lançamentos'!$L$2:$L$5010,'Lançamentos'!$A$2:$A$5010,"Frete de compra",'Lançamentos'!$B$2:$B$5010,$A11,'Lançamentos'!$C$2:$C$5010,B$4) | C11: =SUMIFS('Lançamentos'!$L$2:$L$5010,'Lançamentos'!$A$2:$A$5010,"Frete de compra",'Lançamentos'!$B$2:$B$5010,$A11,'Lançamentos'!$C$2:$C$5010,C$4) | D11: =SUMIFS('Lançamentos'!$L$2:$L$5010,'Lançamentos'!$A$2:$A$5010,"Frete de compra",'Lançamentos'!$B$2:$B$5010,$A11,'Lançamentos'!$C$2:$C$5010,D$4) | E11: =SUMIFS('Lançamentos'!$L$2:$L$5010,'Lançamentos'!$A$2:$A$5010,"Frete de compra",'Lançamentos'!$B$2:$B$5010,$A11,'Lançamentos'!$C$2:$C$5010,E$4) | F11: =SUMIFS('Lançamentos'!$L$2:$L$5010,'Lançamentos'!$A$2:$A$5010,"Frete de compra",'Lançamentos'!$B$2:$B$5010,$A11,'Lançamentos'!$C$2:$C$5010,F$4) | G11: =SUMIFS('Lançamentos'!$L$2:$L$5010,'Lançamentos'!$A$2:$A$5010,"Frete de compra",'Lançamentos'!$B$2:$B$5010,$A11,'Lançamentos'!$C$2:$C$5010,G$4) | H11: =SUMIFS('Lançamentos'!$L$2:$L$5010,'Lançamentos'!$A$2:$A$5010,"Frete de compra",'Lançamentos'!$B$2:$B$5010,$A11,'Lançamentos'!$C$2:$C$5010,H$4) | I11: =SUMIFS('Lançamentos'!$L$2:$L$5010,'Lançamentos'!$A$2:$A$5010,"Frete de compra",'Lançamentos'!$B$2:$B$5010,$A11,'Lançamentos'!$C$2:$C$5010,I$4) | J11: =SUMIFS('Lançamentos'!$L$2:$L$5010,'Lançamentos'!$A$2:$A$5010,"Frete de compra",'Lançamentos'!$B$2:$B$5010,$A11,'Lançamentos'!$C$2:$C$5010,J$4) | K11: =SUM(B11:J11) | L11: =K11/K$12 | M11: =SUMIFS('Lançamentos'!$L$2:$L$5010,'Lançamentos'!$A$2:$A$5010,"Frete de compra",'Lançamentos'!$B$2:$B$5010,$A11,'Lançamentos'!$C$2:$C$5010,"Antes de 2026")
A12: TOTAL FRETE DE COMPRA | B12: =SUM(B5:B11) | C12: =SUM(C5:C11) | D12: =SUM(D5:D11) | E12: =SUM(E5:E11) | F12: =SUM(F5:F11) | G12: =SUM(G5:G11) | H12: =SUM(H5:H11) | I12: =SUM(I5:I11) | ... K12: =SUM(K5:K11) | L12: =K12/K$12 | M12: =SUM(M5:M11)
A14: Memo: valor bruto (com impostos) | B14: =SUMIFS('Lançamentos'!$J$2:$J$5010,'Lançamentos'!$A$2:$A$5010,"Frete de compra",'Lançamentos'!$C$2:$C$5010,B$4) | C14: =SUMIFS('Lançamentos'!$J$2:$J$5010,'Lançamentos'!$A$2:$A$5010,"Frete de compra",'Lançamentos'!$C$2:$C$5010,C$4) | D14: =SUMIFS('Lançamentos'!$J$2:$J$5010,'Lançamentos'!$A$2:$A$5010,"Frete de compra",'Lançamentos'!$C$2:$C$5010,D$4) | E14: =SUMIFS('Lançamentos'!$J$2:$J$5010,'Lançamentos'!$A$2:$A$5010,"Frete de compra",'Lançamentos'!$C$2:$C$5010,E$4) | F14: =SUMIFS('Lançamentos'!$J$2:$J$5010,'Lançamentos'!$A$2:$A$5010,"Frete de compra",'Lançamentos'!$C$2:$C$5010,F$4) | G14: =SUMIFS('Lançamentos'!$J$2:$J$5010,'Lançamentos'!$A$2:$A$5010,"Frete de compra",'Lançamentos'!$C$2:$C$5010,G$4) | H14: =SUMIFS('Lançamentos'!$J$2:$J$5010,'Lançamentos'!$A$2:$A$5010,"Frete de compra",'Lançamentos'!$C$2:$C$5010,H$4) | I14: =SUMIFS('Lançamentos'!$J$2:$J$5010,'Lançamentos'!$A$2:$A$5010,"Frete de compra",'Lançamentos'!$C$2:$C$5010,I$4) | J14: =SUMIFS('Lançamentos'!$J$2:$J$5010,'Lançamentos'!$A$2:$A$5010,"Frete de compra",'Lançamentos'!$C$2:$C$5010,J$4) | K14: =SUM(B14:J14) | M14: =SUMIFS('Lançamentos'!$J$2:$J$5010,'Lançamentos'!$A$2:$A$5010,"Frete de compra",'Lançamentos'!$C$2:$C$5010,"Antes de 2026")
A15: Memo: créditos abatidos | B15: =SUMIFS('Lançamentos'!$K$2:$K$5010,'Lançamentos'!$A$2:$A$5010,"Frete de compra",'Lançamentos'!$C$2:$C$5010,B$4) | C15: =SUMIFS('Lançamentos'!$K$2:$K$5010,'Lançamentos'!$A$2:$A$5010,"Frete de compra",'Lançamentos'!$C$2:$C$5010,C$4) | D15: =SUMIFS('Lançamentos'!$K$2:$K$5010,'Lançamentos'!$A$2:$A$5010,"Frete de compra",'Lançamentos'!$C$2:$C$5010,D$4) | E15: =SUMIFS('Lançamentos'!$K$2:$K$5010,'Lançamentos'!$A$2:$A$5010,"Frete de compra",'Lançamentos'!$C$2:$C$5010,E$4) | F15: =SUMIFS('Lançamentos'!$K$2:$K$5010,'Lançamentos'!$A$2:$A$5010,"Frete de compra",'Lançamentos'!$C$2:$C$5010,F$4) | G15: =SUMIFS('Lançamentos'!$K$2:$K$5010,'Lançamentos'!$A$2:$A$5010,"Frete de compra",'Lançamentos'!$C$2:$C$5010,G$4) | H15: =SUMIFS('Lançamentos'!$K$2:$K$5010,'Lançamentos'!$A$2:$A$5010,"Frete de compra",'Lançamentos'!$C$2:$C$5010,H$4) | I15: =SUMIFS('Lançamentos'!$K$2:$K$5010,'Lançamentos'!$A$2:$A$5010,"Frete de compra",'Lançamentos'!$C$2:$C$5010,I$4) | J15: =SUMIFS('Lançamentos'!$K$2:$K$5010,'Lançamentos'!$A$2:$A$5010,"Frete de compra",'Lançamentos'!$C$2:$C$5010,J$4) | K15: =SUM(B15:J15) | M15: =SUMIFS('Lançamentos'!$K$2:$K$5010,'Lançamentos'!$A$2:$A$5010,"Frete de compra",'Lançamentos'!$C$2:$C$5010,"Antes de 2026")
A16: Conferência: bruto − créditos − total (deve ser zero) | B16: =ROUND(B14-B15-B12,2) | C16: =ROUND(C14-C15-C12,2) | D16: =ROUND(D14-D15-D12,2) | E16: =ROUND(E14-E15-E12,2) | F16: =ROUND(F14-F15-F12,2) | G16: =ROUND(G14-G15-G12,2) | H16: =ROUND(H14-H15-H12,2) | I16: =ROUND(I14-I15-I12,2) | ... K16: =ROUND(K14-K15-K12,2) | M16: =ROUND(M14-M15-M12,2)
A18: Por fornecedor / transportadora
A19: Fornecedor / Transportadora | B19: 46023 | C19: 46054 | D19: 46082 | E19: 46113 | F19: 46143 | G19: 46174 | H19: 46204 | I19: 46235 | J19: 46266 | K19: Total 2026 | L19: % do total | M19: Memo: antes de 2026 | N19: Valor bruto 2026 | O19: Créditos 2026 | P19: Nº docs 2026
A20: ALIANCA NAVEGACAO E LOGISTICA LTDA | B20: =SUMIFS('Lançamentos'!$L$2:$L$5010,'Lançamentos'!$A$2:$A$5010,"Frete de compra",'Lançamentos'!$H$2:$H$5010,$A20,'Lançamentos'!$C$2:$C$5010,B$19) | C20: =SUMIFS('Lançamentos'!$L$2:$L$5010,'Lançamentos'!$A$2:$A$5010,"Frete de compra",'Lançamentos'!$H$2:$H$5010,$A20,'Lançamentos'!$C$2:$C$5010,C$19) | D20: =SUMIFS('Lançamentos'!$L$2:$L$5010,'Lançamentos'!$A$2:$A$5010,"Frete de compra",'Lançamentos'!$H$2:$H$5010,$A20,'Lançamentos'!$C$2:$C$5010,D$19) | E20: =SUMIFS('Lançamentos'!$L$2:$L$5010,'Lançamentos'!$A$2:$A$5010,"Frete de compra",'Lançamentos'!$H$2:$H$5010,$A20,'Lançamentos'!$C$2:$C$5010,E$19) | F20: =SUMIFS('Lançamentos'!$L$2:$L$5010,'Lançamentos'!$A$2:$A$5010,"Frete de compra",'Lançamentos'!$H$2:$H$5010,$A20,'Lançamentos'!$C$2:$C$5010,F$19) | G20: =SUMIFS('Lançamentos'!$L$2:$L$5010,'Lançamentos'!$A$2:$A$5010,"Frete de compra",'Lançamentos'!$H$2:$H$5010,$A20,'Lançamentos'!$C$2:$C$5010,G$19) | H20: =SUMIFS('Lançamentos'!$L$2:$L$5010,'Lançamentos'!$A$2:$A$5010,"Frete de compra",'Lançamentos'!$H$2:$H$5010,$A20,'Lançamentos'!$C$2:$C$5010,H$19) | I20: =SUMIFS('Lançamentos'!$L$2:$L$5010,'Lançamentos'!$A$2:$A$5010,"Frete de compra",'Lançamentos'!$H$2:$H$5010,$A20,'Lançamentos'!$C$2:$C$5010,I$19) | J20: =SUMIFS('Lançamentos'!$L$2:$L$5010,'Lançamentos'!$A$2:$A$5010,"Frete de compra",'Lançamentos'!$H$2:$H$5010,$A20,'Lançamentos'!$C$2:$C$5010,J$19) | K20: =SUM(B20:J20) | L20: =K20/K$24 | M20: =SUMIFS('Lançamentos'!$L$2:$L$5010,'Lançamentos'!$A$2:$A$5010,"Frete de compra",'Lançamentos'!$H$2:$H$5010,$A20,'Lançamentos'!$C$2:$C$5010,"Antes de 2026") | N20: =SUMIFS('Lançamentos'!$J$2:$J$5010,'Lançamentos'!$A$2:$A$5010,"Frete de compra",'Lançamentos'!$H$2:$H$5010,$A20,'Lançamentos'!$D$2:$D$5010,"Em 2026") | O20: =SUMIFS('Lançamentos'!$K$2:$K$5010,'Lançamentos'!$A$2:$A$5010,"Frete de compra",'Lançamentos'!$H$2:$H$5010,$A20,'Lançamentos'!$D$2:$D$5010,"Em 2026") | P20: =COUNTIFS('Lançamentos'!$A$2:$A$5010,"Frete de compra",'Lançamentos'!$H$2:$H$5010,$A20,'Lançamentos'!$D$2:$D$5010,"Em 2026")
A21: TRANSPORTES DE MAQUINAS PLANETA AZUL LTDA | B21: =SUMIFS('Lançamentos'!$L$2:$L$5010,'Lançamentos'!$A$2:$A$5010,"Frete de compra",'Lançamentos'!$H$2:$H$5010,$A21,'Lançamentos'!$C$2:$C$5010,B$19) | C21: =SUMIFS('Lançamentos'!$L$2:$L$5010,'Lançamentos'!$A$2:$A$5010,"Frete de compra",'Lançamentos'!$H$2:$H$5010,$A21,'Lançamentos'!$C$2:$C$5010,C$19) | D21: =SUMIFS('Lançamentos'!$L$2:$L$5010,'Lançamentos'!$A$2:$A$5010,"Frete de compra",'Lançamentos'!$H$2:$H$5010,$A21,'Lançamentos'!$C$2:$C$5010,D$19) | E21: =SUMIFS('Lançamentos'!$L$2:$L$5010,'Lançamentos'!$A$2:$A$5010,"Frete de compra",'Lançamentos'!$H$2:$H$5010,$A21,'Lançamentos'!$C$2:$C$5010,E$19) | F21: =SUMIFS('Lançamentos'!$L$2:$L$5010,'Lançamentos'!$A$2:$A$5010,"Frete de compra",'Lançamentos'!$H$2:$H$5010,$A21,'Lançamentos'!$C$2:$C$5010,F$19) | G21: =SUMIFS('Lançamentos'!$L$2:$L$5010,'Lançamentos'!$A$2:$A$5010,"Frete de compra",'Lançamentos'!$H$2:$H$5010,$A21,'Lançamentos'!$C$2:$C$5010,G$19) | H21: =SUMIFS('Lançamentos'!$L$2:$L$5010,'Lançamentos'!$A$2:$A$5010,"Frete de compra",'Lançamentos'!$H$2:$H$5010,$A21,'Lançamentos'!$C$2:$C$5010,H$19) | I21: =SUMIFS('Lançamentos'!$L$2:$L$5010,'Lançamentos'!$A$2:$A$5010,"Frete de compra",'Lançamentos'!$H$2:$H$5010,$A21,'Lançamentos'!$C$2:$C$5010,I$19) | J21: =SUMIFS('Lançamentos'!$L$2:$L$5010,'Lançamentos'!$A$2:$A$5010,"Frete de compra",'Lançamentos'!$H$2:$H$5010,$A21,'Lançamentos'!$C$2:$C$5010,J$19) | K21: =SUM(B21:J21) | L21: =K21/K$24 | M21: =SUMIFS('Lançamentos'!$L$2:$L$5010,'Lançamentos'!$A$2:$A$5010,"Frete de compra",'Lançamentos'!$H$2:$H$5010,$A21,'Lançamentos'!$C$2:$C$5010,"Antes de 2026") | N21: =SUMIFS('Lançamentos'!$J$2:$J$5010,'Lançamentos'!$A$2:$A$5010,"Frete de compra",'Lançamentos'!$H$2:$H$5010,$A21,'Lançamentos'!$D$2:$D$5010,"Em 2026") | O21: =SUMIFS('Lançamentos'!$K$2:$K$5010,'Lançamentos'!$A$2:$A$5010,"Frete de compra",'Lançamentos'!$H$2:$H$5010,$A21,'Lançamentos'!$D$2:$D$5010,"Em 2026") | P21: =COUNTIFS('Lançamentos'!$A$2:$A$5010,"Frete de compra",'Lançamentos'!$H$2:$H$5010,$A21,'Lançamentos'!$D$2:$D$5010,"Em 2026")
