Workbook

Sheet Resumo
A1: Despesas 2026 – almoxarifado (insumos, papel, uso e consumo, frete de compra) e frete de venda – VINCO
A2: R$, por mês de emissão. Custo líquido = valor bruto menos créditos de impostos recuperáveis (regras na aba Premissas). Só o efetivamente pago (NF-e com título a pagar + CT-e); sem remessa de compra, devolução, transferência, x.949, x.922 e aluguel de contêiner.
A4: Destino / Categoria | B4: 46023 | C4: 46054 | D4: 46082 | E4: 46113 | F4: 46143 | G4: 46174 | H4: 46204 | I4: 46235 | J4: 46266 | K4: Total 2026 | L4: Memo: antes de 2026
A5: Insumos e papel
A6: 2.01.03 Compra de Matéria Prima (Papel) | B6: =SUMIFS(Base!$N$2:$N$4835,Base!$B$2:$B$4835,"Insumos e papel",Base!$C$2:$C$4835,"2.01.03 Compra de Matéria Prima (Papel)",Base!$A$2:$A$4835,B$4) | C6: =SUMIFS(Base!$N$2:$N$4835,Base!$B$2:$B$4835,"Insumos e papel",Base!$C$2:$C$4835,"2.01.03 Compra de Matéria Prima (Papel)",Base!$A$2:$A$4835,C$4) | D6: =SUMIFS(Base!$N$2:$N$4835,Base!$B$2:$B$4835,"Insumos e papel",Base!$C$2:$C$4835,"2.01.03 Compra de Matéria Prima (Papel)",Base!$A$2:$A$4835,D$4) | E6: =SUMIFS(Base!$N$2:$N$4835,Base!$B$2:$B$4835,"Insumos e papel",Base!$C$2:$C$4835,"2.01.03 Compra de Matéria Prima (Papel)",Base!$A$2:$A$4835,E$4) | F6: =SUMIFS(Base!$N$2:$N$4835,Base!$B$2:$B$4835,"Insumos e papel",Base!$C$2:$C$4835,"2.01.03 Compra de Matéria Prima (Papel)",Base!$A$2:$A$4835,F$4) | G6: =SUMIFS(Base!$N$2:$N$4835,Base!$B$2:$B$4835,"Insumos e papel",Base!$C$2:$C$4835,"2.01.03 Compra de Matéria Prima (Papel)",Base!$A$2:$A$4835,G$4) | H6: =SUMIFS(Base!$N$2:$N$4835,Base!$B$2:$B$4835,"Insumos e papel",Base!$C$2:$C$4835,"2.01.03 Compra de Matéria Prima (Papel)",Base!$A$2:$A$4835,H$4) | I6: =SUMIFS(Base!$N$2:$N$4835,Base!$B$2:$B$4835,"Insumos e papel",Base!$C$2:$C$4835,"2.01.03 Compra de Matéria Prima (Papel)",Base!$A$2:$A$4835,I$4) | J6: =SUMIFS(Base!$N$2:$N$4835,Base!$B$2:$B$4835,"Insumos e papel",Base!$C$2:$C$4835,"2.01.03 Compra de Matéria Prima (Papel)",Base!$A$2:$A$4835,J$4) | K6: =SUM(B6:J6) | L6: =SUMIFS(Base!$N$2:$N$4835,Base!$B$2:$B$4835,"Insumos e papel",Base!$C$2:$C$4835,"2.01.03 Compra de Matéria Prima (Papel)",Base!$A$2:$A$4835,"Antes de 2026")
A7: 2.01.79 Compra de Gás | B7: =SUMIFS(Base!$N$2:$N$4835,Base!$B$2:$B$4835,"Insumos e papel",Base!$C$2:$C$4835,"2.01.79 Compra de Gás",Base!$A$2:$A$4835,B$4) | C7: =SUMIFS(Base!$N$2:$N$4835,Base!$B$2:$B$4835,"Insumos e papel",Base!$C$2:$C$4835,"2.01.79 Compra de Gás",Base!$A$2:$A$4835,C$4) | D7: =SUMIFS(Base!$N$2:$N$4835,Base!$B$2:$B$4835,"Insumos e papel",Base!$C$2:$C$4835,"2.01.79 Compra de Gás",Base!$A$2:$A$4835,D$4) | E7: =SUMIFS(Base!$N$2:$N$4835,Base!$B$2:$B$4835,"Insumos e papel",Base!$C$2:$C$4835,"2.01.79 Compra de Gás",Base!$A$2:$A$4835,E$4) | F7: =SUMIFS(Base!$N$2:$N$4835,Base!$B$2:$B$4835,"Insumos e papel",Base!$C$2:$C$4835,"2.01.79 Compra de Gás",Base!$A$2:$A$4835,F$4) | G7: =SUMIFS(Base!$N$2:$N$4835,Base!$B$2:$B$4835,"Insumos e papel",Base!$C$2:$C$4835,"2.01.79 Compra de Gás",Base!$A$2:$A$4835,G$4) | H7: =SUMIFS(Base!$N$2:$N$4835,Base!$B$2:$B$4835,"Insumos e papel",Base!$C$2:$C$4835,"2.01.79 Compra de Gás",Base!$A$2:$A$4835,H$4) | I7: =SUMIFS(Base!$N$2:$N$4835,Base!$B$2:$B$4835,"Insumos e papel",Base!$C$2:$C$4835,"2.01.79 Compra de Gás",Base!$A$2:$A$4835,I$4) | J7: =SUMIFS(Base!$N$2:$N$4835,Base!$B$2:$B$4835,"Insumos e papel",Base!$C$2:$C$4835,"2.01.79 Compra de Gás",Base!$A$2:$A$4835,J$4) | K7: =SUM(B7:J7) | L7: =SUMIFS(Base!$N$2:$N$4835,Base!$B$2:$B$4835,"Insumos e papel",Base!$C$2:$C$4835,"2.01.79 Compra de Gás",Base!$A$2:$A$4835,"Antes de 2026")
A8: 2.01.83 Compra de Etiqueta Personalizada | B8: =SUMIFS(Base!$N$2:$N$4835,Base!$B$2:$B$4835,"Insumos e papel",Base!$C$2:$C$4835,"2.01.83 Compra de Etiqueta Personalizada",Base!$A$2:$A$4835,B$4) | C8: =SUMIFS(Base!$N$2:$N$4835,Base!$B$2:$B$4835,"Insumos e papel",Base!$C$2:$C$4835,"2.01.83 Compra de Etiqueta Personalizada",Base!$A$2:$A$4835,C$4) | D8: =SUMIFS(Base!$N$2:$N$4835,Base!$B$2:$B$4835,"Insumos e papel",Base!$C$2:$C$4835,"2.01.83 Compra de Etiqueta Personalizada",Base!$A$2:$A$4835,D$4) | E8: =SUMIFS(Base!$N$2:$N$4835,Base!$B$2:$B$4835,"Insumos e papel",Base!$C$2:$C$4835,"2.01.83 Compra de Etiqueta Personalizada",Base!$A$2:$A$4835,E$4) | F8: =SUMIFS(Base!$N$2:$N$4835,Base!$B$2:$B$4835,"Insumos e papel",Base!$C$2:$C$4835,"2.01.83 Compra de Etiqueta Personalizada",Base!$A$2:$A$4835,F$4) | G8: =SUMIFS(Base!$N$2:$N$4835,Base!$B$2:$B$4835,"Insumos e papel",Base!$C$2:$C$4835,"2.01.83 Compra de Etiqueta Personalizada",Base!$A$2:$A$4835,G$4) | H8: =SUMIFS(Base!$N$2:$N$4835,Base!$B$2:$B$4835,"Insumos e papel",Base!$C$2:$C$4835,"2.01.83 Compra de Etiqueta Personalizada",Base!$A$2:$A$4835,H$4) | I8: =SUMIFS(Base!$N$2:$N$4835,Base!$B$2:$B$4835,"Insumos e papel",Base!$C$2:$C$4835,"2.01.83 Compra de Etiqueta Personalizada",Base!$A$2:$A$4835,I$4) | J8: =SUMIFS(Base!$N$2:$N$4835,Base!$B$2:$B$4835,"Insumos e papel",Base!$C$2:$C$4835,"2.01.83 Compra de Etiqueta Personalizada",Base!$A$2:$A$4835,J$4) | K8: =SUM(B8:J8) | L8: =SUMIFS(Base!$N$2:$N$4835,Base!$B$2:$B$4835,"Insumos e papel",Base!$C$2:$C$4835,"2.01.83 Compra de Etiqueta Personalizada",Base!$A$2:$A$4835,"Antes de 2026")
A9: 2.01.89 Compra de Pallet | B9: =SUMIFS(Base!$N$2:$N$4835,Base!$B$2:$B$4835,"Insumos e papel",Base!$C$2:$C$4835,"2.01.89 Compra de Pallet",Base!$A$2:$A$4835,B$4) | C9: =SUMIFS(Base!$N$2:$N$4835,Base!$B$2:$B$4835,"Insumos e papel",Base!$C$2:$C$4835,"2.01.89 Compra de Pallet",Base!$A$2:$A$4835,C$4) | D9: =SUMIFS(Base!$N$2:$N$4835,Base!$B$2:$B$4835,"Insumos e papel",Base!$C$2:$C$4835,"2.01.89 Compra de Pallet",Base!$A$2:$A$4835,D$4) | E9: =SUMIFS(Base!$N$2:$N$4835,Base!$B$2:$B$4835,"Insumos e papel",Base!$C$2:$C$4835,"2.01.89 Compra de Pallet",Base!$A$2:$A$4835,E$4) | F9: =SUMIFS(Base!$N$2:$N$4835,Base!$B$2:$B$4835,"Insumos e papel",Base!$C$2:$C$4835,"2.01.89 Compra de Pallet",Base!$A$2:$A$4835,F$4) | G9: =SUMIFS(Base!$N$2:$N$4835,Base!$B$2:$B$4835,"Insumos e papel",Base!$C$2:$C$4835,"2.01.89 Compra de Pallet",Base!$A$2:$A$4835,G$4) | H9: =SUMIFS(Base!$N$2:$N$4835,Base!$B$2:$B$4835,"Insumos e papel",Base!$C$2:$C$4835,"2.01.89 Compra de Pallet",Base!$A$2:$A$4835,H$4) | I9: =SUMIFS(Base!$N$2:$N$4835,Base!$B$2:$B$4835,"Insumos e papel",Base!$C$2:$C$4835,"2.01.89 Compra de Pallet",Base!$A$2:$A$4835,I$4) | J9: =SUMIFS(Base!$N$2:$N$4835,Base!$B$2:$B$4835,"Insumos e papel",Base!$C$2:$C$4835,"2.01.89 Compra de Pallet",Base!$A$2:$A$4835,J$4) | K9: =SUM(B9:J9) | L9: =SUMIFS(Base!$N$2:$N$4835,Base!$B$2:$B$4835,"Insumos e papel",Base!$C$2:$C$4835,"2.01.89 Compra de Pallet",Base!$A$2:$A$4835,"Antes de 2026")
A10: 2.01.91 Compra de Filme Strech | B10: =SUMIFS(Base!$N$2:$N$4835,Base!$B$2:$B$4835,"Insumos e papel",Base!$C$2:$C$4835,"2.01.91 Compra de Filme Strech",Base!$A$2:$A$4835,B$4) | C10: =SUMIFS(Base!$N$2:$N$4835,Base!$B$2:$B$4835,"Insumos e papel",Base!$C$2:$C$4835,"2.01.91 Compra de Filme Strech",Base!$A$2:$A$4835,C$4) | D10: =SUMIFS(Base!$N$2:$N$4835,Base!$B$2:$B$4835,"Insumos e papel",Base!$C$2:$C$4835,"2.01.91 Compra de Filme Strech",Base!$A$2:$A$4835,D$4) | E10: =SUMIFS(Base!$N$2:$N$4835,Base!$B$2:$B$4835,"Insumos e papel",Base!$C$2:$C$4835,"2.01.91 Compra de Filme Strech",Base!$A$2:$A$4835,E$4) | F10: =SUMIFS(Base!$N$2:$N$4835,Base!$B$2:$B$4835,"Insumos e papel",Base!$C$2:$C$4835,"2.01.91 Compra de Filme Strech",Base!$A$2:$A$4835,F$4) | G10: =SUMIFS(Base!$N$2:$N$4835,Base!$B$2:$B$4835,"Insumos e papel",Base!$C$2:$C$4835,"2.01.91 Compra de Filme Strech",Base!$A$2:$A$4835,G$4) | H10: =SUMIFS(Base!$N$2:$N$4835,Base!$B$2:$B$4835,"Insumos e papel",Base!$C$2:$C$4835,"2.01.91 Compra de Filme Strech",Base!$A$2:$A$4835,H$4) | I10: =SUMIFS(Base!$N$2:$N$4835,Base!$B$2:$B$4835,"Insumos e papel",Base!$C$2:$C$4835,"2.01.91 Compra de Filme Strech",Base!$A$2:$A$4835,I$4) | J10: =SUMIFS(Base!$N$2:$N$4835,Base!$B$2:$B$4835,"Insumos e papel",Base!$C$2:$C$4835,"2.01.91 Compra de Filme Strech",Base!$A$2:$A$4835,J$4) | K10: =SUM(B10:J10) | L10: =SUMIFS(Base!$N$2:$N$4835,Base!$B$2:$B$4835,"Insumos e papel",Base!$C$2:$C$4835,"2.01.91 Compra de Filme Strech",Base!$A$2:$A$4835,"Antes de 2026")
A11: 2.01.92 Compra de Tinta | B11: =SUMIFS(Base!$N$2:$N$4835,Base!$B$2:$B$4835,"Insumos e papel",Base!$C$2:$C$4835,"2.01.92 Compra de Tinta",Base!$A$2:$A$4835,B$4) | C11: =SUMIFS(Base!$N$2:$N$4835,Base!$B$2:$B$4835,"Insumos e papel",Base!$C$2:$C$4835,"2.01.92 Compra de Tinta",Base!$A$2:$A$4835,C$4) | D11: =SUMIFS(Base!$N$2:$N$4835,Base!$B$2:$B$4835,"Insumos e papel",Base!$C$2:$C$4835,"2.01.92 Compra de Tinta",Base!$A$2:$A$4835,D$4) | E11: =SUMIFS(Base!$N$2:$N$4835,Base!$B$2:$B$4835,"Insumos e papel",Base!$C$2:$C$4835,"2.01.92 Compra de Tinta",Base!$A$2:$A$4835,E$4) | F11: =SUMIFS(Base!$N$2:$N$4835,Base!$B$2:$B$4835,"Insumos e papel",Base!$C$2:$C$4835,"2.01.92 Compra de Tinta",Base!$A$2:$A$4835,F$4) | G11: =SUMIFS(Base!$N$2:$N$4835,Base!$B$2:$B$4835,"Insumos e papel",Base!$C$2:$C$4835,"2.01.92 Compra de Tinta",Base!$A$2:$A$4835,G$4) | H11: =SUMIFS(Base!$N$2:$N$4835,Base!$B$2:$B$4835,"Insumos e papel",Base!$C$2:$C$4835,"2.01.92 Compra de Tinta",Base!$A$2:$A$4835,H$4) | I11: =SUMIFS(Base!$N$2:$N$4835,Base!$B$2:$B$4835,"Insumos e papel",Base!$C$2:$C$4835,"2.01.92 Compra de Tinta",Base!$A$2:$A$4835,I$4) | J11: =SUMIFS(Base!$N$2:$N$4835,Base!$B$2:$B$4835,"Insumos e papel",Base!$C$2:$C$4835,"2.01.92 Compra de Tinta",Base!$A$2:$A$4835,J$4) | K11: =SUM(B11:J11) | L11: =SUMIFS(Base!$N$2:$N$4835,Base!$B$2:$B$4835,"Insumos e papel",Base!$C$2:$C$4835,"2.01.92 Compra de Tinta",Base!$A$2:$A$4835,"Antes de 2026")
A12: 2.01.93 Compra de Plástico Poliolefínico | B12: =SUMIFS(Base!$N$2:$N$4835,Base!$B$2:$B$4835,"Insumos e papel",Base!$C$2:$C$4835,"2.01.93 Compra de Plástico Poliolefínico",Base!$A$2:$A$4835,B$4) | C12: =SUMIFS(Base!$N$2:$N$4835,Base!$B$2:$B$4835,"Insumos e papel",Base!$C$2:$C$4835,"2.01.93 Compra de Plástico Poliolefínico",Base!$A$2:$A$4835,C$4) | D12: =SUMIFS(Base!$N$2:$N$4835,Base!$B$2:$B$4835,"Insumos e papel",Base!$C$2:$C$4835,"2.01.93 Compra de Plástico Poliolefínico",Base!$A$2:$A$4835,D$4) | E12: =SUMIFS(Base!$N$2:$N$4835,Base!$B$2:$B$4835,"Insumos e papel",Base!$C$2:$C$4835,"2.01.93 Compra de Plástico Poliolefínico",Base!$A$2:$A$4835,E$4) | F12: =SUMIFS(Base!$N$2:$N$4835,Base!$B$2:$B$4835,"Insumos e papel",Base!$C$2:$C$4835,"2.01.93 Compra de Plástico Poliolefínico",Base!$A$2:$A$4835,F$4) | G12: =SUMIFS(Base!$N$2:$N$4835,Base!$B$2:$B$4835,"Insumos e papel",Base!$C$2:$C$4835,"2.01.93 Compra de Plástico Poliolefínico",Base!$A$2:$A$4835,G$4) | H12: =SUMIFS(Base!$N$2:$N$4835,Base!$B$2:$B$4835,"Insumos e papel",Base!$C$2:$C$4835,"2.01.93 Compra de Plástico Poliolefínico",Base!$A$2:$A$4835,H$4) | I12: =SUMIFS(Base!$N$2:$N$4835,Base!$B$2:$B$4835,"Insumos e papel",Base!$C$2:$C$4835,"2.01.93 Compra de Plástico Poliolefínico",Base!$A$2:$A$4835,I$4) | J12: =SUMIFS(Base!$N$2:$N$4835,Base!$B$2:$B$4835,"Insumos e papel",Base!$C$2:$C$4835,"2.01.93 Compra de Plástico Poliolefínico",Base!$A$2:$A$4835,J$4) | K12: =SUM(B12:J12) | L12: =SUMIFS(Base!$N$2:$N$4835,Base!$B$2:$B$4835,"Insumos e papel",Base!$C$2:$C$4835,"2.01.93 Compra de Plástico Poliolefínico",Base!$A$2:$A$4835,"Antes de 2026")
A13: 2.01.94 Compra de Fita Adesiva | B13: =SUMIFS(Base!$N$2:$N$4835,Base!$B$2:$B$4835,"Insumos e papel",Base!$C$2:$C$4835,"2.01.94 Compra de Fita Adesiva",Base!$A$2:$A$4835,B$4) | C13: =SUMIFS(Base!$N$2:$N$4835,Base!$B$2:$B$4835,"Insumos e papel",Base!$C$2:$C$4835,"2.01.94 Compra de Fita Adesiva",Base!$A$2:$A$4835,C$4) | D13: =SUMIFS(Base!$N$2:$N$4835,Base!$B$2:$B$4835,"Insumos e papel",Base!$C$2:$C$4835,"2.01.94 Compra de Fita Adesiva",Base!$A$2:$A$4835,D$4) | E13: =SUMIFS(Base!$N$2:$N$4835,Base!$B$2:$B$4835,"Insumos e papel",Base!$C$2:$C$4835,"2.01.94 Compra de Fita Adesiva",Base!$A$2:$A$4835,E$4) | F13: =SUMIFS(Base!$N$2:$N$4835,Base!$B$2:$B$4835,"Insumos e papel",Base!$C$2:$C$4835,"2.01.94 Compra de Fita Adesiva",Base!$A$2:$A$4835,F$4) | G13: =SUMIFS(Base!$N$2:$N$4835,Base!$B$2:$B$4835,"Insumos e papel",Base!$C$2:$C$4835,"2.01.94 Compra de Fita Adesiva",Base!$A$2:$A$4835,G$4) | H13: =SUMIFS(Base!$N$2:$N$4835,Base!$B$2:$B$4835,"Insumos e papel",Base!$C$2:$C$4835,"2.01.94 Compra de Fita Adesiva",Base!$A$2:$A$4835,H$4) | I13: =SUMIFS(Base!$N$2:$N$4835,Base!$B$2:$B$4835,"Insumos e papel",Base!$C$2:$C$4835,"2.01.94 Compra de Fita Adesiva",Base!$A$2:$A$4835,I$4) | J13: =SUMIFS(Base!$N$2:$N$4835,Base!$B$2:$B$4835,"Insumos e papel",Base!$C$2:$C$4835,"2.01.94 Compra de Fita Adesiva",Base!$A$2:$A$4835,J$4) | K13: =SUM(B13:J13) | L13: =SUMIFS(Base!$N$2:$N$4835,Base!$B$2:$B$4835,"Insumos e papel",Base!$C$2:$C$4835,"2.01.94 Compra de Fita Adesiva",Base!$A$2:$A$4835,"Antes de 2026")
A14: 2.01.95 Compra de Etiqueta | B14: =SUMIFS(Base!$N$2:$N$4835,Base!$B$2:$B$4835,"Insumos e papel",Base!$C$2:$C$4835,"2.01.95 Compra de Etiqueta",Base!$A$2:$A$4835,B$4) | C14: =SUMIFS(Base!$N$2:$N$4835,Base!$B$2:$B$4835,"Insumos e papel",Base!$C$2:$C$4835,"2.01.95 Compra de Etiqueta",Base!$A$2:$A$4835,C$4) | D14: =SUMIFS(Base!$N$2:$N$4835,Base!$B$2:$B$4835,"Insumos e papel",Base!$C$2:$C$4835,"2.01.95 Compra de Etiqueta",Base!$A$2:$A$4835,D$4) | E14: =SUMIFS(Base!$N$2:$N$4835,Base!$B$2:$B$4835,"Insumos e papel",Base!$C$2:$C$4835,"2.01.95 Compra de Etiqueta",Base!$A$2:$A$4835,E$4) | F14: =SUMIFS(Base!$N$2:$N$4835,Base!$B$2:$B$4835,"Insumos e papel",Base!$C$2:$C$4835,"2.01.95 Compra de Etiqueta",Base!$A$2:$A$4835,F$4) | G14: =SUMIFS(Base!$N$2:$N$4835,Base!$B$2:$B$4835,"Insumos e papel",Base!$C$2:$C$4835,"2.01.95 Compra de Etiqueta",Base!$A$2:$A$4835,G$4) | H14: =SUMIFS(Base!$N$2:$N$4835,Base!$B$2:$B$4835,"Insumos e papel",Base!$C$2:$C$4835,"2.01.95 Compra de Etiqueta",Base!$A$2:$A$4835,H$4) | I14: =SUMIFS(Base!$N$2:$N$4835,Base!$B$2:$B$4835,"Insumos e papel",Base!$C$2:$C$4835,"2.01.95 Compra de Etiqueta",Base!$A$2:$A$4835,I$4) | J14: =SUMIFS(Base!$N$2:$N$4835,Base!$B$2:$B$4835,"Insumos e papel",Base!$C$2:$C$4835,"2.01.95 Compra de Etiqueta",Base!$A$2:$A$4835,J$4) | K14: =SUM(B14:J14) | L14: =SUMIFS(Base!$N$2:$N$4835,Base!$B$2:$B$4835,"Insumos e papel",Base!$C$2:$C$4835,"2.01.95 Compra de Etiqueta",Base!$A$2:$A$4835,"Antes de 2026")
A15: 2.01.96 Compra de Cola | B15: =SUMIFS(Base!$N$2:$N$4835,Base!$B$2:$B$4835,"Insumos e papel",Base!$C$2:$C$4835,"2.01.96 Compra de Cola",Base!$A$2:$A$4835,B$4) | C15: =SUMIFS(Base!$N$2:$N$4835,Base!$B$2:$B$4835,"Insumos e papel",Base!$C$2:$C$4835,"2.01.96 Compra de Cola",Base!$A$2:$A$4835,C$4) | D15: =SUMIFS(Base!$N$2:$N$4835,Base!$B$2:$B$4835,"Insumos e papel",Base!$C$2:$C$4835,"2.01.96 Compra de Cola",Base!$A$2:$A$4835,D$4) | E15: =SUMIFS(Base!$N$2:$N$4835,Base!$B$2:$B$4835,"Insumos e papel",Base!$C$2:$C$4835,"2.01.96 Compra de Cola",Base!$A$2:$A$4835,E$4) | F15: =SUMIFS(Base!$N$2:$N$4835,Base!$B$2:$B$4835,"Insumos e papel",Base!$C$2:$C$4835,"2.01.96 Compra de Cola",Base!$A$2:$A$4835,F$4) | G15: =SUMIFS(Base!$N$2:$N$4835,Base!$B$2:$B$4835,"Insumos e papel",Base!$C$2:$C$4835,"2.01.96 Compra de Cola",Base!$A$2:$A$4835,G$4) | H15: =SUMIFS(Base!$N$2:$N$4835,Base!$B$2:$B$4835,"Insumos e papel",Base!$C$2:$C$4835,"2.01.96 Compra de Cola",Base!$A$2:$A$4835,H$4) | I15: =SUMIFS(Base!$N$2:$N$4835,Base!$B$2:$B$4835,"Insumos e papel",Base!$C$2:$C$4835,"2.01.96 Compra de Cola",Base!$A$2:$A$4835,I$4) | J15: =SUMIFS(Base!$N$2:$N$4835,Base!$B$2:$B$4835,"Insumos e papel",Base!$C$2:$C$4835,"2.01.96 Compra de Cola",Base!$A$2:$A$4835,J$4) | K15: =SUM(B15:J15) | L15: =SUMIFS(Base!$N$2:$N$4835,Base!$B$2:$B$4835,"Insumos e papel",Base!$C$2:$C$4835,"2.01.96 Compra de Cola",Base!$A$2:$A$4835,"Antes de 2026")
A16: 2.01.97 Compra de Clichê | B16: =SUMIFS(Base!$N$2:$N$4835,Base!$B$2:$B$4835,"Insumos e papel",Base!$C$2:$C$4835,"2.01.97 Compra de Clichê",Base!$A$2:$A$4835,B$4) | C16: =SUMIFS(Base!$N$2:$N$4835,Base!$B$2:$B$4835,"Insumos e papel",Base!$C$2:$C$4835,"2.01.97 Compra de Clichê",Base!$A$2:$A$4835,C$4) | D16: =SUMIFS(Base!$N$2:$N$4835,Base!$B$2:$B$4835,"Insumos e papel",Base!$C$2:$C$4835,"2.01.97 Compra de Clichê",Base!$A$2:$A$4835,D$4) | E16: =SUMIFS(Base!$N$2:$N$4835,Base!$B$2:$B$4835,"Insumos e papel",Base!$C$2:$C$4835,"2.01.97 Compra de Clichê",Base!$A$2:$A$4835,E$4) | F16: =SUMIFS(Base!$N$2:$N$4835,Base!$B$2:$B$4835,"Insumos e papel",Base!$C$2:$C$4835,"2.01.97 Compra de Clichê",Base!$A$2:$A$4835,F$4) | G16: =SUMIFS(Base!$N$2:$N$4835,Base!$B$2:$B$4835,"Insumos e papel",Base!$C$2:$C$4835,"2.01.97 Compra de Clichê",Base!$A$2:$A$4835,G$4) | H16: =SUMIFS(Base!$N$2:$N$4835,Base!$B$2:$B$4835,"Insumos e papel",Base!$C$2:$C$4835,"2.01.97 Compra de Clichê",Base!$A$2:$A$4835,H$4) | I16: =SUMIFS(Base!$N$2:$N$4835,Base!$B$2:$B$4835,"Insumos e papel",Base!$C$2:$C$4835,"2.01.97 Compra de Clichê",Base!$A$2:$A$4835,I$4) | J16: =SUMIFS(Base!$N$2:$N$4835,Base!$B$2:$B$4835,"Insumos e papel",Base!$C$2:$C$4835,"2.01.97 Compra de Clichê",Base!$A$2:$A$4835,J$4) | K16: =SUM(B16:J16) | L16: =SUMIFS(Base!$N$2:$N$4835,Base!$B$2:$B$4835,"Insumos e papel",Base!$C$2:$C$4835,"2.01.97 Compra de Clichê",Base!$A$2:$A$4835,"Antes de 2026")
A17: 2.01.99 Compra de Caixas | B17: =SUMIFS(Base!$N$2:$N$4835,Base!$B$2:$B$4835,"Insumos e papel",Base!$C$2:$C$4835,"2.01.99 Compra de Caixas",Base!$A$2:$A$4835,B$4) | C17: =SUMIFS(Base!$N$2:$N$4835,Base!$B$2:$B$4835,"Insumos e papel",Base!$C$2:$C$4835,"2.01.99 Compra de Caixas",Base!$A$2:$A$4835,C$4) | D17: =SUMIFS(Base!$N$2:$N$4835,Base!$B$2:$B$4835,"Insumos e papel",Base!$C$2:$C$4835,"2.01.99 Compra de Caixas",Base!$A$2:$A$4835,D$4) | E17: =SUMIFS(Base!$N$2:$N$4835,Base!$B$2:$B$4835,"Insumos e papel",Base!$C$2:$C$4835,"2.01.99 Compra de Caixas",Base!$A$2:$A$4835,E$4) | F17: =SUMIFS(Base!$N$2:$N$4835,Base!$B$2:$B$4835,"Insumos e papel",Base!$C$2:$C$4835,"2.01.99 Compra de Caixas",Base!$A$2:$A$4835,F$4) | G17: =SUMIFS(Base!$N$2:$N$4835,Base!$B$2:$B$4835,"Insumos e papel",Base!$C$2:$C$4835,"2.01.99 Compra de Caixas",Base!$A$2:$A$4835,G$4) | H17: =SUMIFS(Base!$N$2:$N$4835,Base!$B$2:$B$4835,"Insumos e papel",Base!$C$2:$C$4835,"2.01.99 Compra de Caixas",Base!$A$2:$A$4835,H$4) | I17: =SUMIFS(Base!$N$2:$N$4835,Base!$B$2:$B$4835,"Insumos e papel",Base!$C$2:$C$4835,"2.01.99 Compra de Caixas",Base!$A$2:$A$4835,I$4) | J17: =SUMIFS(Base!$N$2:$N$4835,Base!$B$2:$B$4835,"Insumos e papel",Base!$C$2:$C$4835,"2.01.99 Compra de Caixas",Base!$A$2:$A$4835,J$4) | K17: =SUM(B17:J17) | L17: =SUMIFS(Base!$N$2:$N$4835,Base!$B$2:$B$4835,"Insumos e papel",Base!$C$2:$C$4835,"2.01.99 Compra de Caixas",Base!$A$2:$A$4835,"Antes de 2026")
A18: Total Insumos e papel | B18: =SUM(B6:B17) | C18: =SUM(C6:C17) | D18: =SUM(D6:D17) | E18: =SUM(E6:E17) | F18: =SUM(F6:F17) | G18: =SUM(G6:G17) | H18: =SUM(H6:H17) | I18: =SUM(I6:I17) | ... L18: =SUM(L6:L17)
A20: Uso e consumo
A21: 2.01.85 Compra de Uso e Consumo | B21: =SUMIFS(Base!$N$2:$N$4835,Base!$B$2:$B$4835,"Uso e consumo",Base!$C$2:$C$4835,"2.01.85 Compra de Uso e Consumo",Base!$A$2:$A$4835,B$4) | C21: =SUMIFS(Base!$N$2:$N$4835,Base!$B$2:$B$4835,"Uso e consumo",Base!$C$2:$C$4835,"2.01.85 Compra de Uso e Consumo",Base!$A$2:$A$4835,C$4) | D21: =SUMIFS(Base!$N$2:$N$4835,Base!$B$2:$B$4835,"Uso e consumo",Base!$C$2:$C$4835,"2.01.85 Compra de Uso e Consumo",Base!$A$2:$A$4835,D$4) | E21: =SUMIFS(Base!$N$2:$N$4835,Base!$B$2:$B$4835,"Uso e consumo",Base!$C$2:$C$4835,"2.01.85 Compra de Uso e Consumo",Base!$A$2:$A$4835,E$4) | F21: =SUMIFS(Base!$N$2:$N$4835,Base!$B$2:$B$4835,"Uso e consumo",Base!$C$2:$C$4835,"2.01.85 Compra de Uso e Consumo",Base!$A$2:$A$4835,F$4) | G21: =SUMIFS(Base!$N$2:$N$4835,Base!$B$2:$B$4835,"Uso e consumo",Base!$C$2:$C$4835,"2.01.85 Compra de Uso e Consumo",Base!$A$2:$A$4835,G$4) | H21: =SUMIFS(Base!$N$2:$N$4835,Base!$B$2:$B$4835,"Uso e consumo",Base!$C$2:$C$4835,"2.01.85 Compra de Uso e Consumo",Base!$A$2:$A$4835,H$4) | I21: =SUMIFS(Base!$N$2:$N$4835,Base!$B$2:$B$4835,"Uso e consumo",Base!$C$2:$C$4835,"2.01.85 Compra de Uso e Consumo",Base!$A$2:$A$4835,I$4) | J21: =SUMIFS(Base!$N$2:$N$4835,Base!$B$2:$B$4835,"Uso e consumo",Base!$C$2:$C$4835,"2.01.85 Compra de Uso e Consumo",Base!$A$2:$A$4835,J$4) | K21: =SUM(B21:J21) | L21: =SUMIFS(Base!$N$2:$N$4835,Base!$B$2:$B$4835,"Uso e consumo",Base!$C$2:$C$4835,"2.01.85 Compra de Uso e Consumo",Base!$A$2:$A$4835,"Antes de 2026")
A22: 2.01.87 Compra de Peças de Máquinas | B22: =SUMIFS(Base!$N$2:$N$4835,Base!$B$2:$B$4835,"Uso e consumo",Base!$C$2:$C$4835,"2.01.87 Compra de Peças de Máquinas",Base!$A$2:$A$4835,B$4) | C22: =SUMIFS(Base!$N$2:$N$4835,Base!$B$2:$B$4835,"Uso e consumo",Base!$C$2:$C$4835,"2.01.87 Compra de Peças de Máquinas",Base!$A$2:$A$4835,C$4) | D22: =SUMIFS(Base!$N$2:$N$4835,Base!$B$2:$B$4835,"Uso e consumo",Base!$C$2:$C$4835,"2.01.87 Compra de Peças de Máquinas",Base!$A$2:$A$4835,D$4) | E22: =SUMIFS(Base!$N$2:$N$4835,Base!$B$2:$B$4835,"Uso e consumo",Base!$C$2:$C$4835,"2.01.87 Compra de Peças de Máquinas",Base!$A$2:$A$4835,E$4) | F22: =SUMIFS(Base!$N$2:$N$4835,Base!$B$2:$B$4835,"Uso e consumo",Base!$C$2:$C$4835,"2.01.87 Compra de Peças de Máquinas",Base!$A$2:$A$4835,F$4) | G22: =SUMIFS(Base!$N$2:$N$4835,Base!$B$2:$B$4835,"Uso e consumo",Base!$C$2:$C$4835,"2.01.87 Compra de Peças de Máquinas",Base!$A$2:$A$4835,G$4) | H22: =SUMIFS(Base!$N$2:$N$4835,Base!$B$2:$B$4835,"Uso e consumo",Base!$C$2:$C$4835,"2.01.87 Compra de Peças de Máquinas",Base!$A$2:$A$4835,H$4) | I22: =SUMIFS(Base!$N$2:$N$4835,Base!$B$2:$B$4835,"Uso e consumo",Base!$C$2:$C$4835,"2.01.87 Compra de Peças de Máquinas",Base!$A$2:$A$4835,I$4) | J22: =SUMIFS(Base!$N$2:$N$4835,Base!$B$2:$B$4835,"Uso e consumo",Base!$C$2:$C$4835,"2.01.87 Compra de Peças de Máquinas",Base!$A$2:$A$4835,J$4) | K22: =SUM(B22:J22) | L22: =SUMIFS(Base!$N$2:$N$4835,Base!$B$2:$B$4835,"Uso e consumo",Base!$C$2:$C$4835,"2.01.87 Compra de Peças de Máquinas",Base!$A$2:$A$4835,"Antes de 2026")
A23: 2.03.88 Compra de Fardamento | B23: =SUMIFS(Base!$N$2:$N$4835,Base!$B$2:$B$4835,"Uso e consumo",Base!$C$2:$C$4835,"2.03.88 Compra de Fardamento",Base!$A$2:$A$4835,B$4) | C23: =SUMIFS(Base!$N$2:$N$4835,Base!$B$2:$B$4835,"Uso e consumo",Base!$C$2:$C$4835,"2.03.88 Compra de Fardamento",Base!$A$2:$A$4835,C$4) | D23: =SUMIFS(Base!$N$2:$N$4835,Base!$B$2:$B$4835,"Uso e consumo",Base!$C$2:$C$4835,"2.03.88 Compra de Fardamento",Base!$A$2:$A$4835,D$4) | E23: =SUMIFS(Base!$N$2:$N$4835,Base!$B$2:$B$4835,"Uso e consumo",Base!$C$2:$C$4835,"2.03.88 Compra de Fardamento",Base!$A$2:$A$4835,E$4) | F23: =SUMIFS(Base!$N$2:$N$4835,Base!$B$2:$B$4835,"Uso e consumo",Base!$C$2:$C$4835,"2.03.88 Compra de Fardamento",Base!$A$2:$A$4835,F$4) | G23: =SUMIFS(Base!$N$2:$N$4835,Base!$B$2:$B$4835,"Uso e consumo",Base!$C$2:$C$4835,"2.03.88 Compra de Fardamento",Base!$A$2:$A$4835,G$4) | H23: =SUMIFS(Base!$N$2:$N$4835,Base!$B$2:$B$4835,"Uso e consumo",Base!$C$2:$C$4835,"2.03.88 Compra de Fardamento",Base!$A$2:$A$4835,H$4) | I23: =SUMIFS(Base!$N$2:$N$4835,Base!$B$2:$B$4835,"Uso e consumo",Base!$C$2:$C$4835,"2.03.88 Compra de Fardamento",Base!$A$2:$A$4835,I$4) | J23: =SUMIFS(Base!$N$2:$N$4835,Base!$B$2:$B$4835,"Uso e consumo",Base!$C$2:$C$4835,"2.03.88 Compra de Fardamento",Base!$A$2:$A$4835,J$4) | K23: =SUM(B23:J23) | L23: =SUMIFS(Base!$N$2:$N$4835,Base!$B$2:$B$4835,"Uso e consumo",Base!$C$2:$C$4835,"2.03.88 Compra de Fardamento",Base!$A$2:$A$4835,"Antes de 2026")
A24: 2.03.90 Compra de EPI | B24: =SUMIFS(Base!$N$2:$N$4835,Base!$B$2:$B$4835,"Uso e consumo",Base!$C$2:$C$4835,"2.03.90 Compra de EPI",Base!$A$2:$A$4835,B$4) | C24: =SUMIFS(Base!$N$2:$N$4835,Base!$B$2:$B$4835,"Uso e consumo",Base!$C$2:$C$4835,"2.03.90 Compra de EPI",Base!$A$2:$A$4835,C$4) | D24: =SUMIFS(Base!$N$2:$N$4835,Base!$B$2:$B$4835,"Uso e consumo",Base!$C$2:$C$4835,"2.03.90 Compra de EPI",Base!$A$2:$A$4835,D$4) | E24: =SUMIFS(Base!$N$2:$N$4835,Base!$B$2:$B$4835,"Uso e consumo",Base!$C$2:$C$4835,"2.03.90 Compra de EPI",Base!$A$2:$A$4835,E$4) | F24: =SUMIFS(Base!$N$2:$N$4835,Base!$B$2:$B$4835,"Uso e consumo",Base!$C$2:$C$4835,"2.03.90 Compra de EPI",Base!$A$2:$A$4835,F$4) | G24: =SUMIFS(Base!$N$2:$N$4835,Base!$B$2:$B$4835,"Uso e consumo",Base!$C$2:$C$4835,"2.03.90 Compra de EPI",Base!$A$2:$A$4835,G$4) | H24: =SUMIFS(Base!$N$2:$N$4835,Base!$B$2:$B$4835,"Uso e consumo",Base!$C$2:$C$4835,"2.03.90 Compra de EPI",Base!$A$2:$A$4835,H$4) | I24: =SUMIFS(Base!$N$2:$N$4835,Base!$B$2:$B$4835,"Uso e consumo",Base!$C$2:$C$4835,"2.03.90 Compra de EPI",Base!$A$2:$A$4835,I$4) | J24: =SUMIFS(Base!$N$2:$N$4835,Base!$B$2:$B$4835,"Uso e consumo",Base!$C$2:$C$4835,"2.03.90 Compra de EPI",Base!$A$2:$A$4835,J$4) | K24: =SUM(B24:J24) | L24: =SUMIFS(Base!$N$2:$N$4835,Base!$B$2:$B$4835,"Uso e consumo",Base!$C$2:$C$4835,"2.03.90 Compra de EPI",Base!$A$2:$A$4835,"Antes de 2026")
A25: 2.04.06 Material de Escritório | B25: =SUMIFS(Base!$N$2:$N$4835,Base!$B$2:$B$4835,"Uso e consumo",Base!$C$2:$C$4835,"2.04.06 Material de Escritório",Base!$A$2:$A$4835,B$4) | C25: =SUMIFS(Base!$N$2:$N$4835,Base!$B$2:$B$4835,"Uso e consumo",Base!$C$2:$C$4835,"2.04.06 Material de Escritório",Base!$A$2:$A$4835,C$4) | D25: =SUMIFS(Base!$N$2:$N$4835,Base!$B$2:$B$4835,"Uso e consumo",Base!$C$2:$C$4835,"2.04.06 Material de Escritório",Base!$A$2:$A$4835,D$4) | E25: =SUMIFS(Base!$N$2:$N$4835,Base!$B$2:$B$4835,"Uso e consumo",Base!$C$2:$C$4835,"2.04.06 Material de Escritório",Base!$A$2:$A$4835,E$4) | F25: =SUMIFS(Base!$N$2:$N$4835,Base!$B$2:$B$4835,"Uso e consumo",Base!$C$2:$C$4835,"2.04.06 Material de Escritório",Base!$A$2:$A$4835,F$4) | G25: =SUMIFS(Base!$N$2:$N$4835,Base!$B$2:$B$4835,"Uso e consumo",Base!$C$2:$C$4835,"2.04.06 Material de Escritório",Base!$A$2:$A$4835,G$4) | H25: =SUMIFS(Base!$N$2:$N$4835,Base!$B$2:$B$4835,"Uso e consumo",Base!$C$2:$C$4835,"2.04.06 Material de Escritório",Base!$A$2:$A$4835,H$4) | I25: =SUMIFS(Base!$N$2:$N$4835,Base!$B$2:$B$4835,"Uso e consumo",Base!$C$2:$C$4835,"2.04.06 Material de Escritório",Base!$A$2:$A$4835,I$4) | J25: =SUMIFS(Base!$N$2:$N$4835,Base!$B$2:$B$4835,"Uso e consumo",Base!$C$2:$C$4835,"2.04.06 Material de Escritório",Base!$A$2:$A$4835,J$4) | K25: =SUM(B25:J25) | L25: =SUMIFS(Base!$N$2:$N$4835,Base!$B$2:$B$4835,"Uso e consumo",Base!$C$2:$C$4835,"2.04.06 Material de Escritório",Base!$A$2:$A$4835,"Antes de 2026")
A26: 2.04.91 Compra de Material de Limpeza | B26: =SUMIFS(Base!$N$2:$N$4835,Base!$B$2:$B$4835,"Uso e consumo",Base!$C$2:$C$4835,"2.04.91 Compra de Material de Limpeza",Base!$A$2:$A$4835,B$4) | C26: =SUMIFS(Base!$N$2:$N$4835,Base!$B$2:$B$4835,"Uso e consumo",Base!$C$2:$C$4835,"2.04.91 Compra de Material de Limpeza",Base!$A$2:$A$4835,C$4) | D26: =SUMIFS(Base!$N$2:$N$4835,Base!$B$2:$B$4835,"Uso e consumo",Base!$C$2:$C$4835,"2.04.91 Compra de Material de Limpeza",Base!$A$2:$A$4835,D$4) | E26: =SUMIFS(Base!$N$2:$N$4835,Base!$B$2:$B$4835,"Uso e consumo",Base!$C$2:$C$4835,"2.04.91 Compra de Material de Limpeza",Base!$A$2:$A$4835,E$4) | F26: =SUMIFS(Base!$N$2:$N$4835,Base!$B$2:$B$4835,"Uso e consumo",Base!$C$2:$C$4835,"2.04.91 Compra de Material de Limpeza",Base!$A$2:$A$4835,F$4) | G26: =SUMIFS(Base!$N$2:$N$4835,Base!$B$2:$B$4835,"Uso e consumo",Base!$C$2:$C$4835,"2.04.91 Compra de Material de Limpeza",Base!$A$2:$A$4835,G$4) | H26: =SUMIFS(Base!$N$2:$N$4835,Base!$B$2:$B$4835,"Uso e consumo",Base!$C$2:$C$4835,"2.04.91 Compra de Material de Limpeza",Base!$A$2:$A$4835,H$4) | I26: =SUMIFS(Base!$N$2:$N$4835,Base!$B$2:$B$4835,"Uso e consumo",Base!$C$2:$C$4835,"2.04.91 Compra de Material de Limpeza",Base!$A$2:$A$4835,I$4) | J26: =SUMIFS(Base!$N$2:$N$4835,Base!$B$2:$B$4835,"Uso e consumo",Base!$C$2:$C$4835,"2.04.91 Compra de Material de Limpeza",Base!$A$2:$A$4835,J$4) | K26: =SUM(B26:J26) | L26: =SUMIFS(Base!$N$2:$N$4835,Base!$B$2:$B$4835,"Uso e consumo",Base!$C$2:$C$4835,"2.04.91 Compra de Material de Limpeza",Base!$A$2:$A$4835,"Antes de 2026")
A27: 2.04.95 Copa e Cozinha | B27: =SUMIFS(Base!$N$2:$N$4835,Base!$B$2:$B$4835,"Uso e consumo",Base!$C$2:$C$4835,"2.04.95 Copa e Cozinha",Base!$A$2:$A$4835,B$4) | C27: =SUMIFS(Base!$N$2:$N$4835,Base!$B$2:$B$4835,"Uso e consumo",Base!$C$2:$C$4835,"2.04.95 Copa e Cozinha",Base!$A$2:$A$4835,C$4) | D27: =SUMIFS(Base!$N$2:$N$4835,Base!$B$2:$B$4835,"Uso e consumo",Base!$C$2:$C$4835,"2.04.95 Copa e Cozinha",Base!$A$2:$A$4835,D$4) | E27: =SUMIFS(Base!$N$2:$N$4835,Base!$B$2:$B$4835,"Uso e consumo",Base!$C$2:$C$4835,"2.04.95 Copa e Cozinha",Base!$A$2:$A$4835,E$4) | F27: =SUMIFS(Base!$N$2:$N$4835,Base!$B$2:$B$4835,"Uso e consumo",Base!$C$2:$C$4835,"2.04.95 Copa e Cozinha",Base!$A$2:$A$4835,F$4) | G27: =SUMIFS(Base!$N$2:$N$4835,Base!$B$2:$B$4835,"Uso e consumo",Base!$C$2:$C$4835,"2.04.95 Copa e Cozinha",Base!$A$2:$A$4835,G$4) | H27: =SUMIFS(Base!$N$2:$N$4835,Base!$B$2:$B$4835,"Uso e consumo",Base!$C$2:$C$4835,"2.04.95 Copa e Cozinha",Base!$A$2:$A$4835,H$4) | I27: =SUMIFS(Base!$N$2:$N$4835,Base!$B$2:$B$4835,"Uso e consumo",Base!$C$2:$C$4835,"2.04.95 Copa e Cozinha",Base!$A$2:$A$4835,I$4) | J27: =SUMIFS(Base!$N$2:$N$4835,Base!$B$2:$B$4835,"Uso e consumo",Base!$C$2:$C$4835,"2.04.95 Copa e Cozinha",Base!$A$2:$A$4835,J$4) | K27: =SUM(B27:J27) | L27: =SUMIFS(Base!$N$2:$N$4835,Base!$B$2:$B$4835,"Uso e consumo",Base!$C$2:$C$4835,"2.04.95 Copa e Cozinha",Base!$A$2:$A$4835,"Antes de 2026")
A28: 2.04.96 Bens de Pequeno Valor | B28: =SUMIFS(Base!$N$2:$N$4835,Base!$B$2:$B$4835,"Uso e consumo",Base!$C$2:$C$4835,"2.04.96 Bens de Pequeno Valor",Base!$A$2:$A$4835,B$4) | C28: =SUMIFS(Base!$N$2:$N$4835,Base!$B$2:$B$4835,"Uso e consumo",Base!$C$2:$C$4835,"2.04.96 Bens de Pequeno Valor",Base!$A$2:$A$4835,C$4) | D28: =SUMIFS(Base!$N$2:$N$4835,Base!$B$2:$B$4835,"Uso e consumo",Base!$C$2:$C$4835,"2.04.96 Bens de Pequeno Valor",Base!$A$2:$A$4835,D$4) | E28: =SUMIFS(Base!$N$2:$N$4835,Base!$B$2:$B$4835,"Uso e consumo",Base!$C$2:$C$4835,"2.04.96 Bens de Pequeno Valor",Base!$A$2:$A$4835,E$4) | F28: =SUMIFS(Base!$N$2:$N$4835,Base!$B$2:$B$4835,"Uso e consumo",Base!$C$2:$C$4835,"2.04.96 Bens de Pequeno Valor",Base!$A$2:$A$4835,F$4) | G28: =SUMIFS(Base!$N$2:$N$4835,Base!$B$2:$B$4835,"Uso e consumo",Base!$C$2:$C$4835,"2.04.96 Bens de Pequeno Valor",Base!$A$2:$A$4835,G$4) | H28: =SUMIFS(Base!$N$2:$N$4835,Base!$B$2:$B$4835,"Uso e consumo",Base!$C$2:$C$4835,"2.04.96 Bens de Pequeno Valor",Base!$A$2:$A$4835,H$4) | I28: =SUMIFS(Base!$N$2:$N$4835,Base!$B$2:$B$4835,"Uso e consumo",Base!$C$2:$C$4835,"2.04.96 Bens de Pequeno Valor",Base!$A$2:$A$4835,I$4) | J28: =SUMIFS(Base!$N$2:$N$4835,Base!$B$2:$B$4835,"Uso e consumo",Base!$C$2:$C$4835,"2.04.96 Bens de Pequeno Valor",Base!$A$2:$A$4835,J$4) | K28: =SUM(B28:J28) | L28: =SUMIFS(Base!$N$2:$N$4835,Base!$B$2:$B$4835,"Uso e consumo",Base!$C$2:$C$4835,"2.04.96 Bens de Pequeno Valor",Base!$A$2:$A$4835,"Antes de 2026")
A29: Total Uso e consumo | B29: =SUM(B21:B28) | C29: =SUM(C21:C28) | D29: =SUM(D21:D28) | E29: =SUM(E21:E28) | F29: =SUM(F21:F28) | G29: =SUM(G21:G28) | H29: =SUM(H21:H28) | I29: =SUM(I21:I28) | ... L29: =SUM(L21:L28)
A31: Frete de compra
A32: Frete de compra | B32: =SUMIFS(Base!$N$2:$N$4835,Base!$B$2:$B$4835,"Frete de compra",Base!$C$2:$C$4835,"Frete de compra",Base!$A$2:$A$4835,B$4) | C32: =SUMIFS(Base!$N$2:$N$4835,Base!$B$2:$B$4835,"Frete de compra",Base!$C$2:$C$4835,"Frete de compra",Base!$A$2:$A$4835,C$4) | D32: =SUMIFS(Base!$N$2:$N$4835,Base!$B$2:$B$4835,"Frete de compra",Base!$C$2:$C$4835,"Frete de compra",Base!$A$2:$A$4835,D$4) | E32: =SUMIFS(Base!$N$2:$N$4835,Base!$B$2:$B$4835,"Frete de compra",Base!$C$2:$C$4835,"Frete de compra",Base!$A$2:$A$4835,E$4) | F32: =SUMIFS(Base!$N$2:$N$4835,Base!$B$2:$B$4835,"Frete de compra",Base!$C$2:$C$4835,"Frete de compra",Base!$A$2:$A$4835,F$4) | G32: =SUMIFS(Base!$N$2:$N$4835,Base!$B$2:$B$4835,"Frete de compra",Base!$C$2:$C$4835,"Frete de compra",Base!$A$2:$A$4835,G$4) | H32: =SUMIFS(Base!$N$2:$N$4835,Base!$B$2:$B$4835,"Frete de compra",Base!$C$2:$C$4835,"Frete de compra",Base!$A$2:$A$4835,H$4) | I32: =SUMIFS(Base!$N$2:$N$4835,Base!$B$2:$B$4835,"Frete de compra",Base!$C$2:$C$4835,"Frete de compra",Base!$A$2:$A$4835,I$4) | J32: =SUMIFS(Base!$N$2:$N$4835,Base!$B$2:$B$4835,"Frete de compra",Base!$C$2:$C$4835,"Frete de compra",Base!$A$2:$A$4835,J$4) | K32: =SUM(B32:J32) | L32: =SUMIFS(Base!$N$2:$N$4835,Base!$B$2:$B$4835,"Frete de compra",Base!$C$2:$C$4835,"Frete de compra",Base!$A$2:$A$4835,"Antes de 2026")
A33: Total Frete de compra | B33: =SUM(B32:B32) | C33: =SUM(C32:C32) | D33: =SUM(D32:D32) | E33: =SUM(E32:E32) | F33: =SUM(F32:F32) | G33: =SUM(G32:G32) | H33: =SUM(H32:H32) | I33: =SUM(I32:I32) | ... L33: =SUM(L32:L32)
A35: Frete de venda
A36: Frete de venda (para clientes) | B36: =SUMIFS(Base!$N$2:$N$4835,Base!$B$2:$B$4835,"Frete de venda",Base!$C$2:$C$4835,"Frete de venda (para clientes)",Base!$A$2:$A$4835,B$4) | C36: =SUMIFS(Base!$N$2:$N$4835,Base!$B$2:$B$4835,"Frete de venda",Base!$C$2:$C$4835,"Frete de venda (para clientes)",Base!$A$2:$A$4835,C$4) | D36: =SUMIFS(Base!$N$2:$N$4835,Base!$B$2:$B$4835,"Frete de venda",Base!$C$2:$C$4835,"Frete de venda (para clientes)",Base!$A$2:$A$4835,D$4) | E36: =SUMIFS(Base!$N$2:$N$4835,Base!$B$2:$B$4835,"Frete de venda",Base!$C$2:$C$4835,"Frete de venda (para clientes)",Base!$A$2:$A$4835,E$4) | F36: =SUMIFS(Base!$N$2:$N$4835,Base!$B$2:$B$4835,"Frete de venda",Base!$C$2:$C$4835,"Frete de venda (para clientes)",Base!$A$2:$A$4835,F$4) | G36: =SUMIFS(Base!$N$2:$N$4835,Base!$B$2:$B$4835,"Frete de venda",Base!$C$2:$C$4835,"Frete de venda (para clientes)",Base!$A$2:$A$4835,G$4) | H36: =SUMIFS(Base!$N$2:$N$4835,Base!$B$2:$B$4835,"Frete de venda",Base!$C$2:$C$4835,"Frete de venda (para clientes)",Base!$A$2:$A$4835,H$4) | I36: =SUMIFS(Base!$N$2:$N$4835,Base!$B$2:$B$4835,"Frete de venda",Base!$C$2:$C$4835,"Frete de venda (para clientes)",Base!$A$2:$A$4835,I$4) | J36: =SUMIFS(Base!$N$2:$N$4835,Base!$B$2:$B$4835,"Frete de venda",Base!$C$2:$C$4835,"Frete de venda (para clientes)",Base!$A$2:$A$4835,J$4) | K36: =SUM(B36:J36) | L36: =SUMIFS(Base!$N$2:$N$4835,Base!$B$2:$B$4835,"Frete de venda",Base!$C$2:$C$4835,"Frete de venda (para clientes)",Base!$A$2:$A$4835,"Antes de 2026")
A37: Total Frete de venda | B37: =SUM(B36:B36) | C37: =SUM(C36:C36) | D37: =SUM(D36:D36) | E37: =SUM(E36:E36) | F37: =SUM(F36:F36) | G37: =SUM(G36:G36) | H37: =SUM(H36:H36) | I37: =SUM(I36:I36) | ... L37: =SUM(L36:L36)
A39: TOTAL DAS DESPESAS (líquido de créditos) | B39: =B18+B29+B33+B37 | C39: =C18+C29+C33+C37 | D39: =D18+D29+D33+D37 | E39: =E18+E29+E33+E37 | F39: =F18+F29+F33+F37 | G39: =G18+G29+G33+G37 | H39: =H18+H29+H33+H37 | I39: =I18+I29+I33+I37 | ... L39: =L18+L29+L33+L37
A41: Memo: valor bruto (com impostos) | B41: =SUMIFS(Base!$H$2:$H$4835,Base!$A$2:$A$4835,B$4) | C41: =SUMIFS(Base!$H$2:$H$4835,Base!$A$2:$A$4835,C$4) | D41: =SUMIFS(Base!$H$2:$H$4835,Base!$A$2:$A$4835,D$4) | E41: =SUMIFS(Base!$H$2:$H$4835,Base!$A$2:$A$4835,E$4) | F41: =SUMIFS(Base!$H$2:$H$4835,Base!$A$2:$A$4835,F$4) | G41: =SUMIFS(Base!$H$2:$H$4835,Base!$A$2:$A$4835,G$4) | H41: =SUMIFS(Base!$H$2:$H$4835,Base!$A$2:$A$4835,H$4) | I41: =SUMIFS(Base!$H$2:$H$4835,Base!$A$2:$A$4835,I$4) | J41: =SUMIFS(Base!$H$2:$H$4835,Base!$A$2:$A$4835,J$4) | K41: =SUM(B41:J41) | L41: =SUMIFS(Base!$H$2:$H$4835,Base!$A$2:$A$4835,"Antes de 2026")
A42: Memo: créditos de impostos abatidos | B42: =SUMIFS(Base!$M$2:$M$4835,Base!$A$2:$A$4835,B$4) | C42: =SUMIFS(Base!$M$2:$M$4835,Base!$A$2:$A$4835,C$4) | D42: =SUMIFS(Base!$M$2:$M$4835,Base!$A$2:$A$4835,D$4) | E42: =SUMIFS(Base!$M$2:$M$4835,Base!$A$2:$A$4835,E$4) | F42: =SUMIFS(Base!$M$2:$M$4835,Base!$A$2:$A$4835,F$4) | G42: =SUMIFS(Base!$M$2:$M$4835,Base!$A$2:$A$4835,G$4) | H42: =SUMIFS(Base!$M$2:$M$4835,Base!$A$2:$A$4835,H$4) | I42: =SUMIFS(Base!$M$2:$M$4835,Base!$A$2:$A$4835,I$4) | J42: =SUMIFS(Base!$M$2:$M$4835,Base!$A$2:$A$4835,J$4) | K42: =SUM(B42:J42) | L42: =SUMIFS(Base!$M$2:$M$4835,Base!$A$2:$A$4835,"Antes de 2026")
A43: Conferência: bruto − créditos − total (deve ser zero) | B43: =ROUND(B41-B42-B39,2) | C43: =ROUND(C41-C42-C39,2) | D43: =ROUND(D41-D42-D39,2) | E43: =ROUND(E41-E42-E39,2) | F43: =ROUND(F41-F42-F39,2) | G43: =ROUND(G41-G42-G39,2) | H43: =ROUND(H41-H42-H39,2) | I43: =ROUND(I41-I42-I39,2) | ... L43: =ROUND(L41-L42-L39,2)

Sheet Comparação mensal
A1: Comparação mensal – custo líquido de créditos (R$, positivo = gasto)
A2: Variação = mês contra o mês anterior. Vermelho: alta acima de 20%; verde: queda acima de 20%. Pico = mês de maior gasto.
A4: Por destino | B4: 46023 | C4: 46054 | D4: 46082 | E4: 46113 | F4: 46143 | G4: 46174 | H4: 46204 | I4: 46235 | J4: 46266 | K4: Total 2026 | L4: Média mensal | M4: Maior mês | N4: Mês do pico
A5: Insumos e papel | B5: =SUMIFS(Base!$N$2:$N$4835,Base!$B$2:$B$4835,"Insumos e papel",Base!$A$2:$A$4835,B$4) | C5: =SUMIFS(Base!$N$2:$N$4835,Base!$B$2:$B$4835,"Insumos e papel",Base!$A$2:$A$4835,C$4) | D5: =SUMIFS(Base!$N$2:$N$4835,Base!$B$2:$B$4835,"Insumos e papel",Base!$A$2:$A$4835,D$4) | E5: =SUMIFS(Base!$N$2:$N$4835,Base!$B$2:$B$4835,"Insumos e papel",Base!$A$2:$A$4835,E$4) | F5: =SUMIFS(Base!$N$2:$N$4835,Base!$B$2:$B$4835,"Insumos e papel",Base!$A$2:$A$4835,F$4) | G5: =SUMIFS(Base!$N$2:$N$4835,Base!$B$2:$B$4835,"Insumos e papel",Base!$A$2:$A$4835,G$4) | H5: =SUMIFS(Base!$N$2:$N$4835,Base!$B$2:$B$4835,"Insumos e papel",Base!$A$2:$A$4835,H$4) | I5: =SUMIFS(Base!$N$2:$N$4835,Base!$B$2:$B$4835,"Insumos e papel",Base!$A$2:$A$4835,I$4) | J5: =SUMIFS(Base!$N$2:$N$4835,Base!$B$2:$B$4835,"Insumos e papel",Base!$A$2:$A$4835,J$4) | K5: =SUM(B5:J5) | L5: =AVERAGE(B5:J5) | M5: =MAX(B5:J5) | N5: =IF(M5=0,"",INDEX($B$4:$J$4,MATCH(M5,B5:J5,0)))
A6: Uso e consumo | B6: =SUMIFS(Base!$N$2:$N$4835,Base!$B$2:$B$4835,"Uso e consumo",Base!$A$2:$A$4835,B$4) | C6: =SUMIFS(Base!$N$2:$N$4835,Base!$B$2:$B$4835,"Uso e consumo",Base!$A$2:$A$4835,C$4) | D6: =SUMIFS(Base!$N$2:$N$4835,Base!$B$2:$B$4835,"Uso e consumo",Base!$A$2:$A$4835,D$4) | E6: =SUMIFS(Base!$N$2:$N$4835,Base!$B$2:$B$4835,"Uso e consumo",Base!$A$2:$A$4835,E$4) | F6: =SUMIFS(Base!$N$2:$N$4835,Base!$B$2:$B$4835,"Uso e consumo",Base!$A$2:$A$4835,F$4) | G6: =SUMIFS(Base!$N$2:$N$4835,Base!$B$2:$B$4835,"Uso e consumo",Base!$A$2:$A$4835,G$4) | H6: =SUMIFS(Base!$N$2:$N$4835,Base!$B$2:$B$4835,"Uso e consumo",Base!$A$2:$A$4835,H$4) | I6: =SUMIFS(Base!$N$2:$N$4835,Base!$B$2:$B$4835,"Uso e consumo",Base!$A$2:$A$4835,I$4) | J6: =SUMIFS(Base!$N$2:$N$4835,Base!$B$2:$B$4835,"Uso e consumo",Base!$A$2:$A$4835,J$4) | K6: =SUM(B6:J6) | L6: =AVERAGE(B6:J6) | M6: =MAX(B6:J6) | N6: =IF(M6=0,"",INDEX($B$4:$J$4,MATCH(M6,B6:J6,0)))
A7: Frete de compra | B7: =SUMIFS(Base!$N$2:$N$4835,Base!$B$2:$B$4835,"Frete de compra",Base!$A$2:$A$4835,B$4) | C7: =SUMIFS(Base!$N$2:$N$4835,Base!$B$2:$B$4835,"Frete de compra",Base!$A$2:$A$4835,C$4) | D7: =SUMIFS(Base!$N$2:$N$4835,Base!$B$2:$B$4835,"Frete de compra",Base!$A$2:$A$4835,D$4) | E7: =SUMIFS(Base!$N$2:$N$4835,Base!$B$2:$B$4835,"Frete de compra",Base!$A$2:$A$4835,E$4) | F7: =SUMIFS(Base!$N$2:$N$4835,Base!$B$2:$B$4835,"Frete de compra",Base!$A$2:$A$4835,F$4) | G7: =SUMIFS(Base!$N$2:$N$4835,Base!$B$2:$B$4835,"Frete de compra",Base!$A$2:$A$4835,G$4) | H7: =SUMIFS(Base!$N$2:$N$4835,Base!$B$2:$B$4835,"Frete de compra",Base!$A$2:$A$4835,H$4) | I7: =SUMIFS(Base!$N$2:$N$4835,Base!$B$2:$B$4835,"Frete de compra",Base!$A$2:$A$4835,I$4) | J7: =SUMIFS(Base!$N$2:$N$4835,Base!$B$2:$B$4835,"Frete de compra",Base!$A$2:$A$4835,J$4) | K7: =SUM(B7:J7) | L7: =AVERAGE(B7:J7) | M7: =MAX(B7:J7) | N7: =IF(M7=0,"",INDEX($B$4:$J$4,MATCH(M7,B7:J7,0)))
A8: Frete de venda | B8: =SUMIFS(Base!$N$2:$N$4835,Base!$B$2:$B$4835,"Frete de venda",Base!$A$2:$A$4835,B$4) | C8: =SUMIFS(Base!$N$2:$N$4835,Base!$B$2:$B$4835,"Frete de venda",Base!$A$2:$A$4835,C$4) | D8: =SUMIFS(Base!$N$2:$N$4835,Base!$B$2:$B$4835,"Frete de venda",Base!$A$2:$A$4835,D$4) | E8: =SUMIFS(Base!$N$2:$N$4835,Base!$B$2:$B$4835,"Frete de venda",Base!$A$2:$A$4835,E$4) | F8: =SUMIFS(Base!$N$2:$N$4835,Base!$B$2:$B$4835,"Frete de venda",Base!$A$2:$A$4835,F$4) | G8: =SUMIFS(Base!$N$2:$N$4835,Base!$B$2:$B$4835,"Frete de venda",Base!$A$2:$A$4835,G$4) | H8: =SUMIFS(Base!$N$2:$N$4835,Base!$B$2:$B$4835,"Frete de venda",Base!$A$2:$A$4835,H$4) | I8: =SUMIFS(Base!$N$2:$N$4835,Base!$B$2:$B$4835,"Frete de venda",Base!$A$2:$A$4835,I$4) | J8: =SUMIFS(Base!$N$2:$N$4835,Base!$B$2:$B$4835,"Frete de venda",Base!$A$2:$A$4835,J$4) | K8: =SUM(B8:J8) | L8: =AVERAGE(B8:J8) | M8: =MAX(B8:J8) | N8: =IF(M8=0,"",INDEX($B$4:$J$4,MATCH(M8,B8:J8,0)))
A9: TOTAL | B9: =SUM(B5:B8) | C9: =SUM(C5:C8) | D9: =SUM(D5:D8) | E9: =SUM(E5:E8) | F9: =SUM(F5:F8) | G9: =SUM(G5:G8) | H9: =SUM(H5:H8) | I9: =SUM(I5:I8) | ... K9: =SUM(K5:K8) | L9: =AVERAGE(B9:J9) | M9: =MAX(B9:J9) | N9: =INDEX($B$4:$J$4,MATCH(M9,B9:J9,0))
A11: Variação % vs mês anterior – destino | B11: 46023 | C11: 46054 | D11: 46082 | E11: 46113 | F11: 46143 | G11: 46174 | H11: 46204 | I11: 46235 | J11: 46266 | K11: Total 2026 | L11: Média mensal | M11: Maior mês | N11: Mês do pico
A12: =A5 | C12: =IF(B5=0,"",C5/B5-1) | D12: =IF(C5=0,"",D5/C5-1) | E12: =IF(D5=0,"",E5/D5-1) | F12: =IF(E5=0,"",F5/E5-1) | G12: =IF(F5=0,"",G5/F5-1) | H12: =IF(G5=0,"",H5/G5-1) | I12: =IF(H5=0,"",I5/H5-1) | J12: =IF(I5=0,"",J5/I5-1)
A13: =A6 | C13: =IF(B6=0,"",C6/B6-1) | D13: =IF(C6=0,"",D6/C6-1) | E13: =IF(D6=0,"",E6/D6-1) | F13: =IF(E6=0,"",F6/E6-1) | G13: =IF(F6=0,"",G6/F6-1) | H13: =IF(G6=0,"",H6/G6-1) | I13: =IF(H6=0,"",I6/H6-1) | J13: =IF(I6=0,"",J6/I6-1)
A14: =A7 | C14: =IF(B7=0,"",C7/B7-1) | D14: =IF(C7=0,"",D7/C7-1) | E14: =IF(D7=0,"",E7/D7-1) | F14: =IF(E7=0,"",F7/E7-1) | G14: =IF(F7=0,"",G7/F7-1) | H14: =IF(G7=0,"",H7/G7-1) | I14: =IF(H7=0,"",I7/H7-1) | J14: =IF(I7=0,"",J7/I7-1)
A15: =A8 | C15: =IF(B8=0,"",C8/B8-1) | D15: =IF(C8=0,"",D8/C8-1) | E15: =IF(D8=0,"",E8/D8-1) | F15: =IF(E8=0,"",F8/E8-1) | G15: =IF(F8=0,"",G8/F8-1) | H15: =IF(G8=0,"",H8/G8-1) | I15: =IF(H8=0,"",I8/H8-1) | J15: =IF(I8=0,"",J8/I8-1)
A16: =A9 | C16: =IF(B9=0,"",C9/B9-1) | D16: =IF(C9=0,"",D9/C9-1) | E16: =IF(D9=0,"",E9/D9-1) | F16: =IF(E9=0,"",F9/E9-1) | G16: =IF(F9=0,"",G9/F9-1) | H16: =IF(G9=0,"",H9/G9-1) | I16: =IF(H9=0,"",I9/H9-1) | J16: =IF(I9=0,"",J9/I9-1)
A18: Participação no total do mês | B18: 46023 | C18: 46054 | D18: 46082 | E18: 46113 | F18: 46143 | G18: 46174 | H18: 46204 | I18: 46235 | J18: 46266 | K18: Total 2026 | L18: Média mensal | M18: Maior mês | N18: Mês do pico
A19: =A5 | B19: =IFERROR(B5/B$9,"") | C19: =IFERROR(C5/C$9,"") | D19: =IFERROR(D5/D$9,"") | E19: =IFERROR(E5/E$9,"") | F19: =IFERROR(F5/F$9,"") | G19: =IFERROR(G5/G$9,"") | H19: =IFERROR(H5/H$9,"") | I19: =IFERROR(I5/I$9,"") | ... K19: =IFERROR(K5/K$9,"")
A20: =A6 | B20: =IFERROR(B6/B$9,"") | C20: =IFERROR(C6/C$9,"") | D20: =IFERROR(D6/D$9,"") | E20: =IFERROR(E6/E$9,"") | F20: =IFERROR(F6/F$9,"") | G20: =IFERROR(G6/G$9,"") | H20: =IFERROR(H6/H$9,"") | I20: =IFERROR(I6/I$9,"") | ... K20: =IFERROR(K6/K$9,"")
A21: =A7 | B21: =IFERROR(B7/B$9,"") | C21: =IFERROR(C7/C$9,"") | D21: =IFERROR(D7/D$9,"") | E21: =IFERROR(E7/E$9,"") | F21: =IFERROR(F7/F$9,"") | G21: =IFERROR(G7/G$9,"") | H21: =IFERROR(H7/H$9,"") | I21: =IFERROR(I7/I$9,"") | ... K21: =IFERROR(K7/K$9,"")
A22: =A8 | B22: =IFERROR(B8/B$9,"") | C22: =IFERROR(C8/C$9,"") | D22: =IFERROR(D8/D$9,"") | E22: =IFERROR(E8/E$9,"") | F22: =IFERROR(F8/F$9,"") | G22: =IFERROR(G8/G$9,"") | H22: =IFERROR(H8/H$9,"") | I22: =IFERROR(I8/I$9,"") | ... K22: =IFERROR(K8/K$9,"")
A24: Por categoria do Omie | B24: 46023 | C24: 46054 | D24: 46082 | E24: 46113 | F24: 46143 | G24: 46174 | H24: 46204 | I24: 46235 | J24: 46266 | K24: Total 2026 | L24: Média mensal | M24: Maior mês | N24: Mês do pico
A25: Insumos e papel
A26: 2.01.03 Compra de Matéria Prima (Papel) | B26: =SUMIFS(Base!$N$2:$N$4835,Base!$B$2:$B$4835,"Insumos e papel",Base!$C$2:$C$4835,"2.01.03 Compra de Matéria Prima (Papel)",Base!$A$2:$A$4835,B$4) | C26: =SUMIFS(Base!$N$2:$N$4835,Base!$B$2:$B$4835,"Insumos e papel",Base!$C$2:$C$4835,"2.01.03 Compra de Matéria Prima (Papel)",Base!$A$2:$A$4835,C$4) | D26: =SUMIFS(Base!$N$2:$N$4835,Base!$B$2:$B$4835,"Insumos e papel",Base!$C$2:$C$4835,"2.01.03 Compra de Matéria Prima (Papel)",Base!$A$2:$A$4835,D$4) | E26: =SUMIFS(Base!$N$2:$N$4835,Base!$B$2:$B$4835,"Insumos e papel",Base!$C$2:$C$4835,"2.01.03 Compra de Matéria Prima (Papel)",Base!$A$2:$A$4835,E$4) | F26: =SUMIFS(Base!$N$2:$N$4835,Base!$B$2:$B$4835,"Insumos e papel",Base!$C$2:$C$4835,"2.01.03 Compra de Matéria Prima (Papel)",Base!$A$2:$A$4835,F$4) | G26: =SUMIFS(Base!$N$2:$N$4835,Base!$B$2:$B$4835,"Insumos e papel",Base!$C$2:$C$4835,"2.01.03 Compra de Matéria Prima (Papel)",Base!$A$2:$A$4835,G$4) | H26: =SUMIFS(Base!$N$2:$N$4835,Base!$B$2:$B$4835,"Insumos e papel",Base!$C$2:$C$4835,"2.01.03 Compra de Matéria Prima (Papel)",Base!$A$2:$A$4835,H$4) | I26: =SUMIFS(Base!$N$2:$N$4835,Base!$B$2:$B$4835,"Insumos e papel",Base!$C$2:$C$4835,"2.01.03 Compra de Matéria Prima (Papel)",Base!$A$2:$A$4835,I$4) | J26: =SUMIFS(Base!$N$2:$N$4835,Base!$B$2:$B$4835,"Insumos e papel",Base!$C$2:$C$4835,"2.01.03 Compra de Matéria Prima (Papel)",Base!$A$2:$A$4835,J$4) | K26: =SUM(B26:J26) | L26: =AVERAGE(B26:J26) | M26: =MAX(B26:J26) | N26: =IF(M26=0,"",INDEX($B$4:$J$4,MATCH(M26,B26:J26,0)))
A27: 2.01.79 Compra de Gás | B27: =SUMIFS(Base!$N$2:$N$4835,Base!$B$2:$B$4835,"Insumos e papel",Base!$C$2:$C$4835,"2.01.79 Compra de Gás",Base!$A$2:$A$4835,B$4) | C27: =SUMIFS(Base!$N$2:$N$4835,Base!$B$2:$B$4835,"Insumos e papel",Base!$C$2:$C$4835,"2.01.79 Compra de Gás",Base!$A$2:$A$4835,C$4) | D27: =SUMIFS(Base!$N$2:$N$4835,Base!$B$2:$B$4835,"Insumos e papel",Base!$C$2:$C$4835,"2.01.79 Compra de Gás",Base!$A$2:$A$4835,D$4) | E27: =SUMIFS(Base!$N$2:$N$4835,Base!$B$2:$B$4835,"Insumos e papel",Base!$C$2:$C$4835,"2.01.79 Compra de Gás",Base!$A$2:$A$4835,E$4) | F27: =SUMIFS(Base!$N$2:$N$4835,Base!$B$2:$B$4835,"Insumos e papel",Base!$C$2:$C$4835,"2.01.79 Compra de Gás",Base!$A$2:$A$4835,F$4) | G27: =SUMIFS(Base!$N$2:$N$4835,Base!$B$2:$B$4835,"Insumos e papel",Base!$C$2:$C$4835,"2.01.79 Compra de Gás",Base!$A$2:$A$4835,G$4) | H27: =SUMIFS(Base!$N$2:$N$4835,Base!$B$2:$B$4835,"Insumos e papel",Base!$C$2:$C$4835,"2.01.79 Compra de Gás",Base!$A$2:$A$4835,H$4) | I27: =SUMIFS(Base!$N$2:$N$4835,Base!$B$2:$B$4835,"Insumos e papel",Base!$C$2:$C$4835,"2.01.79 Compra de Gás",Base!$A$2:$A$4835,I$4) | J27: =SUMIFS(Base!$N$2:$N$4835,Base!$B$2:$B$4835,"Insumos e papel",Base!$C$2:$C$4835,"2.01.79 Compra de Gás",Base!$A$2:$A$4835,J$4) | K27: =SUM(B27:J27) | L27: =AVERAGE(B27:J27) | M27: =MAX(B27:J27) | N27: =IF(M27=0,"",INDEX($B$4:$J$4,MATCH(M27,B27:J27,0)))
A28: 2.01.83 Compra de Etiqueta Personalizada | B28: =SUMIFS(Base!$N$2:$N$4835,Base!$B$2:$B$4835,"Insumos e papel",Base!$C$2:$C$4835,"2.01.83 Compra de Etiqueta Personalizada",Base!$A$2:$A$4835,B$4) | C28: =SUMIFS(Base!$N$2:$N$4835,Base!$B$2:$B$4835,"Insumos e papel",Base!$C$2:$C$4835,"2.01.83 Compra de Etiqueta Personalizada",Base!$A$2:$A$4835,C$4) | D28: =SUMIFS(Base!$N$2:$N$4835,Base!$B$2:$B$4835,"Insumos e papel",Base!$C$2:$C$4835,"2.01.83 Compra de Etiqueta Personalizada",Base!$A$2:$A$4835,D$4) | E28: =SUMIFS(Base!$N$2:$N$4835,Base!$B$2:$B$4835,"Insumos e papel",Base!$C$2:$C$4835,"2.01.83 Compra de Etiqueta Personalizada",Base!$A$2:$A$4835,E$4) | F28: =SUMIFS(Base!$N$2:$N$4835,Base!$B$2:$B$4835,"Insumos e papel",Base!$C$2:$C$4835,"2.01.83 Compra de Etiqueta Personalizada",Base!$A$2:$A$4835,F$4) | G28: =SUMIFS(Base!$N$2:$N$4835,Base!$B$2:$B$4835,"Insumos e papel",Base!$C$2:$C$4835,"2.01.83 Compra de Etiqueta Personalizada",Base!$A$2:$A$4835,G$4) | H28: =SUMIFS(Base!$N$2:$N$4835,Base!$B$2:$B$4835,"Insumos e papel",Base!$C$2:$C$4835,"2.01.83 Compra de Etiqueta Personalizada",Base!$A$2:$A$4835,H$4) | I28: =SUMIFS(Base!$N$2:$N$4835,Base!$B$2:$B$4835,"Insumos e papel",Base!$C$2:$C$4835,"2.01.83 Compra de Etiqueta Personalizada",Base!$A$2:$A$4835,I$4) | J28: =SUMIFS(Base!$N$2:$N$4835,Base!$B$2:$B$4835,"Insumos e papel",Base!$C$2:$C$4835,"2.01.83 Compra de Etiqueta Personalizada",Base!$A$2:$A$4835,J$4) | K28: =SUM(B28:J28) | L28: =AVERAGE(B28:J28) | M28: =MAX(B28:J28) | N28: =IF(M28=0,"",INDEX($B$4:$J$4,MATCH(M28,B28:J28,0)))
A29: 2.01.89 Compra de Pallet | B29: =SUMIFS(Base!$N$2:$N$4835,Base!$B$2:$B$4835,"Insumos e papel",Base!$C$2:$C$4835,"2.01.89 Compra de Pallet",Base!$A$2:$A$4835,B$4) | C29: =SUMIFS(Base!$N$2:$N$4835,Base!$B$2:$B$4835,"Insumos e papel",Base!$C$2:$C$4835,"2.01.89 Compra de Pallet",Base!$A$2:$A$4835,C$4) | D29: =SUMIFS(Base!$N$2:$N$4835,Base!$B$2:$B$4835,"Insumos e papel",Base!$C$2:$C$4835,"2.01.89 Compra de Pallet",Base!$A$2:$A$4835,D$4) | E29: =SUMIFS(Base!$N$2:$N$4835,Base!$B$2:$B$4835,"Insumos e papel",Base!$C$2:$C$4835,"2.01.89 Compra de Pallet",Base!$A$2:$A$4835,E$4) | F29: =SUMIFS(Base!$N$2:$N$4835,Base!$B$2:$B$4835,"Insumos e papel",Base!$C$2:$C$4835,"2.01.89 Compra de Pallet",Base!$A$2:$A$4835,F$4) | G29: =SUMIFS(Base!$N$2:$N$4835,Base!$B$2:$B$4835,"Insumos e papel",Base!$C$2:$C$4835,"2.01.89 Compra de Pallet",Base!$A$2:$A$4835,G$4) | H29: =SUMIFS(Base!$N$2:$N$4835,Base!$B$2:$B$4835,"Insumos e papel",Base!$C$2:$C$4835,"2.01.89 Compra de Pallet",Base!$A$2:$A$4835,H$4) | I29: =SUMIFS(Base!$N$2:$N$4835,Base!$B$2:$B$4835,"Insumos e papel",Base!$C$2:$C$4835,"2.01.89 Compra de Pallet",Base!$A$2:$A$4835,I$4) | J29: =SUMIFS(Base!$N$2:$N$4835,Base!$B$2:$B$4835,"Insumos e papel",Base!$C$2:$C$4835,"2.01.89 Compra de Pallet",Base!$A$2:$A$4835,J$4) | K29: =SUM(B29:J29) | L29: =AVERAGE(B29:J29) | M29: =MAX(B29:J29) | N29: =IF(M29=0,"",INDEX($B$4:$J$4,MATCH(M29,B29:J29,0)))
A30: 2.01.91 Compra de Filme Strech | B30: =SUMIFS(Base!$N$2:$N$4835,Base!$B$2:$B$4835,"Insumos e papel",Base!$C$2:$C$4835,"2.01.91 Compra de Filme Strech",Base!$A$2:$A$4835,B$4) | C30: =SUMIFS(Base!$N$2:$N$4835,Base!$B$2:$B$4835,"Insumos e papel",Base!$C$2:$C$4835,"2.01.91 Compra de Filme Strech",Base!$A$2:$A$4835,C$4) | D30: =SUMIFS(Base!$N$2:$N$4835,Base!$B$2:$B$4835,"Insumos e papel",Base!$C$2:$C$4835,"2.01.91 Compra de Filme Strech",Base!$A$2:$A$4835,D$4) | E30: =SUMIFS(Base!$N$2:$N$4835,Base!$B$2:$B$4835,"Insumos e papel",Base!$C$2:$C$4835,"2.01.91 Compra de Filme Strech",Base!$A$2:$A$4835,E$4) | F30: =SUMIFS(Base!$N$2:$N$4835,Base!$B$2:$B$4835,"Insumos e papel",Base!$C$2:$C$4835,"2.01.91 Compra de Filme Strech",Base!$A$2:$A$4835,F$4) | G30: =SUMIFS(Base!$N$2:$N$4835,Base!$B$2:$B$4835,"Insumos e papel",Base!$C$2:$C$4835,"2.01.91 Compra de Filme Strech",Base!$A$2:$A$4835,G$4) | H30: =SUMIFS(Base!$N$2:$N$4835,Base!$B$2:$B$4835,"Insumos e papel",Base!$C$2:$C$4835,"2.01.91 Compra de Filme Strech",Base!$A$2:$A$4835,H$4) | I30: =SUMIFS(Base!$N$2:$N$4835,Base!$B$2:$B$4835,"Insumos e papel",Base!$C$2:$C$4835,"2.01.91 Compra de Filme Strech",Base!$A$2:$A$4835,I$4) | J30: =SUMIFS(Base!$N$2:$N$4835,Base!$B$2:$B$4835,"Insumos e papel",Base!$C$2:$C$4835,"2.01.91 Compra de Filme Strech",Base!$A$2:$A$4835,J$4) | K30: =SUM(B30:J30) | L30: =AVERAGE(B30:J30) | M30: =MAX(B30:J30) | N30: =IF(M30=0,"",INDEX($B$4:$J$4,MATCH(M30,B30:J30,0)))
A31: 2.01.92 Compra de Tinta | B31: =SUMIFS(Base!$N$2:$N$4835,Base!$B$2:$B$4835,"Insumos e papel",Base!$C$2:$C$4835,"2.01.92 Compra de Tinta",Base!$A$2:$A$4835,B$4) | C31: =SUMIFS(Base!$N$2:$N$4835,Base!$B$2:$B$4835,"Insumos e papel",Base!$C$2:$C$4835,"2.01.92 Compra de Tinta",Base!$A$2:$A$4835,C$4) | D31: =SUMIFS(Base!$N$2:$N$4835,Base!$B$2:$B$4835,"Insumos e papel",Base!$C$2:$C$4835,"2.01.92 Compra de Tinta",Base!$A$2:$A$4835,D$4) | E31: =SUMIFS(Base!$N$2:$N$4835,Base!$B$2:$B$4835,"Insumos e papel",Base!$C$2:$C$4835,"2.01.92 Compra de Tinta",Base!$A$2:$A$4835,E$4) | F31: =SUMIFS(Base!$N$2:$N$4835,Base!$B$2:$B$4835,"Insumos e papel",Base!$C$2:$C$4835,"2.01.92 Compra de Tinta",Base!$A$2:$A$4835,F$4) | G31: =SUMIFS(Base!$N$2:$N$4835,Base!$B$2:$B$4835,"Insumos e papel",Base!$C$2:$C$4835,"2.01.92 Compra de Tinta",Base!$A$2:$A$4835,G$4) | H31: =SUMIFS(Base!$N$2:$N$4835,Base!$B$2:$B$4835,"Insumos e papel",Base!$C$2:$C$4835,"2.01.92 Compra de Tinta",Base!$A$2:$A$4835,H$4) | I31: =SUMIFS(Base!$N$2:$N$4835,Base!$B$2:$B$4835,"Insumos e papel",Base!$C$2:$C$4835,"2.01.92 Compra de Tinta",Base!$A$2:$A$4835,I$4) | J31: =SUMIFS(Base!$N$2:$N$4835,Base!$B$2:$B$4835,"Insumos e papel",Base!$C$2:$C$4835,"2.01.92 Compra de Tinta",Base!$A$2:$A$4835,J$4) | K31: =SUM(B31:J31) | L31: =AVERAGE(B31:J31) | M31: =MAX(B31:J31) | N31: =IF(M31=0,"",INDEX($B$4:$J$4,MATCH(M31,B31:J31,0)))
A32: 2.01.93 Compra de Plástico Poliolefínico | B32: =SUMIFS(Base!$N$2:$N$4835,Base!$B$2:$B$4835,"Insumos e papel",Base!$C$2:$C$4835,"2.01.93 Compra de Plástico Poliolefínico",Base!$A$2:$A$4835,B$4) | C32: =SUMIFS(Base!$N$2:$N$4835,Base!$B$2:$B$4835,"Insumos e papel",Base!$C$2:$C$4835,"2.01.93 Compra de Plástico Poliolefínico",Base!$A$2:$A$4835,C$4) | D32: =SUMIFS(Base!$N$2:$N$4835,Base!$B$2:$B$4835,"Insumos e papel",Base!$C$2:$C$4835,"2.01.93 Compra de Plástico Poliolefínico",Base!$A$2:$A$4835,D$4) | E32: =SUMIFS(Base!$N$2:$N$4835,Base!$B$2:$B$4835,"Insumos e papel",Base!$C$2:$C$4835,"2.01.93 Compra de Plástico Poliolefínico",Base!$A$2:$A$4835,E$4) | F32: =SUMIFS(Base!$N$2:$N$4835,Base!$B$2:$B$4835,"Insumos e papel",Base!$C$2:$C$4835,"2.01.93 Compra de Plástico Poliolefínico",Base!$A$2:$A$4835,F$4) | G32: =SUMIFS(Base!$N$2:$N$4835,Base!$B$2:$B$4835,"Insumos e papel",Base!$C$2:$C$4835,"2.01.93 Compra de Plástico Poliolefínico",Base!$A$2:$A$4835,G$4) | H32: =SUMIFS(Base!$N$2:$N$4835,Base!$B$2:$B$4835,"Insumos e papel",Base!$C$2:$C$4835,"2.01.93 Compra de Plástico Poliolefínico",Base!$A$2:$A$4835,H$4) | I32: =SUMIFS(Base!$N$2:$N$4835,Base!$B$2:$B$4835,"Insumos e papel",Base!$C$2:$C$4835,"2.01.93 Compra de Plástico Poliolefínico",Base!$A$2:$A$4835,I$4) | J32: =SUMIFS(Base!$N$2:$N$4835,Base!$B$2:$B$4835,"Insumos e papel",Base!$C$2:$C$4835,"2.01.93 Compra de Plástico Poliolefínico",Base!$A$2:$A$4835,J$4) | K32: =SUM(B32:J32) | L32: =AVERAGE(B32:J32) | M32: =MAX(B32:J32) | N32: =IF(M32=0,"",INDEX($B$4:$J$4,MATCH(M32,B32:J32,0)))
A33: 2.01.94 Compra de Fita Adesiva | B33: =SUMIFS(Base!$N$2:$N$4835,Base!$B$2:$B$4835,"Insumos e papel",Base!$C$2:$C$4835,"2.01.94 Compra de Fita Adesiva",Base!$A$2:$A$4835,B$4) | C33: =SUMIFS(Base!$N$2:$N$4835,Base!$B$2:$B$4835,"Insumos e papel",Base!$C$2:$C$4835,"2.01.94 Compra de Fita Adesiva",Base!$A$2:$A$4835,C$4) | D33: =SUMIFS(Base!$N$2:$N$4835,Base!$B$2:$B$4835,"Insumos e papel",Base!$C$2:$C$4835,"2.01.94 Compra de Fita Adesiva",Base!$A$2:$A$4835,D$4) | E33: =SUMIFS(Base!$N$2:$N$4835,Base!$B$2:$B$4835,"Insumos e papel",Base!$C$2:$C$4835,"2.01.94 Compra de Fita Adesiva",Base!$A$2:$A$4835,E$4) | F33: =SUMIFS(Base!$N$2:$N$4835,Base!$B$2:$B$4835,"Insumos e papel",Base!$C$2:$C$4835,"2.01.94 Compra de Fita Adesiva",Base!$A$2:$A$4835,F$4) | G33: =SUMIFS(Base!$N$2:$N$4835,Base!$B$2:$B$4835,"Insumos e papel",Base!$C$2:$C$4835,"2.01.94 Compra de Fita Adesiva",Base!$A$2:$A$4835,G$4) | H33: =SUMIFS(Base!$N$2:$N$4835,Base!$B$2:$B$4835,"Insumos e papel",Base!$C$2:$C$4835,"2.01.94 Compra de Fita Adesiva",Base!$A$2:$A$4835,H$4) | I33: =SUMIFS(Base!$N$2:$N$4835,Base!$B$2:$B$4835,"Insumos e papel",Base!$C$2:$C$4835,"2.01.94 Compra de Fita Adesiva",Base!$A$2:$A$4835,I$4) | J33: =SUMIFS(Base!$N$2:$N$4835,Base!$B$2:$B$4835,"Insumos e papel",Base!$C$2:$C$4835,"2.01.94 Compra de Fita Adesiva",Base!$A$2:$A$4835,J$4) | K33: =SUM(B33:J33) | L33: =AVERAGE(B33:J33) | M33: =MAX(B33:J33) | N33: =IF(M33=0,"",INDEX($B$4:$J$4,MATCH(M33,B33:J33,0)))
A34: 2.01.95 Compra de Etiqueta | B34: =SUMIFS(Base!$N$2:$N$4835,Base!$B$2:$B$4835,"Insumos e papel",Base!$C$2:$C$4835,"2.01.95 Compra de Etiqueta",Base!$A$2:$A$4835,B$4) | C34: =SUMIFS(Base!$N$2:$N$4835,Base!$B$2:$B$4835,"Insumos e papel",Base!$C$2:$C$4835,"2.01.95 Compra de Etiqueta",Base!$A$2:$A$4835,C$4) | D34: =SUMIFS(Base!$N$2:$N$4835,Base!$B$2:$B$4835,"Insumos e papel",Base!$C$2:$C$4835,"2.01.95 Compra de Etiqueta",Base!$A$2:$A$4835,D$4) | E34: =SUMIFS(Base!$N$2:$N$4835,Base!$B$2:$B$4835,"Insumos e papel",Base!$C$2:$C$4835,"2.01.95 Compra de Etiqueta",Base!$A$2:$A$4835,E$4) | F34: =SUMIFS(Base!$N$2:$N$4835,Base!$B$2:$B$4835,"Insumos e papel",Base!$C$2:$C$4835,"2.01.95 Compra de Etiqueta",Base!$A$2:$A$4835,F$4) | G34: =SUMIFS(Base!$N$2:$N$4835,Base!$B$2:$B$4835,"Insumos e papel",Base!$C$2:$C$4835,"2.01.95 Compra de Etiqueta",Base!$A$2:$A$4835,G$4) | H34: =SUMIFS(Base!$N$2:$N$4835,Base!$B$2:$B$4835,"Insumos e papel",Base!$C$2:$C$4835,"2.01.95 Compra de Etiqueta",Base!$A$2:$A$4835,H$4) | I34: =SUMIFS(Base!$N$2:$N$4835,Base!$B$2:$B$4835,"Insumos e papel",Base!$C$2:$C$4835,"2.01.95 Compra de Etiqueta",Base!$A$2:$A$4835,I$4) | J34: =SUMIFS(Base!$N$2:$N$4835,Base!$B$2:$B$4835,"Insumos e papel",Base!$C$2:$C$4835,"2.01.95 Compra de Etiqueta",Base!$A$2:$A$4835,J$4) | K34: =SUM(B34:J34) | L34: =AVERAGE(B34:J34) | M34: =MAX(B34:J34) | N34: =IF(M34=0,"",INDEX($B$4:$J$4,MATCH(M34,B34:J34,0)))
A35: 2.01.96 Compra de Cola | B35: =SUMIFS(Base!$N$2:$N$4835,Base!$B$2:$B$4835,"Insumos e papel",Base!$C$2:$C$4835,"2.01.96 Compra de Cola",Base!$A$2:$A$4835,B$4) | C35: =SUMIFS(Base!$N$2:$N$4835,Base!$B$2:$B$4835,"Insumos e papel",Base!$C$2:$C$4835,"2.01.96 Compra de Cola",Base!$A$2:$A$4835,C$4) | D35: =SUMIFS(Base!$N$2:$N$4835,Base!$B$2:$B$4835,"Insumos e papel",Base!$C$2:$C$4835,"2.01.96 Compra de Cola",Base!$A$2:$A$4835,D$4) | E35: =SUMIFS(Base!$N$2:$N$4835,Base!$B$2:$B$4835,"Insumos e papel",Base!$C$2:$C$4835,"2.01.96 Compra de Cola",Base!$A$2:$A$4835,E$4) | F35: =SUMIFS(Base!$N$2:$N$4835,Base!$B$2:$B$4835,"Insumos e papel",Base!$C$2:$C$4835,"2.01.96 Compra de Cola",Base!$A$2:$A$4835,F$4) | G35: =SUMIFS(Base!$N$2:$N$4835,Base!$B$2:$B$4835,"Insumos e papel",Base!$C$2:$C$4835,"2.01.96 Compra de Cola",Base!$A$2:$A$4835,G$4) | H35: =SUMIFS(Base!$N$2:$N$4835,Base!$B$2:$B$4835,"Insumos e papel",Base!$C$2:$C$4835,"2.01.96 Compra de Cola",Base!$A$2:$A$4835,H$4) | I35: =SUMIFS(Base!$N$2:$N$4835,Base!$B$2:$B$4835,"Insumos e papel",Base!$C$2:$C$4835,"2.01.96 Compra de Cola",Base!$A$2:$A$4835,I$4) | J35: =SUMIFS(Base!$N$2:$N$4835,Base!$B$2:$B$4835,"Insumos e papel",Base!$C$2:$C$4835,"2.01.96 Compra de Cola",Base!$A$2:$A$4835,J$4) | K35: =SUM(B35:J35) | L35: =AVERAGE(B35:J35) | M35: =MAX(B35:J35) | N35: =IF(M35=0,"",INDEX($B$4:$J$4,MATCH(M35,B35:J35,0)))
A36: 2.01.97 Compra de Clichê | B36: =SUMIFS(Base!$N$2:$N$4835,Base!$B$2:$B$4835,"Insumos e papel",Base!$C$2:$C$4835,"2.01.97 Compra de Clichê",Base!$A$2:$A$4835,B$4) | C36: =SUMIFS(Base!$N$2:$N$4835,Base!$B$2:$B$4835,"Insumos e papel",Base!$C$2:$C$4835,"2.01.97 Compra de Clichê",Base!$A$2:$A$4835,C$4) | D36: =SUMIFS(Base!$N$2:$N$4835,Base!$B$2:$B$4835,"Insumos e papel",Base!$C$2:$C$4835,"2.01.97 Compra de Clichê",Base!$A$2:$A$4835,D$4) | E36: =SUMIFS(Base!$N$2:$N$4835,Base!$B$2:$B$4835,"Insumos e papel",Base!$C$2:$C$4835,"2.01.97 Compra de Clichê",Base!$A$2:$A$4835,E$4) | F36: =SUMIFS(Base!$N$2:$N$4835,Base!$B$2:$B$4835,"Insumos e papel",Base!$C$2:$C$4835,"2.01.97 Compra de Clichê",Base!$A$2:$A$4835,F$4) | G36: =SUMIFS(Base!$N$2:$N$4835,Base!$B$2:$B$4835,"Insumos e papel",Base!$C$2:$C$4835,"2.01.97 Compra de Clichê",Base!$A$2:$A$4835,G$4) | H36: =SUMIFS(Base!$N$2:$N$4835,Base!$B$2:$B$4835,"Insumos e papel",Base!$C$2:$C$4835,"2.01.97 Compra de Clichê",Base!$A$2:$A$4835,H$4) | I36: =SUMIFS(Base!$N$2:$N$4835,Base!$B$2:$B$4835,"Insumos e papel",Base!$C$2:$C$4835,"2.01.97 Compra de Clichê",Base!$A$2:$A$4835,I$4) | J36: =SUMIFS(Base!$N$2:$N$4835,Base!$B$2:$B$4835,"Insumos e papel",Base!$C$2:$C$4835,"2.01.97 Compra de Clichê",Base!$A$2:$A$4835,J$4) | K36: =SUM(B36:J36) | L36: =AVERAGE(B36:J36) | M36: =MAX(B36:J36) | N36: =IF(M36=0,"",INDEX($B$4:$J$4,MATCH(M36,B36:J36,0)))
A37: 2.01.99 Compra de Caixas | B37: =SUMIFS(Base!$N$2:$N$4835,Base!$B$2:$B$4835,"Insumos e papel",Base!$C$2:$C$4835,"2.01.99 Compra de Caixas",Base!$A$2:$A$4835,B$4) | C37: =SUMIFS(Base!$N$2:$N$4835,Base!$B$2:$B$4835,"Insumos e papel",Base!$C$2:$C$4835,"2.01.99 Compra de Caixas",Base!$A$2:$A$4835,C$4) | D37: =SUMIFS(Base!$N$2:$N$4835,Base!$B$2:$B$4835,"Insumos e papel",Base!$C$2:$C$4835,"2.01.99 Compra de Caixas",Base!$A$2:$A$4835,D$4) | E37: =SUMIFS(Base!$N$2:$N$4835,Base!$B$2:$B$4835,"Insumos e papel",Base!$C$2:$C$4835,"2.01.99 Compra de Caixas",Base!$A$2:$A$4835,E$4) | F37: =SUMIFS(Base!$N$2:$N$4835,Base!$B$2:$B$4835,"Insumos e papel",Base!$C$2:$C$4835,"2.01.99 Compra de Caixas",Base!$A$2:$A$4835,F$4) | G37: =SUMIFS(Base!$N$2:$N$4835,Base!$B$2:$B$4835,"Insumos e papel",Base!$C$2:$C$4835,"2.01.99 Compra de Caixas",Base!$A$2:$A$4835,G$4) | H37: =SUMIFS(Base!$N$2:$N$4835,Base!$B$2:$B$4835,"Insumos e papel",Base!$C$2:$C$4835,"2.01.99 Compra de Caixas",Base!$A$2:$A$4835,H$4) | I37: =SUMIFS(Base!$N$2:$N$4835,Base!$B$2:$B$4835,"Insumos e papel",Base!$C$2:$C$4835,"2.01.99 Compra de Caixas",Base!$A$2:$A$4835,I$4) | J37: =SUMIFS(Base!$N$2:$N$4835,Base!$B$2:$B$4835,"Insumos e papel",Base!$C$2:$C$4835,"2.01.99 Compra de Caixas",Base!$A$2:$A$4835,J$4) | K37: =SUM(B37:J37) | L37: =AVERAGE(B37:J37) | M37: =MAX(B37:J37) | N37: =IF(M37=0,"",INDEX($B$4:$J$4,MATCH(M37,B37:J37,0)))
A38: Uso e consumo
A39: 2.01.85 Compra de Uso e Consumo | B39: =SUMIFS(Base!$N$2:$N$4835,Base!$B$2:$B$4835,"Uso e consumo",Base!$C$2:$C$4835,"2.01.85 Compra de Uso e Consumo",Base!$A$2:$A$4835,B$4) | C39: =SUMIFS(Base!$N$2:$N$4835,Base!$B$2:$B$4835,"Uso e consumo",Base!$C$2:$C$4835,"2.01.85 Compra de Uso e Consumo",Base!$A$2:$A$4835,C$4) | D39: =SUMIFS(Base!$N$2:$N$4835,Base!$B$2:$B$4835,"Uso e consumo",Base!$C$2:$C$4835,"2.01.85 Compra de Uso e Consumo",Base!$A$2:$A$4835,D$4) | E39: =SUMIFS(Base!$N$2:$N$4835,Base!$B$2:$B$4835,"Uso e consumo",Base!$C$2:$C$4835,"2.01.85 Compra de Uso e Consumo",Base!$A$2:$A$4835,E$4) | F39: =SUMIFS(Base!$N$2:$N$4835,Base!$B$2:$B$4835,"Uso e consumo",Base!$C$2:$C$4835,"2.01.85 Compra de Uso e Consumo",Base!$A$2:$A$4835,F$4) | G39: =SUMIFS(Base!$N$2:$N$4835,Base!$B$2:$B$4835,"Uso e consumo",Base!$C$2:$C$4835,"2.01.85 Compra de Uso e Consumo",Base!$A$2:$A$4835,G$4) | H39: =SUMIFS(Base!$N$2:$N$4835,Base!$B$2:$B$4835,"Uso e consumo",Base!$C$2:$C$4835,"2.01.85 Compra de Uso e Consumo",Base!$A$2:$A$4835,H$4) | I39: =SUMIFS(Base!$N$2:$N$4835,Base!$B$2:$B$4835,"Uso e consumo",Base!$C$2:$C$4835,"2.01.85 Compra de Uso e Consumo",Base!$A$2:$A$4835,I$4) | J39: =SUMIFS(Base!$N$2:$N$4835,Base!$B$2:$B$4835,"Uso e consumo",Base!$C$2:$C$4835,"2.01.85 Compra de Uso e Consumo",Base!$A$2:$A$4835,J$4) | K39: =SUM(B39:J39) | L39: =AVERAGE(B39:J39) | M39: =MAX(B39:J39) | N39: =IF(M39=0,"",INDEX($B$4:$J$4,MATCH(M39,B39:J39,0)))
A40: 2.01.87 Compra de Peças de Máquinas | B40: =SUMIFS(Base!$N$2:$N$4835,Base!$B$2:$B$4835,"Uso e consumo",Base!$C$2:$C$4835,"2.01.87 Compra de Peças de Máquinas",Base!$A$2:$A$4835,B$4) | C40: =SUMIFS(Base!$N$2:$N$4835,Base!$B$2:$B$4835,"Uso e consumo",Base!$C$2:$C$4835,"2.01.87 Compra de Peças de Máquinas",Base!$A$2:$A$4835,C$4) | D40: =SUMIFS(Base!$N$2:$N$4835,Base!$B$2:$B$4835,"Uso e consumo",Base!$C$2:$C$4835,"2.01.87 Compra de Peças de Máquinas",Base!$A$2:$A$4835,D$4) | E40: =SUMIFS(Base!$N$2:$N$4835,Base!$B$2:$B$4835,"Uso e consumo",Base!$C$2:$C$4835,"2.01.87 Compra de Peças de Máquinas",Base!$A$2:$A$4835,E$4) | F40: =SUMIFS(Base!$N$2:$N$4835,Base!$B$2:$B$4835,"Uso e consumo",Base!$C$2:$C$4835,"2.01.87 Compra de Peças de Máquinas",Base!$A$2:$A$4835,F$4) | G40: =SUMIFS(Base!$N$2:$N$4835,Base!$B$2:$B$4835,"Uso e consumo",Base!$C$2:$C$4835,"2.01.87 Compra de Peças de Máquinas",Base!$A$2:$A$4835,G$4) | H40: =SUMIFS(Base!$N$2:$N$4835,Base!$B$2:$B$4835,"Uso e consumo",Base!$C$2:$C$4835,"2.01.87 Compra de Peças de Máquinas",Base!$A$2:$A$4835,H$4) | I40: =SUMIFS(Base!$N$2:$N$4835,Base!$B$2:$B$4835,"Uso e consumo",Base!$C$2:$C$4835,"2.01.87 Compra de Peças de Máquinas",Base!$A$2:$A$4835,I$4) | J40: =SUMIFS(Base!$N$2:$N$4835,Base!$B$2:$B$4835,"Uso e consumo",Base!$C$2:$C$4835,"2.01.87 Compra de Peças de Máquinas",Base!$A$2:$A$4835,J$4) | K40: =SUM(B40:J40) | L40: =AVERAGE(B40:J40) | M40: =MAX(B40:J40) | N40: =IF(M40=0,"",INDEX($B$4:$J$4,MATCH(M40,B40:J40,0)))
A41: 2.03.88 Compra de Fardamento | B41: =SUMIFS(Base!$N$2:$N$4835,Base!$B$2:$B$4835,"Uso e consumo",Base!$C$2:$C$4835,"2.03.88 Compra de Fardamento",Base!$A$2:$A$4835,B$4) | C41: =SUMIFS(Base!$N$2:$N$4835,Base!$B$2:$B$4835,"Uso e consumo",Base!$C$2:$C$4835,"2.03.88 Compra de Fardamento",Base!$A$2:$A$4835,C$4) | D41: =SUMIFS(Base!$N$2:$N$4835,Base!$B$2:$B$4835,"Uso e consumo",Base!$C$2:$C$4835,"2.03.88 Compra de Fardamento",Base!$A$2:$A$4835,D$4) | E41: =SUMIFS(Base!$N$2:$N$4835,Base!$B$2:$B$4835,"Uso e consumo",Base!$C$2:$C$4835,"2.03.88 Compra de Fardamento",Base!$A$2:$A$4835,E$4) | F41: =SUMIFS(Base!$N$2:$N$4835,Base!$B$2:$B$4835,"Uso e consumo",Base!$C$2:$C$4835,"2.03.88 Compra de Fardamento",Base!$A$2:$A$4835,F$4) | G41: =SUMIFS(Base!$N$2:$N$4835,Base!$B$2:$B$4835,"Uso e consumo",Base!$C$2:$C$4835,"2.03.88 Compra de Fardamento",Base!$A$2:$A$4835,G$4) | H41: =SUMIFS(Base!$N$2:$N$4835,Base!$B$2:$B$4835,"Uso e consumo",Base!$C$2:$C$4835,"2.03.88 Compra de Fardamento",Base!$A$2:$A$4835,H$4) | I41: =SUMIFS(Base!$N$2:$N$4835,Base!$B$2:$B$4835,"Uso e consumo",Base!$C$2:$C$4835,"2.03.88 Compra de Fardamento",Base!$A$2:$A$4835,I$4) | J41: =SUMIFS(Base!$N$2:$N$4835,Base!$B$2:$B$4835,"Uso e consumo",Base!$C$2:$C$4835,"2.03.88 Compra de Fardamento",Base!$A$2:$A$4835,J$4) | K41: =SUM(B41:J41) | L41: =AVERAGE(B41:J41) | M41: =MAX(B41:J41) | N41: =IF(M41=0,"",INDEX($B$4:$J$4,MATCH(M41,B41:J41,0)))
A42: 2.03.90 Compra de EPI | B42: =SUMIFS(Base!$N$2:$N$4835,Base!$B$2:$B$4835,"Uso e consumo",Base!$C$2:$C$4835,"2.03.90 Compra de EPI",Base!$A$2:$A$4835,B$4) | C42: =SUMIFS(Base!$N$2:$N$4835,Base!$B$2:$B$4835,"Uso e consumo",Base!$C$2:$C$4835,"2.03.90 Compra de EPI",Base!$A$2:$A$4835,C$4) | D42: =SUMIFS(Base!$N$2:$N$4835,Base!$B$2:$B$4835,"Uso e consumo",Base!$C$2:$C$4835,"2.03.90 Compra de EPI",Base!$A$2:$A$4835,D$4) | E42: =SUMIFS(Base!$N$2:$N$4835,Base!$B$2:$B$4835,"Uso e consumo",Base!$C$2:$C$4835,"2.03.90 Compra de EPI",Base!$A$2:$A$4835,E$4) | F42: =SUMIFS(Base!$N$2:$N$4835,Base!$B$2:$B$4835,"Uso e consumo",Base!$C$2:$C$4835,"2.03.90 Compra de EPI",Base!$A$2:$A$4835,F$4) | G42: =SUMIFS(Base!$N$2:$N$4835,Base!$B$2:$B$4835,"Uso e consumo",Base!$C$2:$C$4835,"2.03.90 Compra de EPI",Base!$A$2:$A$4835,G$4) | H42: =SUMIFS(Base!$N$2:$N$4835,Base!$B$2:$B$4835,"Uso e consumo",Base!$C$2:$C$4835,"2.03.90 Compra de EPI",Base!$A$2:$A$4835,H$4) | I42: =SUMIFS(Base!$N$2:$N$4835,Base!$B$2:$B$4835,"Uso e consumo",Base!$C$2:$C$4835,"2.03.90 Compra de EPI",Base!$A$2:$A$4835,I$4) | J42: =SUMIFS(Base!$N$2:$N$4835,Base!$B$2:$B$4835,"Uso e consumo",Base!$C$2:$C$4835,"2.03.90 Compra de EPI",Base!$A$2:$A$4835,J$4) | K42: =SUM(B42:J42) | L42: =AVERAGE(B42:J42) | M42: =MAX(B42:J42) | N42: =IF(M42=0,"",INDEX($B$4:$J$4,MATCH(M42,B42:J42,0)))
A43: 2.04.06 Material de Escritório | B43: =SUMIFS(Base!$N$2:$N$4835,Base!$B$2:$B$4835,"Uso e consumo",Base!$C$2:$C$4835,"2.04.06 Material de Escritório",Base!$A$2:$A$4835,B$4) | C43: =SUMIFS(Base!$N$2:$N$4835,Base!$B$2:$B$4835,"Uso e consumo",Base!$C$2:$C$4835,"2.04.06 Material de Escritório",Base!$A$2:$A$4835,C$4) | D43: =SUMIFS(Base!$N$2:$N$4835,Base!$B$2:$B$4835,"Uso e consumo",Base!$C$2:$C$4835,"2.04.06 Material de Escritório",Base!$A$2:$A$4835,D$4) | E43: =SUMIFS(Base!$N$2:$N$4835,Base!$B$2:$B$4835,"Uso e consumo",Base!$C$2:$C$4835,"2.04.06 Material de Escritório",Base!$A$2:$A$4835,E$4) | F43: =SUMIFS(Base!$N$2:$N$4835,Base!$B$2:$B$4835,"Uso e consumo",Base!$C$2:$C$4835,"2.04.06 Material de Escritório",Base!$A$2:$A$4835,F$4) | G43: =SUMIFS(Base!$N$2:$N$4835,Base!$B$2:$B$4835,"Uso e consumo",Base!$C$2:$C$4835,"2.04.06 Material de Escritório",Base!$A$2:$A$4835,G$4) | H43: =SUMIFS(Base!$N$2:$N$4835,Base!$B$2:$B$4835,"Uso e consumo",Base!$C$2:$C$4835,"2.04.06 Material de Escritório",Base!$A$2:$A$4835,H$4) | I43: =SUMIFS(Base!$N$2:$N$4835,Base!$B$2:$B$4835,"Uso e consumo",Base!$C$2:$C$4835,"2.04.06 Material de Escritório",Base!$A$2:$A$4835,I$4) | J43: =SUMIFS(Base!$N$2:$N$4835,Base!$B$2:$B$4835,"Uso e consumo",Base!$C$2:$C$4835,"2.04.06 Material de Escritório",Base!$A$2:$A$4835,J$4) | K43: =SUM(B43:J43) | L43: =AVERAGE(B43:J43) | M43: =MAX(B43:J43) | N43: =IF(M43=0,"",INDEX($B$4:$J$4,MATCH(M43,B43:J43,0)))
A44: 2.04.91 Compra de Material de Limpeza | B44: =SUMIFS(Base!$N$2:$N$4835,Base!$B$2:$B$4835,"Uso e consumo",Base!$C$2:$C$4835,"2.04.91 Compra de Material de Limpeza",Base!$A$2:$A$4835,B$4) | C44: =SUMIFS(Base!$N$2:$N$4835,Base!$B$2:$B$4835,"Uso e consumo",Base!$C$2:$C$4835,"2.04.91 Compra de Material de Limpeza",Base!$A$2:$A$4835,C$4) | D44: =SUMIFS(Base!$N$2:$N$4835,Base!$B$2:$B$4835,"Uso e consumo",Base!$C$2:$C$4835,"2.04.91 Compra de Material de Limpeza",Base!$A$2:$A$4835,D$4) | E44: =SUMIFS(Base!$N$2:$N$4835,Base!$B$2:$B$4835,"Uso e consumo",Base!$C$2:$C$4835,"2.04.91 Compra de Material de Limpeza",Base!$A$2:$A$4835,E$4) | F44: =SUMIFS(Base!$N$2:$N$4835,Base!$B$2:$B$4835,"Uso e consumo",Base!$C$2:$C$4835,"2.04.91 Compra de Material de Limpeza",Base!$A$2:$A$4835,F$4) | G44: =SUMIFS(Base!$N$2:$N$4835,Base!$B$2:$B$4835,"Uso e consumo",Base!$C$2:$C$4835,"2.04.91 Compra de Material de Limpeza",Base!$A$2:$A$4835,G$4) | H44: =SUMIFS(Base!$N$2:$N$4835,Base!$B$2:$B$4835,"Uso e consumo",Base!$C$2:$C$4835,"2.04.91 Compra de Material de Limpeza",Base!$A$2:$A$4835,H$4) | I44: =SUMIFS(Base!$N$2:$N$4835,Base!$B$2:$B$4835,"Uso e consumo",Base!$C$2:$C$4835,"2.04.91 Compra de Material de Limpeza",Base!$A$2:$A$4835,I$4) | J44: =SUMIFS(Base!$N$2:$N$4835,Base!$B$2:$B$4835,"Uso e consumo",Base!$C$2:$C$4835,"2.04.91 Compra de Material de Limpeza",Base!$A$2:$A$4835,J$4) | K44: =SUM(B44:J44) | L44: =AVERAGE(B44:J44) | M44: =MAX(B44:J44) | N44: =IF(M44=0,"",INDEX($B$4:$J$4,MATCH(M44,B44:J44,0)))
A45: 2.04.95 Copa e Cozinha | B45: =SUMIFS(Base!$N$2:$N$4835,Base!$B$2:$B$4835,"Uso e consumo",Base!$C$2:$C$4835,"2.04.95 Copa e Cozinha",Base!$A$2:$A$4835,B$4) | C45: =SUMIFS(Base!$N$2:$N$4835,Base!$B$2:$B$4835,"Uso e consumo",Base!$C$2:$C$4835,"2.04.95 Copa e Cozinha",Base!$A$2:$A$4835,C$4) | D45: =SUMIFS(Base!$N$2:$N$4835,Base!$B$2:$B$4835,"Uso e consumo",Base!$C$2:$C$4835,"2.04.95 Copa e Cozinha",Base!$A$2:$A$4835,D$4) | E45: =SUMIFS(Base!$N$2:$N$4835,Base!$B$2:$B$4835,"Uso e consumo",Base!$C$2:$C$4835,"2.04.95 Copa e Cozinha",Base!$A$2:$A$4835,E$4) | F45: =SUMIFS(Base!$N$2:$N$4835,Base!$B$2:$B$4835,"Uso e consumo",Base!$C$2:$C$4835,"2.04.95 Copa e Cozinha",Base!$A$2:$A$4835,F$4) | G45: =SUMIFS(Base!$N$2:$N$4835,Base!$B$2:$B$4835,"Uso e consumo",Base!$C$2:$C$4835,"2.04.95 Copa e Cozinha",Base!$A$2:$A$4835,G$4) | H45: =SUMIFS(Base!$N$2:$N$4835,Base!$B$2:$B$4835,"Uso e consumo",Base!$C$2:$C$4835,"2.04.95 Copa e Cozinha",Base!$A$2:$A$4835,H$4) | I45: =SUMIFS(Base!$N$2:$N$4835,Base!$B$2:$B$4835,"Uso e consumo",Base!$C$2:$C$4835,"2.04.95 Copa e Cozinha",Base!$A$2:$A$4835,I$4) | J45: =SUMIFS(Base!$N$2:$N$4835,Base!$B$2:$B$4835,"Uso e consumo",Base!$C$2:$C$4835,"2.04.95 Copa e Cozinha",Base!$A$2:$A$4835,J$4) | K45: =SUM(B45:J45) | L45: =AVERAGE(B45:J45) | M45: =MAX(B45:J45) | N45: =IF(M45=0,"",INDEX($B$4:$J$4,MATCH(M45,B45:J45,0)))
A46: 2.04.96 Bens de Pequeno Valor | B46: =SUMIFS(Base!$N$2:$N$4835,Base!$B$2:$B$4835,"Uso e consumo",Base!$C$2:$C$4835,"2.04.96 Bens de Pequeno Valor",Base!$A$2:$A$4835,B$4) | C46: =SUMIFS(Base!$N$2:$N$4835,Base!$B$2:$B$4835,"Uso e consumo",Base!$C$2:$C$4835,"2.04.96 Bens de Pequeno Valor",Base!$A$2:$A$4835,C$4) | D46: =SUMIFS(Base!$N$2:$N$4835,Base!$B$2:$B$4835,"Uso e consumo",Base!$C$2:$C$4835,"2.04.96 Bens de Pequeno Valor",Base!$A$2:$A$4835,D$4) | E46: =SUMIFS(Base!$N$2:$N$4835,Base!$B$2:$B$4835,"Uso e consumo",Base!$C$2:$C$4835,"2.04.96 Bens de Pequeno Valor",Base!$A$2:$A$4835,E$4) | F46: =SUMIFS(Base!$N$2:$N$4835,Base!$B$2:$B$4835,"Uso e consumo",Base!$C$2:$C$4835,"2.04.96 Bens de Pequeno Valor",Base!$A$2:$A$4835,F$4) | G46: =SUMIFS(Base!$N$2:$N$4835,Base!$B$2:$B$4835,"Uso e consumo",Base!$C$2:$C$4835,"2.04.96 Bens de Pequeno Valor",Base!$A$2:$A$4835,G$4) | H46: =SUMIFS(Base!$N$2:$N$4835,Base!$B$2:$B$4835,"Uso e consumo",Base!$C$2:$C$4835,"2.04.96 Bens de Pequeno Valor",Base!$A$2:$A$4835,H$4) | I46: =SUMIFS(Base!$N$2:$N$4835,Base!$B$2:$B$4835,"Uso e consumo",Base!$C$2:$C$4835,"2.04.96 Bens de Pequeno Valor",Base!$A$2:$A$4835,I$4) | J46: =SUMIFS(Base!$N$2:$N$4835,Base!$B$2:$B$4835,"Uso e consumo",Base!$C$2:$C$4835,"2.04.96 Bens de Pequeno Valor",Base!$A$2:$A$4835,J$4) | K46: =SUM(B46:J46) | L46: =AVERAGE(B46:J46) | M46: =MAX(B46:J46) | N46: =IF(M46=0,"",INDEX($B$4:$J$4,MATCH(M46,B46:J46,0)))
A47: Frete de compra
A48: Frete de compra | B48: =SUMIFS(Base!$N$2:$N$4835,Base!$B$2:$B$4835,"Frete de compra",Base!$C$2:$C$4835,"Frete de compra",Base!$A$2:$A$4835,B$4) | C48: =SUMIFS(Base!$N$2:$N$4835,Base!$B$2:$B$4835,"Frete de compra",Base!$C$2:$C$4835,"Frete de compra",Base!$A$2:$A$4835,C$4) | D48: =SUMIFS(Base!$N$2:$N$4835,Base!$B$2:$B$4835,"Frete de compra",Base!$C$2:$C$4835,"Frete de compra",Base!$A$2:$A$4835,D$4) | E48: =SUMIFS(Base!$N$2:$N$4835,Base!$B$2:$B$4835,"Frete de compra",Base!$C$2:$C$4835,"Frete de compra",Base!$A$2:$A$4835,E$4) | F48: =SUMIFS(Base!$N$2:$N$4835,Base!$B$2:$B$4835,"Frete de compra",Base!$C$2:$C$4835,"Frete de compra",Base!$A$2:$A$4835,F$4) | G48: =SUMIFS(Base!$N$2:$N$4835,Base!$B$2:$B$4835,"Frete de compra",Base!$C$2:$C$4835,"Frete de compra",Base!$A$2:$A$4835,G$4) | H48: =SUMIFS(Base!$N$2:$N$4835,Base!$B$2:$B$4835,"Frete de compra",Base!$C$2:$C$4835,"Frete de compra",Base!$A$2:$A$4835,H$4) | I48: =SUMIFS(Base!$N$2:$N$4835,Base!$B$2:$B$4835,"Frete de compra",Base!$C$2:$C$4835,"Frete de compra",Base!$A$2:$A$4835,I$4) | J48: =SUMIFS(Base!$N$2:$N$4835,Base!$B$2:$B$4835,"Frete de compra",Base!$C$2:$C$4835,"Frete de compra",Base!$A$2:$A$4835,J$4) | K48: =SUM(B48:J48) | L48: =AVERAGE(B48:J48) | M48: =MAX(B48:J48) | N48: =IF(M48=0,"",INDEX($B$4:$J$4,MATCH(M48,B48:J48,0)))
A49: Frete de venda
A50: Frete de venda (para clientes) | B50: =SUMIFS(Base!$N$2:$N$4835,Base!$B$2:$B$4835,"Frete de venda",Base!$C$2:$C$4835,"Frete de venda (para clientes)",Base!$A$2:$A$4835,B$4) | C50: =SUMIFS(Base!$N$2:$N$4835,Base!$B$2:$B$4835,"Frete de venda",Base!$C$2:$C$4835,"Frete de venda (para clientes)",Base!$A$2:$A$4835,C$4) | D50: =SUMIFS(Base!$N$2:$N$4835,Base!$B$2:$B$4835,"Frete de venda",Base!$C$2:$C$4835,"Frete de venda (para clientes)",Base!$A$2:$A$4835,D$4) | E50: =SUMIFS(Base!$N$2:$N$4835,Base!$B$2:$B$4835,"Frete de venda",Base!$C$2:$C$4835,"Frete de venda (para clientes)",Base!$A$2:$A$4835,E$4) | F50: =SUMIFS(Base!$N$2:$N$4835,Base!$B$2:$B$4835,"Frete de venda",Base!$C$2:$C$4835,"Frete de venda (para clientes)",Base!$A$2:$A$4835,F$4) | G50: =SUMIFS(Base!$N$2:$N$4835,Base!$B$2:$B$4835,"Frete de venda",Base!$C$2:$C$4835,"Frete de venda (para clientes)",Base!$A$2:$A$4835,G$4) | H50: =SUMIFS(Base!$N$2:$N$4835,Base!$B$2:$B$4835,"Frete de venda",Base!$C$2:$C$4835,"Frete de venda (para clientes)",Base!$A$2:$A$4835,H$4) | I50: =SUMIFS(Base!$N$2:$N$4835,Base!$B$2:$B$4835,"Frete de venda",Base!$C$2:$C$4835,"Frete de venda (para clientes)",Base!$A$2:$A$4835,I$4) | J50: =SUMIFS(Base!$N$2:$N$4835,Base!$B$2:$B$4835,"Frete de venda",Base!$C$2:$C$4835,"Frete de venda (para clientes)",Base!$A$2:$A$4835,J$4) | K50: =SUM(B50:J50) | L50: =AVERAGE(B50:J50) | M50: =MAX(B50:J50) | N50: =IF(M50=0,"",INDEX($B$4:$J$4,MATCH(M50,B50:J50,0)))
A52: Variação % vs mês anterior – categoria | B52: 46023 | C52: 46054 | D52: 46082 | E52: 46113 | F52: 46143 | G52: 46174 | H52: 46204 | I52: 46235 | J52: 46266 | K52: Total 2026 | L52: Média mensal | M52: Maior mês | N52: Mês do pico
A53: =A26 | C53: =IF(B26=0,"",C26/B26-1) | D53: =IF(C26=0,"",D26/C26-1) | E53: =IF(D26=0,"",E26/D26-1) | F53: =IF(E26=0,"",F26/E26-1) | G53: =IF(F26=0,"",G26/F26-1) | H53: =IF(G26=0,"",H26/G26-1) | I53: =IF(H26=0,"",I26/H26-1) | J53: =IF(I26=0,"",J26/I26-1)
A54: =A27 | C54: =IF(B27=0,"",C27/B27-1) | D54: =IF(C27=0,"",D27/C27-1) | E54: =IF(D27=0,"",E27/D27-1) | F54: =IF(E27=0,"",F27/E27-1) | G54: =IF(F27=0,"",G27/F27-1) | H54: =IF(G27=0,"",H27/G27-1) | I54: =IF(H27=0,"",I27/H27-1) | J54: =IF(I27=0,"",J27/I27-1)
A55: =A28 | C55: =IF(B28=0,"",C28/B28-1) | D55: =IF(C28=0,"",D28/C28-1) | E55: =IF(D28=0,"",E28/D28-1) | F55: =IF(E28=0,"",F28/E28-1) | G55: =IF(F28=0,"",G28/F28-1) | H55: =IF(G28=0,"",H28/G28-1) | I55: =IF(H28=0,"",I28/H28-1) | J55: =IF(I28=0,"",J28/I28-1)
A56: =A29 | C56: =IF(B29=0,"",C29/B29-1) | D56: =IF(C29=0,"",D29/C29-1) | E56: =IF(D29=0,"",E29/D29-1) | F56: =IF(E29=0,"",F29/E29-1) | G56: =IF(F29=0,"",G29/F29-1) | H56: =IF(G29=0,"",H29/G29-1) | I56: =IF(H29=0,"",I29/H29-1) | J56: =IF(I29=0,"",J29/I29-1)
A57: =A30 | C57: =IF(B30=0,"",C30/B30-1) | D57: =IF(C30=0,"",D30/C30-1) | E57: =IF(D30=0,"",E30/D30-1) | F57: =IF(E30=0,"",F30/E30-1) | G57: =IF(F30=0,"",G30/F30-1) | H57: =IF(G30=0,"",H30/G30-1) | I57: =IF(H30=0,"",I30/H30-1) | J57: =IF(I30=0,"",J30/I30-1)
A58: =A31 | C58: =IF(B31=0,"",C31/B31-1) | D58: =IF(C31=0,"",D31/C31-1) | E58: =IF(D31=0,"",E31/D31-1) | F58: =IF(E31=0,"",F31/E31-1) | G58: =IF(F31=0,"",G31/F31-1) | H58: =IF(G31=0,"",H31/G31-1) | I58: =IF(H31=0,"",I31/H31-1) | J58: =IF(I31=0,"",J31/I31-1)
A59: =A32 | C59: =IF(B32=0,"",C32/B32-1) | D59: =IF(C32=0,"",D32/C32-1) | E59: =IF(D32=0,"",E32/D32-1) | F59: =IF(E32=0,"",F32/E32-1) | G59: =IF(F32=0,"",G32/F32-1) | H59: =IF(G32=0,"",H32/G32-1) | I59: =IF(H32=0,"",I32/H32-1) | J59: =IF(I32=0,"",J32/I32-1)
A60: =A33 | C60: =IF(B33=0,"",C33/B33-1) | D60: =IF(C33=0,"",D33/C33-1) | E60: =IF(D33=0,"",E33/D33-1) | F60: =IF(E33=0,"",F33/E33-1) | G60: =IF(F33=0,"",G33/F33-1) | H60: =IF(G33=0,"",H33/G33-1) | I60: =IF(H33=0,"",I33/H33-1) | J60: =IF(I33=0,"",J33/I33-1)
A61: =A34 | C61: =IF(B34=0,"",C34/B34-1) | D61: =IF(C34=0,"",D34/C34-1) | E61: =IF(D34=0,"",E34/D34-1) | F61: =IF(E34=0,"",F34/E34-1) | G61: =IF(F34=0,"",G34/F34-1) | H61: =IF(G34=0,"",H34/G34-1) | I61: =IF(H34=0,"",I34/H34-1) | J61: =IF(I34=0,"",J34/I34-1)
A62: =A35 | C62: =IF(B35=0,"",C35/B35-1) | D62: =IF(C35=0,"",D35/C35-1) | E62: =IF(D35=0,"",E35/D35-1) | F62: =IF(E35=0,"",F35/E35-1) | G62: =IF(F35=0,"",G35/F35-1) | H62: =IF(G35=0,"",H35/G35-1) | I62: =IF(H35=0,"",I35/H35-1) | J62: =IF(I35=0,"",J35/I35-1)
A63: =A36 | C63: =IF(B36=0,"",C36/B36-1) | D63: =IF(C36=0,"",D36/C36-1) | E63: =IF(D36=0,"",E36/D36-1) | F63: =IF(E36=0,"",F36/E36-1) | G63: =IF(F36=0,"",G36/F36-1) | H63: =IF(G36=0,"",H36/G36-1) | I63: =IF(H36=0,"",I36/H36-1) | J63: =IF(I36=0,"",J36/I36-1)
A64: =A37 | C64: =IF(B37=0,"",C37/B37-1) | D64: =IF(C37=0,"",D37/C37-1) | E64: =IF(D37=0,"",E37/D37-1) | F64: =IF(E37=0,"",F37/E37-1) | G64: =IF(F37=0,"",G37/F37-1) | H64: =IF(G37=0,"",H37/G37-1) | I64: =IF(H37=0,"",I37/H37-1) | J64: =IF(I37=0,"",J37/I37-1)
A65: =A39 | C65: =IF(B39=0,"",C39/B39-1) | D65: =IF(C39=0,"",D39/C39-1) | E65: =IF(D39=0,"",E39/D39-1) | F65: =IF(E39=0,"",F39/E39-1) | G65: =IF(F39=0,"",G39/F39-1) | H65: =IF(G39=0,"",H39/G39-1) | I65: =IF(H39=0,"",I39/H39-1) | J65: =IF(I39=0,"",J39/I39-1)
A66: =A40 | C66: =IF(B40=0,"",C40/B40-1) | D66: =IF(C40=0,"",D40/C40-1) | E66: =IF(D40=0,"",E40/D40-1) | F66: =IF(E40=0,"",F40/E40-1) | G66: =IF(F40=0,"",G40/F40-1) | H66: =IF(G40=0,"",H40/G40-1) | I66: =IF(H40=0,"",I40/H40-1) | J66: =IF(I40=0,"",J40/I40-1)
A67: =A41 | C67: =IF(B41=0,"",C41/B41-1) | D67: =IF(C41=0,"",D41/C41-1) | E67: =IF(D41=0,"",E41/D41-1) | F67: =IF(E41=0,"",F41/E41-1) | G67: =IF(F41=0,"",G41/F41-1) | H67: =IF(G41=0,"",H41/G41-1) | I67: =IF(H41=0,"",I41/H41-1) | J67: =IF(I41=0,"",J41/I41-1)
A68: =A42 | C68: =IF(B42=0,"",C42/B42-1) | D68: =IF(C42=0,"",D42/C42-1) | E68: =IF(D42=0,"",E42/D42-1) | F68: =IF(E42=0,"",F42/E42-1) | G68: =IF(F42=0,"",G42/F42-1) | H68: =IF(G42=0,"",H42/G42-1) | I68: =IF(H42=0,"",I42/H42-1) | J68: =IF(I42=0,"",J42/I42-1)
A69: =A43 | C69: =IF(B43=0,"",C43/B43-1) | D69: =IF(C43=0,"",D43/C43-1) | E69: =IF(D43=0,"",E43/D43-1) | F69: =IF(E43=0,"",F43/E43-1) | G69: =IF(F43=0,"",G43/F43-1) | H69: =IF(G43=0,"",H43/G43-1) | I69: =IF(H43=0,"",I43/H43-1) | J69: =IF(I43=0,"",J43/I43-1)
A70: =A44 | C70: =IF(B44=0,"",C44/B44-1) | D70: =IF(C44=0,"",D44/C44-1) | E70: =IF(D44=0,"",E44/D44-1) | F70: =IF(E44=0,"",F44/E44-1) | G70: =IF(F44=0,"",G44/F44-1) | H70: =IF(G44=0,"",H44/G44-1) | I70: =IF(H44=0,"",I44/H44-1) | J70: =IF(I44=0,"",J44/I44-1)
A71: =A45 | C71: =IF(B45=0,"",C45/B45-1) | D71: =IF(C45=0,"",D45/C45-1) | E71: =IF(D45=0,"",E45/D45-1) | F71: =IF(E45=0,"",F45/E45-1) | G71: =IF(F45=0,"",G45/F45-1) | H71: =IF(G45=0,"",H45/G45-1) | I71: =IF(H45=0,"",I45/H45-1) | J71: =IF(I45=0,"",J45/I45-1)
A72: =A46 | C72: =IF(B46=0,"",C46/B46-1) | D72: =IF(C46=0,"",D46/C46-1) | E72: =IF(D46=0,"",E46/D46-1) | F72: =IF(E46=0,"",F46/E46-1) | G72: =IF(F46=0,"",G46/F46-1) | H72: =IF(G46=0,"",H46/G46-1) | I72: =IF(H46=0,"",I46/H46-1) | J72: =IF(I46=0,"",J46/I46-1)
A73: =A48 | C73: =IF(B48=0,"",C48/B48-1) | D73: =IF(C48=0,"",D48/C48-1) | E73: =IF(D48=0,"",E48/D48-1) | F73: =IF(E48=0,"",F48/E48-1) | G73: =IF(F48=0,"",G48/F48-1) | H73: =IF(G48=0,"",H48/G48-1) | I73: =IF(H48=0,"",I48/H48-1) | J73: =IF(I48=0,"",J48/I48-1)
A74: =A50 | C74: =IF(B50=0,"",C50/B50-1) | D74: =IF(C50=0,"",D50/C50-1) | E74: =IF(D50=0,"",E50/D50-1) | F74: =IF(E50=0,"",F50/E50-1) | G74: =IF(F50=0,"",G50/F50-1) | H74: =IF(G50=0,"",H50/G50-1) | I74: =IF(H50=0,"",I50/H50-1) | J74: =IF(I50=0,"",J50/I50-1)

Sheet Por fornecedor
A1: Por fornecedor / transportadora – custo líquido 2026 (R$)
A4: Destino | B4: Fornecedor / Transportadora | C4: 46023 | D4: 46054 | E4: 46082 | F4: 46113 | G4: 46143 | H4: 46174 | I4: 46204 | J4: 46235 | K4: 46266 | L4: Total 2026 | M4: % do destino
A5: Insumos e papel | B5: CMPC Iguacu Embalagens Ltda | C5: =SUMIFS(Base!$N$2:$N$4835,Base!$B$2:$B$4835,$A5,Base!$F$2:$F$4835,$B5,Base!$A$2:$A$4835,C$4) | D5: =SUMIFS(Base!$N$2:$N$4835,Base!$B$2:$B$4835,$A5,Base!$F$2:$F$4835,$B5,Base!$A$2:$A$4835,D$4) | E5: =SUMIFS(Base!$N$2:$N$4835,Base!$B$2:$B$4835,$A5,Base!$F$2:$F$4835,$B5,Base!$A$2:$A$4835,E$4) | F5: =SUMIFS(Base!$N$2:$N$4835,Base!$B$2:$B$4835,$A5,Base!$F$2:$F$4835,$B5,Base!$A$2:$A$4835,F$4) | G5: =SUMIFS(Base!$N$2:$N$4835,Base!$B$2:$B$4835,$A5,Base!$F$2:$F$4835,$B5,Base!$A$2:$A$4835,G$4) | H5: =SUMIFS(Base!$N$2:$N$4835,Base!$B$2:$B$4835,$A5,Base!$F$2:$F$4835,$B5,Base!$A$2:$A$4835,H$4) | I5: =SUMIFS(Base!$N$2:$N$4835,Base!$B$2:$B$4835,$A5,Base!$F$2:$F$4835,$B5,Base!$A$2:$A$4835,I$4) | J5: =SUMIFS(Base!$N$2:$N$4835,Base!$B$2:$B$4835,$A5,Base!$F$2:$F$4835,$B5,Base!$A$2:$A$4835,J$4) | K5: =SUMIFS(Base!$N$2:$N$4835,Base!$B$2:$B$4835,$A5,Base!$F$2:$F$4835,$B5,Base!$A$2:$A$4835,K$4) | L5: =SUM(C5:K5) | M5: =IFERROR(L5/L$41,"")
A6: Insumos e papel | B6: NOVA CONPEL COMPANHIA NORDESTINA DE PAPEL LTDA | C6: =SUMIFS(Base!$N$2:$N$4835,Base!$B$2:$B$4835,$A6,Base!$F$2:$F$4835,$B6,Base!$A$2:$A$4835,C$4) | D6: =SUMIFS(Base!$N$2:$N$4835,Base!$B$2:$B$4835,$A6,Base!$F$2:$F$4835,$B6,Base!$A$2:$A$4835,D$4) | E6: =SUMIFS(Base!$N$2:$N$4835,Base!$B$2:$B$4835,$A6,Base!$F$2:$F$4835,$B6,Base!$A$2:$A$4835,E$4) | F6: =SUMIFS(Base!$N$2:$N$4835,Base!$B$2:$B$4835,$A6,Base!$F$2:$F$4835,$B6,Base!$A$2:$A$4835,F$4) | G6: =SUMIFS(Base!$N$2:$N$4835,Base!$B$2:$B$4835,$A6,Base!$F$2:$F$4835,$B6,Base!$A$2:$A$4835,G$4) | H6: =SUMIFS(Base!$N$2:$N$4835,Base!$B$2:$B$4835,$A6,Base!$F$2:$F$4835,$B6,Base!$A$2:$A$4835,H$4) | I6: =SUMIFS(Base!$N$2:$N$4835,Base!$B$2:$B$4835,$A6,Base!$F$2:$F$4835,$B6,Base!$A$2:$A$4835,I$4) | J6: =SUMIFS(Base!$N$2:$N$4835,Base!$B$2:$B$4835,$A6,Base!$F$2:$F$4835,$B6,Base!$A$2:$A$4835,J$4) | K6: =SUMIFS(Base!$N$2:$N$4835,Base!$B$2:$B$4835,$A6,Base!$F$2:$F$4835,$B6,Base!$A$2:$A$4835,K$4) | L6: =SUM(C6:K6) | M6: =IFERROR(L6/L$41,"")
A7: Insumos e papel | B7: COCELPA CIA DE CEL. E PAPEL DO PARANA SA | C7: =SUMIFS(Base!$N$2:$N$4835,Base!$B$2:$B$4835,$A7,Base!$F$2:$F$4835,$B7,Base!$A$2:$A$4835,C$4) | D7: =SUMIFS(Base!$N$2:$N$4835,Base!$B$2:$B$4835,$A7,Base!$F$2:$F$4835,$B7,Base!$A$2:$A$4835,D$4) | E7: =SUMIFS(Base!$N$2:$N$4835,Base!$B$2:$B$4835,$A7,Base!$F$2:$F$4835,$B7,Base!$A$2:$A$4835,E$4) | F7: =SUMIFS(Base!$N$2:$N$4835,Base!$B$2:$B$4835,$A7,Base!$F$2:$F$4835,$B7,Base!$A$2:$A$4835,F$4) | G7: =SUMIFS(Base!$N$2:$N$4835,Base!$B$2:$B$4835,$A7,Base!$F$2:$F$4835,$B7,Base!$A$2:$A$4835,G$4) | H7: =SUMIFS(Base!$N$2:$N$4835,Base!$B$2:$B$4835,$A7,Base!$F$2:$F$4835,$B7,Base!$A$2:$A$4835,H$4) | I7: =SUMIFS(Base!$N$2:$N$4835,Base!$B$2:$B$4835,$A7,Base!$F$2:$F$4835,$B7,Base!$A$2:$A$4835,I$4) | J7: =SUMIFS(Base!$N$2:$N$4835,Base!$B$2:$B$4835,$A7,Base!$F$2:$F$4835,$B7,Base!$A$2:$A$4835,J$4) | K7: =SUMIFS(Base!$N$2:$N$4835,Base!$B$2:$B$4835,$A7,Base!$F$2:$F$4835,$B7,Base!$A$2:$A$4835,K$4) | L7: =SUM(C7:K7) | M7: =IFERROR(L7/L$41,"")
A8: Insumos e papel | B8: COLAMID | C8: =SUMIFS(Base!$N$2:$N$4835,Base!$B$2:$B$4835,$A8,Base!$F$2:$F$4835,$B8,Base!$A$2:$A$4835,C$4) | D8: =SUMIFS(Base!$N$2:$N$4835,Base!$B$2:$B$4835,$A8,Base!$F$2:$F$4835,$B8,Base!$A$2:$A$4835,D$4) | E8: =SUMIFS(Base!$N$2:$N$4835,Base!$B$2:$B$4835,$A8,Base!$F$2:$F$4835,$B8,Base!$A$2:$A$4835,E$4) | F8: =SUMIFS(Base!$N$2:$N$4835,Base!$B$2:$B$4835,$A8,Base!$F$2:$F$4835,$B8,Base!$A$2:$A$4835,F$4) | G8: =SUMIFS(Base!$N$2:$N$4835,Base!$B$2:$B$4835,$A8,Base!$F$2:$F$4835,$B8,Base!$A$2:$A$4835,G$4) | H8: =SUMIFS(Base!$N$2:$N$4835,Base!$B$2:$B$4835,$A8,Base!$F$2:$F$4835,$B8,Base!$A$2:$A$4835,H$4) | I8: =SUMIFS(Base!$N$2:$N$4835,Base!$B$2:$B$4835,$A8,Base!$F$2:$F$4835,$B8,Base!$A$2:$A$4835,I$4) | J8: =SUMIFS(Base!$N$2:$N$4835,Base!$B$2:$B$4835,$A8,Base!$F$2:$F$4835,$B8,Base!$A$2:$A$4835,J$4) | K8: =SUMIFS(Base!$N$2:$N$4835,Base!$B$2:$B$4835,$A8,Base!$F$2:$F$4835,$B8,Base!$A$2:$A$4835,K$4) | L8: =SUM(C8:K8) | M8: =IFERROR(L8/L$41,"")
A9: Insumos e papel | B9: SANTA MARIA CIA DE PAPEL E CELULOSE | C9: =SUMIFS(Base!$N$2:$N$4835,Base!$B$2:$B$4835,$A9,Base!$F$2:$F$4835,$B9,Base!$A$2:$A$4835,C$4) | D9: =SUMIFS(Base!$N$2:$N$4835,Base!$B$2:$B$4835,$A9,Base!$F$2:$F$4835,$B9,Base!$A$2:$A$4835,D$4) | E9: =SUMIFS(Base!$N$2:$N$4835,Base!$B$2:$B$4835,$A9,Base!$F$2:$F$4835,$B9,Base!$A$2:$A$4835,E$4) | F9: =SUMIFS(Base!$N$2:$N$4835,Base!$B$2:$B$4835,$A9,Base!$F$2:$F$4835,$B9,Base!$A$2:$A$4835,F$4) | G9: =SUMIFS(Base!$N$2:$N$4835,Base!$B$2:$B$4835,$A9,Base!$F$2:$F$4835,$B9,Base!$A$2:$A$4835,G$4) | H9: =SUMIFS(Base!$N$2:$N$4835,Base!$B$2:$B$4835,$A9,Base!$F$2:$F$4835,$B9,Base!$A$2:$A$4835,H$4) | I9: =SUMIFS(Base!$N$2:$N$4835,Base!$B$2:$B$4835,$A9,Base!$F$2:$F$4835,$B9,Base!$A$2:$A$4835,I$4) | J9: =SUMIFS(Base!$N$2:$N$4835,Base!$B$2:$B$4835,$A9,Base!$F$2:$F$4835,$B9,Base!$A$2:$A$4835,J$4) | K9: =SUMIFS(Base!$N$2:$N$4835,Base!$B$2:$B$4835,$A9,Base!$F$2:$F$4835,$B9,Base!$A$2:$A$4835,K$4) | L9: =SUM(C9:K9) | M9: =IFERROR(L9/L$41,"")
A10: Insumos e papel | B10: ALSTEK SOLUCOES EM EMBALAGENS LTDA | C10: =SUMIFS(Base!$N$2:$N$4835,Base!$B$2:$B$4835,$A10,Base!$F$2:$F$4835,$B10,Base!$A$2:$A$4835,C$4) | D10: =SUMIFS(Base!$N$2:$N$4835,Base!$B$2:$B$4835,$A10,Base!$F$2:$F$4835,$B10,Base!$A$2:$A$4835,D$4) | E10: =SUMIFS(Base!$N$2:$N$4835,Base!$B$2:$B$4835,$A10,Base!$F$2:$F$4835,$B10,Base!$A$2:$A$4835,E$4) | F10: =SUMIFS(Base!$N$2:$N$4835,Base!$B$2:$B$4835,$A10,Base!$F$2:$F$4835,$B10,Base!$A$2:$A$4835,F$4) | G10: =SUMIFS(Base!$N$2:$N$4835,Base!$B$2:$B$4835,$A10,Base!$F$2:$F$4835,$B10,Base!$A$2:$A$4835,G$4) | H10: =SUMIFS(Base!$N$2:$N$4835,Base!$B$2:$B$4835,$A10,Base!$F$2:$F$4835,$B10,Base!$A$2:$A$4835,H$4) | I10: =SUMIFS(Base!$N$2:$N$4835,Base!$B$2:$B$4835,$A10,Base!$F$2:$F$4835,$B10,Base!$A$2:$A$4835,I$4) | J10: =SUMIFS(Base!$N$2:$N$4835,Base!$B$2:$B$4835,$A10,Base!$F$2:$F$4835,$B10,Base!$A$2:$A$4835,J$4) | K10: =SUMIFS(Base!$N$2:$N$4835,Base!$B$2:$B$4835,$A10,Base!$F$2:$F$4835,$B10,Base!$A$2:$A$4835,K$4) | L10: =SUM(C10:K10) | M10: =IFERROR(L10/L$41,"")
A11: Insumos e papel | B11: REQUIM PRODUTOS QUIMICOS LTDA | C11: =SUMIFS(Base!$N$2:$N$4835,Base!$B$2:$B$4835,$A11,Base!$F$2:$F$4835,$B11,Base!$A$2:$A$4835,C$4) | D11: =SUMIFS(Base!$N$2:$N$4835,Base!$B$2:$B$4835,$A11,Base!$F$2:$F$4835,$B11,Base!$A$2:$A$4835,D$4) | E11: =SUMIFS(Base!$N$2:$N$4835,Base!$B$2:$B$4835,$A11,Base!$F$2:$F$4835,$B11,Base!$A$2:$A$4835,E$4) | F11: =SUMIFS(Base!$N$2:$N$4835,Base!$B$2:$B$4835,$A11,Base!$F$2:$F$4835,$B11,Base!$A$2:$A$4835,F$4) | G11: =SUMIFS(Base!$N$2:$N$4835,Base!$B$2:$B$4835,$A11,Base!$F$2:$F$4835,$B11,Base!$A$2:$A$4835,G$4) | H11: =SUMIFS(Base!$N$2:$N$4835,Base!$B$2:$B$4835,$A11,Base!$F$2:$F$4835,$B11,Base!$A$2:$A$4835,H$4) | I11: =SUMIFS(Base!$N$2:$N$4835,Base!$B$2:$B$4835,$A11,Base!$F$2:$F$4835,$B11,Base!$A$2:$A$4835,I$4) | J11: =SUMIFS(Base!$N$2:$N$4835,Base!$B$2:$B$4835,$A11,Base!$F$2:$F$4835,$B11,Base!$A$2:$A$4835,J$4) | K11: =SUMIFS(Base!$N$2:$N$4835,Base!$B$2:$B$4835,$A11,Base!$F$2:$F$4835,$B11,Base!$A$2:$A$4835,K$4) | L11: =SUM(C11:K11) | M11: =IFERROR(L11/L$41,"")
A12: Insumos e papel | B12: IRANI PAPEL E EMBALAGEM S.A. | C12: =SUMIFS(Base!$N$2:$N$4835,Base!$B$2:$B$4835,$A12,Base!$F$2:$F$4835,$B12,Base!$A$2:$A$4835,C$4) | D12: =SUMIFS(Base!$N$2:$N$4835,Base!$B$2:$B$4835,$A12,Base!$F$2:$F$4835,$B12,Base!$A$2:$A$4835,D$4) | E12: =SUMIFS(Base!$N$2:$N$4835,Base!$B$2:$B$4835,$A12,Base!$F$2:$F$4835,$B12,Base!$A$2:$A$4835,E$4) | F12: =SUMIFS(Base!$N$2:$N$4835,Base!$B$2:$B$4835,$A12,Base!$F$2:$F$4835,$B12,Base!$A$2:$A$4835,F$4) | G12: =SUMIFS(Base!$N$2:$N$4835,Base!$B$2:$B$4835,$A12,Base!$F$2:$F$4835,$B12,Base!$A$2:$A$4835,G$4) | H12: =SUMIFS(Base!$N$2:$N$4835,Base!$B$2:$B$4835,$A12,Base!$F$2:$F$4835,$B12,Base!$A$2:$A$4835,H$4) | I12: =SUMIFS(Base!$N$2:$N$4835,Base!$B$2:$B$4835,$A12,Base!$F$2:$F$4835,$B12,Base!$A$2:$A$4835,I$4) | J12: =SUMIFS(Base!$N$2:$N$4835,Base!$B$2:$B$4835,$A12,Base!$F$2:$F$4835,$B12,Base!$A$2:$A$4835,J$4) | K12: =SUMIFS(Base!$N$2:$N$4835,Base!$B$2:$B$4835,$A12,Base!$F$2:$F$4835,$B12,Base!$A$2:$A$4835,K$4) | L12: =SUM(C12:K12) | M12: =IFERROR(L12/L$41,"")
A13: Insumos e papel | B13: FITTYCOR - INDUSTRIA E COMERCIO DE TINTAS ESPECIAIS LTDA | C13: =SUMIFS(Base!$N$2:$N$4835,Base!$B$2:$B$4835,$A13,Base!$F$2:$F$4835,$B13,Base!$A$2:$A$4835,C$4) | D13: =SUMIFS(Base!$N$2:$N$4835,Base!$B$2:$B$4835,$A13,Base!$F$2:$F$4835,$B13,Base!$A$2:$A$4835,D$4) | E13: =SUMIFS(Base!$N$2:$N$4835,Base!$B$2:$B$4835,$A13,Base!$F$2:$F$4835,$B13,Base!$A$2:$A$4835,E$4) | F13: =SUMIFS(Base!$N$2:$N$4835,Base!$B$2:$B$4835,$A13,Base!$F$2:$F$4835,$B13,Base!$A$2:$A$4835,F$4) | G13: =SUMIFS(Base!$N$2:$N$4835,Base!$B$2:$B$4835,$A13,Base!$F$2:$F$4835,$B13,Base!$A$2:$A$4835,G$4) | H13: =SUMIFS(Base!$N$2:$N$4835,Base!$B$2:$B$4835,$A13,Base!$F$2:$F$4835,$B13,Base!$A$2:$A$4835,H$4) | I13: =SUMIFS(Base!$N$2:$N$4835,Base!$B$2:$B$4835,$A13,Base!$F$2:$F$4835,$B13,Base!$A$2:$A$4835,I$4) | J13: =SUMIFS(Base!$N$2:$N$4835,Base!$B$2:$B$4835,$A13,Base!$F$2:$F$4835,$B13,Base!$A$2:$A$4835,J$4) | K13: =SUMIFS(Base!$N$2:$N$4835,Base!$B$2:$B$4835,$A13,Base!$F$2:$F$4835,$B13,Base!$A$2:$A$4835,K$4) | L13: =SUM(C13:K13) | M13: =IFERROR(L13/L$41,"")
A14: Insumos e papel | B14: BR EMBALAGENS INDUSTRIA E COMERCIO LTDA | C14: =SUMIFS(Base!$N$2:$N$4835,Base!$B$2:$B$4835,$A14,Base!$F$2:$F$4835,$B14,Base!$A$2:$A$4835,C$4) | D14: =SUMIFS(Base!$N$2:$N$4835,Base!$B$2:$B$4835,$A14,Base!$F$2:$F$4835,$B14,Base!$A$2:$A$4835,D$4) | E14: =SUMIFS(Base!$N$2:$N$4835,Base!$B$2:$B$4835,$A14,Base!$F$2:$F$4835,$B14,Base!$A$2:$A$4835,E$4) | F14: =SUMIFS(Base!$N$2:$N$4835,Base!$B$2:$B$4835,$A14,Base!$F$2:$F$4835,$B14,Base!$A$2:$A$4835,F$4) | G14: =SUMIFS(Base!$N$2:$N$4835,Base!$B$2:$B$4835,$A14,Base!$F$2:$F$4835,$B14,Base!$A$2:$A$4835,G$4) | H14: =SUMIFS(Base!$N$2:$N$4835,Base!$B$2:$B$4835,$A14,Base!$F$2:$F$4835,$B14,Base!$A$2:$A$4835,H$4) | I14: =SUMIFS(Base!$N$2:$N$4835,Base!$B$2:$B$4835,$A14,Base!$F$2:$F$4835,$B14,Base!$A$2:$A$4835,I$4) | J14: =SUMIFS(Base!$N$2:$N$4835,Base!$B$2:$B$4835,$A14,Base!$F$2:$F$4835,$B14,Base!$A$2:$A$4835,J$4) | K14: =SUMIFS(Base!$N$2:$N$4835,Base!$B$2:$B$4835,$A14,Base!$F$2:$F$4835,$B14,Base!$A$2:$A$4835,K$4) | L14: =SUM(C14:K14) | M14: =IFERROR(L14/L$41,"")
A15: Insumos e papel | B15: GDM INDUSTRIA E COMERCIO DE PLASTICOS LTDA. | C15: =SUMIFS(Base!$N$2:$N$4835,Base!$B$2:$B$4835,$A15,Base!$F$2:$F$4835,$B15,Base!$A$2:$A$4835,C$4) | D15: =SUMIFS(Base!$N$2:$N$4835,Base!$B$2:$B$4835,$A15,Base!$F$2:$F$4835,$B15,Base!$A$2:$A$4835,D$4) | E15: =SUMIFS(Base!$N$2:$N$4835,Base!$B$2:$B$4835,$A15,Base!$F$2:$F$4835,$B15,Base!$A$2:$A$4835,E$4) | F15: =SUMIFS(Base!$N$2:$N$4835,Base!$B$2:$B$4835,$A15,Base!$F$2:$F$4835,$B15,Base!$A$2:$A$4835,F$4) | G15: =SUMIFS(Base!$N$2:$N$4835,Base!$B$2:$B$4835,$A15,Base!$F$2:$F$4835,$B15,Base!$A$2:$A$4835,G$4) | H15: =SUMIFS(Base!$N$2:$N$4835,Base!$B$2:$B$4835,$A15,Base!$F$2:$F$4835,$B15,Base!$A$2:$A$4835,H$4) | I15: =SUMIFS(Base!$N$2:$N$4835,Base!$B$2:$B$4835,$A15,Base!$F$2:$F$4835,$B15,Base!$A$2:$A$4835,I$4) | J15: =SUMIFS(Base!$N$2:$N$4835,Base!$B$2:$B$4835,$A15,Base!$F$2:$F$4835,$B15,Base!$A$2:$A$4835,J$4) | K15: =SUMIFS(Base!$N$2:$N$4835,Base!$B$2:$B$4835,$A15,Base!$F$2:$F$4835,$B15,Base!$A$2:$A$4835,K$4) | L15: =SUM(C15:K15) | M15: =IFERROR(L15/L$41,"")
A16: Insumos e papel | B16: ANIN INDUSTRIA E COMERCIO DE PAPEL LTDA | C16: =SUMIFS(Base!$N$2:$N$4835,Base!$B$2:$B$4835,$A16,Base!$F$2:$F$4835,$B16,Base!$A$2:$A$4835,C$4) | D16: =SUMIFS(Base!$N$2:$N$4835,Base!$B$2:$B$4835,$A16,Base!$F$2:$F$4835,$B16,Base!$A$2:$A$4835,D$4) | E16: =SUMIFS(Base!$N$2:$N$4835,Base!$B$2:$B$4835,$A16,Base!$F$2:$F$4835,$B16,Base!$A$2:$A$4835,E$4) | F16: =SUMIFS(Base!$N$2:$N$4835,Base!$B$2:$B$4835,$A16,Base!$F$2:$F$4835,$B16,Base!$A$2:$A$4835,F$4) | G16: =SUMIFS(Base!$N$2:$N$4835,Base!$B$2:$B$4835,$A16,Base!$F$2:$F$4835,$B16,Base!$A$2:$A$4835,G$4) | H16: =SUMIFS(Base!$N$2:$N$4835,Base!$B$2:$B$4835,$A16,Base!$F$2:$F$4835,$B16,Base!$A$2:$A$4835,H$4) | I16: =SUMIFS(Base!$N$2:$N$4835,Base!$B$2:$B$4835,$A16,Base!$F$2:$F$4835,$B16,Base!$A$2:$A$4835,I$4) | J16: =SUMIFS(Base!$N$2:$N$4835,Base!$B$2:$B$4835,$A16,Base!$F$2:$F$4835,$B16,Base!$A$2:$A$4835,J$4) | K16: =SUMIFS(Base!$N$2:$N$4835,Base!$B$2:$B$4835,$A16,Base!$F$2:$F$4835,$B16,Base!$A$2:$A$4835,K$4) | L16: =SUM(C16:K16) | M16: =IFERROR(L16/L$41,"")
... A40: Insumos e papel | B40: INFORPOINT SERVICOS E COMERCIO EM TECNOLOGIA LTDA | C40: =SUMIFS(Base!$N$2:$N$4835,Base!$B$2:$B$4835,$A40,Base!$F$2:$F$4835,$B40,Base!$A$2:$A$4835,C$4) | D40: =SUMIFS(Base!$N$2:$N$4835,Base!$B$2:$B$4835,$A40,Base!$F$2:$F$4835,$B40,Base!$A$2:$A$4835,D$4) | E40: =SUMIFS(Base!$N$2:$N$4835,Base!$B$2:$B$4835,$A40,Base!$F$2:$F$4835,$B40,Base!$A$2:$A$4835,E$4) | F40: =SUMIFS(Base!$N$2:$N$4835,Base!$B$2:$B$4835,$A40,Base!$F$2:$F$4835,$B40,Base!$A$2:$A$4835,F$4) | G40: =SUMIFS(Base!$N$2:$N$4835,Base!$B$2:$B$4835,$A40,Base!$F$2:$F$4835,$B40,Base!$A$2:$A$4835,G$4) | H40: =SUMIFS(Base!$N$2:$N$4835,Base!$B$2:$B$4835,$A40,Base!$F$2:$F$4835,$B40,Base!$A$2:$A$4835,H$4) | I40: =SUMIFS(Base!$N$2:$N$4835,Base!$B$2:$B$4835,$A40,Base!$F$2:$F$4835,$B40,Base!$A$2:$A$4835,I$4) | J40: =SUMIFS(Base!$N$2:$N$4835,Base!$B$2:$B$4835,$A40,Base!$F$2:$F$4835,$B40,Base!$A$2:$A$4835,J$4) | K40: =SUMIFS(Base!$N$2:$N$4835,Base!$B$2:$B$4835,$A40,Base!$F$2:$F$4835,$B40,Base!$A$2:$A$4835,K$4) | L40: =SUM(C40:K40) | M40: =IFERROR(L40/L$41,"")
A41: Insumos e papel | B41: TOTAL Insumos e papel | C41: =SUM(C5:C40) | D41: =SUM(D5:D40) | E41: =SUM(E5:E40) | F41: =SUM(F5:F40) | G41: =SUM(G5:G40) | H41: =SUM(H5:H40) | I41: =SUM(I5:I40) | J41: =SUM(J5:J40) | ... L41: =SUM(L5:L40)
A43: Uso e consumo | B43: FURNAX COMERCIAL E IMPORTADORA EIRELI | C43: =SUMIFS(Base!$N$2:$N$4835,Base!$B$2:$B$4835,$A43,Base!$F$2:$F$4835,$B43,Base!$A$2:$A$4835,C$4) | D43: =SUMIFS(Base!$N$2:$N$4835,Base!$B$2:$B$4835,$A43,Base!$F$2:$F$4835,$B43,Base!$A$2:$A$4835,D$4) | E43: =SUMIFS(Base!$N$2:$N$4835,Base!$B$2:$B$4835,$A43,Base!$F$2:$F$4835,$B43,Base!$A$2:$A$4835,E$4) | F43: =SUMIFS(Base!$N$2:$N$4835,Base!$B$2:$B$4835,$A43,Base!$F$2:$F$4835,$B43,Base!$A$2:$A$4835,F$4) | G43: =SUMIFS(Base!$N$2:$N$4835,Base!$B$2:$B$4835,$A43,Base!$F$2:$F$4835,$B43,Base!$A$2:$A$4835,G$4) | H43: =SUMIFS(Base!$N$2:$N$4835,Base!$B$2:$B$4835,$A43,Base!$F$2:$F$4835,$B43,Base!$A$2:$A$4835,H$4) | I43: =SUMIFS(Base!$N$2:$N$4835,Base!$B$2:$B$4835,$A43,Base!$F$2:$F$4835,$B43,Base!$A$2:$A$4835,I$4) | J43: =SUMIFS(Base!$N$2:$N$4835,Base!$B$2:$B$4835,$A43,Base!$F$2:$F$4835,$B43,Base!$A$2:$A$4835,J$4) | K43: =SUMIFS(Base!$N$2:$N$4835,Base!$B$2:$B$4835,$A43,Base!$F$2:$F$4835,$B43,Base!$A$2:$A$4835,K$4) | L43: =SUM(C43:K43) | M43: =IFERROR(L43/L$123,"")
A44: Uso e consumo | B44: Limptech Paper Comercio Ltda | C44: =SUMIFS(Base!$N$2:$N$4835,Base!$B$2:$B$4835,$A44,Base!$F$2:$F$4835,$B44,Base!$A$2:$A$4835,C$4) | D44: =SUMIFS(Base!$N$2:$N$4835,Base!$B$2:$B$4835,$A44,Base!$F$2:$F$4835,$B44,Base!$A$2:$A$4835,D$4) | E44: =SUMIFS(Base!$N$2:$N$4835,Base!$B$2:$B$4835,$A44,Base!$F$2:$F$4835,$B44,Base!$A$2:$A$4835,E$4) | F44: =SUMIFS(Base!$N$2:$N$4835,Base!$B$2:$B$4835,$A44,Base!$F$2:$F$4835,$B44,Base!$A$2:$A$4835,F$4) | G44: =SUMIFS(Base!$N$2:$N$4835,Base!$B$2:$B$4835,$A44,Base!$F$2:$F$4835,$B44,Base!$A$2:$A$4835,G$4) | H44: =SUMIFS(Base!$N$2:$N$4835,Base!$B$2:$B$4835,$A44,Base!$F$2:$F$4835,$B44,Base!$A$2:$A$4835,H$4) | I44: =SUMIFS(Base!$N$2:$N$4835,Base!$B$2:$B$4835,$A44,Base!$F$2:$F$4835,$B44,Base!$A$2:$A$4835,I$4) | J44: =SUMIFS(Base!$N$2:$N$4835,Base!$B$2:$B$4835,$A44,Base!$F$2:$F$4835,$B44,Base!$A$2:$A$4835,J$4) | K44: =SUMIFS(Base!$N$2:$N$4835,Base!$B$2:$B$4835,$A44,Base!$F$2:$F$4835,$B44,Base!$A$2:$A$4835,K$4) | L44: =SUM(C44:K44) | M44: =IFERROR(L44/L$123,"")
A45: Uso e consumo | B45: R M FARDAMENTOS LTDA | C45: =SUMIFS(Base!$N$2:$N$4835,Base!$B$2:$B$4835,$A45,Base!$F$2:$F$4835,$B45,Base!$A$2:$A$4835,C$4) | D45: =SUMIFS(Base!$N$2:$N$4835,Base!$B$2:$B$4835,$A45,Base!$F$2:$F$4835,$B45,Base!$A$2:$A$4835,D$4) | E45: =SUMIFS(Base!$N$2:$N$4835,Base!$B$2:$B$4835,$A45,Base!$F$2:$F$4835,$B45,Base!$A$2:$A$4835,E$4) | F45: =SUMIFS(Base!$N$2:$N$4835,Base!$B$2:$B$4835,$A45,Base!$F$2:$F$4835,$B45,Base!$A$2:$A$4835,F$4) | G45: =SUMIFS(Base!$N$2:$N$4835,Base!$B$2:$B$4835,$A45,Base!$F$2:$F$4835,$B45,Base!$A$2:$A$4835,G$4) | H45: =SUMIFS(Base!$N$2:$N$4835,Base!$B$2:$B$4835,$A45,Base!$F$2:$F$4835,$B45,Base!$A$2:$A$4835,H$4) | I45: =SUMIFS(Base!$N$2:$N$4835,Base!$B$2:$B$4835,$A45,Base!$F$2:$F$4835,$B45,Base!$A$2:$A$4835,I$4) | J45: =SUMIFS(Base!$N$2:$N$4835,Base!$B$2:$B$4835,$A45,Base!$F$2:$F$4835,$B45,Base!$A$2:$A$4835,J$4) | K45: =SUMIFS(Base!$N$2:$N$4835,Base!$B$2:$B$4835,$A45,Base!$F$2:$F$4835,$B45,Base!$A$2:$A$4835,K$4) | L45: =SUM(C45:K45) | M45: =IFERROR(L45/L$123,"")
A46: Uso e consumo | B46: PERNAMBUCO DISTRIBUIDORA ATAC EPIS, INS IND e MRO LTDA | C46: =SUMIFS(Base!$N$2:$N$4835,Base!$B$2:$B$4835,$A46,Base!$F$2:$F$4835,$B46,Base!$A$2:$A$4835,C$4) | D46: =SUMIFS(Base!$N$2:$N$4835,Base!$B$2:$B$4835,$A46,Base!$F$2:$F$4835,$B46,Base!$A$2:$A$4835,D$4) | E46: =SUMIFS(Base!$N$2:$N$4835,Base!$B$2:$B$4835,$A46,Base!$F$2:$F$4835,$B46,Base!$A$2:$A$4835,E$4) | F46: =SUMIFS(Base!$N$2:$N$4835,Base!$B$2:$B$4835,$A46,Base!$F$2:$F$4835,$B46,Base!$A$2:$A$4835,F$4) | G46: =SUMIFS(Base!$N$2:$N$4835,Base!$B$2:$B$4835,$A46,Base!$F$2:$F$4835,$B46,Base!$A$2:$A$4835,G$4) | H46: =SUMIFS(Base!$N$2:$N$4835,Base!$B$2:$B$4835,$A46,Base!$F$2:$F$4835,$B46,Base!$A$2:$A$4835,H$4) | I46: =SUMIFS(Base!$N$2:$N$4835,Base!$B$2:$B$4835,$A46,Base!$F$2:$F$4835,$B46,Base!$A$2:$A$4835,I$4) | J46: =SUMIFS(Base!$N$2:$N$4835,Base!$B$2:$B$4835,$A46,Base!$F$2:$F$4835,$B46,Base!$A$2:$A$4835,J$4) | K46: =SUMIFS(Base!$N$2:$N$4835,Base!$B$2:$B$4835,$A46,Base!$F$2:$F$4835,$B46,Base!$A$2:$A$4835,K$4) | L46: =SUM(C46:K46) | M46: =IFERROR(L46/L$123,"")
A47: Uso e consumo | B47: ELETROPOLO ELETRICIDADE LTDA | C47: =SUMIFS(Base!$N$2:$N$4835,Base!$B$2:$B$4835,$A47,Base!$F$2:$F$4835,$B47,Base!$A$2:$A$4835,C$4) | D47: =SUMIFS(Base!$N$2:$N$4835,Base!$B$2:$B$4835,$A47,Base!$F$2:$F$4835,$B47,Base!$A$2:$A$4835,D$4) | E47: =SUMIFS(Base!$N$2:$N$4835,Base!$B$2:$B$4835,$A47,Base!$F$2:$F$4835,$B47,Base!$A$2:$A$4835,E$4) | F47: =SUMIFS(Base!$N$2:$N$4835,Base!$B$2:$B$4835,$A47,Base!$F$2:$F$4835,$B47,Base!$A$2:$A$4835,F$4) | G47: =SUMIFS(Base!$N$2:$N$4835,Base!$B$2:$B$4835,$A47,Base!$F$2:$F$4835,$B47,Base!$A$2:$A$4835,G$4) | H47: =SUMIFS(Base!$N$2:$N$4835,Base!$B$2:$B$4835,$A47,Base!$F$2:$F$4835,$B47,Base!$A$2:$A$4835,H$4) | I47: =SUMIFS(Base!$N$2:$N$4835,Base!$B$2:$B$4835,$A47,Base!$F$2:$F$4835,$B47,Base!$A$2:$A$4835,I$4) | J47: =SUMIFS(Base!$N$2:$N$4835,Base!$B$2:$B$4835,$A47,Base!$F$2:$F$4835,$B47,Base!$A$2:$A$4835,J$4) | K47: =SUMIFS(Base!$N$2:$N$4835,Base!$B$2:$B$4835,$A47,Base!$F$2:$F$4835,$B47,Base!$A$2:$A$4835,K$4) | L47: =SUM(C47:K47) | M47: =IFERROR(L47/L$123,"")
A48: Uso e consumo | B48: FERGE COMERCIO DE PRODUTOS INDUSTRIAIS LTDA | C48: =SUMIFS(Base!$N$2:$N$4835,Base!$B$2:$B$4835,$A48,Base!$F$2:$F$4835,$B48,Base!$A$2:$A$4835,C$4) | D48: =SUMIFS(Base!$N$2:$N$4835,Base!$B$2:$B$4835,$A48,Base!$F$2:$F$4835,$B48,Base!$A$2:$A$4835,D$4) | E48: =SUMIFS(Base!$N$2:$N$4835,Base!$B$2:$B$4835,$A48,Base!$F$2:$F$4835,$B48,Base!$A$2:$A$4835,E$4) | F48: =SUMIFS(Base!$N$2:$N$4835,Base!$B$2:$B$4835,$A48,Base!$F$2:$F$4835,$B48,Base!$A$2:$A$4835,F$4) | G48: =SUMIFS(Base!$N$2:$N$4835,Base!$B$2:$B$4835,$A48,Base!$F$2:$F$4835,$B48,Base!$A$2:$A$4835,G$4) | H48: =SUMIFS(Base!$N$2:$N$4835,Base!$B$2:$B$4835,$A48,Base!$F$2:$F$4835,$B48,Base!$A$2:$A$4835,H$4) | I48: =SUMIFS(Base!$N$2:$N$4835,Base!$B$2:$B$4835,$A48,Base!$F$2:$F$4835,$B48,Base!$A$2:$A$4835,I$4) | J48: =SUMIFS(Base!$N$2:$N$4835,Base!$B$2:$B$4835,$A48,Base!$F$2:$F$4835,$B48,Base!$A$2:$A$4835,J$4) | K48: =SUMIFS(Base!$N$2:$N$4835,Base!$B$2:$B$4835,$A48,Base!$F$2:$F$4835,$B48,Base!$A$2:$A$4835,K$4) | L48: =SUM(C48:K48) | M48: =IFERROR(L48/L$123,"")
A49: Uso e consumo | B49: GF COMERCIO DE PRODUTOS INDUSTRIAIS LTDA | C49: =SUMIFS(Base!$N$2:$N$4835,Base!$B$2:$B$4835,$A49,Base!$F$2:$F$4835,$B49,Base!$A$2:$A$4835,C$4) | D49: =SUMIFS(Base!$N$2:$N$4835,Base!$B$2:$B$4835,$A49,Base!$F$2:$F$4835,$B49,Base!$A$2:$A$4835,D$4) | E49: =SUMIFS(Base!$N$2:$N$4835,Base!$B$2:$B$4835,$A49,Base!$F$2:$F$4835,$B49,Base!$A$2:$A$4835,E$4) | F49: =SUMIFS(Base!$N$2:$N$4835,Base!$B$2:$B$4835,$A49,Base!$F$2:$F$4835,$B49,Base!$A$2:$A$4835,F$4) | G49: =SUMIFS(Base!$N$2:$N$4835,Base!$B$2:$B$4835,$A49,Base!$F$2:$F$4835,$B49,Base!$A$2:$A$4835,G$4) | H49: =SUMIFS(Base!$N$2:$N$4835,Base!$B$2:$B$4835,$A49,Base!$F$2:$F$4835,$B49,Base!$A$2:$A$4835,H$4) | I49: =SUMIFS(Base!$N$2:$N$4835,Base!$B$2:$B$4835,$A49,Base!$F$2:$F$4835,$B49,Base!$A$2:$A$4835,I$4) | J49: =SUMIFS(Base!$N$2:$N$4835,Base!$B$2:$B$4835,$A49,Base!$F$2:$F$4835,$B49,Base!$A$2:$A$4835,J$4) | K49: =SUMIFS(Base!$N$2:$N$4835,Base!$B$2:$B$4835,$A49,Base!$F$2:$F$4835,$B49,Base!$A$2:$A$4835,K$4) | L49: =SUM(C49:K49) | M49: =IFERROR(L49/L$123,"")
A50: Uso e consumo | B50: ATACADAO ECONOMICO - COMERCIO DE MATERIAL DE CONSTRUCAO LTDA | C50: =SUMIFS(Base!$N$2:$N$4835,Base!$B$2:$B$4835,$A50,Base!$F$2:$F$4835,$B50,Base!$A$2:$A$4835,C$4) | D50: =SUMIFS(Base!$N$2:$N$4835,Base!$B$2:$B$4835,$A50,Base!$F$2:$F$4835,$B50,Base!$A$2:$A$4835,D$4) | E50: =SUMIFS(Base!$N$2:$N$4835,Base!$B$2:$B$4835,$A50,Base!$F$2:$F$4835,$B50,Base!$A$2:$A$4835,E$4) | F50: =SUMIFS(Base!$N$2:$N$4835,Base!$B$2:$B$4835,$A50,Base!$F$2:$F$4835,$B50,Base!$A$2:$A$4835,F$4) | G50: =SUMIFS(Base!$N$2:$N$4835,Base!$B$2:$B$4835,$A50,Base!$F$2:$F$4835,$B50,Base!$A$2:$A$4835,G$4) | H50: =SUMIFS(Base!$N$2:$N$4835,Base!$B$2:$B$4835,$A50,Base!$F$2:$F$4835,$B50,Base!$A$2:$A$4835,H$4) | I50: =SUMIFS(Base!$N$2:$N$4835,Base!$B$2:$B$4835,$A50,Base!$F$2:$F$4835,$B50,Base!$A$2:$A$4835,I$4) | J50: =SUMIFS(Base!$N$2:$N$4835,Base!$B$2:$B$4835,$A50,Base!$F$2:$F$4835,$B50,Base!$A$2:$A$4835,J$4) | K50: =SUMIFS(Base!$N$2:$N$4835,Base!$B$2:$B$4835,$A50,Base!$F$2:$F$4835,$B50,Base!$A$2:$A$4835,K$4) | L50: =SUM(C50:K50) | M50: =IFERROR(L50/L$123,"")
A51: Uso e consumo | B51: TECHPRINT FACAS INDUSTRIAIS | C51: =SUMIFS(Base!$N$2:$N$4835,Base!$B$2:$B$4835,$A51,Base!$F$2:$F$4835,$B51,Base!$A$2:$A$4835,C$4) | D51: =SUMIFS(Base!$N$2:$N$4835,Base!$B$2:$B$4835,$A51,Base!$F$2:$F$4835,$B51,Base!$A$2:$A$4835,D$4) | E51: =SUMIFS(Base!$N$2:$N$4835,Base!$B$2:$B$4835,$A51,Base!$F$2:$F$4835,$B51,Base!$A$2:$A$4835,E$4) | F51: =SUMIFS(Base!$N$2:$N$4835,Base!$B$2:$B$4835,$A51,Base!$F$2:$F$4835,$B51,Base!$A$2:$A$4835,F$4) | G51: =SUMIFS(Base!$N$2:$N$4835,Base!$B$2:$B$4835,$A51,Base!$F$2:$F$4835,$B51,Base!$A$2:$A$4835,G$4) | H51: =SUMIFS(Base!$N$2:$N$4835,Base!$B$2:$B$4835,$A51,Base!$F$2:$F$4835,$B51,Base!$A$2:$A$4835,H$4) | I51: =SUMIFS(Base!$N$2:$N$4835,Base!$B$2:$B$4835,$A51,Base!$F$2:$F$4835,$B51,Base!$A$2:$A$4835,I$4) | J51: =SUMIFS(Base!$N$2:$N$4835,Base!$B$2:$B$4835,$A51,Base!$F$2:$F$4835,$B51,Base!$A$2:$A$4835,J$4) | K51: =SUMIFS(Base!$N$2:$N$4835,Base!$B$2:$B$4835,$A51,Base!$F$2:$F$4835,$B51,Base!$A$2:$A$4835,K$4) | L51: =SUM(C51:K51) | M51: =IFERROR(L51/L$123,"")
A52: Uso e consumo | B52: MARILENE CARVALHO LUCENA DE BRITO - ME | C52: =SUMIFS(Base!$N$2:$N$4835,Base!$B$2:$B$4835,$A52,Base!$F$2:$F$4835,$B52,Base!$A$2:$A$4835,C$4) | D52: =SUMIFS(Base!$N$2:$N$4835,Base!$B$2:$B$4835,$A52,Base!$F$2:$F$4835,$B52,Base!$A$2:$A$4835,D$4) | E52: =SUMIFS(Base!$N$2:$N$4835,Base!$B$2:$B$4835,$A52,Base!$F$2:$F$4835,$B52,Base!$A$2:$A$4835,E$4) | F52: =SUMIFS(Base!$N$2:$N$4835,Base!$B$2:$B$4835,$A52,Base!$F$2:$F$4835,$B52,Base!$A$2:$A$4835,F$4) | G52: =SUMIFS(Base!$N$2:$N$4835,Base!$B$2:$B$4835,$A52,Base!$F$2:$F$4835,$B52,Base!$A$2:$A$4835,G$4) | H52: =SUMIFS(Base!$N$2:$N$4835,Base!$B$2:$B$4835,$A52,Base!$F$2:$F$4835,$B52,Base!$A$2:$A$4835,H$4) | I52: =SUMIFS(Base!$N$2:$N$4835,Base!$B$2:$B$4835,$A52,Base!$F$2:$F$4835,$B52,Base!$A$2:$A$4835,I$4) | J52: =SUMIFS(Base!$N$2:$N$4835,Base!$B$2:$B$4835,$A52,Base!$F$2:$F$4835,$B52,Base!$A$2:$A$4835,J$4) | K52: =SUMIFS(Base!$N$2:$N$4835,Base!$B$2:$B$4835,$A52,Base!$F$2:$F$4835,$B52,Base!$A$2:$A$4835,K$4) | L52: =SUM(C52:K52) | M52: =IFERROR(L52/L$123,"")
A53: Uso e consumo | B53: EDNA DE ARAUJO PACHECO LTDA | C53: =SUMIFS(Base!$N$2:$N$4835,Base!$B$2:$B$4835,$A53,Base!$F$2:$F$4835,$B53,Base!$A$2:$A$4835,C$4) | D53: =SUMIFS(Base!$N$2:$N$4835,Base!$B$2:$B$4835,$A53,Base!$F$2:$F$4835,$B53,Base!$A$2:$A$4835,D$4) | E53: =SUMIFS(Base!$N$2:$N$4835,Base!$B$2:$B$4835,$A53,Base!$F$2:$F$4835,$B53,Base!$A$2:$A$4835,E$4) | F53: =SUMIFS(Base!$N$2:$N$4835,Base!$B$2:$B$4835,$A53,Base!$F$2:$F$4835,$B53,Base!$A$2:$A$4835,F$4) | G53: =SUMIFS(Base!$N$2:$N$4835,Base!$B$2:$B$4835,$A53,Base!$F$2:$F$4835,$B53,Base!$A$2:$A$4835,G$4) | H53: =SUMIFS(Base!$N$2:$N$4835,Base!$B$2:$B$4835,$A53,Base!$F$2:$F$4835,$B53,Base!$A$2:$A$4835,H$4) | I53: =SUMIFS(Base!$N$2:$N$4835,Base!$B$2:$B$4835,$A53,Base!$F$2:$F$4835,$B53,Base!$A$2:$A$4835,I$4) | J53: =SUMIFS(Base!$N$2:$N$4835,Base!$B$2:$B$4835,$A53,Base!$F$2:$F$4835,$B53,Base!$A$2:$A$4835,J$4) | K53: =SUMIFS(Base!$N$2:$N$4835,Base!$B$2:$B$4835,$A53,Base!$F$2:$F$4835,$B53,Base!$A$2:$A$4835,K$4) | L53: =SUM(C53:K53) | M53: =IFERROR(L53/L$123,"")
A54: Uso e consumo | B54: GDM INDUSTRIA E COMERCIO DE PLASTICOS LTDA. | C54: =SUMIFS(Base!$N$2:$N$4835,Base!$B$2:$B$4835,$A54,Base!$F$2:$F$4835,$B54,Base!$A$2:$A$4835,C$4) | D54: =SUMIFS(Base!$N$2:$N$4835,Base!$B$2:$B$4835,$A54,Base!$F$2:$F$4835,$B54,Base!$A$2:$A$4835,D$4) | E54: =SUMIFS(Base!$N$2:$N$4835,Base!$B$2:$B$4835,$A54,Base!$F$2:$F$4835,$B54,Base!$A$2:$A$4835,E$4) | F54: =SUMIFS(Base!$N$2:$N$4835,Base!$B$2:$B$4835,$A54,Base!$F$2:$F$4835,$B54,Base!$A$2:$A$4835,F$4) | G54: =SUMIFS(Base!$N$2:$N$4835,Base!$B$2:$B$4835,$A54,Base!$F$2:$F$4835,$B54,Base!$A$2:$A$4835,G$4) | H54: =SUMIFS(Base!$N$2:$N$4835,Base!$B$2:$B$4835,$A54,Base!$F$2:$F$4835,$B54,Base!$A$2:$A$4835,H$4) | I54: =SUMIFS(Base!$N$2:$N$4835,Base!$B$2:$B$4835,$A54,Base!$F$2:$F$4835,$B54,Base!$A$2:$A$4835,I$4) | J54: =SUMIFS(Base!$N$2:$N$4835,Base!$B$2:$B$4835,$A54,Base!$F$2:$F$4835,$B54,Base!$A$2:$A$4835,J$4) | K54: =SUMIFS(Base!$N$2:$N$4835,Base!$B$2:$B$4835,$A54,Base!$F$2:$F$4835,$B54,Base!$A$2:$A$4835,K$4) | L54: =SUM(C54:K54) | M54: =IFERROR(L54/L$123,"")
... A122: Uso e consumo | B122: BRICOZE CELL ELETRONICOS LTDA | C122: =SUMIFS(Base!$N$2:$N$4835,Base!$B$2:$B$4835,$A122,Base!$F$2:$F$4835,$B122,Base!$A$2:$A$4835,C$4) | D122: =SUMIFS(Base!$N$2:$N$4835,Base!$B$2:$B$4835,$A122,Base!$F$2:$F$4835,$B122,Base!$A$2:$A$4835,D$4) | E122: =SUMIFS(Base!$N$2:$N$4835,Base!$B$2:$B$4835,$A122,Base!$F$2:$F$4835,$B122,Base!$A$2:$A$4835,E$4) | F122: =SUMIFS(Base!$N$2:$N$4835,Base!$B$2:$B$4835,$A122,Base!$F$2:$F$4835,$B122,Base!$A$2:$A$4835,F$4) | G122: =SUMIFS(Base!$N$2:$N$4835,Base!$B$2:$B$4835,$A122,Base!$F$2:$F$4835,$B122,Base!$A$2:$A$4835,G$4) | H122: =SUMIFS(Base!$N$2:$N$4835,Base!$B$2:$B$4835,$A122,Base!$F$2:$F$4835,$B122,Base!$A$2:$A$4835,H$4) | I122: =SUMIFS(Base!$N$2:$N$4835,Base!$B$2:$B$4835,$A122,Base!$F$2:$F$4835,$B122,Base!$A$2:$A$4835,I$4) | J122: =SUMIFS(Base!$N$2:$N$4835,Base!$B$2:$B$4835,$A122,Base!$F$2:$F$4835,$B122,Base!$A$2:$A$4835,J$4) | K122: =SUMIFS(Base!$N$2:$N$4835,Base!$B$2:$B$4835,$A122,Base!$F$2:$F$4835,$B122,Base!$A$2:$A$4835,K$4) | L122: =SUM(C122:K122) | M122: =IFERROR(L122/L$123,"")
A123: Uso e consumo | B123: TOTAL Uso e consumo | C123: =SUM(C43:C122) | D123: =SUM(D43:D122) | E123: =SUM(E43:E122) | F123: =SUM(F43:F122) | G123: =SUM(G43:G122) | H123: =SUM(H43:H122) | I123: =SUM(I43:I122) | J123: =SUM(J43:J122) | ... L123: =SUM(L43:L122)
A125: Frete de compra | B125: ALIANCA NAVEGACAO E LOGISTICA LTDA | C125: =SUMIFS(Base!$N$2:$N$4835,Base!$B$2:$B$4835,$A125,Base!$F$2:$F$4835,$B125,Base!$A$2:$A$4835,C$4) | D125: =SUMIFS(Base!$N$2:$N$4835,Base!$B$2:$B$4835,$A125,Base!$F$2:$F$4835,$B125,Base!$A$2:$A$4835,D$4) | E125: =SUMIFS(Base!$N$2:$N$4835,Base!$B$2:$B$4835,$A125,Base!$F$2:$F$4835,$B125,Base!$A$2:$A$4835,E$4) | F125: =SUMIFS(Base!$N$2:$N$4835,Base!$B$2:$B$4835,$A125,Base!$F$2:$F$4835,$B125,Base!$A$2:$A$4835,F$4) | G125: =SUMIFS(Base!$N$2:$N$4835,Base!$B$2:$B$4835,$A125,Base!$F$2:$F$4835,$B125,Base!$A$2:$A$4835,G$4) | H125: =SUMIFS(Base!$N$2:$N$4835,Base!$B$2:$B$4835,$A125,Base!$F$2:$F$4835,$B125,Base!$A$2:$A$4835,H$4) | I125: =SUMIFS(Base!$N$2:$N$4835,Base!$B$2:$B$4835,$A125,Base!$F$2:$F$4835,$B125,Base!$A$2:$A$4835,I$4) | J125: =SUMIFS(Base!$N$2:$N$4835,Base!$B$2:$B$4835,$A125,Base!$F$2:$F$4835,$B125,Base!$A$2:$A$4835,J$4) | K125: =SUMIFS(Base!$N$2:$N$4835,Base!$B$2:$B$4835,$A125,Base!$F$2:$F$4835,$B125,Base!$A$2:$A$4835,K$4) | L125: =SUM(C125:K125) | M125: =IFERROR(L125/L$129,"")
A126: Frete de compra | B126: TRANSPORTES DE MAQUINAS PLANETA AZUL LTDA | C126: =SUMIFS(Base!$N$2:$N$4835,Base!$B$2:$B$4835,$A126,Base!$F$2:$F$4835,$B126,Base!$A$2:$A$4835,C$4) | D126: =SUMIFS(Base!$N$2:$N$4835,Base!$B$2:$B$4835,$A126,Base!$F$2:$F$4835,$B126,Base!$A$2:$A$4835,D$4) | E126: =SUMIFS(Base!$N$2:$N$4835,Base!$B$2:$B$4835,$A126,Base!$F$2:$F$4835,$B126,Base!$A$2:$A$4835,E$4) | F126: =SUMIFS(Base!$N$2:$N$4835,Base!$B$2:$B$4835,$A126,Base!$F$2:$F$4835,$B126,Base!$A$2:$A$4835,F$4) | G126: =SUMIFS(Base!$N$2:$N$4835,Base!$B$2:$B$4835,$A126,Base!$F$2:$F$4835,$B126,Base!$A$2:$A$4835,G$4) | H126: =SUMIFS(Base!$N$2:$N$4835,Base!$B$2:$B$4835,$A126,Base!$F$2:$F$4835,$B126,Base!$A$2:$A$4835,H$4) | I126: =SUMIFS(Base!$N$2:$N$4835,Base!$B$2:$B$4835,$A126,Base!$F$2:$F$4835,$B126,Base!$A$2:$A$4835,I$4) | J126: =SUMIFS(Base!$N$2:$N$4835,Base!$B$2:$B$4835,$A126,Base!$F$2:$F$4835,$B126,Base!$A$2:$A$4835,J$4) | K126: =SUMIFS(Base!$N$2:$N$4835,Base!$B$2:$B$4835,$A126,Base!$F$2:$F$4835,$B126,Base!$A$2:$A$4835,K$4) | L126: =SUM(C126:K126) | M126: =IFERROR(L126/L$129,"")
A127: Frete de compra | B127: ALIANCA NAVEGACAO E LOGISTICA LTDA. | C127: =SUMIFS(Base!$N$2:$N$4835,Base!$B$2:$B$4835,$A127,Base!$F$2:$F$4835,$B127,Base!$A$2:$A$4835,C$4) | D127: =SUMIFS(Base!$N$2:$N$4835,Base!$B$2:$B$4835,$A127,Base!$F$2:$F$4835,$B127,Base!$A$2:$A$4835,D$4) | E127: =SUMIFS(Base!$N$2:$N$4835,Base!$B$2:$B$4835,$A127,Base!$F$2:$F$4835,$B127,Base!$A$2:$A$4835,E$4) | F127: =SUMIFS(Base!$N$2:$N$4835,Base!$B$2:$B$4835,$A127,Base!$F$2:$F$4835,$B127,Base!$A$2:$A$4835,F$4) | G127: =SUMIFS(Base!$N$2:$N$4835,Base!$B$2:$B$4835,$A127,Base!$F$2:$F$4835,$B127,Base!$A$2:$A$4835,G$4) | H127: =SUMIFS(Base!$N$2:$N$4835,Base!$B$2:$B$4835,$A127,Base!$F$2:$F$4835,$B127,Base!$A$2:$A$4835,H$4) | I127: =SUMIFS(Base!$N$2:$N$4835,Base!$B$2:$B$4835,$A127,Base!$F$2:$F$4835,$B127,Base!$A$2:$A$4835,I$4) | J127: =SUMIFS(Base!$N$2:$N$4835,Base!$B$2:$B$4835,$A127,Base!$F$2:$F$4835,$B127,Base!$A$2:$A$4835,J$4) | K127: =SUMIFS(Base!$N$2:$N$4835,Base!$B$2:$B$4835,$A127,Base!$F$2:$F$4835,$B127,Base!$A$2:$A$4835,K$4) | L127: =SUM(C127:K127) | M127: =IFERROR(L127/L$129,"")
A128: Frete de compra | B128: GOL LINHAS AEREAS S.A. | C128: =SUMIFS(Base!$N$2:$N$4835,Base!$B$2:$B$4835,$A128,Base!$F$2:$F$4835,$B128,Base!$A$2:$A$4835,C$4) | D128: =SUMIFS(Base!$N$2:$N$4835,Base!$B$2:$B$4835,$A128,Base!$F$2:$F$4835,$B128,Base!$A$2:$A$4835,D$4) | E128: =SUMIFS(Base!$N$2:$N$4835,Base!$B$2:$B$4835,$A128,Base!$F$2:$F$4835,$B128,Base!$A$2:$A$4835,E$4) | F128: =SUMIFS(Base!$N$2:$N$4835,Base!$B$2:$B$4835,$A128,Base!$F$2:$F$4835,$B128,Base!$A$2:$A$4835,F$4) | G128: =SUMIFS(Base!$N$2:$N$4835,Base!$B$2:$B$4835,$A128,Base!$F$2:$F$4835,$B128,Base!$A$2:$A$4835,G$4) | H128: =SUMIFS(Base!$N$2:$N$4835,Base!$B$2:$B$4835,$A128,Base!$F$2:$F$4835,$B128,Base!$A$2:$A$4835,H$4) | I128: =SUMIFS(Base!$N$2:$N$4835,Base!$B$2:$B$4835,$A128,Base!$F$2:$F$4835,$B128,Base!$A$2:$A$4835,I$4) | J128: =SUMIFS(Base!$N$2:$N$4835,Base!$B$2:$B$4835,$A128,Base!$F$2:$F$4835,$B128,Base!$A$2:$A$4835,J$4) | K128: =SUMIFS(Base!$N$2:$N$4835,Base!$B$2:$B$4835,$A128,Base!$F$2:$F$4835,$B128,Base!$A$2:$A$4835,K$4) | L128: =SUM(C128:K128) | M128: =IFERROR(L128/L$129,"")
A129: Frete de compra | B129: TOTAL Frete de compra | C129: =SUM(C125:C128) | D129: =SUM(D125:D128) | E129: =SUM(E125:E128) | F129: =SUM(F125:F128) | G129: =SUM(G125:G128) | H129: =SUM(H125:H128) | I129: =SUM(I125:I128) | J129: =SUM(J125:J128) | ... L129: =SUM(L125:L128)
A131: Frete de venda | B131: DURA MAIS TRANSPORTES LTDA | C131: =SUMIFS(Base!$N$2:$N$4835,Base!$B$2:$B$4835,$A131,Base!$F$2:$F$4835,$B131,Base!$A$2:$A$4835,C$4) | D131: =SUMIFS(Base!$N$2:$N$4835,Base!$B$2:$B$4835,$A131,Base!$F$2:$F$4835,$B131,Base!$A$2:$A$4835,D$4) | E131: =SUMIFS(Base!$N$2:$N$4835,Base!$B$2:$B$4835,$A131,Base!$F$2:$F$4835,$B131,Base!$A$2:$A$4835,E$4) | F131: =SUMIFS(Base!$N$2:$N$4835,Base!$B$2:$B$4835,$A131,Base!$F$2:$F$4835,$B131,Base!$A$2:$A$4835,F$4) | G131: =SUMIFS(Base!$N$2:$N$4835,Base!$B$2:$B$4835,$A131,Base!$F$2:$F$4835,$B131,Base!$A$2:$A$4835,G$4) | H131: =SUMIFS(Base!$N$2:$N$4835,Base!$B$2:$B$4835,$A131,Base!$F$2:$F$4835,$B131,Base!$A$2:$A$4835,H$4) | I131: =SUMIFS(Base!$N$2:$N$4835,Base!$B$2:$B$4835,$A131,Base!$F$2:$F$4835,$B131,Base!$A$2:$A$4835,I$4) | J131: =SUMIFS(Base!$N$2:$N$4835,Base!$B$2:$B$4835,$A131,Base!$F$2:$F$4835,$B131,Base!$A$2:$A$4835,J$4) | K131: =SUMIFS(Base!$N$2:$N$4835,Base!$B$2:$B$4835,$A131,Base!$F$2:$F$4835,$B131,Base!$A$2:$A$4835,K$4) | L131: =SUM(C131:K131) | M131: =IFERROR(L131/L$155,"")
A132: Frete de venda | B132: R&R TRANSPORTE E LOGISTICA | C132: =SUMIFS(Base!$N$2:$N$4835,Base!$B$2:$B$4835,$A132,Base!$F$2:$F$4835,$B132,Base!$A$2:$A$4835,C$4) | D132: =SUMIFS(Base!$N$2:$N$4835,Base!$B$2:$B$4835,$A132,Base!$F$2:$F$4835,$B132,Base!$A$2:$A$4835,D$4) | E132: =SUMIFS(Base!$N$2:$N$4835,Base!$B$2:$B$4835,$A132,Base!$F$2:$F$4835,$B132,Base!$A$2:$A$4835,E$4) | F132: =SUMIFS(Base!$N$2:$N$4835,Base!$B$2:$B$4835,$A132,Base!$F$2:$F$4835,$B132,Base!$A$2:$A$4835,F$4) | G132: =SUMIFS(Base!$N$2:$N$4835,Base!$B$2:$B$4835,$A132,Base!$F$2:$F$4835,$B132,Base!$A$2:$A$4835,G$4) | H132: =SUMIFS(Base!$N$2:$N$4835,Base!$B$2:$B$4835,$A132,Base!$F$2:$F$4835,$B132,Base!$A$2:$A$4835,H$4) | I132: =SUMIFS(Base!$N$2:$N$4835,Base!$B$2:$B$4835,$A132,Base!$F$2:$F$4835,$B132,Base!$A$2:$A$4835,I$4) | J132: =SUMIFS(Base!$N$2:$N$4835,Base!$B$2:$B$4835,$A132,Base!$F$2:$F$4835,$B132,Base!$A$2:$A$4835,J$4) | K132: =SUMIFS(Base!$N$2:$N$4835,Base!$B$2:$B$4835,$A132,Base!$F$2:$F$4835,$B132,Base!$A$2:$A$4835,K$4) | L132: =SUM(C132:K132) | M132: =IFERROR(L132/L$155,"")
A133: Frete de venda | B133: RAPIDO XAPURI TRANSPORTES E LOGISTICA LTDA | C133: =SUMIFS(Base!$N$2:$N$4835,Base!$B$2:$B$4835,$A133,Base!$F$2:$F$4835,$B133,Base!$A$2:$A$4835,C$4) | D133: =SUMIFS(Base!$N$2:$N$4835,Base!$B$2:$B$4835,$A133,Base!$F$2:$F$4835,$B133,Base!$A$2:$A$4835,D$4) | E133: =SUMIFS(Base!$N$2:$N$4835,Base!$B$2:$B$4835,$A133,Base!$F$2:$F$4835,$B133,Base!$A$2:$A$4835,E$4) | F133: =SUMIFS(Base!$N$2:$N$4835,Base!$B$2:$B$4835,$A133,Base!$F$2:$F$4835,$B133,Base!$A$2:$A$4835,F$4) | G133: =SUMIFS(Base!$N$2:$N$4835,Base!$B$2:$B$4835,$A133,Base!$F$2:$F$4835,$B133,Base!$A$2:$A$4835,G$4) | H133: =SUMIFS(Base!$N$2:$N$4835,Base!$B$2:$B$4835,$A133,Base!$F$2:$F$4835,$B133,Base!$A$2:$A$4835,H$4) | I133: =SUMIFS(Base!$N$2:$N$4835,Base!$B$2:$B$4835,$A133,Base!$F$2:$F$4835,$B133,Base!$A$2:$A$4835,I$4) | J133: =SUMIFS(Base!$N$2:$N$4835,Base!$B$2:$B$4835,$A133,Base!$F$2:$F$4835,$B133,Base!$A$2:$A$4835,J$4) | K133: =SUMIFS(Base!$N$2:$N$4835,Base!$B$2:$B$4835,$A133,Base!$F$2:$F$4835,$B133,Base!$A$2:$A$4835,K$4) | L133: =SUM(C133:K133) | M133: =IFERROR(L133/L$155,"")
A134: Frete de venda | B134: TRANSPORTE OLIVEIRA E MELLOI - IDEALIZA TRANSPORTES | C134: =SUMIFS(Base!$N$2:$N$4835,Base!$B$2:$B$4835,$A134,Base!$F$2:$F$4835,$B134,Base!$A$2:$A$4835,C$4) | D134: =SUMIFS(Base!$N$2:$N$4835,Base!$B$2:$B$4835,$A134,Base!$F$2:$F$4835,$B134,Base!$A$2:$A$4835,D$4) | E134: =SUMIFS(Base!$N$2:$N$4835,Base!$B$2:$B$4835,$A134,Base!$F$2:$F$4835,$B134,Base!$A$2:$A$4835,E$4) | F134: =SUMIFS(Base!$N$2:$N$4835,Base!$B$2:$B$4835,$A134,Base!$F$2:$F$4835,$B134,Base!$A$2:$A$4835,F$4) | G134: =SUMIFS(Base!$N$2:$N$4835,Base!$B$2:$B$4835,$A134,Base!$F$2:$F$4835,$B134,Base!$A$2:$A$4835,G$4) | H134: =SUMIFS(Base!$N$2:$N$4835,Base!$B$2:$B$4835,$A134,Base!$F$2:$F$4835,$B134,Base!$A$2:$A$4835,H$4) | I134: =SUMIFS(Base!$N$2:$N$4835,Base!$B$2:$B$4835,$A134,Base!$F$2:$F$4835,$B134,Base!$A$2:$A$4835,I$4) | J134: =SUMIFS(Base!$N$2:$N$4835,Base!$B$2:$B$4835,$A134,Base!$F$2:$F$4835,$B134,Base!$A$2:$A$4835,J$4) | K134: =SUMIFS(Base!$N$2:$N$4835,Base!$B$2:$B$4835,$A134,Base!$F$2:$F$4835,$B134,Base!$A$2:$A$4835,K$4) | L134: =SUM(C134:K134) | M134: =IFERROR(L134/L$155,"")
A135: Frete de venda | B135: PICCOLI TRANSPORTES LTDA | C135: =SUMIFS(Base!$N$2:$N$4835,Base!$B$2:$B$4835,$A135,Base!$F$2:$F$4835,$B135,Base!$A$2:$A$4835,C$4) | D135: =SUMIFS(Base!$N$2:$N$4835,Base!$B$2:$B$4835,$A135,Base!$F$2:$F$4835,$B135,Base!$A$2:$A$4835,D$4) | E135: =SUMIFS(Base!$N$2:$N$4835,Base!$B$2:$B$4835,$A135,Base!$F$2:$F$4835,$B135,Base!$A$2:$A$4835,E$4) | F135: =SUMIFS(Base!$N$2:$N$4835,Base!$B$2:$B$4835,$A135,Base!$F$2:$F$4835,$B135,Base!$A$2:$A$4835,F$4) | G135: =SUMIFS(Base!$N$2:$N$4835,Base!$B$2:$B$4835,$A135,Base!$F$2:$F$4835,$B135,Base!$A$2:$A$4835,G$4) | H135: =SUMIFS(Base!$N$2:$N$4835,Base!$B$2:$B$4835,$A135,Base!$F$2:$F$4835,$B135,Base!$A$2:$A$4835,H$4) | I135: =SUMIFS(Base!$N$2:$N$4835,Base!$B$2:$B$4835,$A135,Base!$F$2:$F$4835,$B135,Base!$A$2:$A$4835,I$4) | J135: =SUMIFS(Base!$N$2:$N$4835,Base!$B$2:$B$4835,$A135,Base!$F$2:$F$4835,$B135,Base!$A$2:$A$4835,J$4) | K135: =SUMIFS(Base!$N$2:$N$4835,Base!$B$2:$B$4835,$A135,Base!$F$2:$F$4835,$B135,Base!$A$2:$A$4835,K$4) | L135: =SUM(C135:K135) | M135: =IFERROR(L135/L$155,"")
A136: Frete de venda | B136: ADIL CARLOS DA SILVA | C136: =SUMIFS(Base!$N$2:$N$4835,Base!$B$2:$B$4835,$A136,Base!$F$2:$F$4835,$B136,Base!$A$2:$A$4835,C$4) | D136: =SUMIFS(Base!$N$2:$N$4835,Base!$B$2:$B$4835,$A136,Base!$F$2:$F$4835,$B136,Base!$A$2:$A$4835,D$4) | E136: =SUMIFS(Base!$N$2:$N$4835,Base!$B$2:$B$4835,$A136,Base!$F$2:$F$4835,$B136,Base!$A$2:$A$4835,E$4) | F136: =SUMIFS(Base!$N$2:$N$4835,Base!$B$2:$B$4835,$A136,Base!$F$2:$F$4835,$B136,Base!$A$2:$A$4835,F$4) | G136: =SUMIFS(Base!$N$2:$N$4835,Base!$B$2:$B$4835,$A136,Base!$F$2:$F$4835,$B136,Base!$A$2:$A$4835,G$4) | H136: =SUMIFS(Base!$N$2:$N$4835,Base!$B$2:$B$4835,$A136,Base!$F$2:$F$4835,$B136,Base!$A$2:$A$4835,H$4) | I136: =SUMIFS(Base!$N$2:$N$4835,Base!$B$2:$B$4835,$A136,Base!$F$2:$F$4835,$B136,Base!$A$2:$A$4835,I$4) | J136: =SUMIFS(Base!$N$2:$N$4835,Base!$B$2:$B$4835,$A136,Base!$F$2:$F$4835,$B136,Base!$A$2:$A$4835,J$4) | K136: =SUMIFS(Base!$N$2:$N$4835,Base!$B$2:$B$4835,$A136,Base!$F$2:$F$4835,$B136,Base!$A$2:$A$4835,K$4) | L136: =SUM(C136:K136) | M136: =IFERROR(L136/L$155,"")
A137: Frete de venda | B137: TRANSFORRECHI TRANSPORTES LTDA | C137: =SUMIFS(Base!$N$2:$N$4835,Base!$B$2:$B$4835,$A137,Base!$F$2:$F$4835,$B137,Base!$A$2:$A$4835,C$4) | D137: =SUMIFS(Base!$N$2:$N$4835,Base!$B$2:$B$4835,$A137,Base!$F$2:$F$4835,$B137,Base!$A$2:$A$4835,D$4) | E137: =SUMIFS(Base!$N$2:$N$4835,Base!$B$2:$B$4835,$A137,Base!$F$2:$F$4835,$B137,Base!$A$2:$A$4835,E$4) | F137: =SUMIFS(Base!$N$2:$N$4835,Base!$B$2:$B$4835,$A137,Base!$F$2:$F$4835,$B137,Base!$A$2:$A$4835,F$4) | G137: =SUMIFS(Base!$N$2:$N$4835,Base!$B$2:$B$4835,$A137,Base!$F$2:$F$4835,$B137,Base!$A$2:$A$4835,G$4) | H137: =SUMIFS(Base!$N$2:$N$4835,Base!$B$2:$B$4835,$A137,Base!$F$2:$F$4835,$B137,Base!$A$2:$A$4835,H$4) | I137: =SUMIFS(Base!$N$2:$N$4835,Base!$B$2:$B$4835,$A137,Base!$F$2:$F$4835,$B137,Base!$A$2:$A$4835,I$4) | J137: =SUMIFS(Base!$N$2:$N$4835,Base!$B$2:$B$4835,$A137,Base!$F$2:$F$4835,$B137,Base!$A$2:$A$4835,J$4) | K137: =SUMIFS(Base!$N$2:$N$4835,Base!$B$2:$B$4835,$A137,Base!$F$2:$F$4835,$B137,Base!$A$2:$A$4835,K$4) | L137: =SUM(C137:K137) | M137: =IFERROR(L137/L$155,"")
A138: Frete de venda | B138: BEM TRANSPORTES E LOGISTICA | C138: =SUMIFS(Base!$N$2:$N$4835,Base!$B$2:$B$4835,$A138,Base!$F$2:$F$4835,$B138,Base!$A$2:$A$4835,C$4) | D138: =SUMIFS(Base!$N$2:$N$4835,Base!$B$2:$B$4835,$A138,Base!$F$2:$F$4835,$B138,Base!$A$2:$A$4835,D$4) | E138: =SUMIFS(Base!$N$2:$N$4835,Base!$B$2:$B$4835,$A138,Base!$F$2:$F$4835,$B138,Base!$A$2:$A$4835,E$4) | F138: =SUMIFS(Base!$N$2:$N$4835,Base!$B$2:$B$4835,$A138,Base!$F$2:$F$4835,$B138,Base!$A$2:$A$4835,F$4) | G138: =SUMIFS(Base!$N$2:$N$4835,Base!$B$2:$B$4835,$A138,Base!$F$2:$F$4835,$B138,Base!$A$2:$A$4835,G$4) | H138: =SUMIFS(Base!$N$2:$N$4835,Base!$B$2:$B$4835,$A138,Base!$F$2:$F$4835,$B138,Base!$A$2:$A$4835,H$4) | I138: =SUMIFS(Base!$N$2:$N$4835,Base!$B$2:$B$4835,$A138,Base!$F$2:$F$4835,$B138,Base!$A$2:$A$4835,I$4) | J138: =SUMIFS(Base!$N$2:$N$4835,Base!$B$2:$B$4835,$A138,Base!$F$2:$F$4835,$B138,Base!$A$2:$A$4835,J$4) | K138: =SUMIFS(Base!$N$2:$N$4835,Base!$B$2:$B$4835,$A138,Base!$F$2:$F$4835,$B138,Base!$A$2:$A$4835,K$4) | L138: =SUM(C138:K138) | M138: =IFERROR(L138/L$155,"")
A139: Frete de venda | B139: REIMAG - REINALDO DOMINGUES BARROS DA SILVA | C139: =SUMIFS(Base!$N$2:$N$4835,Base!$B$2:$B$4835,$A139,Base!$F$2:$F$4835,$B139,Base!$A$2:$A$4835,C$4) | D139: =SUMIFS(Base!$N$2:$N$4835,Base!$B$2:$B$4835,$A139,Base!$F$2:$F$4835,$B139,Base!$A$2:$A$4835,D$4) | E139: =SUMIFS(Base!$N$2:$N$4835,Base!$B$2:$B$4835,$A139,Base!$F$2:$F$4835,$B139,Base!$A$2:$A$4835,E$4) | F139: =SUMIFS(Base!$N$2:$N$4835,Base!$B$2:$B$4835,$A139,Base!$F$2:$F$4835,$B139,Base!$A$2:$A$4835,F$4) | G139: =SUMIFS(Base!$N$2:$N$4835,Base!$B$2:$B$4835,$A139,Base!$F$2:$F$4835,$B139,Base!$A$2:$A$4835,G$4) | H139: =SUMIFS(Base!$N$2:$N$4835,Base!$B$2:$B$4835,$A139,Base!$F$2:$F$4835,$B139,Base!$A$2:$A$4835,H$4) | I139: =SUMIFS(Base!$N$2:$N$4835,Base!$B$2:$B$4835,$A139,Base!$F$2:$F$4835,$B139,Base!$A$2:$A$4835,I$4) | J139: =SUMIFS(Base!$N$2:$N$4835,Base!$B$2:$B$4835,$A139,Base!$F$2:$F$4835,$B139,Base!$A$2:$A$4835,J$4) | K139: =SUMIFS(Base!$N$2:$N$4835,Base!$B$2:$B$4835,$A139,Base!$F$2:$F$4835,$B139,Base!$A$2:$A$4835,K$4) | L139: =SUM(C139:K139) | M139: =IFERROR(L139/L$155,"")
A140: Frete de venda | B140: CAZAN TRANSPORTES LTDA | C140: =SUMIFS(Base!$N$2:$N$4835,Base!$B$2:$B$4835,$A140,Base!$F$2:$F$4835,$B140,Base!$A$2:$A$4835,C$4) | D140: =SUMIFS(Base!$N$2:$N$4835,Base!$B$2:$B$4835,$A140,Base!$F$2:$F$4835,$B140,Base!$A$2:$A$4835,D$4) | E140: =SUMIFS(Base!$N$2:$N$4835,Base!$B$2:$B$4835,$A140,Base!$F$2:$F$4835,$B140,Base!$A$2:$A$4835,E$4) | F140: =SUMIFS(Base!$N$2:$N$4835,Base!$B$2:$B$4835,$A140,Base!$F$2:$F$4835,$B140,Base!$A$2:$A$4835,F$4) | G140: =SUMIFS(Base!$N$2:$N$4835,Base!$B$2:$B$4835,$A140,Base!$F$2:$F$4835,$B140,Base!$A$2:$A$4835,G$4) | H140: =SUMIFS(Base!$N$2:$N$4835,Base!$B$2:$B$4835,$A140,Base!$F$2:$F$4835,$B140,Base!$A$2:$A$4835,H$4) | I140: =SUMIFS(Base!$N$2:$N$4835,Base!$B$2:$B$4835,$A140,Base!$F$2:$F$4835,$B140,Base!$A$2:$A$4835,I$4) | J140: =SUMIFS(Base!$N$2:$N$4835,Base!$B$2:$B$4835,$A140,Base!$F$2:$F$4835,$B140,Base!$A$2:$A$4835,J$4) | K140: =SUMIFS(Base!$N$2:$N$4835,Base!$B$2:$B$4835,$A140,Base!$F$2:$F$4835,$B140,Base!$A$2:$A$4835,K$4) | L140: =SUM(C140:K140) | M140: =IFERROR(L140/L$155,"")
A141: Frete de venda | B141: 26.221.654 ROGERIO DA CUNHA FERREIRA | C141: =SUMIFS(Base!$N$2:$N$4835,Base!$B$2:$B$4835,$A141,Base!$F$2:$F$4835,$B141,Base!$A$2:$A$4835,C$4) | D141: =SUMIFS(Base!$N$2:$N$4835,Base!$B$2:$B$4835,$A141,Base!$F$2:$F$4835,$B141,Base!$A$2:$A$4835,D$4) | E141: =SUMIFS(Base!$N$2:$N$4835,Base!$B$2:$B$4835,$A141,Base!$F$2:$F$4835,$B141,Base!$A$2:$A$4835,E$4) | F141: =SUMIFS(Base!$N$2:$N$4835,Base!$B$2:$B$4835,$A141,Base!$F$2:$F$4835,$B141,Base!$A$2:$A$4835,F$4) | G141: =SUMIFS(Base!$N$2:$N$4835,Base!$B$2:$B$4835,$A141,Base!$F$2:$F$4835,$B141,Base!$A$2:$A$4835,G$4) | H141: =SUMIFS(Base!$N$2:$N$4835,Base!$B$2:$B$4835,$A141,Base!$F$2:$F$4835,$B141,Base!$A$2:$A$4835,H$4) | I141: =SUMIFS(Base!$N$2:$N$4835,Base!$B$2:$B$4835,$A141,Base!$F$2:$F$4835,$B141,Base!$A$2:$A$4835,I$4) | J141: =SUMIFS(Base!$N$2:$N$4835,Base!$B$2:$B$4835,$A141,Base!$F$2:$F$4835,$B141,Base!$A$2:$A$4835,J$4) | K141: =SUMIFS(Base!$N$2:$N$4835,Base!$B$2:$B$4835,$A141,Base!$F$2:$F$4835,$B141,Base!$A$2:$A$4835,K$4) | L141: =SUM(C141:K141) | M141: =IFERROR(L141/L$155,"")
A142: Frete de venda | B142: DR CARGO TRANSPORTE DE CARGAS LTDA | C142: =SUMIFS(Base!$N$2:$N$4835,Base!$B$2:$B$4835,$A142,Base!$F$2:$F$4835,$B142,Base!$A$2:$A$4835,C$4) | D142: =SUMIFS(Base!$N$2:$N$4835,Base!$B$2:$B$4835,$A142,Base!$F$2:$F$4835,$B142,Base!$A$2:$A$4835,D$4) | E142: =SUMIFS(Base!$N$2:$N$4835,Base!$B$2:$B$4835,$A142,Base!$F$2:$F$4835,$B142,Base!$A$2:$A$4835,E$4) | F142: =SUMIFS(Base!$N$2:$N$4835,Base!$B$2:$B$4835,$A142,Base!$F$2:$F$4835,$B142,Base!$A$2:$A$4835,F$4) | G142: =SUMIFS(Base!$N$2:$N$4835,Base!$B$2:$B$4835,$A142,Base!$F$2:$F$4835,$B142,Base!$A$2:$A$4835,G$4) | H142: =SUMIFS(Base!$N$2:$N$4835,Base!$B$2:$B$4835,$A142,Base!$F$2:$F$4835,$B142,Base!$A$2:$A$4835,H$4) | I142: =SUMIFS(Base!$N$2:$N$4835,Base!$B$2:$B$4835,$A142,Base!$F$2:$F$4835,$B142,Base!$A$2:$A$4835,I$4) | J142: =SUMIFS(Base!$N$2:$N$4835,Base!$B$2:$B$4835,$A142,Base!$F$2:$F$4835,$B142,Base!$A$2:$A$4835,J$4) | K142: =SUMIFS(Base!$N$2:$N$4835,Base!$B$2:$B$4835,$A142,Base!$F$2:$F$4835,$B142,Base!$A$2:$A$4835,K$4) | L142: =SUM(C142:K142) | M142: =IFERROR(L142/L$155,"")
... A154: Frete de venda | B154: JAGUARE TRANSPORTES E ARMAZENAGENS LTDA | C154: =SUMIFS(Base!$N$2:$N$4835,Base!$B$2:$B$4835,$A154,Base!$F$2:$F$4835,$B154,Base!$A$2:$A$4835,C$4) | D154: =SUMIFS(Base!$N$2:$N$4835,Base!$B$2:$B$4835,$A154,Base!$F$2:$F$4835,$B154,Base!$A$2:$A$4835,D$4) | E154: =SUMIFS(Base!$N$2:$N$4835,Base!$B$2:$B$4835,$A154,Base!$F$2:$F$4835,$B154,Base!$A$2:$A$4835,E$4) | F154: =SUMIFS(Base!$N$2:$N$4835,Base!$B$2:$B$4835,$A154,Base!$F$2:$F$4835,$B154,Base!$A$2:$A$4835,F$4) | G154: =SUMIFS(Base!$N$2:$N$4835,Base!$B$2:$B$4835,$A154,Base!$F$2:$F$4835,$B154,Base!$A$2:$A$4835,G$4) | H154: =SUMIFS(Base!$N$2:$N$4835,Base!$B$2:$B$4835,$A154,Base!$F$2:$F$4835,$B154,Base!$A$2:$A$4835,H$4) | I154: =SUMIFS(Base!$N$2:$N$4835,Base!$B$2:$B$4835,$A154,Base!$F$2:$F$4835,$B154,Base!$A$2:$A$4835,I$4) | J154: =SUMIFS(Base!$N$2:$N$4835,Base!$B$2:$B$4835,$A154,Base!$F$2:$F$4835,$B154,Base!$A$2:$A$4835,J$4) | K154: =SUMIFS(Base!$N$2:$N$4835,Base!$B$2:$B$4835,$A154,Base!$F$2:$F$4835,$B154,Base!$A$2:$A$4835,K$4) | L154: =SUM(C154:K154) | M154: =IFERROR(L154/L$155,"")
A155: Frete de venda | B155: TOTAL Frete de venda | C155: =SUM(C131:C154) | D155: =SUM(D131:D154) | E155: =SUM(E131:E154) | F155: =SUM(F131:F154) | G155: =SUM(G131:G154) | H155: =SUM(H131:H154) | I155: =SUM(I131:I154) | J155: =SUM(J131:J154) | ... L155: =SUM(L131:L154)

Sheet Base
A1: Mês (emissão) | B1: Destino | C1: Categoria do Omie | D1: Tipo | E1: Número | F1: Parte / Transportadora | G1: Emissão | H1: Valor bruto (R$) | I1: IPI | J1: ICMS | K1: PIS | L1: COFINS | M1: Crédito abatido | N1: Custo líquido (R$) | O1: Gerou título | P1: CFOPs entrada
A2: Antes de 2026 | B2: Frete de compra | C2: Frete de compra | D2: CT-e | E2: 000058287 | F2: GOL LINHAS AEREAS S.A. | G2: 45618 | H2: 100.64 | I2: 0 | J2: 4.03 | K2: 0 | L2: 0 | M2: =IF(B2="Frete de venda",0,(1-ISNUMBER(SEARCH("556",P2)))*(I2*VLOOKUP($B2,Premissas!$A$4:$E$7,2,0)+J2*VLOOKUP($B2,Premissas!$A$4:$E$7,3,0))+K2*VLOOKUP($B2,Premissas!$A$4:$E$7,4,0)+L2*VLOOKUP($B2,Premissas!$A$4:$E$7,5,0)) | N2: =H2-M2 | O2: Não | P2: 1.350
A3: Antes de 2026 | B3: Frete de compra | C3: Frete de compra | D3: CT-e | E3: 000058286 | F3: GOL LINHAS AEREAS S.A. | G3: 45618 | H3: 191.66 | I3: 0 | J3: 7.67 | K3: 0 | L3: 0 | M3: =IF(B3="Frete de venda",0,(1-ISNUMBER(SEARCH("556",P3)))*(I3*VLOOKUP($B3,Premissas!$A$4:$E$7,2,0)+J3*VLOOKUP($B3,Premissas!$A$4:$E$7,3,0))+K3*VLOOKUP($B3,Premissas!$A$4:$E$7,4,0)+L3*VLOOKUP($B3,Premissas!$A$4:$E$7,5,0)) | N3: =H3-M3 | O3: Não | P3: 1.350
A4: Antes de 2026 | B4: Frete de compra | C4: Frete de compra | D4: CT-e | E4: 000059052 | F4: GOL LINHAS AEREAS S.A. | G4: 45638 | H4: 70.99 | I4: 0 | J4: 2.84 | K4: 0 | L4: 0 | M4: =IF(B4="Frete de venda",0,(1-ISNUMBER(SEARCH("556",P4)))*(I4*VLOOKUP($B4,Premissas!$A$4:$E$7,2,0)+J4*VLOOKUP($B4,Premissas!$A$4:$E$7,3,0))+K4*VLOOKUP($B4,Premissas!$A$4:$E$7,4,0)+L4*VLOOKUP($B4,Premissas!$A$4:$E$7,5,0)) | N4: =H4-M4 | O4: Não | P4: 1.350
A5: Antes de 2026 | B5: Frete de compra | C5: Frete de compra | D5: CT-e | E5: 000059047 | F5: GOL LINHAS AEREAS S.A. | G5: 45638 | H5: 111.99 | I5: 0 | J5: 4.48 | K5: 0 | L5: 0 | M5: =IF(B5="Frete de venda",0,(1-ISNUMBER(SEARCH("556",P5)))*(I5*VLOOKUP($B5,Premissas!$A$4:$E$7,2,0)+J5*VLOOKUP($B5,Premissas!$A$4:$E$7,3,0))+K5*VLOOKUP($B5,Premissas!$A$4:$E$7,4,0)+L5*VLOOKUP($B5,Premissas!$A$4:$E$7,5,0)) | N5: =H5-M5 | O5: Não | P5: 1.350
A6: Antes de 2026 | B6: Frete de compra | C6: Frete de compra | D6: CT-e | E6: 000058716 | F6: GOL LINHAS AEREAS S.A. | G6: 45630 | H6: 162.04 | I6: 0 | J6: 6.48 | K6: 0 | L6: 0 | M6: =IF(B6="Frete de venda",0,(1-ISNUMBER(SEARCH("556",P6)))*(I6*VLOOKUP($B6,Premissas!$A$4:$E$7,2,0)+J6*VLOOKUP($B6,Premissas!$A$4:$E$7,3,0))+K6*VLOOKUP($B6,Premissas!$A$4:$E$7,4,0)+L6*VLOOKUP($B6,Premissas!$A$4:$E$7,5,0)) | N6: =H6-M6 | O6: Não | P6: 1.350
A7: Antes de 2026 | B7: Frete de compra | C7: Frete de compra | D7: CT-e | E7: 000059446 | F7: GOL LINHAS AEREAS S.A. | G7: 45653 | H7: 44.99 | I7: 0 | J7: 1.8 | K7: 0 | L7: 0 | M7: =IF(B7="Frete de venda",0,(1-ISNUMBER(SEARCH("556",P7)))*(I7*VLOOKUP($B7,Premissas!$A$4:$E$7,2,0)+J7*VLOOKUP($B7,Premissas!$A$4:$E$7,3,0))+K7*VLOOKUP($B7,Premissas!$A$4:$E$7,4,0)+L7*VLOOKUP($B7,Premissas!$A$4:$E$7,5,0)) | N7: =H7-M7 | O7: Não | P7: 1.350
A8: Antes de 2026 | B8: Frete de compra | C8: Frete de compra | D8: CT-e | E8: 000058282 | F8: GOL LINHAS AEREAS S.A. | G8: 45618 | H8: 173.39 | I8: 0 | J8: 6.94 | K8: 0 | L8: 0 | M8: =IF(B8="Frete de venda",0,(1-ISNUMBER(SEARCH("556",P8)))*(I8*VLOOKUP($B8,Premissas!$A$4:$E$7,2,0)+J8*VLOOKUP($B8,Premissas!$A$4:$E$7,3,0))+K8*VLOOKUP($B8,Premissas!$A$4:$E$7,4,0)+L8*VLOOKUP($B8,Premissas!$A$4:$E$7,5,0)) | N8: =H8-M8 | O8: Não | P8: 1.350
A9: Antes de 2026 | B9: Frete de compra | C9: Frete de compra | D9: CT-e | E9: 000059051 | F9: GOL LINHAS AEREAS S.A. | G9: 45638 | H9: 128.54 | I9: 0 | J9: 5.14 | K9: 0 | L9: 0 | M9: =IF(B9="Frete de venda",0,(1-ISNUMBER(SEARCH("556",P9)))*(I9*VLOOKUP($B9,Premissas!$A$4:$E$7,2,0)+J9*VLOOKUP($B9,Premissas!$A$4:$E$7,3,0))+K9*VLOOKUP($B9,Premissas!$A$4:$E$7,4,0)+L9*VLOOKUP($B9,Premissas!$A$4:$E$7,5,0)) | N9: =H9-M9 | O9: Não | P9: 1.350
A10: Antes de 2026 | B10: Frete de compra | C10: Frete de compra | D10: CT-e | E10: 000059055 | F10: GOL LINHAS AEREAS S.A. | G10: 45638 | H10: 132.4 | I10: 0 | J10: 5.3 | K10: 0 | L10: 0 | M10: =IF(B10="Frete de venda",0,(1-ISNUMBER(SEARCH("556",P10)))*(I10*VLOOKUP($B10,Premissas!$A$4:$E$7,2,0)+J10*VLOOKUP($B10,Premissas!$A$4:$E$7,3,0))+K10*VLOOKUP($B10,Premissas!$A$4:$E$7,4,0)+L10*VLOOKUP($B10,Premissas!$A$4:$E$7,5,0)) | N10: =H10-M10 | O10: Não | P10: 1.350
A11: Antes de 2026 | B11: Frete de compra | C11: Frete de compra | D11: CT-e | E11: 000058724 | F11: GOL LINHAS AEREAS S.A. | G11: 45630 | H11: 207.45 | I11: 0 | J11: 8.3 | K11: 0 | L11: 0 | M11: =IF(B11="Frete de venda",0,(1-ISNUMBER(SEARCH("556",P11)))*(I11*VLOOKUP($B11,Premissas!$A$4:$E$7,2,0)+J11*VLOOKUP($B11,Premissas!$A$4:$E$7,3,0))+K11*VLOOKUP($B11,Premissas!$A$4:$E$7,4,0)+L11*VLOOKUP($B11,Premissas!$A$4:$E$7,5,0)) | N11: =H11-M11 | O11: Não | P11: 1.350
A12: Antes de 2026 | B12: Frete de compra | C12: Frete de compra | D12: CT-e | E12: 000059048 | F12: GOL LINHAS AEREAS S.A. | G12: 45638 | H12: 136.99 | I12: 0 | J12: 5.48 | K12: 0 | L12: 0 | M12: =IF(B12="Frete de venda",0,(1-ISNUMBER(SEARCH("556",P12)))*(I12*VLOOKUP($B12,Premissas!$A$4:$E$7,2,0)+J12*VLOOKUP($B12,Premissas!$A$4:$E$7,3,0))+K12*VLOOKUP($B12,Premissas!$A$4:$E$7,4,0)+L12*VLOOKUP($B12,Premissas!$A$4:$E$7,5,0)) | N12: =H12-M12 | O12: Não | P12: 1.350
A13: Antes de 2026 | B13: Frete de compra | C13: Frete de compra | D13: CT-e | E13: 000058713 | F13: GOL LINHAS AEREAS S.A. | G13: 45630 | H13: 162.04 | I13: 0 | J13: 6.48 | K13: 0 | L13: 0 | M13: =IF(B13="Frete de venda",0,(1-ISNUMBER(SEARCH("556",P13)))*(I13*VLOOKUP($B13,Premissas!$A$4:$E$7,2,0)+J13*VLOOKUP($B13,Premissas!$A$4:$E$7,3,0))+K13*VLOOKUP($B13,Premissas!$A$4:$E$7,4,0)+L13*VLOOKUP($B13,Premissas!$A$4:$E$7,5,0)) | N13: =H13-M13 | O13: Não | P13: 1.350
... A2061: Antes de 2026 | B2061: Insumos e papel | C2061: 2.01.99 Compra de Caixas | D2061: NF-e | E2061: 000011554 | F2061: NOVA CONPEL COMPANHIA NORDESTINA DE PAPEL LTDA | G2061: 46021 | H2061: 3604.74 | I2061: 470.18 | J2061: 626.91 | K2061: 41.38 | L2061: 190.58 | M2061: =IF(B2061="Frete de venda",0,(1-ISNUMBER(SEARCH("556",P2061)))*(I2061*VLOOKUP($B2061,Premissas!$A$4:$E$7,2,0)+J2061*VLOOKUP($B2061,Premissas!$A$4:$E$7,3,0))+K2061*VLOOKUP($B2061,Premissas!$A$4:$E$7,4,0)+L2061*VLOOKUP($B2061,Premissas!$A$4:$E$7,5,0)) | N2061: =H2061-M2061 | O2061: Sim | P2061: 1.102
A2062: 46023 | B2062: Frete de venda | C2062: Frete de venda (para clientes) | D2062: CT-e | E2062: 000000318 | F2062: ADEMIR DA SILVA LTDA | G2062: 46052 | H2062: 300 | I2062: 0 | J2062: 0 | K2062: 0 | L2062: 0 | M2062: =IF(B2062="Frete de venda",0,(1-ISNUMBER(SEARCH("556",P2062)))*(I2062*VLOOKUP($B2062,Premissas!$A$4:$E$7,2,0)+J2062*VLOOKUP($B2062,Premissas!$A$4:$E$7,3,0))+K2062*VLOOKUP($B2062,Premissas!$A$4:$E$7,4,0)+L2062*VLOOKUP($B2062,Premissas!$A$4:$E$7,5,0)) | N2062: =H2062-M2062 | O2062: Sim | P2062: 1.350
A2063: 46023 | B2063: Frete de venda | C2063: Frete de venda (para clientes) | D2063: CT-e | E2063: 000083544 | F2063: CRUZ DE MALTA TRANSPORTES LTDA | G2063: 46049 | H2063: 800 | I2063: 0 | J2063: 152 | K2063: 0 | L2063: 0 | M2063: =IF(B2063="Frete de venda",0,(1-ISNUMBER(SEARCH("556",P2063)))*(I2063*VLOOKUP($B2063,Premissas!$A$4:$E$7,2,0)+J2063*VLOOKUP($B2063,Premissas!$A$4:$E$7,3,0))+K2063*VLOOKUP($B2063,Premissas!$A$4:$E$7,4,0)+L2063*VLOOKUP($B2063,Premissas!$A$4:$E$7,5,0)) | N2063: =H2063-M2063 | O2063: Sim | P2063: 1.350
A2064: 46023 | B2064: Frete de venda | C2064: Frete de venda (para clientes) | D2064: CT-e | E2064: 000000316 | F2064: ADEMIR DA SILVA LTDA | G2064: 46052 | H2064: 300 | I2064: 0 | J2064: 0 | K2064: 0 | L2064: 0 | M2064: =IF(B2064="Frete de venda",0,(1-ISNUMBER(SEARCH("556",P2064)))*(I2064*VLOOKUP($B2064,Premissas!$A$4:$E$7,2,0)+J2064*VLOOKUP($B2064,Premissas!$A$4:$E$7,3,0))+K2064*VLOOKUP($B2064,Premissas!$A$4:$E$7,4,0)+L2064*VLOOKUP($B2064,Premissas!$A$4:$E$7,5,0)) | N2064: =H2064-M2064 | O2064: Sim | P2064: 1.350
A2065: 46023 | B2065: Frete de venda | C2065: Frete de venda (para clientes) | D2065: CT-e | E2065: 000000315 | F2065: ADEMIR DA SILVA LTDA | G2065: 46052 | H2065: 600 | I2065: 0 | J2065: 0 | K2065: 0 | L2065: 0 | M2065: =IF(B2065="Frete de venda",0,(1-ISNUMBER(SEARCH("556",P2065)))*(I2065*VLOOKUP($B2065,Premissas!$A$4:$E$7,2,0)+J2065*VLOOKUP($B2065,Premissas!$A$4:$E$7,3,0))+K2065*VLOOKUP($B2065,Premissas!$A$4:$E$7,4,0)+L2065*VLOOKUP($B2065,Premissas!$A$4:$E$7,5,0)) | N2065: =H2065-M2065 | O2065: Sim | P2065: 1.350
A2066: 46023 | B2066: Frete de venda | C2066: Frete de venda (para clientes) | D2066: CT-e | E2066: 000000317 | F2066: ADEMIR DA SILVA LTDA | G2066: 46052 | H2066: 300 | I2066: 0 | J2066: 0 | K2066: 0 | L2066: 0 | M2066: =IF(B2066="Frete de venda",0,(1-ISNUMBER(SEARCH("556",P2066)))*(I2066*VLOOKUP($B2066,Premissas!$A$4:$E$7,2,0)+J2066*VLOOKUP($B2066,Premissas!$A$4:$E$7,3,0))+K2066*VLOOKUP($B2066,Premissas!$A$4:$E$7,4,0)+L2066*VLOOKUP($B2066,Premissas!$A$4:$E$7,5,0)) | N2066: =H2066-M2066 | O2066: Sim | P2066: 1.350
A2067: 46023 | B2067: Frete de venda | C2067: Frete de venda (para clientes) | D2067: CT-e | E2067: 000083545 | F2067: CRUZ DE MALTA TRANSPORTES LTDA | G2067: 46049 | H2067: 500 | I2067: 0 | J2067: 95 | K2067: 0 | L2067: 0 | M2067: =IF(B2067="Frete de venda",0,(1-ISNUMBER(SEARCH("556",P2067)))*(I2067*VLOOKUP($B2067,Premissas!$A$4:$E$7,2,0)+J2067*VLOOKUP($B2067,Premissas!$A$4:$E$7,3,0))+K2067*VLOOKUP($B2067,Premissas!$A$4:$E$7,4,0)+L2067*VLOOKUP($B2067,Premissas!$A$4:$E$7,5,0)) | N2067: =H2067-M2067 | O2067: Sim | P2067: 1.350
A2068: 46023 | B2068: Frete de compra | C2068: Frete de compra | D2068: CT-e | E2068: 000075476 | F2068: GOL LINHAS AEREAS S.A. | G2068: 46037 | H2068: 1163.65 | I2068: 0 | J2068: 46.55 | K2068: 0 | L2068: 0 | M2068: =IF(B2068="Frete de venda",0,(1-ISNUMBER(SEARCH("556",P2068)))*(I2068*VLOOKUP($B2068,Premissas!$A$4:$E$7,2,0)+J2068*VLOOKUP($B2068,Premissas!$A$4:$E$7,3,0))+K2068*VLOOKUP($B2068,Premissas!$A$4:$E$7,4,0)+L2068*VLOOKUP($B2068,Premissas!$A$4:$E$7,5,0)) | N2068: =H2068-M2068 | O2068: Sim | P2068: 1.350
A2069: 46023 | B2069: Frete de venda | C2069: Frete de venda (para clientes) | D2069: CT-e | E2069: 000213565 | F2069: CAZAN TRANSPORTES LTDA | G2069: 46052 | H2069: 8287 | I2069: 0 | J2069: 580.09 | K2069: 0 | L2069: 0 | M2069: =IF(B2069="Frete de venda",0,(1-ISNUMBER(SEARCH("556",P2069)))*(I2069*VLOOKUP($B2069,Premissas!$A$4:$E$7,2,0)+J2069*VLOOKUP($B2069,Premissas!$A$4:$E$7,3,0))+K2069*VLOOKUP($B2069,Premissas!$A$4:$E$7,4,0)+L2069*VLOOKUP($B2069,Premissas!$A$4:$E$7,5,0)) | N2069: =H2069-M2069 | O2069: Sim | P2069: 1.350
A2070: 46023 | B2070: Frete de compra | C2070: Frete de compra | D2070: CT-e | E2070: 000188201 | F2070: ALIANCA NAVEGACAO E LOGISTICA LTDA | G2070: 46045 | H2070: 17208.34 | I2070: 0 | J2070: 1204.58 | K2070: 0 | L2070: 0 | M2070: =IF(B2070="Frete de venda",0,(1-ISNUMBER(SEARCH("556",P2070)))*(I2070*VLOOKUP($B2070,Premissas!$A$4:$E$7,2,0)+J2070*VLOOKUP($B2070,Premissas!$A$4:$E$7,3,0))+K2070*VLOOKUP($B2070,Premissas!$A$4:$E$7,4,0)+L2070*VLOOKUP($B2070,Premissas!$A$4:$E$7,5,0)) | N2070: =H2070-M2070 | O2070: Sim | P2070: 1.350
A2071: 46023 | B2071: Frete de compra | C2071: Frete de compra | D2071: CT-e | E2071: 000188202 | F2071: ALIANCA NAVEGACAO E LOGISTICA LTDA | G2071: 46045 | H2071: 17211.95 | I2071: 0 | J2071: 1204.84 | K2071: 0 | L2071: 0 | M2071: =IF(B2071="Frete de venda",0,(1-ISNUMBER(SEARCH("556",P2071)))*(I2071*VLOOKUP($B2071,Premissas!$A$4:$E$7,2,0)+J2071*VLOOKUP($B2071,Premissas!$A$4:$E$7,3,0))+K2071*VLOOKUP($B2071,Premissas!$A$4:$E$7,4,0)+L2071*VLOOKUP($B2071,Premissas!$A$4:$E$7,5,0)) | N2071: =H2071-M2071 | O2071: Sim | P2071: 1.350
A2072: 46023 | B2072: Frete de compra | C2072: Frete de compra | D2072: CT-e | E2072: 000188203 | F2072: ALIANCA NAVEGACAO E LOGISTICA LTDA | G2072: 46046 | H2072: 17204.9 | I2072: 0 | J2072: 1204.34 | K2072: 0 | L2072: 0 | M2072: =IF(B2072="Frete de venda",0,(1-ISNUMBER(SEARCH("556",P2072)))*(I2072*VLOOKUP($B2072,Premissas!$A$4:$E$7,2,0)+J2072*VLOOKUP($B2072,Premissas!$A$4:$E$7,3,0))+K2072*VLOOKUP($B2072,Premissas!$A$4:$E$7,4,0)+L2072*VLOOKUP($B2072,Premissas!$A$4:$E$7,5,0)) | N2072: =H2072-M2072 | O2072: Sim | P2072: 1.350
A2073: 46023 | B2073: Frete de compra | C2073: Frete de compra | D2073: CT-e | E2073: 000188204 | F2073: ALIANCA NAVEGACAO E LOGISTICA LTDA | G2073: 46046 | H2073: 17205.39 | I2073: 0 | J2073: 1204.38 | K2073: 0 | L2073: 0 | M2073: =IF(B2073="Frete de venda",0,(1-ISNUMBER(SEARCH("556",P2073)))*(I2073*VLOOKUP($B2073,Premissas!$A$4:$E$7,2,0)+J2073*VLOOKUP($B2073,Premissas!$A$4:$E$7,3,0))+K2073*VLOOKUP($B2073,Premissas!$A$4:$E$7,4,0)+L2073*VLOOKUP($B2073,Premissas!$A$4:$E$7,5,0)) | N2073: =H2073-M2073 | O2073: Sim | P2073: 1.350
... A4831: 46266 | B4831: Uso e consumo | C4831: 2.04.91 Compra de Material de Limpeza | D4831: NF-e | E4831: 000001541 | F4831: Limptech Paper Comercio Ltda | G4831: 46282 | H4831: 549 | I4831: 0 | J4831: 0 | K4831: 0 | L4831: 0 | M4831: =IF(B4831="Frete de venda",0,(1-ISNUMBER(SEARCH("556",P4831)))*(I4831*VLOOKUP($B4831,Premissas!$A$4:$E$7,2,0)+J4831*VLOOKUP($B4831,Premissas!$A$4:$E$7,3,0))+K4831*VLOOKUP($B4831,Premissas!$A$4:$E$7,4,0)+L4831*VLOOKUP($B4831,Premissas!$A$4:$E$7,5,0)) | N4831: =H4831-M4831 | O4831: Sim | P4831: 1.556
A4832: 46235 | B4832: Frete de venda | C4832: Frete de venda (para clientes) | D4832: Pgto sem CT-e | E4832: 000000056 | F4832: 26.221.654 ROGERIO DA CUNHA FERREIRA | H4832: 18300 | I4832: 0 | J4832: 0 | K4832: 0 | L4832: 0 | M4832: =IF(B4832="Frete de venda",0,(1-ISNUMBER(SEARCH("556",P4832)))*(I4832*VLOOKUP($B4832,Premissas!$A$4:$E$7,2,0)+J4832*VLOOKUP($B4832,Premissas!$A$4:$E$7,3,0))+K4832*VLOOKUP($B4832,Premissas!$A$4:$E$7,4,0)+L4832*VLOOKUP($B4832,Premissas!$A$4:$E$7,5,0)) | N4832: =H4832-M4832 | O4832: n/d
A4833: 46235 | B4833: Frete de venda | C4833: Frete de venda (para clientes) | D4833: Pgto sem CT-e | E4833: 000000012 | F4833: MARCOS RIBEIRO DE MELO | H4833: 13800 | I4833: 0 | J4833: 0 | K4833: 0 | L4833: 0 | M4833: =IF(B4833="Frete de venda",0,(1-ISNUMBER(SEARCH("556",P4833)))*(I4833*VLOOKUP($B4833,Premissas!$A$4:$E$7,2,0)+J4833*VLOOKUP($B4833,Premissas!$A$4:$E$7,3,0))+K4833*VLOOKUP($B4833,Premissas!$A$4:$E$7,4,0)+L4833*VLOOKUP($B4833,Premissas!$A$4:$E$7,5,0)) | N4833: =H4833-M4833 | O4833: n/d
A4834: 46235 | B4834: Frete de venda | C4834: Frete de venda (para clientes) | D4834: Pgto sem CT-e | E4834: 000000070 | F4834: PEDRO HENRIQUE MODESTO DE QUEIROZ SILVEIRA | H4834: 650 | I4834: 0 | J4834: 0 | K4834: 0 | L4834: 0 | M4834: =IF(B4834="Frete de venda",0,(1-ISNUMBER(SEARCH("556",P4834)))*(I4834*VLOOKUP($B4834,Premissas!$A$4:$E$7,2,0)+J4834*VLOOKUP($B4834,Premissas!$A$4:$E$7,3,0))+K4834*VLOOKUP($B4834,Premissas!$A$4:$E$7,4,0)+L4834*VLOOKUP($B4834,Premissas!$A$4:$E$7,5,0)) | N4834: =H4834-M4834 | O4834: n/d
A4835: 46235 | B4835: Frete de venda | C4835: Frete de venda (para clientes) | D4835: Pgto sem CT-e | E4835: FATURA | F4835: ADIL CARLOS DA SILVA | H4835: 34500 | I4835: 0 | J4835: 0 | K4835: 0 | L4835: 0 | M4835: =IF(B4835="Frete de venda",0,(1-ISNUMBER(SEARCH("556",P4835)))*(I4835*VLOOKUP($B4835,Premissas!$A$4:$E$7,2,0)+J4835*VLOOKUP($B4835,Premissas!$A$4:$E$7,3,0))+K4835*VLOOKUP($B4835,Premissas!$A$4:$E$7,4,0)+L4835*VLOOKUP($B4835,Premissas!$A$4:$E$7,5,0)) | N4835: =H4835-M4835 | O4835: n/d

Sheet Premissas
A1: Créditos de impostos recuperáveis abatidos do custo (1 = abate, 0 = não abate). Editável.
A3: Destino | B3: IPI | C3: ICMS | D3: PIS | E3: COFINS
A4: Insumos e papel | B4: 1 | C4: 1 | D4: 1 | E4: 1
A5: Uso e consumo | B5: 0 | C5: 0 | D5: 1 | E5: 1
A6: Frete de compra | B6: 0 | C6: 1 | D6: 0 | E6: 0
A7: Frete de venda | B7: 0 | C7: 0 | D7: 0 | E7: 0
A9: Premissas:
A10: 1) Base = pagamentos efetivos: NF-e só entra se gerou título a pagar; exclui remessa (2.01.84), transferências 0.01, x.949, x.922 e grupo 2.09 devoluções.
A11: 2) Valores da aba Notas são brutos (com IPI/ST/frete destacado). Custo líquido = valor − créditos marcados acima (padrão: Lucro Real não cumulativo). ICMS-ST nunca é abatido.
A12: 3) Uso e consumo: ICMS/IPI sem crédito (CFOP x.556); só PIS/COFINS. Frete de compra: só ICMS. Frete de venda é despesa comercial, sem crédito. Ajuste se o contador orientar diferente.
A13: 4) Parecer fiscal: documentos com CFOP x.556 (compra para uso e consumo) não geram crédito de ICMS nem IPI; a Base zera esses créditos automaticamente (coluna CFOPs entrada). PIS/COFINS seguem as marcações da tabela.
A14: 4b) Em 14 documentos rateados por categoria os impostos constam só na 1ª linha; efeito pequeno.
A15: 5) Competência = mês de emissão. Documentos emitidos antes de 2026 e conferidos em 2026 aparecem na coluna Memo, fora do Total.
A16: 6) Esta planilha é só de despesas (sem receita, estoque ou DRE). A aba Fora do escopo lista o que foi pago mas não é almoxarifado nem frete de venda (imobilizado, manutenção, brindes, aluguel de contêiner etc.).
A17: 7) Fora do escopo desta DRE: imobilizado (2.07), manutenção, brindes, combustível, sede etc. (ver almoxarifado_e_frete_venda_2026.xlsx, aba Fora do escopo).

Sheet Fora do escopo
A1: Mês (emissão) | B1: Bloco anterior | C1: Seção | D1: Grupo | E1: Categoria do Omie | F1: Tipo | G1: Número | H1: Parte / Transportadora | I1: CNPJ/CPF | J1: Emissão | K1: Valor (R$) | L1: Gerou título a pagar | M1: Observação
A2: Antes de 2026 | B2: Investimento (imobilizado) | C2: NF-e | D2: 2.07 Investimento | E2: 2.07.01 Máquinas e Equipamentos | F2: NF-e | G2: 008094334 | H2: DELL COMPUTADORES DO BRASIL LTDA | I2: 72.381.189/0010-01 | J2: 45945 | K2: 1160.04 | L2: Sim
A3: Antes de 2026 | B3: Investimento (imobilizado) | C3: NF-e | D3: 2.07 Investimento | E3: 2.07.01 Máquinas e Equipamentos | F3: NF-e | G3: 000070767 | H3: FURNAX COMERCIAL E IMPORTADORA EIRELI | I3: 00.144.257/0001-17 | J3: 46006 | K3: 2065 | L3: Sim
A4: Antes de 2026 | B4: Investimento (imobilizado) | C4: NF-e | D4: 2.07 Investimento | E4: 2.07.05 Compra de Móveis e Utensílios | F4: NF-e | G4: 000000221 | H4: INOVAMAIS | I4: 30.087.865/0001-06 | J4: 45986 | K4: 7306.8 | L4: Sim
A5: Antes de 2026 | B5: Despesas gerais | C5: NF-e | D5: 2.16 Sede Vinco | E5: 2.16.94 Sede - Despesas Gerais | F5: NF-e | G5: 000000003 | H5: TREVO CIMENTO LTDA | I5: 55.314.437/0001-91 | J5: 46008 | K5: 6000 | L5: Sim
A6: Antes de 2026 | B6: Despesas gerais | C6: NF-e | D6: 2.16 Sede Vinco | E6: 2.16.98 Aporte - Embalafoods (Sede) | F6: NF-e | G6: 000000150 | H6: TREVO CIMENTO LTDA | I6: 55.314.437/0001-91 | J6: 45995 | K6: 6000 | L6: Sim
A7: 46023 | B7: Despesas gerais | C7: NF-e | D7: 2.02 Despesas Comerciais | E7: 2.02.95 Brindes | F7: NF-e | G7: 000001979 | H7: KASSUA.COM.BR LTDA | I7: 42.948.791/0001-26 | J7: 46044 | K7: 748 | L7: Sim
A8: 46023 | B8: Investimento (imobilizado) | C8: NF-e | D8: 2.07 Investimento | E8: 2.07.01 Máquinas e Equipamentos | F8: NF-e | G8: 000082330 | H8: KALUNGA SA | I8: 43.283.811/0198-45 | J8: 46049 | K8: 39.9 | L8: Sim
A9: 46023 | B9: Investimento (imobilizado) | C9: NF-e | D9: 2.07 Investimento | E9: 2.07.01 Máquinas e Equipamentos | F9: NF-e | G9: 000241188 | H9: NORDIFE MATERIAIS ELETRICOS LTDA | I9: 35.589.365/0004-20 | J9: 46052 | K9: 811.62 | L9: Sim
A10: 46023 | B10: Investimento (imobilizado) | C10: NF-e | D10: 2.07 Investimento | E10: 2.07.04 Equipamentos de Informática | F10: NF-e | G10: 000043368 | H10: MIRANDA COMPUTACAO E COMERCIO LTDA | I10: 11.982.113/0011-28 | J10: 46041 | K10: 578 | L10: Sim
A11: 46023 | B11: Investimento (imobilizado) | C11: NF-e | D11: 2.07 Investimento | E11: 2.07.04 Equipamentos de Informática | F11: NF-e | G11: 000043597 | H11: MIRANDA COMPUTACAO E COMERCIO LTDA | I11: 11.982.113/0011-28 | J11: 46049 | K11: 332.02 | L11: Sim
A12: 46023 | B12: Investimento (imobilizado) | C12: NF-e | D12: 2.07 Investimento | E12: 2.07.05 Compra de Móveis e Utensílios | F12: NF-e | G12: 000003780 | H12: THIAGO GABRIEL MOVEIS LTDA | I12: 47.698.480/0001-70 | J12: 46052 | K12: 4380 | L12: Sim
A13: 46023 | B13: Despesas gerais | C13: NF-e | D13: 2.12 Despesas com Veículos | E13: 2.12.99 Combustível | F13: NF-e | G13: 000006726 | H13: SUPERGASBRAS ENERGIA LTDA | I13: 19.791.896/0166-00 | J13: 46041 | K13: 615.56 | L13: Sim
A14: 46054 | B14: Serviços e manutenção | C14: NF-e | D14: 2.01 Custos | E14: 2.01.88 Manutenção e Conservação de Máquina | F14: NF-e | G14: 000004536 | H14: ARLINDO ALVES PASCOAL JUNIOR | I14: 08.624.940/0001-63 | J14: 46066 | K14: 3340 | L14: Sim
A15: 46054 | B15: Serviços e manutenção | C15: NF-e | D15: 2.01 Custos | E15: 2.01.88 Manutenção e Conservação de Máquina | F15: NF-e | G15: 000004537 | H15: ARLINDO ALVES PASCOAL JUNIOR | I15: 08.624.940/0001-63 | J15: 46067 | K15: 2849.6 | L15: Sim
A16: 46054 | B16: Serviços e manutenção | C16: NF-e | D16: 2.01 Custos | E16: 2.01.88 Manutenção e Conservação de Máquina | F16: NF-e | G16: 000004546 | H16: ARLINDO ALVES PASCOAL JUNIOR | I16: 08.624.940/0001-63 | J16: 46078 | K16: 3060 | L16: Sim
A17: 46054 | B17: Serviços e manutenção | C17: NF-e | D17: 2.01 Custos | E17: 2.01.88 Manutenção e Conservação de Máquina | F17: NF-e | G17: 000004547 | H17: ARLINDO ALVES PASCOAL JUNIOR | I17: 08.624.940/0001-63 | J17: 46078 | K17: 270 | L17: Sim
A18: 46054 | B18: Serviços e manutenção | C18: NF-e | D18: 2.01 Custos | E18: 2.01.88 Manutenção e Conservação de Máquina | F18: NF-e | G18: 000093202 | H18: BENE COMERCIO VAREJISTA E ATACADISTA LTDA | I18: 02.994.420/0001-66 | J18: 46065 | K18: 8 | L18: Sim
... A48: 46113 | B48: Serviços e manutenção | C48: NF-e | D48: 2.01 Custos | E48: 2.01.88 Manutenção e Conservação de Máquina | F48: NF-e | G48: 000309036 | H48: ALUMIFER ALUMINIO E FERRO LTDA. | I48: 05.515.224/0003-11 | J48: 46128 | K48: 590 | L48: Sim
A49: 46113 | B49: Serviços e manutenção | C49: NF-e | D49: 2.01 Custos | E49: 2.01.88 Manutenção e Conservação de Máquina | F49: NF-e | G49: 000092837 | H49: CONSTRUTIVA MATERIAIS ELETRICOS LTDA | I49: 06.267.222/0001-51 | J49: 46122 | K49: 633.25 | L49: Sim | M49: Valor rateado entre categorias, como no Omie
A50: 46113 | B50: Serviços e manutenção | C50: NF-e | D50: 2.01 Custos | E50: 2.01.88 Manutenção e Conservação de Máquina | F50: NF-e | G50: 000051503 | H50: ELETROPOLO ELETRICIDADE LTDA | I50: 02.375.199/0005-91 | J50: 46118 | K50: 1351 | L50: Sim | M50: Valor rateado entre categorias, como no Omie
A51: 46113 | B51: Despesas gerais | C51: NF-e | D51: 2.03 Despesas com Pessoal | E51: 2.03.02 EndoMarketing | F51: NF-e | G51: 000496170 | H51: FAZENDA SANTA TEREZINHA LTDA. | I51: 01.778.112/0001-30 | J51: 46141 | K51: 531 | L51: Sim
A52: 46113 | B52: Despesas gerais | C52: NF-e | D52: 2.04 Despesas Administrativas | E52: 2.04.87 Frete sobre Compra | F52: NF-e | G52: 000001768 | H52: B. B. A. INDUSTRIA E COMERCIO IMPORTACAO E EXPORTACAO LTDA | I52: 25.247.287/0001-80 | J52: 46122 | K52: 6521.26 | L52: Sim
A53: 46113 | B53: Investimento (imobilizado) | C53: NF-e | D53: 2.07 Investimento | E53: 2.07.01 Máquinas e Equipamentos | F53: NF-e | G53: 004295109 | H53: 2ELETRO COMERCIO E DISTRIBUICAO DE PROD DE INFORMATICA | I53: 34.036.601/0005-08 | J53: 46136 | K53: 6569.9 | L53: Sim
A54: 46113 | B54: Investimento (imobilizado) | C54: NF-e | D54: 2.07 Investimento | E54: 2.07.01 Máquinas e Equipamentos | F54: NF-e | G54: 000092837 | H54: CONSTRUTIVA MATERIAIS ELETRICOS LTDA | I54: 06.267.222/0001-51 | J54: 46122 | K54: 4174.91 | L54: Sim | M54: Valor rateado entre categorias, como no Omie
A55: 46113 | B55: Investimento (imobilizado) | C55: NF-e | D55: 2.07 Investimento | E55: 2.07.01 Máquinas e Equipamentos | F55: NF-e | G55: 000092944 | H55: CONSTRUTIVA MATERIAIS ELETRICOS LTDA | I55: 06.267.222/0001-51 | J55: 46127 | K55: 798.74 | L55: Sim
A56: 46113 | B56: Investimento (imobilizado) | C56: NF-e | D56: 2.07 Investimento | E56: 2.07.01 Máquinas e Equipamentos | F56: NF-e | G56: 117146763 | H56: Ebazar.com.br. ltda | I56: 03.007.331/0010-32 | J56: 46136 | K56: 724.5 | L56: Sim
A57: 46113 | B57: Investimento (imobilizado) | C57: NF-e | D57: 2.07 Investimento | E57: 2.07.01 Máquinas e Equipamentos | F57: NF-e | G57: 117220598 | H57: Ebazar.com.br. ltda | I57: 03.007.331/0010-32 | J57: 46136 | K57: 3999 | L57: Sim
A58: 46113 | B58: Investimento (imobilizado) | C58: NF-e | D58: 2.07 Investimento | E58: 2.07.01 Máquinas e Equipamentos | F58: NF-e | G58: 000084303 | H58: KALUNGA SA | I58: 43.283.811/0198-45 | J58: 46140 | K58: 239.8 | L58: Sim | M58: Valor rateado entre categorias, como no Omie
A59: 46113 | B59: Investimento (imobilizado) | C59: NF-e | D59: 2.07 Investimento | E59: 2.07.01 Máquinas e Equipamentos | F59: NF-e | G59: 000000053 | H59: M STEEL METALURGICA LTDA | I59: 61.858.794/0001-13 | J59: 46129 | K59: 3600 | L59: Sim
A60: 46113 | B60: Investimento (imobilizado) | C60: NF-e | D60: 2.07 Investimento | E60: 2.07.05 Compra de Móveis e Utensílios | F60: NF-e | G60: 000016398 | H60: BR EMBALAGENS INDUSTRIA E COMERCIO LTDA | I60: 28.150.494/0001-00 | J60: 46120 | K60: 9349.2 | L60: Sim | M60: Valor rateado entre categorias, como no Omie
A61: 46113 | B61: Investimento (imobilizado) | C61: NF-e | D61: 2.07 Investimento | E61: 2.07.05 Compra de Móveis e Utensílios | F61: NF-e | G61: 000051503 | H61: ELETROPOLO ELETRICIDADE LTDA | I61: 02.375.199/0005-91 | J61: 46118 | K61: 626.8 | L61: Sim | M61: Valor rateado entre categorias, como no Omie
A62: 46113 | B62: Investimento (imobilizado) | C62: NF-e | D62: 2.07 Investimento | E62: 2.07.05 Compra de Móveis e Utensílios | F62: NF-e | G62: 000151894 | H62: STREETING CAR LTDA | I62: 53.847.868/0001-98 | J62: 46123 | K62: 135.96 | L62: Sim
A63: 46113 | B63: Investimento (imobilizado) | C63: NF-e | D63: 2.07 Investimento | E63: 2.07.05 Compra de Móveis e Utensílios | F63: NF-e | G63: 000151895 | H63: STREETING CAR LTDA | I63: 53.847.868/0001-98 | J63: 46123 | K63: 67.98 | L63: Sim
A64: 46113 | B64: Despesas gerais | C64: NF-e | D64: 2.12 Despesas com Veículos | E64: 2.12.99 Combustível | F64: NF-e | G64: 000007528 | H64: SUPERGASBRAS ENERGIA LTDA | I64: 19.791.896/0166-00 | J64: 46125 | K64: 472.47 | L64: Sim
A65: 46113 | B65: Despesas gerais | C65: NF-e | D65: 2.16 Sede Vinco | E65: 2.16.99 Investimento Sede Vinco | F65: NF-e | G65: 000000100 | H65: COMERCIAL CASA NOVA MATERIAL DE CONSTRUCAO PB LTDA | I65: 44.336.205/0001-18 | J65: 46134 | K65: 6600 | L65: Sim
A66: 46113 | B66: Despesas gerais | C66: NF-e | D66: 2.16 Sede Vinco | E66: 2.16.99 Investimento Sede Vinco | F66: NF-e | G66: 000000102 | H66: COMERCIAL CASA NOVA MATERIAL DE CONSTRUCAO PB LTDA | I66: 44.336.205/0001-18 | J66: 46142 | K66: 400 | L66: Sim
A67: 46143 | B67: Despesas gerais | C67: NF-e | D67: 2.02 Despesas Comerciais | E67: 2.02.95 Brindes | F67: NF-e | G67: 900564807 | H67: 38.277.962 RAQUEL BARBOSA DE PAIVA SANTOS SALES | I67: 38.277.962/0001-65 | J67: 46153 | K67: 4850 | L67: Sim
A68: 46143 | B68: Despesas gerais | C68: NF-e | D68: 2.02 Despesas Comerciais | E68: 2.02.95 Brindes | F68: NF-e | G68: 000000195 | H68: Omega Soul Brindes e Servicos Ltda | I68: 61.699.265/0001-14 | J68: 46168 | K68: 1383.3 | L68: Sim
A69: 46143 | B69: Despesas gerais | C69: NF-e | D69: 2.03 Despesas com Pessoal | E69: 2.03.02 EndoMarketing | F69: NF-e | G69: 000002313 | H69: UP GIFTS PERSONALIZADOS LTDA | I69: 46.230.617/0001-02 | J69: 46150 | K69: 84 | L69: Sim
A70: 46143 | B70: Investimento (imobilizado) | C70: NF-e | D70: 2.07 Investimento | E70: 2.07.01 Máquinas e Equipamentos | F70: NF-e | G70: 000012299 | H70: E. M. AMARAL - MAQUINAS E FERRAMENTAS LTDA | I70: 25.114.989/0001-95 | J70: 46149 | K70: 6330.63 | L70: Sim
A71: 46143 | B71: Investimento (imobilizado) | C71: NF-e | D71: 2.07 Investimento | E71: 2.07.01 Máquinas e Equipamentos | F71: NF-e | G71: 000014204 | H71: EDNA DE ARAUJO PACHECO LTDA | I71: 17.433.873/0001-90 | J71: 46169 | K71: 955.9 | L71: Sim
A72: 46143 | B72: Investimento (imobilizado) | C72: NF-e | D72: 2.07 Investimento | E72: 2.07.01 Máquinas e Equipamentos | F72: NF-e | G72: 124857793 | H72: Ebazar.com.br. ltda | I72: 03.007.331/0010-32 | J72: 46168 | K72: 3227.76 | L72: Sim
A73: 46143 | B73: Investimento (imobilizado) | C73: NF-e | D73: 2.07 Investimento | E73: 2.07.01 Máquinas e Equipamentos | F73: NF-e | G73: 125044430 | H73: Ebazar.com.br. ltda | I73: 03.007.331/0010-32 | J73: 46169 | K73: 1066.68 | L73: Sim
... A80: 46174 | B80: Serviços e manutenção | C80: NF-e | D80: 2.01 Custos | E80: 2.01.88 Manutenção e Conservação de Máquina | F80: NF-e | G80: 000160132 | H80: Beltex Ind. e Com. de Correias Ltda. | I80: 82.317.900/0001-21 | J80: 46184 | K80: 3229.63 | L80: Sim
A81: 46174 | B81: Serviços e manutenção | C81: NF-e | D81: 2.01 Custos | E81: 2.01.88 Manutenção e Conservação de Máquina | F81: NF-e | G81: 000014392 | H81: EDNA DE ARAUJO PACHECO LTDA | I81: 17.433.873/0001-90 | J81: 46185 | K81: 1183.7 | L81: Sim | M81: Valor rateado entre categorias, como no Omie
A82: 46174 | B82: Serviços e manutenção | C82: NF-e | D82: 2.01 Custos | E82: 2.01.88 Manutenção e Conservação de Máquina | F82: NF-e | G82: 000104864 | H82: FERGE COMERCIO DE PRODUTOS INDUSTRIAIS LTDA | I82: 09.057.961/0001-07 | J82: 46177 | K82: 160 | L82: Sim
A83: 46174 | B83: Serviços e manutenção | C83: NF-e | D83: 2.01 Custos | E83: 2.01.88 Manutenção e Conservação de Máquina | F83: NF-e | G83: 000105080 | H83: FERGE COMERCIO DE PRODUTOS INDUSTRIAIS LTDA | I83: 09.057.961/0001-07 | J83: 46185 | K83: 620 | L83: Sim
A84: 46174 | B84: Serviços e manutenção | C84: NF-e | D84: 2.01 Custos | E84: 2.01.88 Manutenção e Conservação de Máquina | F84: NF-e | G84: 000105121 | H84: FERGE COMERCIO DE PRODUTOS INDUSTRIAIS LTDA | I84: 09.057.961/0001-07 | J84: 46188 | K84: 392 | L84: Sim
A85: 46174 | B85: Serviços e manutenção | C85: NF-e | D85: 2.01 Custos | E85: 2.01.88 Manutenção e Conservação de Máquina | F85: NF-e | G85: 000105277 | H85: FERGE COMERCIO DE PRODUTOS INDUSTRIAIS LTDA | I85: 09.057.961/0001-07 | J85: 46192 | K85: 315 | L85: Sim
A86: 46174 | B86: Serviços e manutenção | C86: NF-e | D86: 2.01 Custos | E86: 2.01.88 Manutenção e Conservação de Máquina | F86: NF-e | G86: 000072400 | H86: FURNAX COMERCIAL E IMPORTADORA EIRELI | I86: 00.144.257/0001-17 | J86: 46195 | K86: 4273.86 | L86: Sim
A87: 46174 | B87: Serviços e manutenção | C87: NF-e | D87: 2.01 Custos | E87: 2.01.88 Manutenção e Conservação de Máquina | F87: NF-e | G87: 000010118 | H87: LED NORDESTE ILUMINACAO LTDA | I87: 11.651.809/0001-08 | J87: 46184 | K87: 705 | L87: Sim
A88: 46174 | B88: Serviços e manutenção | C88: NF-e | D88: 2.01 Custos | E88: 2.01.88 Manutenção e Conservação de Máquina | F88: NF-e | G88: 000282371 | H88: ROLIMEC ROLAMENTOS LTDA | I88: 01.612.046/0001-24 | J88: 46203 | K88: 4146 | L88: Sim
A89: 46174 | B89: Despesas gerais | C89: NF-e | D89: 2.02 Despesas Comerciais | E89: 2.02.95 Brindes | F89: NF-e | G89: 000003591 | H89: PRESENTES ESPECIAIS LTDA | I89: 11.612.564/0001-00 | J89: 46181 | K89: 135 | L89: Sim
A90: 46174 | B90: Despesas gerais | C90: NF-e | D90: 2.03 Despesas com Pessoal | E90: 2.03.02 EndoMarketing | F90: NF-e | G90: 000003661 | H90: NOVO ATACADO COMERCIO DE ALIMENTOS SA | I90: 20.300.157/0066-95 | J90: 46183 | K90: 1277.47 | L90: Sim
A91: 46174 | B91: Despesas gerais | C91: NF-e | D91: 2.03 Despesas com Pessoal | E91: 2.03.02 EndoMarketing | F91: NF-e | G91: 000004066 | H91: NOVO ATACADO COMERCIO DE ALIMENTOS SA | I91: 20.300.157/0066-95 | J91: 46196 | K91: 196.07 | L91: Sim
A92: 46174 | B92: Investimento (imobilizado) | C92: NF-e | D92: 2.07 Investimento | E92: 2.07.01 Máquinas e Equipamentos | F92: NF-e | G92: 000014392 | H92: EDNA DE ARAUJO PACHECO LTDA | I92: 17.433.873/0001-90 | J92: 46185 | K92: 71.38 | L92: Sim | M92: Valor rateado entre categorias, como no Omie
A93: 46174 | B93: Investimento (imobilizado) | C93: NF-e | D93: 2.07 Investimento | E93: 2.07.01 Máquinas e Equipamentos | F93: NF-e | G93: 000014400 | H93: EDNA DE ARAUJO PACHECO LTDA | I93: 17.433.873/0001-90 | J93: 46188 | K93: 939.9 | L93: Sim
A94: 46174 | B94: Investimento (imobilizado) | C94: NF-e | D94: 2.07 Investimento | E94: 2.07.04 Equipamentos de Informática | F94: NF-e | G94: 000268886 | H94: BETEL COMERCIO DE VARIEDADES LTDA | I94: 60.238.815/0001-35 | J94: 46188 | K94: 41.99 | L94: Sim
A95: 46174 | B95: Investimento (imobilizado) | C95: NF-e | D95: 2.07 Investimento | E95: 2.07.04 Equipamentos de Informática | F95: NF-e | G95: 000047239 | H95: MIRANDA COMPUTACAO E COMERCIO LTDA | I95: 11.982.113/0011-28 | J95: 46191 | K95: 4198 | L95: Sim
A96: 46174 | B96: Investimento (imobilizado) | C96: NF-e | D96: 2.07 Investimento | E96: 2.07.04 Equipamentos de Informática | F96: NF-e | G96: 000047238 | H96: MIRANDA COMPUTACAO E COMERCIO LTDA | I96: 11.982.113/0011-28 | J96: 46191 | K96: 8396 | L96: Sim
A97: 46174 | B97: Serviços e manutenção | C97: NF-e | D97: 2.11 Despesa com Imóvel | E97: 2.11.93 Manutenção Predial | F97: NF-e | G97: 000057219 | H97: ELETROPOLO ELETRICIDADE LTDA | I97: 02.375.199/0005-91 | J97: 46191 | K97: 403.19 | L97: Sim
A98: 46174 | B98: Despesas gerais | C98: NF-e | D98: 2.12 Despesas com Veículos | E98: 2.12.99 Combustível | F98: NF-e | G98: 000008221 | H98: SUPERGASBRAS ENERGIA LTDA | I98: 19.791.896/0166-00 | J98: 46196 | K98: 629.96 | L98: Sim
A99: 46174 | B99: Despesas gerais | C99: NF-e | D99: 2.16 Sede Vinco | E99: 2.16.99 Investimento Sede Vinco | F99: NF-e | G99: 000000104 | H99: COMERCIAL CASA NOVA MATERIAL DE CONSTRUCAO PB LTDA | I99: 44.336.205/0001-18 | J99: 46178 | K99: 550 | L99: Sim
A100: 46174 | B100: Despesas gerais | C100: NF-e | D100: 2.16 Sede Vinco | E100: 2.16.99 Investimento Sede Vinco | F100: NF-e | G100: 000033572 | H100: VIEIRA ACO INDUSTRIA e COMERCIO LTDA | I100: 12.281.632/0011-21 | J100: 46182 | K100: 195 | L100: Sim
A101: 46174 | B101: Despesas gerais | C101: NF-e | D101: 2.16 Sede Vinco | E101: 2.16.99 Investimento Sede Vinco | F101: NF-e | G101: 000033807 | H101: VIEIRA ACO INDUSTRIA e COMERCIO LTDA | I101: 12.281.632/0011-21 | J101: 46190 | K101: 96 | L101: Sim
A102: 46204 | B102: Serviços e manutenção | C102: NF-e | D102: 2.01 Custos | E102: 2.01.88 Manutenção e Conservação de Máquina | F102: NF-e | G102: 000014706 | H102: EDNA DE ARAUJO PACHECO LTDA | I102: 17.433.873/0001-90 | J102: 46213 | K102: 213.28 | L102: Sim
A103: 46204 | B103: Serviços e manutenção | C103: NF-e | D103: 2.01 Custos | E103: 2.01.88 Manutenção e Conservação de Máquina | F103: NF-e | G103: 000014776 | H103: EDNA DE ARAUJO PACHECO LTDA | I103: 17.433.873/0001-90 | J103: 46218 | K103: 169.12 | L103: Sim
A104: 46204 | B104: Serviços e manutenção | C104: NF-e | D104: 2.01 Custos | E104: 2.01.88 Manutenção e Conservação de Máquina | F104: NF-e | G104: 000014935 | H104: EDNA DE ARAUJO PACHECO LTDA | I104: 17.433.873/0001-90 | J104: 46231 | K104: 143.14 | L104: Sim
... A176: 46266 | B176: Despesas gerais | C176: NF-e | D176: 2.16 Sede Vinco | E176: 2.16.99 Investimento Sede Vinco | F176: NF-e | G176: 000036295 | H176: VIEIRA ACO INDUSTRIA e COMERCIO LTDA | I176: 12.281.632/0011-21 | J176: 46288 | K176: 81 | L176: Sim
